Workbook
Name AcctCodes: Sync!$B$10:$B$259
Name AcctTbl: Sync!$B$10:$G$259
Name BankCodes: Sync!$AK$10:$AK$19
Name BankTbl: Sync!$AK$10:$AN$19
Name BasketCodeCol: Sync!$Z$10:$Z$21
Name BasketTbl: Sync!$Y$10:$AF$21
Name GroupTbl: Sync!$AR$10:$AS$51
Name ListAllCodes: OFFSET(Sync!$B$10,0,0,MAX(COUNTIF(Sync!$C$10:$C$259,"?*"),1),1)
Name ListBanks: OFFSET(Sync!$AL$10,0,0,MAX(COUNTIF(Sync!$AL$10:$AL$19,"?*"),1),1)
Name ListBasketOps: OFFSET(Sync!$AW$10,0,0,MAX(COUNTIF(Sync!$AW$10:$AW$14,"?*"),1),1)
Name ListBaskets: OFFSET(Sync!$Y$10,0,0,MAX(COUNTIF(Sync!$Y$10:$Y$21,"?*"),1),1)
Name ListBasketSellerCodes: OFFSET(Sync!$B$72,0,0,MAX(COUNTIF(Sync!$C$72:$C$74,"?*"),1),1)
Name ListBaskolOps: OFFSET(Sync!$AZ$10,0,0,MAX(COUNTIF(Sync!$AZ$10:$AZ$23,"?*"),1),1)
Name ListCategories: OFFSET(Sync!$CB$10,0,0,MAX(COUNTIF(Sync!$CB$10:$CB$29,"?*"),1),1)
Name ListChequeStatus: OFFSET(Sync!$CG$10,0,0,MAX(COUNTIF(Sync!$CG$10:$CG$29,"?*"),1),1)
Name ListColorKeys: OFFSET(Sync!$CP$10,0,0,MAX(COUNTIF(Sync!$CP$10:$CP$29,"?*"),1),1)
Name ListDirections: OFFSET(Sync!$CC$10,0,0,MAX(COUNTIF(Sync!$CC$10:$CC$29,"?*"),1),1)
Name ListGroups: Sync!$AU$10:$AU$19
Name ListGrowerCodes: OFFSET(Sync!$B$10,0,0,MAX(COUNTIF(Sync!$C$10:$C$66,"?*"),1),1)
Name ListInclude: OFFSET(Sync!$CH$10,0,0,MAX(COUNTIF(Sync!$CH$10:$CH$29,"?*"),1),1)
Name ListLoadBuyerCodes: OFFSET(Sync!$B$67,0,0,MAX(COUNTIF(Sync!$C$67:$C$71,"?*"),1),1)
Name ListManualRoles: OFFSET(Sync!$CI$10,0,0,MAX(COUNTIF(Sync!$CI$10:$CI$29,"?*"),1),1)
Name ListOpCategories: OFFSET(Sync!$CL$10,0,0,MAX(COUNTIF(Sync!$CL$10:$CL$29,"?*"),1),1)
Name ListOps: OFFSET(Sync!$I$10,0,0,MAX(COUNTIF(Sync!$I$10:$I$33,"?*"),1),1)
Name ListOtherScaleCodes: Sync!$AX$10:$AX$29
Name ListPartyBasis: OFFSET(Sync!$CO$10,0,0,MAX(COUNTIF(Sync!$CO$10:$CO$29,"?*"),1),1)
Name ListPartyTypes: OFFSET(Sync!$CE$10,0,0,MAX(COUNTIF(Sync!$CE$10:$CE$29,"?*"),1),1)
Name ListPayMethods: OFFSET(Sync!$CF$10,0,0,MAX(COUNTIF(Sync!$CF$10:$CF$29,"?*"),1),1)
Name ListPosEffects: OFFSET(Sync!$CJ$10,0,0,MAX(COUNTIF(Sync!$CJ$10:$CJ$29,"?*"),1),1)
Name ListProducts: OFFSET(Sync!$AH$10,0,0,MAX(COUNTIF(Sync!$AH$10:$AH$29,"?*"),1),1)
Name ListReportSheets: OFFSET(Sync!$CN$10,0,0,MAX(COUNTIF(Sync!$CN$10:$CN$29,"?*"),1),1)
Name ListSeasons: OFFSET(Sync!$CQ$10,0,0,MAX(COUNTIF(Sync!$CQ$10:$CQ$29,"?*"),1),1)
Name ListSides: OFFSET(Sync!$CK$10,0,0,MAX(COUNTIF(Sync!$CK$10:$CK$29,"?*"),1),1)
Name ListStatus: OFFSET(Sync!$CM$10,0,0,MAX(COUNTIF(Sync!$CM$10:$CM$29,"?*"),1),1)
Name ListSubgroups: OFFSET(Sync!$AR$10,0,0,MAX(COUNTIF(Sync!$AS$10:$AS$51,"?*"),1),1)
Name ListTxnDirections: OFFSET(Sync!$CR$10,0,0,MAX(COUNTIF(Sync!$CR$10:$CR$29,"?*"),1),1)
Name ListUnits: OFFSET(Sync!$CA$10,0,0,MAX(COUNTIF(Sync!$CA$10:$CA$29,"?*"),1),1)
Name ListYesNo: OFFSET(Sync!$CD$10,0,0,MAX(COUNTIF(Sync!$CD$10:$CD$29,"?*"),1),1)
Name OpTbl: Sync!$I$10:$W$33
Name ParamTbl: Sync!$AO$10:$AP$21
Name ProductTbl: Sync!$AH$10:$AI$29

Sheet Data
A9: تاریخ | B9: سند | C9: حساب | D9: شرح | E9: گروه | F9: نوع | G9: بدهکار | H9: بستانکار | I9: مبلغ | J9: پوز | K9: محصول | L9: سبد | M9: وزن خالص | N9: ماه
A10: ='[01_Entry.xlsx]Book'!A10 -> 1405/07/01 | B10: ='[01_Entry.xlsx]Book'!B10 -> BS-001 | C10: ='[01_Entry.xlsx]Book'!D10 -> C001 | D10: ='[01_Entry.xlsx]Book'!E10 | E10: ='[01_Entry.xlsx]Book'!O10 -> باغدار | F10: ='[01_Entry.xlsx]Book'!N10 -> خرید مرکبات | G10: ='[01_Entry.xlsx]Book'!L10 | H10: ='[01_Entry.xlsx]Book'!M10 -> 64181000 | I10: ='[01_Entry.xlsx]Book'!K10 -> 64181000 | J10: ='[01_Entry.xlsx]Book'!P10 | K10: ='[01_Entry.xlsx]Book'!F10 -> نارنگی پیچ | L10: ='[01_Entry.xlsx]Book'!G10 -> 139 | M10: ='[01_Entry.xlsx]Book'!I10 -> 2005.641 | N10: =IF($A10="","",MID($A10,6,2)) -> 0 | O10: =IF(OR($C10="",$C10<>'Inv'!$D$12),"",N(O$9)+1) -> 0
A11: ='[01_Entry.xlsx]Book'!A11 -> 1405/07/01 | B11: ='[01_Entry.xlsx]Book'!B11 -> BS-001 | C11: ='[01_Entry.xlsx]Book'!D11 -> X004 | D11: ='[01_Entry.xlsx]Book'!E11 -> مقابل: خرید مرکبات | E11: ='[01_Entry.xlsx]Book'!O11 -> سایر حساب | F11: ='[01_Entry.xlsx]Book'!N11 -> مقابل | G11: ='[01_Entry.xlsx]Book'!L11 -> 64181000 | H11: ='[01_Entry.xlsx]Book'!M11 | I11: ='[01_Entry.xlsx]Book'!K11 -> 64181000 | J11: ='[01_Entry.xlsx]Book'!P11 | K11: ='[01_Entry.xlsx]Book'!F11 | L11: ='[01_Entry.xlsx]Book'!G11 | M11: ='[01_Entry.xlsx]Book'!I11 | N11: =IF($A11="","",MID($A11,6,2)) -> 0 | O11: =IF(OR($C11="",$C11<>'Inv'!$D$12),"",N(O$10)+1) -> 0
A12: ='[01_Entry.xlsx]Book'!A12 | B12: ='[01_Entry.xlsx]Book'!B12 | C12: ='[01_Entry.xlsx]Book'!D12 | D12: ='[01_Entry.xlsx]Book'!E12 | E12: ='[01_Entry.xlsx]Book'!O12 | F12: ='[01_Entry.xlsx]Book'!N12 | G12: ='[01_Entry.xlsx]Book'!L12 | H12: ='[01_Entry.xlsx]Book'!M12 | I12: ='[01_Entry.xlsx]Book'!K12 | J12: ='[01_Entry.xlsx]Book'!P12 | K12: ='[01_Entry.xlsx]Book'!F12 | L12: ='[01_Entry.xlsx]Book'!G12 | M12: ='[01_Entry.xlsx]Book'!I12 | N12: =IF($A12="","",MID($A12,6,2)) -> 0 | O12: =IF(OR($C12="",$C12<>'Inv'!$D$12),"",N(O$11)+1) -> 0
A13: ='[01_Entry.xlsx]Book'!A13 | B13: ='[01_Entry.xlsx]Book'!B13 | C13: ='[01_Entry.xlsx]Book'!D13 | D13: ='[01_Entry.xlsx]Book'!E13 | E13: ='[01_Entry.xlsx]Book'!O13 | F13: ='[01_Entry.xlsx]Book'!N13 | G13: ='[01_Entry.xlsx]Book'!L13 | H13: ='[01_Entry.xlsx]Book'!M13 | I13: ='[01_Entry.xlsx]Book'!K13 | J13: ='[01_Entry.xlsx]Book'!P13 | K13: ='[01_Entry.xlsx]Book'!F13 | L13: ='[01_Entry.xlsx]Book'!G13 | M13: ='[01_Entry.xlsx]Book'!I13 | N13: =IF($A13="","",MID($A13,6,2)) -> 0 | O13: =IF(OR($C13="",$C13<>'Inv'!$D$12),"",N(O$12)+1) -> 0
A14: ='[01_Entry.xlsx]Book'!A14 -> 1405/07/01 | B14: ='[01_Entry.xlsx]Book'!B14 -> BS-002 | C14: ='[01_Entry.xlsx]Book'!D14 -> C003 | D14: ='[01_Entry.xlsx]Book'!E14 | E14: ='[01_Entry.xlsx]Book'!O14 -> باغدار | F14: ='[01_Entry.xlsx]Book'!N14 -> خرید مرکبات | G14: ='[01_Entry.xlsx]Book'!L14 | H14: ='[01_Entry.xlsx]Book'!M14 -> 28777000 | I14: ='[01_Entry.xlsx]Book'!K14 -> 28777000 | J14: ='[01_Entry.xlsx]Book'!P14 | K14: ='[01_Entry.xlsx]Book'!F14 -> پرتقال تامسون | L14: ='[01_Entry.xlsx]Book'!G14 -> 53 | M14: ='[01_Entry.xlsx]Book'!I14 -> 822.195 | N14: =IF($A14="","",MID($A14,6,2)) -> 0 | O14: =IF(OR($C14="",$C14<>'Inv'!$D$12),"",N(O$13)+1) -> 0
A15: ='[01_Entry.xlsx]Book'!A15 -> 1405/07/01 | B15: ='[01_Entry.xlsx]Book'!B15 -> BS-002 | C15: ='[01_Entry.xlsx]Book'!D15 -> X004 | D15: ='[01_Entry.xlsx]Book'!E15 -> مقابل: خرید مرکبات | E15: ='[01_Entry.xlsx]Book'!O15 -> سایر حساب | F15: ='[01_Entry.xlsx]Book'!N15 -> مقابل | G15: ='[01_Entry.xlsx]Book'!L15 -> 28777000 | H15: ='[01_Entry.xlsx]Book'!M15 | I15: ='[01_Entry.xlsx]Book'!K15 -> 28777000 | J15: ='[01_Entry.xlsx]Book'!P15 | K15: ='[01_Entry.xlsx]Book'!F15 | L15: ='[01_Entry.xlsx]Book'!G15 | M15: ='[01_Entry.xlsx]Book'!I15 | N15: =IF($A15="","",MID($A15,6,2)) -> 0 | O15: =IF(OR($C15="",$C15<>'Inv'!$D$12),"",N(O$14)+1) -> 0
A16: ='[01_Entry.xlsx]Book'!A16 | B16: ='[01_Entry.xlsx]Book'!B16 | C16: ='[01_Entry.xlsx]Book'!D16 | D16: ='[01_Entry.xlsx]Book'!E16 | E16: ='[01_Entry.xlsx]Book'!O16 | F16: ='[01_Entry.xlsx]Book'!N16 | G16: ='[01_Entry.xlsx]Book'!L16 | H16: ='[01_Entry.xlsx]Book'!M16 | I16: ='[01_Entry.xlsx]Book'!K16 | J16: ='[01_Entry.xlsx]Book'!P16 | K16: ='[01_Entry.xlsx]Book'!F16 | L16: ='[01_Entry.xlsx]Book'!G16 | M16: ='[01_Entry.xlsx]Book'!I16 | N16: =IF($A16="","",MID($A16,6,2)) -> 0 | O16: =IF(OR($C16="",$C16<>'Inv'!$D$12),"",N(O$15)+1) -> 0
A17: ='[01_Entry.xlsx]Book'!A17 | B17: ='[01_Entry.xlsx]Book'!B17 | C17: ='[01_Entry.xlsx]Book'!D17 | D17: ='[01_Entry.xlsx]Book'!E17 | E17: ='[01_Entry.xlsx]Book'!O17 | F17: ='[01_Entry.xlsx]Book'!N17 | G17: ='[01_Entry.xlsx]Book'!L17 | H17: ='[01_Entry.xlsx]Book'!M17 | I17: ='[01_Entry.xlsx]Book'!K17 | J17: ='[01_Entry.xlsx]Book'!P17 | K17: ='[01_Entry.xlsx]Book'!F17 | L17: ='[01_Entry.xlsx]Book'!G17 | M17: ='[01_Entry.xlsx]Book'!I17 | N17: =IF($A17="","",MID($A17,6,2)) -> 0 | O17: =IF(OR($C17="",$C17<>'Inv'!$D$12),"",N(O$16)+1) -> 0
A18: ='[01_Entry.xlsx]Book'!A18 -> 1405/07/02 | B18: ='[01_Entry.xlsx]Book'!B18 -> BS-003 | C18: ='[01_Entry.xlsx]Book'!D18 -> C006 | D18: ='[01_Entry.xlsx]Book'!E18 -> کرایه حمل ۵۰۰٬۰۰۰ | E18: ='[01_Entry.xlsx]Book'!O18 -> باغدار | F18: ='[01_Entry.xlsx]Book'!N18 -> خرید مرکبات | G18: ='[01_Entry.xlsx]Book'!L18 | H18: ='[01_Entry.xlsx]Book'!M18 -> 37848000 | I18: ='[01_Entry.xlsx]Book'!K18 -> 37848000 | J18: ='[01_Entry.xlsx]Book'!P18 | K18: ='[01_Entry.xlsx]Book'!F18 -> نارنگی اونشو | L18: ='[01_Entry.xlsx]Book'!G18 -> 85 | M18: ='[01_Entry.xlsx]Book'!I18 -> 1244.925 | N18: =IF($A18="","",MID($A18,6,2)) -> 0 | O18: =IF(OR($C18="",$C18<>'Inv'!$D$12),"",N(O$17)+1) -> 0
A19: ='[01_Entry.xlsx]Book'!A19 -> 1405/07/02 | B19: ='[01_Entry.xlsx]Book'!B19 -> BS-003 | C19: ='[01_Entry.xlsx]Book'!D19 -> X004 | D19: ='[01_Entry.xlsx]Book'!E19 -> مقابل: خرید مرکبات | E19: ='[01_Entry.xlsx]Book'!O19 -> سایر حساب | F19: ='[01_Entry.xlsx]Book'!N19 -> مقابل | G19: ='[01_Entry.xlsx]Book'!L19 -> 37848000 | H19: ='[01_Entry.xlsx]Book'!M19 | I19: ='[01_Entry.xlsx]Book'!K19 -> 37848000 | J19: ='[01_Entry.xlsx]Book'!P19 | K19: ='[01_Entry.xlsx]Book'!F19 | L19: ='[01_Entry.xlsx]Book'!G19 | M19: ='[01_Entry.xlsx]Book'!I19 | N19: =IF($A19="","",MID($A19,6,2)) -> 0 | O19: =IF(OR($C19="",$C19<>'Inv'!$D$12),"",N(O$18)+1) -> 0
A20: ='[01_Entry.xlsx]Book'!A20 | B20: ='[01_Entry.xlsx]Book'!B20 | C20: ='[01_Entry.xlsx]Book'!D20 | D20: ='[01_Entry.xlsx]Book'!E20 | E20: ='[01_Entry.xlsx]Book'!O20 | F20: ='[01_Entry.xlsx]Book'!N20 | G20: ='[01_Entry.xlsx]Book'!L20 | H20: ='[01_Entry.xlsx]Book'!M20 | I20: ='[01_Entry.xlsx]Book'!K20 | J20: ='[01_Entry.xlsx]Book'!P20 | K20: ='[01_Entry.xlsx]Book'!F20 | L20: ='[01_Entry.xlsx]Book'!G20 | M20: ='[01_Entry.xlsx]Book'!I20 | N20: =IF($A20="","",MID($A20,6,2)) -> 0 | O20: =IF(OR($C20="",$C20<>'Inv'!$D$12),"",N(O$19)+1) -> 0
A21: ='[01_Entry.xlsx]Book'!A21 | B21: ='[01_Entry.xlsx]Book'!B21 | C21: ='[01_Entry.xlsx]Book'!D21 | D21: ='[01_Entry.xlsx]Book'!E21 | E21: ='[01_Entry.xlsx]Book'!O21 | F21: ='[01_Entry.xlsx]Book'!N21 | G21: ='[01_Entry.xlsx]Book'!L21 | H21: ='[01_Entry.xlsx]Book'!M21 | I21: ='[01_Entry.xlsx]Book'!K21 | J21: ='[01_Entry.xlsx]Book'!P21 | K21: ='[01_Entry.xlsx]Book'!F21 | L21: ='[01_Entry.xlsx]Book'!G21 | M21: ='[01_Entry.xlsx]Book'!I21 | N21: =IF($A21="","",MID($A21,6,2)) -> 0 | O21: =IF(OR($C21="",$C21<>'Inv'!$D$12),"",N(O$20)+1) -> 0
A22: ='[01_Entry.xlsx]Book'!A22 -> 1405/07/02 | B22: ='[01_Entry.xlsx]Book'!B22 -> BS-004 | C22: ='[01_Entry.xlsx]Book'!D22 -> C002 | D22: ='[01_Entry.xlsx]Book'!E22 | E22: ='[01_Entry.xlsx]Book'!O22 -> باغدار | F22: ='[01_Entry.xlsx]Book'!N22 -> خرید مرکبات | G22: ='[01_Entry.xlsx]Book'!L22 | H22: ='[01_Entry.xlsx]Book'!M22 -> 20187000 | I22: ='[01_Entry.xlsx]Book'!K22 -> 20187000 | J22: ='[01_Entry.xlsx]Book'!P22 | K22: ='[01_Entry.xlsx]Book'!F22 -> پرتقال خونی | L22: ='[01_Entry.xlsx]Book'!G22 -> 36 | M22: ='[01_Entry.xlsx]Book'!I22 -> 531.234 | N22: =IF($A22="","",MID($A22,6,2)) -> 0 | O22: =IF(OR($C22="",$C22<>'Inv'!$D$12),"",N(O$21)+1) -> 0
A23: ='[01_Entry.xlsx]Book'!A23 -> 1405/07/02 | B23: ='[01_Entry.xlsx]Book'!B23 -> BS-004 | C23: ='[01_Entry.xlsx]Book'!D23 -> X004 | D23: ='[01_Entry.xlsx]Book'!E23 -> مقابل: خرید مرکبات | E23: ='[01_Entry.xlsx]Book'!O23 -> سایر حساب | F23: ='[01_Entry.xlsx]Book'!N23 -> مقابل | G23: ='[01_Entry.xlsx]Book'!L23 -> 20187000 | H23: ='[01_Entry.xlsx]Book'!M23 | I23: ='[01_Entry.xlsx]Book'!K23 -> 20187000 | J23: ='[01_Entry.xlsx]Book'!P23 | K23: ='[01_Entry.xlsx]Book'!F23 | L23: ='[01_Entry.xlsx]Book'!G23 | M23: ='[01_Entry.xlsx]Book'!I23 | N23: =IF($A23="","",MID($A23,6,2)) -> 0 | O23: =IF(OR($C23="",$C23<>'Inv'!$D$12),"",N(O$22)+1) -> 0
A24: ='[01_Entry.xlsx]Book'!A24 | B24: ='[01_Entry.xlsx]Book'!B24 | C24: ='[01_Entry.xlsx]Book'!D24 | D24: ='[01_Entry.xlsx]Book'!E24 | E24: ='[01_Entry.xlsx]Book'!O24 | F24: ='[01_Entry.xlsx]Book'!N24 | G24: ='[01_Entry.xlsx]Book'!L24 | H24: ='[01_Entry.xlsx]Book'!M24 | I24: ='[01_Entry.xlsx]Book'!K24 | J24: ='[01_Entry.xlsx]Book'!P24 | K24: ='[01_Entry.xlsx]Book'!F24 | L24: ='[01_Entry.xlsx]Book'!G24 | M24: ='[01_Entry.xlsx]Book'!I24 | N24: =IF($A24="","",MID($A24,6,2)) -> 0 | O24: =IF(OR($C24="",$C24<>'Inv'!$D$12),"",N(O$23)+1) -> 0
A25: ='[01_Entry.xlsx]Book'!A25 | B25: ='[01_Entry.xlsx]Book'!B25 | C25: ='[01_Entry.xlsx]Book'!D25 | D25: ='[01_Entry.xlsx]Book'!E25 | E25: ='[01_Entry.xlsx]Book'!O25 | F25: ='[01_Entry.xlsx]Book'!N25 | G25: ='[01_Entry.xlsx]Book'!L25 | H25: ='[01_Entry.xlsx]Book'!M25 | I25: ='[01_Entry.xlsx]Book'!K25 | J25: ='[01_Entry.xlsx]Book'!P25 | K25: ='[01_Entry.xlsx]Book'!F25 | L25: ='[01_Entry.xlsx]Book'!G25 | M25: ='[01_Entry.xlsx]Book'!I25 | N25: =IF($A25="","",MID($A25,6,2)) -> 0 | O25: =IF(OR($C25="",$C25<>'Inv'!$D$12),"",N(O$24)+1) -> 0
A26: ='[01_Entry.xlsx]Book'!A26 -> 1405/07/03 | B26: ='[01_Entry.xlsx]Book'!B26 -> BS-005 | C26: ='[01_Entry.xlsx]Book'!D26 -> C008 | D26: ='[01_Entry.xlsx]Book'!E26 | E26: ='[01_Entry.xlsx]Book'!O26 -> باغدار | F26: ='[01_Entry.xlsx]Book'!N26 -> خرید مرکبات | G26: ='[01_Entry.xlsx]Book'!L26 | H26: ='[01_Entry.xlsx]Book'!M26 -> 48110000 | I26: ='[01_Entry.xlsx]Book'!K26 -> 48110000 | J26: ='[01_Entry.xlsx]Book'!P26 | K26: ='[01_Entry.xlsx]Book'!F26 -> نارنگی ژاپنی | L26: ='[01_Entry.xlsx]Book'!G26 -> 108 | M26: ='[01_Entry.xlsx]Book'!I26 -> 1551.924 | N26: =IF($A26="","",MID($A26,6,2)) -> 0 | O26: =IF(OR($C26="",$C26<>'Inv'!$D$12),"",N(O$25)+1) -> 0
A27: ='[01_Entry.xlsx]Book'!A27 -> 1405/07/03 | B27: ='[01_Entry.xlsx]Book'!B27 -> BS-005 | C27: ='[01_Entry.xlsx]Book'!D27 -> X004 | D27: ='[01_Entry.xlsx]Book'!E27 -> مقابل: خرید مرکبات | E27: ='[01_Entry.xlsx]Book'!O27 -> سایر حساب | F27: ='[01_Entry.xlsx]Book'!N27 -> مقابل | G27: ='[01_Entry.xlsx]Book'!L27 -> 48110000 | H27: ='[01_Entry.xlsx]Book'!M27 | I27: ='[01_Entry.xlsx]Book'!K27 -> 48110000 | J27: ='[01_Entry.xlsx]Book'!P27 | K27: ='[01_Entry.xlsx]Book'!F27 | L27: ='[01_Entry.xlsx]Book'!G27 | M27: ='[01_Entry.xlsx]Book'!I27 | N27: =IF($A27="","",MID($A27,6,2)) -> 0 | O27: =IF(OR($C27="",$C27<>'Inv'!$D$12),"",N(O$26)+1) -> 0
A28: ='[01_Entry.xlsx]Book'!A28 | B28: ='[01_Entry.xlsx]Book'!B28 | C28: ='[01_Entry.xlsx]Book'!D28 | D28: ='[01_Entry.xlsx]Book'!E28 | E28: ='[01_Entry.xlsx]Book'!O28 | F28: ='[01_Entry.xlsx]Book'!N28 | G28: ='[01_Entry.xlsx]Book'!L28 | H28: ='[01_Entry.xlsx]Book'!M28 | I28: ='[01_Entry.xlsx]Book'!K28 | J28: ='[01_Entry.xlsx]Book'!P28 | K28: ='[01_Entry.xlsx]Book'!F28 | L28: ='[01_Entry.xlsx]Book'!G28 | M28: ='[01_Entry.xlsx]Book'!I28 | N28: =IF($A28="","",MID($A28,6,2)) -> 0 | O28: =IF(OR($C28="",$C28<>'Inv'!$D$12),"",N(O$27)+1) -> 0
A29: ='[01_Entry.xlsx]Book'!A29 | B29: ='[01_Entry.xlsx]Book'!B29 | C29: ='[01_Entry.xlsx]Book'!D29 | D29: ='[01_Entry.xlsx]Book'!E29 | E29: ='[01_Entry.xlsx]Book'!O29 | F29: ='[01_Entry.xlsx]Book'!N29 | G29: ='[01_Entry.xlsx]Book'!L29 | H29: ='[01_Entry.xlsx]Book'!M29 | I29: ='[01_Entry.xlsx]Book'!K29 | J29: ='[01_Entry.xlsx]Book'!P29 | K29: ='[01_Entry.xlsx]Book'!F29 | L29: ='[01_Entry.xlsx]Book'!G29 | M29: ='[01_Entry.xlsx]Book'!I29 | N29: =IF($A29="","",MID($A29,6,2)) -> 0 | O29: =IF(OR($C29="",$C29<>'Inv'!$D$12),"",N(O$28)+1) -> 0
A30: ='[01_Entry.xlsx]Book'!A30 -> 1405/07/03 | B30: ='[01_Entry.xlsx]Book'!B30 -> BS-006 | C30: ='[01_Entry.xlsx]Book'!D30 -> SL001 | D30: ='[01_Entry.xlsx]Book'!E30 -> هزینه باسکول پوز | E30: ='[01_Entry.xlsx]Book'!O30 -> بارفروش | F30: ='[01_Entry.xlsx]Book'!N30 -> فروش بار (بارفروش) | G30: ='[01_Entry.xlsx]Book'!L30 -> 145000000 | H30: ='[01_Entry.xlsx]Book'!M30 | I30: ='[01_Entry.xlsx]Book'!K30 -> 145000000 | J30: ='[01_Entry.xlsx]Book'!P30 | K30: ='[01_Entry.xlsx]Book'!F30 -> پرتقال تامسون | L30: ='[01_Entry.xlsx]Book'!G30 -> 0 | M30: ='[01_Entry.xlsx]Book'!I30 -> 2500 | N30: =IF($A30="","",MID($A30,6,2)) -> 0 | O30: =IF(OR($C30="",$C30<>'Inv'!$D$12),"",N(O$29)+1) -> 0
A31: ='[01_Entry.xlsx]Book'!A31 -> 1405/07/03 | B31: ='[01_Entry.xlsx]Book'!B31 -> BS-006 | C31: ='[01_Entry.xlsx]Book'!D31 -> X006 | D31: ='[01_Entry.xlsx]Book'!E31 -> مقابل: فروش بار (بارفروش) | E31: ='[01_Entry.xlsx]Book'!O31 -> سایر حساب | F31: ='[01_Entry.xlsx]Book'!N31 -> مقابل | G31: ='[01_Entry.xlsx]Book'!L31 | H31: ='[01_Entry.xlsx]Book'!M31 -> 145000000 | I31: ='[01_Entry.xlsx]Book'!K31 -> 145000000 | J31: ='[01_Entry.xlsx]Book'!P31 | K31: ='[01_Entry.xlsx]Book'!F31 | L31: ='[01_Entry.xlsx]Book'!G31 | M31: ='[01_Entry.xlsx]Book'!I31 | N31: =IF($A31="","",MID($A31,6,2)) -> 0 | O31: =IF(OR($C31="",$C31<>'Inv'!$D$12),"",N(O$30)+1) -> 0
A32: ='[01_Entry.xlsx]Book'!A32 -> 1405/07/03 | B32: ='[01_Entry.xlsx]Book'!B32 -> BS-006 | C32: ='[01_Entry.xlsx]Book'!D32 -> BANK02 | D32: ='[01_Entry.xlsx]Book'!E32 -> پوز باسکول — فروش بار (بارفروش) | E32: ='[01_Entry.xlsx]Book'!O32 | F32: ='[01_Entry.xlsx]Book'!N32 -> پوز | G32: ='[01_Entry.xlsx]Book'!L32 -> 120000 | H32: ='[01_Entry.xlsx]Book'!M32 | I32: ='[01_Entry.xlsx]Book'!K32 -> 120000 | J32: ='[01_Entry.xlsx]Book'!P32 | K32: ='[01_Entry.xlsx]Book'!F32 | L32: ='[01_Entry.xlsx]Book'!G32 | M32: ='[01_Entry.xlsx]Book'!I32 | N32: =IF($A32="","",MID($A32,6,2)) -> 0 | O32: =IF(OR($C32="",$C32<>'Inv'!$D$12),"",N(O$31)+1) -> 0
A33: ='[01_Entry.xlsx]Book'!A33 -> 1405/07/03 | B33: ='[01_Entry.xlsx]Book'!B33 -> BS-006 | C33: ='[01_Entry.xlsx]Book'!D33 -> X002 | D33: ='[01_Entry.xlsx]Book'!E33 -> مقابل پوز — فروش بار (بارفروش) | E33: ='[01_Entry.xlsx]Book'!O33 -> سایر حساب | F33: ='[01_Entry.xlsx]Book'!N33 -> مقابل پوز | G33: ='[01_Entry.xlsx]Book'!L33 | H33: ='[01_Entry.xlsx]Book'!M33 -> 120000 | I33: ='[01_Entry.xlsx]Book'!K33 -> 120000 | J33: ='[01_Entry.xlsx]Book'!P33 | K33: ='[01_Entry.xlsx]Book'!F33 | L33: ='[01_Entry.xlsx]Book'!G33 | M33: ='[01_Entry.xlsx]Book'!I33 | N33: =IF($A33="","",MID($A33,6,2)) -> 0 | O33: =IF(OR($C33="",$C33<>'Inv'!$D$12),"",N(O$32)+1) -> 0
A34: ='[01_Entry.xlsx]Book'!A34 -> 1405/07/04 | B34: ='[01_Entry.xlsx]Book'!B34 -> BS-007 | C34: ='[01_Entry.xlsx]Book'!D34 -> C004 | D34: ='[01_Entry.xlsx]Book'!E34 | E34: ='[01_Entry.xlsx]Book'!O34 -> باغدار | F34: ='[01_Entry.xlsx]Book'!N34 -> خرید مرکبات | G34: ='[01_Entry.xlsx]Book'!L34 | H34: ='[01_Entry.xlsx]Book'!M34 -> 19047000 | I34: ='[01_Entry.xlsx]Book'!K34 -> 19047000 | J34: ='[01_Entry.xlsx]Book'!P34 | K34: ='[01_Entry.xlsx]Book'!F34 -> نارنگی پیچ | L34: ='[01_Entry.xlsx]Book'!G34 -> 38 | M34: ='[01_Entry.xlsx]Book'!I34 -> 577.17 | N34: =IF($A34="","",MID($A34,6,2)) -> 0 | O34: =IF(OR($C34="",$C34<>'Inv'!$D$12),"",N(O$33)+1) -> 0
A35: ='[01_Entry.xlsx]Book'!A35 -> 1405/07/04 | B35: ='[01_Entry.xlsx]Book'!B35 -> BS-007 | C35: ='[01_Entry.xlsx]Book'!D35 -> X004 | D35: ='[01_Entry.xlsx]Book'!E35 -> مقابل: خرید مرکبات | E35: ='[01_Entry.xlsx]Book'!O35 -> سایر حساب | F35: ='[01_Entry.xlsx]Book'!N35 -> مقابل | G35: ='[01_Entry.xlsx]Book'!L35 -> 19047000 | H35: ='[01_Entry.xlsx]Book'!M35 | I35: ='[01_Entry.xlsx]Book'!K35 -> 19047000 | J35: ='[01_Entry.xlsx]Book'!P35 | K35: ='[01_Entry.xlsx]Book'!F35 | L35: ='[01_Entry.xlsx]Book'!G35 | M35: ='[01_Entry.xlsx]Book'!I35 | N35: =IF($A35="","",MID($A35,6,2)) -> 0 | O35: =IF(OR($C35="",$C35<>'Inv'!$D$12),"",N(O$34)+1) -> 0
A36: ='[01_Entry.xlsx]Book'!A36 | B36: ='[01_Entry.xlsx]Book'!B36 | C36: ='[01_Entry.xlsx]Book'!D36 | D36: ='[01_Entry.xlsx]Book'!E36 | E36: ='[01_Entry.xlsx]Book'!O36 | F36: ='[01_Entry.xlsx]Book'!N36 | G36: ='[01_Entry.xlsx]Book'!L36 | H36: ='[01_Entry.xlsx]Book'!M36 | I36: ='[01_Entry.xlsx]Book'!K36 | J36: ='[01_Entry.xlsx]Book'!P36 | K36: ='[01_Entry.xlsx]Book'!F36 | L36: ='[01_Entry.xlsx]Book'!G36 | M36: ='[01_Entry.xlsx]Book'!I36 | N36: =IF($A36="","",MID($A36,6,2)) -> 0 | O36: =IF(OR($C36="",$C36<>'Inv'!$D$12),"",N(O$35)+1) -> 0
A37: ='[01_Entry.xlsx]Book'!A37 | B37: ='[01_Entry.xlsx]Book'!B37 | C37: ='[01_Entry.xlsx]Book'!D37 | D37: ='[01_Entry.xlsx]Book'!E37 | E37: ='[01_Entry.xlsx]Book'!O37 | F37: ='[01_Entry.xlsx]Book'!N37 | G37: ='[01_Entry.xlsx]Book'!L37 | H37: ='[01_Entry.xlsx]Book'!M37 | I37: ='[01_Entry.xlsx]Book'!K37 | J37: ='[01_Entry.xlsx]Book'!P37 | K37: ='[01_Entry.xlsx]Book'!F37 | L37: ='[01_Entry.xlsx]Book'!G37 | M37: ='[01_Entry.xlsx]Book'!I37 | N37: =IF($A37="","",MID($A37,6,2)) -> 0 | O37: =IF(OR($C37="",$C37<>'Inv'!$D$12),"",N(O$36)+1) -> 0
A38: ='[01_Entry.xlsx]Book'!A38 -> 1405/07/04 | B38: ='[01_Entry.xlsx]Book'!B38 -> BS-008 | C38: ='[01_Entry.xlsx]Book'!D38 -> SL002 | D38: ='[01_Entry.xlsx]Book'!E38 -> هزینه باسکول پوز | E38: ='[01_Entry.xlsx]Book'!O38 -> بارفروش | F38: ='[01_Entry.xlsx]Book'!N38 -> فروش بار (بارفروش) | G38: ='[01_Entry.xlsx]Book'!L38 -> 93600000 | H38: ='[01_Entry.xlsx]Book'!M38 | I38: ='[01_Entry.xlsx]Book'!K38 -> 93600000 | J38: ='[01_Entry.xlsx]Book'!P38 | K38: ='[01_Entry.xlsx]Book'!F38 -> نارنگی اونشو | L38: ='[01_Entry.xlsx]Book'!G38 -> 0 | M38: ='[01_Entry.xlsx]Book'!I38 -> 1800 | N38: =IF($A38="","",MID($A38,6,2)) -> 0 | O38: =IF(OR($C38="",$C38<>'Inv'!$D$12),"",N(O$37)+1) -> 0
A39: ='[01_Entry.xlsx]Book'!A39 -> 1405/07/04 | B39: ='[01_Entry.xlsx]Book'!B39 -> BS-008 | C39: ='[01_Entry.xlsx]Book'!D39 -> X006 | D39: ='[01_Entry.xlsx]Book'!E39 -> مقابل: فروش بار (بارفروش) | E39: ='[01_Entry.xlsx]Book'!O39 -> سایر حساب | F39: ='[01_Entry.xlsx]Book'!N39 -> مقابل | G39: ='[01_Entry.xlsx]Book'!L39 | H39: ='[01_Entry.xlsx]Book'!M39 -> 93600000 | I39: ='[01_Entry.xlsx]Book'!K39 -> 93600000 | J39: ='[01_Entry.xlsx]Book'!P39 | K39: ='[01_Entry.xlsx]Book'!F39 | L39: ='[01_Entry.xlsx]Book'!G39 | M39: ='[01_Entry.xlsx]Book'!I39 | N39: =IF($A39="","",MID($A39,6,2)) -> 0 | O39: =IF(OR($C39="",$C39<>'Inv'!$D$12),"",N(O$38)+1) -> 0
A40: ='[01_Entry.xlsx]Book'!A40 -> 1405/07/04 | B40: ='[01_Entry.xlsx]Book'!B40 -> BS-008 | C40: ='[01_Entry.xlsx]Book'!D40 -> BANK02 | D40: ='[01_Entry.xlsx]Book'!E40 -> پوز باسکول — فروش بار (بارفروش) | E40: ='[01_Entry.xlsx]Book'!O40 | F40: ='[01_Entry.xlsx]Book'!N40 -> پوز | G40: ='[01_Entry.xlsx]Book'!L40 -> 90000 | H40: ='[01_Entry.xlsx]Book'!M40 | I40: ='[01_Entry.xlsx]Book'!K40 -> 90000 | J40: ='[01_Entry.xlsx]Book'!P40 | K40: ='[01_Entry.xlsx]Book'!F40 | L40: ='[01_Entry.xlsx]Book'!G40 | M40: ='[01_Entry.xlsx]Book'!I40 | N40: =IF($A40="","",MID($A40,6,2)) -> 0 | O40: =IF(OR($C40="",$C40<>'Inv'!$D$12),"",N(O$39)+1) -> 0
A41: ='[01_Entry.xlsx]Book'!A41 -> 1405/07/04 | B41: ='[01_Entry.xlsx]Book'!B41 -> BS-008 | C41: ='[01_Entry.xlsx]Book'!D41 -> X002 | D41: ='[01_Entry.xlsx]Book'!E41 -> مقابل پوز — فروش بار (بارفروش) | E41: ='[01_Entry.xlsx]Book'!O41 -> سایر حساب | F41: ='[01_Entry.xlsx]Book'!N41 -> مقابل پوز | G41: ='[01_Entry.xlsx]Book'!L41 | H41: ='[01_Entry.xlsx]Book'!M41 -> 90000 | I41: ='[01_Entry.xlsx]Book'!K41 -> 90000 | J41: ='[01_Entry.xlsx]Book'!P41 | K41: ='[01_Entry.xlsx]Book'!F41 | L41: ='[01_Entry.xlsx]Book'!G41 | M41: ='[01_Entry.xlsx]Book'!I41 | N41: =IF($A41="","",MID($A41,6,2)) -> 0 | O41: =IF(OR($C41="",$C41<>'Inv'!$D$12),"",N(O$40)+1) -> 0
A42: ='[01_Entry.xlsx]Book'!A42 -> 1405/07/05 | B42: ='[01_Entry.xlsx]Book'!B42 -> BS-009 | C42: ='[01_Entry.xlsx]Book'!D42 -> C007 | D42: ='[01_Entry.xlsx]Book'!E42 -> آبگیری — طرف حساب بستانکار | E42: ='[01_Entry.xlsx]Book'!O42 -> باغدار | F42: ='[01_Entry.xlsx]Book'!N42 -> آبگیری | G42: ='[01_Entry.xlsx]Book'!L42 | H42: ='[01_Entry.xlsx]Book'!M42 -> 12000000 | I42: ='[01_Entry.xlsx]Book'!K42 -> 12000000 | J42: ='[01_Entry.xlsx]Book'!P42 | K42: ='[01_Entry.xlsx]Book'!F42 -> نارنگی پیچ | L42: ='[01_Entry.xlsx]Book'!G42 -> 0 | M42: ='[01_Entry.xlsx]Book'!I42 -> 800 | N42: =IF($A42="","",MID($A42,6,2)) -> 0 | O42: =IF(OR($C42="",$C42<>'Inv'!$D$12),"",N(O$41)+1) -> 0
A43: ='[01_Entry.xlsx]Book'!A43 -> 1405/07/05 | B43: ='[01_Entry.xlsx]Book'!B43 -> BS-009 | C43: ='[01_Entry.xlsx]Book'!D43 -> X008 | D43: ='[01_Entry.xlsx]Book'!E43 -> مقابل: آبگیری | E43: ='[01_Entry.xlsx]Book'!O43 -> سایر حساب | F43: ='[01_Entry.xlsx]Book'!N43 -> مقابل | G43: ='[01_Entry.xlsx]Book'!L43 -> 12000000 | H43: ='[01_Entry.xlsx]Book'!M43 | I43: ='[01_Entry.xlsx]Book'!K43 -> 12000000 | J43: ='[01_Entry.xlsx]Book'!P43 | K43: ='[01_Entry.xlsx]Book'!F43 | L43: ='[01_Entry.xlsx]Book'!G43 | M43: ='[01_Entry.xlsx]Book'!I43 | N43: =IF($A43="","",MID($A43,6,2)) -> 0 | O43: =IF(OR($C43="",$C43<>'Inv'!$D$12),"",N(O$42)+1) -> 0
A44: ='[01_Entry.xlsx]Book'!A44 | B44: ='[01_Entry.xlsx]Book'!B44 | C44: ='[01_Entry.xlsx]Book'!D44 | D44: ='[01_Entry.xlsx]Book'!E44 | E44: ='[01_Entry.xlsx]Book'!O44 | F44: ='[01_Entry.xlsx]Book'!N44 | G44: ='[01_Entry.xlsx]Book'!L44 | H44: ='[01_Entry.xlsx]Book'!M44 | I44: ='[01_Entry.xlsx]Book'!K44 | J44: ='[01_Entry.xlsx]Book'!P44 | K44: ='[01_Entry.xlsx]Book'!F44 | L44: ='[01_Entry.xlsx]Book'!G44 | M44: ='[01_Entry.xlsx]Book'!I44 | N44: =IF($A44="","",MID($A44,6,2)) -> 0 | O44: =IF(OR($C44="",$C44<>'Inv'!$D$12),"",N(O$43)+1) -> 0
A45: ='[01_Entry.xlsx]Book'!A45 | B45: ='[01_Entry.xlsx]Book'!B45 | C45: ='[01_Entry.xlsx]Book'!D45 | D45: ='[01_Entry.xlsx]Book'!E45 | E45: ='[01_Entry.xlsx]Book'!O45 | F45: ='[01_Entry.xlsx]Book'!N45 | G45: ='[01_Entry.xlsx]Book'!L45 | H45: ='[01_Entry.xlsx]Book'!M45 | I45: ='[01_Entry.xlsx]Book'!K45 | J45: ='[01_Entry.xlsx]Book'!P45 | K45: ='[01_Entry.xlsx]Book'!F45 | L45: ='[01_Entry.xlsx]Book'!G45 | M45: ='[01_Entry.xlsx]Book'!I45 | N45: =IF($A45="","",MID($A45,6,2)) -> 0 | O45: =IF(OR($C45="",$C45<>'Inv'!$D$12),"",N(O$44)+1) -> 0
A46: ='[01_Entry.xlsx]Book'!A46 -> 1405/07/05 | B46: ='[01_Entry.xlsx]Book'!B46 -> BS-010 | C46: ='[01_Entry.xlsx]Book'!D46 -> X001 | D46: ='[01_Entry.xlsx]Book'!E46 -> انعام از پوز باسکول | E46: ='[01_Entry.xlsx]Book'!O46 -> سایر حساب | F46: ='[01_Entry.xlsx]Book'!N46 -> انعام مصطفی | G46: ='[01_Entry.xlsx]Book'!L46 | H46: ='[01_Entry.xlsx]Book'!M46 -> 500000 | I46: ='[01_Entry.xlsx]Book'!K46 -> 500000 | J46: ='[01_Entry.xlsx]Book'!P46 | K46: ='[01_Entry.xlsx]Book'!F46 -> 0 | L46: ='[01_Entry.xlsx]Book'!G46 -> 0 | M46: ='[01_Entry.xlsx]Book'!I46 -> 0 | N46: =IF($A46="","",MID($A46,6,2)) -> 0 | O46: =IF(OR($C46="",$C46<>'Inv'!$D$12),"",N(O$45)+1) -> 0
A47: ='[01_Entry.xlsx]Book'!A47 -> 1405/07/05 | B47: ='[01_Entry.xlsx]Book'!B47 -> BS-010 | C47: ='[01_Entry.xlsx]Book'!D47 -> BANK02 | D47: ='[01_Entry.xlsx]Book'!E47 -> مقابل: انعام مصطفی | E47: ='[01_Entry.xlsx]Book'!O47 | F47: ='[01_Entry.xlsx]Book'!N47 -> مقابل | G47: ='[01_Entry.xlsx]Book'!L47 -> 500000 | H47: ='[01_Entry.xlsx]Book'!M47 | I47: ='[01_Entry.xlsx]Book'!K47 -> 500000 | J47: ='[01_Entry.xlsx]Book'!P47 | K47: ='[01_Entry.xlsx]Book'!F47 | L47: ='[01_Entry.xlsx]Book'!G47 | M47: ='[01_Entry.xlsx]Book'!I47 | N47: =IF($A47="","",MID($A47,6,2)) -> 0 | O47: =IF(OR($C47="",$C47<>'Inv'!$D$12),"",N(O$46)+1) -> 0
A48: ='[01_Entry.xlsx]Book'!A48 | B48: ='[01_Entry.xlsx]Book'!B48 | C48: ='[01_Entry.xlsx]Book'!D48 | D48: ='[01_Entry.xlsx]Book'!E48 | E48: ='[01_Entry.xlsx]Book'!O48 | F48: ='[01_Entry.xlsx]Book'!N48 | G48: ='[01_Entry.xlsx]Book'!L48 | H48: ='[01_Entry.xlsx]Book'!M48 | I48: ='[01_Entry.xlsx]Book'!K48 | J48: ='[01_Entry.xlsx]Book'!P48 | K48: ='[01_Entry.xlsx]Book'!F48 | L48: ='[01_Entry.xlsx]Book'!G48 | M48: ='[01_Entry.xlsx]Book'!I48 | N48: =IF($A48="","",MID($A48,6,2)) -> 0 | O48: =IF(OR($C48="",$C48<>'Inv'!$D$12),"",N(O$47)+1) -> 0
A49: ='[01_Entry.xlsx]Book'!A49 | B49: ='[01_Entry.xlsx]Book'!B49 | C49: ='[01_Entry.xlsx]Book'!D49 | D49: ='[01_Entry.xlsx]Book'!E49 | E49: ='[01_Entry.xlsx]Book'!O49 | F49: ='[01_Entry.xlsx]Book'!N49 | G49: ='[01_Entry.xlsx]Book'!L49 | H49: ='[01_Entry.xlsx]Book'!M49 | I49: ='[01_Entry.xlsx]Book'!K49 | J49: ='[01_Entry.xlsx]Book'!P49 | K49: ='[01_Entry.xlsx]Book'!F49 | L49: ='[01_Entry.xlsx]Book'!G49 | M49: ='[01_Entry.xlsx]Book'!I49 | N49: =IF($A49="","",MID($A49,6,2)) -> 0 | O49: =IF(OR($C49="",$C49<>'Inv'!$D$12),"",N(O$48)+1) -> 0
A50: ='[01_Entry.xlsx]Book'!A50 -> 1405/07/06 | B50: ='[01_Entry.xlsx]Book'!B50 -> BS-011 | C50: ='[01_Entry.xlsx]Book'!D50 -> BD001 | D50: ='[01_Entry.xlsx]Book'!E50 -> هزینه باسکول مهمان | E50: ='[01_Entry.xlsx]Book'!O50 -> باسکول دیگران | F50: ='[01_Entry.xlsx]Book'!N50 -> باسکول دیگران | G50: ='[01_Entry.xlsx]Book'!L50 -> 150000 | H50: ='[01_Entry.xlsx]Book'!M50 | I50: ='[01_Entry.xlsx]Book'!K50 -> 150000 | J50: ='[01_Entry.xlsx]Book'!P50 | K50: ='[01_Entry.xlsx]Book'!F50 -> 0 | L50: ='[01_Entry.xlsx]Book'!G50 -> 0 | M50: ='[01_Entry.xlsx]Book'!I50 -> 0 | N50: =IF($A50="","",MID($A50,6,2)) -> 0 | O50: =IF(OR($C50="",$C50<>'Inv'!$D$12),"",N(O$49)+1) -> 0
A51: ='[01_Entry.xlsx]Book'!A51 -> 1405/07/06 | B51: ='[01_Entry.xlsx]Book'!B51 -> BS-011 | C51: ='[01_Entry.xlsx]Book'!D51 -> X002 | D51: ='[01_Entry.xlsx]Book'!E51 -> مقابل: باسکول دیگران | E51: ='[01_Entry.xlsx]Book'!O51 -> سایر حساب | F51: ='[01_Entry.xlsx]Book'!N51 -> مقابل | G51: ='[01_Entry.xlsx]Book'!L51 | H51: ='[01_Entry.xlsx]Book'!M51 -> 150000 | I51: ='[01_Entry.xlsx]Book'!K51 -> 150000 | J51: ='[01_Entry.xlsx]Book'!P51 | K51: ='[01_Entry.xlsx]Book'!F51 | L51: ='[01_Entry.xlsx]Book'!G51 | M51: ='[01_Entry.xlsx]Book'!I51 | N51: =IF($A51="","",MID($A51,6,2)) -> 0 | O51: =IF(OR($C51="",$C51<>'Inv'!$D$12),"",N(O$50)+1) -> 0
A52: ='[01_Entry.xlsx]Book'!A52 | B52: ='[01_Entry.xlsx]Book'!B52 | C52: ='[01_Entry.xlsx]Book'!D52 | D52: ='[01_Entry.xlsx]Book'!E52 | E52: ='[01_Entry.xlsx]Book'!O52 | F52: ='[01_Entry.xlsx]Book'!N52 | G52: ='[01_Entry.xlsx]Book'!L52 | H52: ='[01_Entry.xlsx]Book'!M52 | I52: ='[01_Entry.xlsx]Book'!K52 | J52: ='[01_Entry.xlsx]Book'!P52 | K52: ='[01_Entry.xlsx]Book'!F52 | L52: ='[01_Entry.xlsx]Book'!G52 | M52: ='[01_Entry.xlsx]Book'!I52 | N52: =IF($A52="","",MID($A52,6,2)) -> 0 | O52: =IF(OR($C52="",$C52<>'Inv'!$D$12),"",N(O$51)+1) -> 0
A53: ='[01_Entry.xlsx]Book'!A53 | B53: ='[01_Entry.xlsx]Book'!B53 | C53: ='[01_Entry.xlsx]Book'!D53 | D53: ='[01_Entry.xlsx]Book'!E53 | E53: ='[01_Entry.xlsx]Book'!O53 | F53: ='[01_Entry.xlsx]Book'!N53 | G53: ='[01_Entry.xlsx]Book'!L53 | H53: ='[01_Entry.xlsx]Book'!M53 | I53: ='[01_Entry.xlsx]Book'!K53 | J53: ='[01_Entry.xlsx]Book'!P53 | K53: ='[01_Entry.xlsx]Book'!F53 | L53: ='[01_Entry.xlsx]Book'!G53 | M53: ='[01_Entry.xlsx]Book'!I53 | N53: =IF($A53="","",MID($A53,6,2)) -> 0 | O53: =IF(OR($C53="",$C53<>'Inv'!$D$12),"",N(O$52)+1) -> 0
A54: ='[01_Entry.xlsx]Book'!A54 -> 1405/07/06 | B54: ='[01_Entry.xlsx]Book'!B54 -> BS-012 | C54: ='[01_Entry.xlsx]Book'!D54 -> C005 | D54: ='[01_Entry.xlsx]Book'!E54 | E54: ='[01_Entry.xlsx]Book'!O54 -> باغدار | F54: ='[01_Entry.xlsx]Book'!N54 -> خرید مرکبات | G54: ='[01_Entry.xlsx]Book'!L54 | H54: ='[01_Entry.xlsx]Book'!M54 -> 81235000 | I54: ='[01_Entry.xlsx]Book'!K54 -> 81235000 | J54: ='[01_Entry.xlsx]Book'!P54 | K54: ='[01_Entry.xlsx]Book'!F54 -> پرتقال یافا | L54: ='[01_Entry.xlsx]Book'!G54 -> 195 | M54: ='[01_Entry.xlsx]Book'!I54 -> 2801.205 | N54: =IF($A54="","",MID($A54,6,2)) -> 0 | O54: =IF(OR($C54="",$C54<>'Inv'!$D$12),"",N(O$53)+1) -> 0
A55: ='[01_Entry.xlsx]Book'!A55 -> 1405/07/06 | B55: ='[01_Entry.xlsx]Book'!B55 -> BS-012 | C55: ='[01_Entry.xlsx]Book'!D55 -> X004 | D55: ='[01_Entry.xlsx]Book'!E55 -> مقابل: خرید مرکبات | E55: ='[01_Entry.xlsx]Book'!O55 -> سایر حساب | F55: ='[01_Entry.xlsx]Book'!N55 -> مقابل | G55: ='[01_Entry.xlsx]Book'!L55 -> 81235000 | H55: ='[01_Entry.xlsx]Book'!M55 | I55: ='[01_Entry.xlsx]Book'!K55 -> 81235000 | J55: ='[01_Entry.xlsx]Book'!P55 | K55: ='[01_Entry.xlsx]Book'!F55 | L55: ='[01_Entry.xlsx]Book'!G55 | M55: ='[01_Entry.xlsx]Book'!I55 | N55: =IF($A55="","",MID($A55,6,2)) -> 0 | O55: =IF(OR($C55="",$C55<>'Inv'!$D$12),"",N(O$54)+1) -> 0
A56: ='[01_Entry.xlsx]Book'!A56 | B56: ='[01_Entry.xlsx]Book'!B56 | C56: ='[01_Entry.xlsx]Book'!D56 | D56: ='[01_Entry.xlsx]Book'!E56 | E56: ='[01_Entry.xlsx]Book'!O56 | F56: ='[01_Entry.xlsx]Book'!N56 | G56: ='[01_Entry.xlsx]Book'!L56 | H56: ='[01_Entry.xlsx]Book'!M56 | I56: ='[01_Entry.xlsx]Book'!K56 | J56: ='[01_Entry.xlsx]Book'!P56 | K56: ='[01_Entry.xlsx]Book'!F56 | L56: ='[01_Entry.xlsx]Book'!G56 | M56: ='[01_Entry.xlsx]Book'!I56 | N56: =IF($A56="","",MID($A56,6,2)) -> 0 | O56: =IF(OR($C56="",$C56<>'Inv'!$D$12),"",N(O$55)+1) -> 0
A57: ='[01_Entry.xlsx]Book'!A57 | B57: ='[01_Entry.xlsx]Book'!B57 | C57: ='[01_Entry.xlsx]Book'!D57 | D57: ='[01_Entry.xlsx]Book'!E57 | E57: ='[01_Entry.xlsx]Book'!O57 | F57: ='[01_Entry.xlsx]Book'!N57 | G57: ='[01_Entry.xlsx]Book'!L57 | H57: ='[01_Entry.xlsx]Book'!M57 | I57: ='[01_Entry.xlsx]Book'!K57 | J57: ='[01_Entry.xlsx]Book'!P57 | K57: ='[01_Entry.xlsx]Book'!F57 | L57: ='[01_Entry.xlsx]Book'!G57 | M57: ='[01_Entry.xlsx]Book'!I57 | N57: =IF($A57="","",MID($A57,6,2)) -> 0 | O57: =IF(OR($C57="",$C57<>'Inv'!$D$12),"",N(O$56)+1) -> 0
A58: ='[01_Entry.xlsx]Book'!A58 -> 1405/07/07 | B58: ='[01_Entry.xlsx]Book'!B58 -> BS-013 | C58: ='[01_Entry.xlsx]Book'!D58 -> C001 | D58: ='[01_Entry.xlsx]Book'!E58 -> برگشت ۱۲ سبد | E58: ='[01_Entry.xlsx]Book'!O58 -> باغدار | F58: ='[01_Entry.xlsx]Book'!N58 -> مرجوعی خرید | G58: ='[01_Entry.xlsx]Book'!L58 -> 6399000 | H58: ='[01_Entry.xlsx]Book'!M58 | I58: ='[01_Entry.xlsx]Book'!K58 -> 6399000 | J58: ='[01_Entry.xlsx]Book'!P58 | K58: ='[01_Entry.xlsx]Book'!F58 -> نارنگی پیچ | L58: ='[01_Entry.xlsx]Book'!G58 -> 12 | M58: ='[01_Entry.xlsx]Book'!I58 -> 199.98 | N58: =IF($A58="","",MID($A58,6,2)) -> 0 | O58: =IF(OR($C58="",$C58<>'Inv'!$D$12),"",N(O$57)+1) -> 0
A59: ='[01_Entry.xlsx]Book'!A59 -> 1405/07/07 | B59: ='[01_Entry.xlsx]Book'!B59 -> BS-013 | C59: ='[01_Entry.xlsx]Book'!D59 -> X004 | D59: ='[01_Entry.xlsx]Book'!E59 -> مقابل: مرجوعی خرید | E59: ='[01_Entry.xlsx]Book'!O59 -> سایر حساب | F59: ='[01_Entry.xlsx]Book'!N59 -> مقابل | G59: ='[01_Entry.xlsx]Book'!L59 | H59: ='[01_Entry.xlsx]Book'!M59 -> 6399000 | I59: ='[01_Entry.xlsx]Book'!K59 -> 6399000 | J59: ='[01_Entry.xlsx]Book'!P59 | K59: ='[01_Entry.xlsx]Book'!F59 | L59: ='[01_Entry.xlsx]Book'!G59 | M59: ='[01_Entry.xlsx]Book'!I59 | N59: =IF($A59="","",MID($A59,6,2)) -> 0 | O59: =IF(OR($C59="",$C59<>'Inv'!$D$12),"",N(O$58)+1) -> 0
A60: ='[01_Entry.xlsx]Book'!A60 | B60: ='[01_Entry.xlsx]Book'!B60 | C60: ='[01_Entry.xlsx]Book'!D60 | D60: ='[01_Entry.xlsx]Book'!E60 | E60: ='[01_Entry.xlsx]Book'!O60 | F60: ='[01_Entry.xlsx]Book'!N60 | G60: ='[01_Entry.xlsx]Book'!L60 | H60: ='[01_Entry.xlsx]Book'!M60 | I60: ='[01_Entry.xlsx]Book'!K60 | J60: ='[01_Entry.xlsx]Book'!P60 | K60: ='[01_Entry.xlsx]Book'!F60 | L60: ='[01_Entry.xlsx]Book'!G60 | M60: ='[01_Entry.xlsx]Book'!I60 | N60: =IF($A60="","",MID($A60,6,2)) -> 0 | O60: =IF(OR($C60="",$C60<>'Inv'!$D$12),"",N(O$59)+1) -> 0
A61: ='[01_Entry.xlsx]Book'!A61 | B61: ='[01_Entry.xlsx]Book'!B61 | C61: ='[01_Entry.xlsx]Book'!D61 | D61: ='[01_Entry.xlsx]Book'!E61 | E61: ='[01_Entry.xlsx]Book'!O61 | F61: ='[01_Entry.xlsx]Book'!N61 | G61: ='[01_Entry.xlsx]Book'!L61 | H61: ='[01_Entry.xlsx]Book'!M61 | I61: ='[01_Entry.xlsx]Book'!K61 | J61: ='[01_Entry.xlsx]Book'!P61 | K61: ='[01_Entry.xlsx]Book'!F61 | L61: ='[01_Entry.xlsx]Book'!G61 | M61: ='[01_Entry.xlsx]Book'!I61 | N61: =IF($A61="","",MID($A61,6,2)) -> 0 | O61: =IF(OR($C61="",$C61<>'Inv'!$D$12),"",N(O$60)+1) -> 0
A62: ='[01_Entry.xlsx]Book'!A62 -> 1405/07/08 | B62: ='[01_Entry.xlsx]Book'!B62 -> BS-014 | C62: ='[01_Entry.xlsx]Book'!D62 -> C009 | D62: ='[01_Entry.xlsx]Book'!E62 | E62: ='[01_Entry.xlsx]Book'!O62 -> باغدار | F62: ='[01_Entry.xlsx]Book'!N62 -> خرید مرکبات | G62: ='[01_Entry.xlsx]Book'!L62 | H62: ='[01_Entry.xlsx]Book'!M62 -> 38782000 | I62: ='[01_Entry.xlsx]Book'!K62 -> 38782000 | J62: ='[01_Entry.xlsx]Book'!P62 | K62: ='[01_Entry.xlsx]Book'!F62 -> نارنگی ژاپنی | L62: ='[01_Entry.xlsx]Book'!G62 -> 92 | M62: ='[01_Entry.xlsx]Book'!I62 -> 1271.556 | N62: =IF($A62="","",MID($A62,6,2)) -> 0 | O62: =IF(OR($C62="",$C62<>'Inv'!$D$12),"",N(O$61)+1) -> 0
A63: ='[01_Entry.xlsx]Book'!A63 -> 1405/07/08 | B63: ='[01_Entry.xlsx]Book'!B63 -> BS-014 | C63: ='[01_Entry.xlsx]Book'!D63 -> X004 | D63: ='[01_Entry.xlsx]Book'!E63 -> مقابل: خرید مرکبات | E63: ='[01_Entry.xlsx]Book'!O63 -> سایر حساب | F63: ='[01_Entry.xlsx]Book'!N63 -> مقابل | G63: ='[01_Entry.xlsx]Book'!L63 -> 38782000 | H63: ='[01_Entry.xlsx]Book'!M63 | I63: ='[01_Entry.xlsx]Book'!K63 -> 38782000 | J63: ='[01_Entry.xlsx]Book'!P63 | K63: ='[01_Entry.xlsx]Book'!F63 | L63: ='[01_Entry.xlsx]Book'!G63 | M63: ='[01_Entry.xlsx]Book'!I63 | N63: =IF($A63="","",MID($A63,6,2)) -> 0 | O63: =IF(OR($C63="",$C63<>'Inv'!$D$12),"",N(O$62)+1) -> 0
A64: ='[01_Entry.xlsx]Book'!A64 | B64: ='[01_Entry.xlsx]Book'!B64 | C64: ='[01_Entry.xlsx]Book'!D64 | D64: ='[01_Entry.xlsx]Book'!E64 | E64: ='[01_Entry.xlsx]Book'!O64 | F64: ='[01_Entry.xlsx]Book'!N64 | G64: ='[01_Entry.xlsx]Book'!L64 | H64: ='[01_Entry.xlsx]Book'!M64 | I64: ='[01_Entry.xlsx]Book'!K64 | J64: ='[01_Entry.xlsx]Book'!P64 | K64: ='[01_Entry.xlsx]Book'!F64 | L64: ='[01_Entry.xlsx]Book'!G64 | M64: ='[01_Entry.xlsx]Book'!I64 | N64: =IF($A64="","",MID($A64,6,2)) -> 0 | O64: =IF(OR($C64="",$C64<>'Inv'!$D$12),"",N(O$63)+1) -> 0
A65: ='[01_Entry.xlsx]Book'!A65 | B65: ='[01_Entry.xlsx]Book'!B65 | C65: ='[01_Entry.xlsx]Book'!D65 | D65: ='[01_Entry.xlsx]Book'!E65 | E65: ='[01_Entry.xlsx]Book'!O65 | F65: ='[01_Entry.xlsx]Book'!N65 | G65: ='[01_Entry.xlsx]Book'!L65 | H65: ='[01_Entry.xlsx]Book'!M65 | I65: ='[01_Entry.xlsx]Book'!K65 | J65: ='[01_Entry.xlsx]Book'!P65 | K65: ='[01_Entry.xlsx]Book'!F65 | L65: ='[01_Entry.xlsx]Book'!G65 | M65: ='[01_Entry.xlsx]Book'!I65 | N65: =IF($A65="","",MID($A65,6,2)) -> 0 | O65: =IF(OR($C65="",$C65<>'Inv'!$D$12),"",N(O$64)+1) -> 0
A66: ='[01_Entry.xlsx]Book'!A66 -> 1405/07/09 | B66: ='[01_Entry.xlsx]Book'!B66 -> BS-015 | C66: ='[01_Entry.xlsx]Book'!D66 -> SL001 | D66: ='[01_Entry.xlsx]Book'!E66 -> هزینه باسکول پوز | E66: ='[01_Entry.xlsx]Book'!O66 -> بارفروش | F66: ='[01_Entry.xlsx]Book'!N66 -> فروش بار (بارفروش) | G66: ='[01_Entry.xlsx]Book'!L66 -> 96000000 | H66: ='[01_Entry.xlsx]Book'!M66 | I66: ='[01_Entry.xlsx]Book'!K66 -> 96000000 | J66: ='[01_Entry.xlsx]Book'!P66 | K66: ='[01_Entry.xlsx]Book'!F66 -> پرتقال تامسون | L66: ='[01_Entry.xlsx]Book'!G66 -> 0 | M66: ='[01_Entry.xlsx]Book'!I66 -> 1600 | N66: =IF($A66="","",MID($A66,6,2)) -> 0 | O66: =IF(OR($C66="",$C66<>'Inv'!$D$12),"",N(O$65)+1) -> 0
A67: ='[01_Entry.xlsx]Book'!A67 -> 1405/07/09 | B67: ='[01_Entry.xlsx]Book'!B67 -> BS-015 | C67: ='[01_Entry.xlsx]Book'!D67 -> X006 | D67: ='[01_Entry.xlsx]Book'!E67 -> مقابل: فروش بار (بارفروش) | E67: ='[01_Entry.xlsx]Book'!O67 -> سایر حساب | F67: ='[01_Entry.xlsx]Book'!N67 -> مقابل | G67: ='[01_Entry.xlsx]Book'!L67 | H67: ='[01_Entry.xlsx]Book'!M67 -> 96000000 | I67: ='[01_Entry.xlsx]Book'!K67 -> 96000000 | J67: ='[01_Entry.xlsx]Book'!P67 | K67: ='[01_Entry.xlsx]Book'!F67 | L67: ='[01_Entry.xlsx]Book'!G67 | M67: ='[01_Entry.xlsx]Book'!I67 | N67: =IF($A67="","",MID($A67,6,2)) -> 0 | O67: =IF(OR($C67="",$C67<>'Inv'!$D$12),"",N(O$66)+1) -> 0
A68: ='[01_Entry.xlsx]Book'!A68 -> 1405/07/09 | B68: ='[01_Entry.xlsx]Book'!B68 -> BS-015 | C68: ='[01_Entry.xlsx]Book'!D68 -> BANK02 | D68: ='[01_Entry.xlsx]Book'!E68 -> پوز باسکول — فروش بار (بارفروش) | E68: ='[01_Entry.xlsx]Book'!O68 | F68: ='[01_Entry.xlsx]Book'!N68 -> پوز | G68: ='[01_Entry.xlsx]Book'!L68 -> 80000 | H68: ='[01_Entry.xlsx]Book'!M68 | I68: ='[01_Entry.xlsx]Book'!K68 -> 80000 | J68: ='[01_Entry.xlsx]Book'!P68 | K68: ='[01_Entry.xlsx]Book'!F68 | L68: ='[01_Entry.xlsx]Book'!G68 | M68: ='[01_Entry.xlsx]Book'!I68 | N68: =IF($A68="","",MID($A68,6,2)) -> 0 | O68: =IF(OR($C68="",$C68<>'Inv'!$D$12),"",N(O$67)+1) -> 0
A69: ='[01_Entry.xlsx]Book'!A69 -> 1405/07/09 | B69: ='[01_Entry.xlsx]Book'!B69 -> BS-015 | C69: ='[01_Entry.xlsx]Book'!D69 -> X002 | D69: ='[01_Entry.xlsx]Book'!E69 -> مقابل پوز — فروش بار (بارفروش) | E69: ='[01_Entry.xlsx]Book'!O69 -> سایر حساب | F69: ='[01_Entry.xlsx]Book'!N69 -> مقابل پوز | G69: ='[01_Entry.xlsx]Book'!L69 | H69: ='[01_Entry.xlsx]Book'!M69 -> 80000 | I69: ='[01_Entry.xlsx]Book'!K69 -> 80000 | J69: ='[01_Entry.xlsx]Book'!P69 | K69: ='[01_Entry.xlsx]Book'!F69 | L69: ='[01_Entry.xlsx]Book'!G69 | M69: ='[01_Entry.xlsx]Book'!I69 | N69: =IF($A69="","",MID($A69,6,2)) -> 0 | O69: =IF(OR($C69="",$C69<>'Inv'!$D$12),"",N(O$68)+1) -> 0
A70: ='[01_Entry.xlsx]Book'!A70 -> 1405/07/10 | B70: ='[01_Entry.xlsx]Book'!B70 -> BS-016 | C70: ='[01_Entry.xlsx]Book'!D70 -> C010 | D70: ='[01_Entry.xlsx]Book'!E70 | E70: ='[01_Entry.xlsx]Book'!O70 -> باغدار | F70: ='[01_Entry.xlsx]Book'!N70 -> خرید مرکبات | G70: ='[01_Entry.xlsx]Book'!L70 | H70: ='[01_Entry.xlsx]Book'!M70 -> 29930000 | I70: ='[01_Entry.xlsx]Book'!K70 -> 29930000 | J70: ='[01_Entry.xlsx]Book'!P70 | K70: ='[01_Entry.xlsx]Book'!F70 -> پرتقال کاراکارا | L70: ='[01_Entry.xlsx]Book'!G70 -> 58 | M70: ='[01_Entry.xlsx]Book'!I70 -> 831.402 | N70: =IF($A70="","",MID($A70,6,2)) -> 0 | O70: =IF(OR($C70="",$C70<>'Inv'!$D$12),"",N(O$69)+1) -> 0
A71: ='[01_Entry.xlsx]Book'!A71 -> 1405/07/10 | B71: ='[01_Entry.xlsx]Book'!B71 -> BS-016 | C71: ='[01_Entry.xlsx]Book'!D71 -> X004 | D71: ='[01_Entry.xlsx]Book'!E71 -> مقابل: خرید مرکبات | E71: ='[01_Entry.xlsx]Book'!O71 -> سایر حساب | F71: ='[01_Entry.xlsx]Book'!N71 -> مقابل | G71: ='[01_Entry.xlsx]Book'!L71 -> 29930000 | H71: ='[01_Entry.xlsx]Book'!M71 | I71: ='[01_Entry.xlsx]Book'!K71 -> 29930000 | J71: ='[01_Entry.xlsx]Book'!P71 | K71: ='[01_Entry.xlsx]Book'!F71 | L71: ='[01_Entry.xlsx]Book'!G71 | M71: ='[01_Entry.xlsx]Book'!I71 | N71: =IF($A71="","",MID($A71,6,2)) -> 0 | O71: =IF(OR($C71="",$C71<>'Inv'!$D$12),"",N(O$70)+1) -> 0
A72: ='[01_Entry.xlsx]Book'!A72 | B72: ='[01_Entry.xlsx]Book'!B72 | C72: ='[01_Entry.xlsx]Book'!D72 | D72: ='[01_Entry.xlsx]Book'!E72 | E72: ='[01_Entry.xlsx]Book'!O72 | F72: ='[01_Entry.xlsx]Book'!N72 | G72: ='[01_Entry.xlsx]Book'!L72 | H72: ='[01_Entry.xlsx]Book'!M72 | I72: ='[01_Entry.xlsx]Book'!K72 | J72: ='[01_Entry.xlsx]Book'!P72 | K72: ='[01_Entry.xlsx]Book'!F72 | L72: ='[01_Entry.xlsx]Book'!G72 | M72: ='[01_Entry.xlsx]Book'!I72 | N72: =IF($A72="","",MID($A72,6,2)) -> 0 | O72: =IF(OR($C72="",$C72<>'Inv'!$D$12),"",N(O$71)+1) -> 0
A73: ='[01_Entry.xlsx]Book'!A73 | B73: ='[01_Entry.xlsx]Book'!B73 | C73: ='[01_Entry.xlsx]Book'!D73 | D73: ='[01_Entry.xlsx]Book'!E73 | E73: ='[01_Entry.xlsx]Book'!O73 | F73: ='[01_Entry.xlsx]Book'!N73 | G73: ='[01_Entry.xlsx]Book'!L73 | H73: ='[01_Entry.xlsx]Book'!M73 | I73: ='[01_Entry.xlsx]Book'!K73 | J73: ='[01_Entry.xlsx]Book'!P73 | K73: ='[01_Entry.xlsx]Book'!F73 | L73: ='[01_Entry.xlsx]Book'!G73 | M73: ='[01_Entry.xlsx]Book'!I73 | N73: =IF($A73="","",MID($A73,6,2)) -> 0 | O73: =IF(OR($C73="",$C73<>'Inv'!$D$12),"",N(O$72)+1) -> 0
A74: ='[01_Entry.xlsx]Book'!A74 -> 1405/07/11 | B74: ='[01_Entry.xlsx]Book'!B74 -> BS-017 | C74: ='[01_Entry.xlsx]Book'!D74 | D74: ='[01_Entry.xlsx]Book'!E74 -> هزینه باسکول نقدی | E74: ='[01_Entry.xlsx]Book'!O74 | F74: ='[01_Entry.xlsx]Book'!N74 -> درآمد پوز باسکول (بدون طرف) | G74: ='[01_Entry.xlsx]Book'!L74 | H74: ='[01_Entry.xlsx]Book'!M74 | I74: ='[01_Entry.xlsx]Book'!K74 -> 0 | J74: ='[01_Entry.xlsx]Book'!P74 | K74: ='[01_Entry.xlsx]Book'!F74 -> 0 | L74: ='[01_Entry.xlsx]Book'!G74 -> 0 | M74: ='[01_Entry.xlsx]Book'!I74 -> 0 | N74: =IF($A74="","",MID($A74,6,2)) -> 0 | O74: =IF(OR($C74="",$C74<>'Inv'!$D$12),"",N(O$73)+1) -> 0
A75: ='[01_Entry.xlsx]Book'!A75 -> 1405/07/11 | B75: ='[01_Entry.xlsx]Book'!B75 -> BS-017 | C75: ='[01_Entry.xlsx]Book'!D75 | D75: ='[01_Entry.xlsx]Book'!E75 -> مقابل: درآمد پوز باسکول (بدون طرف) | E75: ='[01_Entry.xlsx]Book'!O75 | F75: ='[01_Entry.xlsx]Book'!N75 -> مقابل | G75: ='[01_Entry.xlsx]Book'!L75 | H75: ='[01_Entry.xlsx]Book'!M75 | I75: ='[01_Entry.xlsx]Book'!K75 -> 0 | J75: ='[01_Entry.xlsx]Book'!P75 | K75: ='[01_Entry.xlsx]Book'!F75 | L75: ='[01_Entry.xlsx]Book'!G75 | M75: ='[01_Entry.xlsx]Book'!I75 | N75: =IF($A75="","",MID($A75,6,2)) -> 0 | O75: =IF(OR($C75="",$C75<>'Inv'!$D$12),"",N(O$74)+1) -> 0
A76: ='[01_Entry.xlsx]Book'!A76 -> 1405/07/11 | B76: ='[01_Entry.xlsx]Book'!B76 -> BS-017 | C76: ='[01_Entry.xlsx]Book'!D76 -> BANK02 | D76: ='[01_Entry.xlsx]Book'!E76 -> پوز باسکول — درآمد پوز باسکول (بدون طرف) | E76: ='[01_Entry.xlsx]Book'!O76 | F76: ='[01_Entry.xlsx]Book'!N76 -> پوز | G76: ='[01_Entry.xlsx]Book'!L76 -> 300000 | H76: ='[01_Entry.xlsx]Book'!M76 | I76: ='[01_Entry.xlsx]Book'!K76 -> 300000 | J76: ='[01_Entry.xlsx]Book'!P76 | K76: ='[01_Entry.xlsx]Book'!F76 | L76: ='[01_Entry.xlsx]Book'!G76 | M76: ='[01_Entry.xlsx]Book'!I76 | N76: =IF($A76="","",MID($A76,6,2)) -> 0 | O76: =IF(OR($C76="",$C76<>'Inv'!$D$12),"",N(O$75)+1) -> 0
A77: ='[01_Entry.xlsx]Book'!A77 -> 1405/07/11 | B77: ='[01_Entry.xlsx]Book'!B77 -> BS-017 | C77: ='[01_Entry.xlsx]Book'!D77 -> X002 | D77: ='[01_Entry.xlsx]Book'!E77 -> مقابل پوز — درآمد پوز باسکول (بدون طرف) | E77: ='[01_Entry.xlsx]Book'!O77 -> سایر حساب | F77: ='[01_Entry.xlsx]Book'!N77 -> مقابل پوز | G77: ='[01_Entry.xlsx]Book'!L77 | H77: ='[01_Entry.xlsx]Book'!M77 -> 300000 | I77: ='[01_Entry.xlsx]Book'!K77 -> 300000 | J77: ='[01_Entry.xlsx]Book'!P77 | K77: ='[01_Entry.xlsx]Book'!F77 | L77: ='[01_Entry.xlsx]Book'!G77 | M77: ='[01_Entry.xlsx]Book'!I77 | N77: =IF($A77="","",MID($A77,6,2)) -> 0 | O77: =IF(OR($C77="",$C77<>'Inv'!$D$12),"",N(O$76)+1) -> 0
A78: ='[01_Entry.xlsx]Book'!A78 -> 1405/07/12 | B78: ='[01_Entry.xlsx]Book'!B78 -> BS-018 | C78: ='[01_Entry.xlsx]Book'!D78 -> C011 | D78: ='[01_Entry.xlsx]Book'!E78 | E78: ='[01_Entry.xlsx]Book'!O78 -> باغدار | F78: ='[01_Entry.xlsx]Book'!N78 -> خرید مرکبات | G78: ='[01_Entry.xlsx]Book'!L78 | H78: ='[01_Entry.xlsx]Book'!M78 -> 36757000 | I78: ='[01_Entry.xlsx]Book'!K78 -> 36757000 | J78: ='[01_Entry.xlsx]Book'!P78 | K78: ='[01_Entry.xlsx]Book'!F78 -> پرتقال بیروتی | L78: ='[01_Entry.xlsx]Book'!G78 -> 72 | M78: ='[01_Entry.xlsx]Book'!I78 -> 1081.08 | N78: =IF($A78="","",MID($A78,6,2)) -> 0 | O78: =IF(OR($C78="",$C78<>'Inv'!$D$12),"",N(O$77)+1) -> 0
A79: ='[01_Entry.xlsx]Book'!A79 -> 1405/07/12 | B79: ='[01_Entry.xlsx]Book'!B79 -> BS-018 | C79: ='[01_Entry.xlsx]Book'!D79 -> X004 | D79: ='[01_Entry.xlsx]Book'!E79 -> مقابل: خرید مرکبات | E79: ='[01_Entry.xlsx]Book'!O79 -> سایر حساب | F79: ='[01_Entry.xlsx]Book'!N79 -> مقابل | G79: ='[01_Entry.xlsx]Book'!L79 -> 36757000 | H79: ='[01_Entry.xlsx]Book'!M79 | I79: ='[01_Entry.xlsx]Book'!K79 -> 36757000 | J79: ='[01_Entry.xlsx]Book'!P79 | K79: ='[01_Entry.xlsx]Book'!F79 | L79: ='[01_Entry.xlsx]Book'!G79 | M79: ='[01_Entry.xlsx]Book'!I79 | N79: =IF($A79="","",MID($A79,6,2)) -> 0 | O79: =IF(OR($C79="",$C79<>'Inv'!$D$12),"",N(O$78)+1) -> 0
A80: ='[01_Entry.xlsx]Book'!A80 | B80: ='[01_Entry.xlsx]Book'!B80 | C80: ='[01_Entry.xlsx]Book'!D80 | D80: ='[01_Entry.xlsx]Book'!E80 | E80: ='[01_Entry.xlsx]Book'!O80 | F80: ='[01_Entry.xlsx]Book'!N80 | G80: ='[01_Entry.xlsx]Book'!L80 | H80: ='[01_Entry.xlsx]Book'!M80 | I80: ='[01_Entry.xlsx]Book'!K80 | J80: ='[01_Entry.xlsx]Book'!P80 | K80: ='[01_Entry.xlsx]Book'!F80 | L80: ='[01_Entry.xlsx]Book'!G80 | M80: ='[01_Entry.xlsx]Book'!I80 | N80: =IF($A80="","",MID($A80,6,2)) -> 0 | O80: =IF(OR($C80="",$C80<>'Inv'!$D$12),"",N(O$79)+1) -> 0
A81: ='[01_Entry.xlsx]Book'!A81 | B81: ='[01_Entry.xlsx]Book'!B81 | C81: ='[01_Entry.xlsx]Book'!D81 | D81: ='[01_Entry.xlsx]Book'!E81 | E81: ='[01_Entry.xlsx]Book'!O81 | F81: ='[01_Entry.xlsx]Book'!N81 | G81: ='[01_Entry.xlsx]Book'!L81 | H81: ='[01_Entry.xlsx]Book'!M81 | I81: ='[01_Entry.xlsx]Book'!K81 | J81: ='[01_Entry.xlsx]Book'!P81 | K81: ='[01_Entry.xlsx]Book'!F81 | L81: ='[01_Entry.xlsx]Book'!G81 | M81: ='[01_Entry.xlsx]Book'!I81 | N81: =IF($A81="","",MID($A81,6,2)) -> 0 | O81: =IF(OR($C81="",$C81<>'Inv'!$D$12),"",N(O$80)+1) -> 0
A82: ='[01_Entry.xlsx]Book'!A82 | B82: ='[01_Entry.xlsx]Book'!B82 | C82: ='[01_Entry.xlsx]Book'!D82 | D82: ='[01_Entry.xlsx]Book'!E82 | E82: ='[01_Entry.xlsx]Book'!O82 | F82: ='[01_Entry.xlsx]Book'!N82 | G82: ='[01_Entry.xlsx]Book'!L82 | H82: ='[01_Entry.xlsx]Book'!M82 | I82: ='[01_Entry.xlsx]Book'!K82 | J82: ='[01_Entry.xlsx]Book'!P82 | K82: ='[01_Entry.xlsx]Book'!F82 | L82: ='[01_Entry.xlsx]Book'!G82 | M82: ='[01_Entry.xlsx]Book'!I82 | N82: =IF($A82="","",MID($A82,6,2)) -> 0 | O82: =IF(OR($C82="",$C82<>'Inv'!$D$12),"",N(O$81)+1) -> 0
A83: ='[01_Entry.xlsx]Book'!A83 | B83: ='[01_Entry.xlsx]Book'!B83 | C83: ='[01_Entry.xlsx]Book'!D83 | D83: ='[01_Entry.xlsx]Book'!E83 | E83: ='[01_Entry.xlsx]Book'!O83 | F83: ='[01_Entry.xlsx]Book'!N83 | G83: ='[01_Entry.xlsx]Book'!L83 | H83: ='[01_Entry.xlsx]Book'!M83 | I83: ='[01_Entry.xlsx]Book'!K83 | J83: ='[01_Entry.xlsx]Book'!P83 | K83: ='[01_Entry.xlsx]Book'!F83 | L83: ='[01_Entry.xlsx]Book'!G83 | M83: ='[01_Entry.xlsx]Book'!I83 | N83: =IF($A83="","",MID($A83,6,2)) -> 0 | O83: =IF(OR($C83="",$C83<>'Inv'!$D$12),"",N(O$82)+1) -> 0
A84: ='[01_Entry.xlsx]Book'!A84 | B84: ='[01_Entry.xlsx]Book'!B84 | C84: ='[01_Entry.xlsx]Book'!D84 | D84: ='[01_Entry.xlsx]Book'!E84 | E84: ='[01_Entry.xlsx]Book'!O84 | F84: ='[01_Entry.xlsx]Book'!N84 | G84: ='[01_Entry.xlsx]Book'!L84 | H84: ='[01_Entry.xlsx]Book'!M84 | I84: ='[01_Entry.xlsx]Book'!K84 | J84: ='[01_Entry.xlsx]Book'!P84 | K84: ='[01_Entry.xlsx]Book'!F84 | L84: ='[01_Entry.xlsx]Book'!G84 | M84: ='[01_Entry.xlsx]Book'!I84 | N84: =IF($A84="","",MID($A84,6,2)) -> 0 | O84: =IF(OR($C84="",$C84<>'Inv'!$D$12),"",N(O$83)+1) -> 0
A85: ='[01_Entry.xlsx]Book'!A85 | B85: ='[01_Entry.xlsx]Book'!B85 | C85: ='[01_Entry.xlsx]Book'!D85 | D85: ='[01_Entry.xlsx]Book'!E85 | E85: ='[01_Entry.xlsx]Book'!O85 | F85: ='[01_Entry.xlsx]Book'!N85 | G85: ='[01_Entry.xlsx]Book'!L85 | H85: ='[01_Entry.xlsx]Book'!M85 | I85: ='[01_Entry.xlsx]Book'!K85 | J85: ='[01_Entry.xlsx]Book'!P85 | K85: ='[01_Entry.xlsx]Book'!F85 | L85: ='[01_Entry.xlsx]Book'!G85 | M85: ='[01_Entry.xlsx]Book'!I85 | N85: =IF($A85="","",MID($A85,6,2)) -> 0 | O85: =IF(OR($C85="",$C85<>'Inv'!$D$12),"",N(O$84)+1) -> 0
A86: ='[01_Entry.xlsx]Book'!A86 | B86: ='[01_Entry.xlsx]Book'!B86 | C86: ='[01_Entry.xlsx]Book'!D86 | D86: ='[01_Entry.xlsx]Book'!E86 | E86: ='[01_Entry.xlsx]Book'!O86 | F86: ='[01_Entry.xlsx]Book'!N86 | G86: ='[01_Entry.xlsx]Book'!L86 | H86: ='[01_Entry.xlsx]Book'!M86 | I86: ='[01_Entry.xlsx]Book'!K86 | J86: ='[01_Entry.xlsx]Book'!P86 | K86: ='[01_Entry.xlsx]Book'!F86 | L86: ='[01_Entry.xlsx]Book'!G86 | M86: ='[01_Entry.xlsx]Book'!I86 | N86: =IF($A86="","",MID($A86,6,2)) -> 0 | O86: =IF(OR($C86="",$C86<>'Inv'!$D$12),"",N(O$85)+1) -> 0
A87: ='[01_Entry.xlsx]Book'!A87 | B87: ='[01_Entry.xlsx]Book'!B87 | C87: ='[01_Entry.xlsx]Book'!D87 | D87: ='[01_Entry.xlsx]Book'!E87 | E87: ='[01_Entry.xlsx]Book'!O87 | F87: ='[01_Entry.xlsx]Book'!N87 | G87: ='[01_Entry.xlsx]Book'!L87 | H87: ='[01_Entry.xlsx]Book'!M87 | I87: ='[01_Entry.xlsx]Book'!K87 | J87: ='[01_Entry.xlsx]Book'!P87 | K87: ='[01_Entry.xlsx]Book'!F87 | L87: ='[01_Entry.xlsx]Book'!G87 | M87: ='[01_Entry.xlsx]Book'!I87 | N87: =IF($A87="","",MID($A87,6,2)) -> 0 | O87: =IF(OR($C87="",$C87<>'Inv'!$D$12),"",N(O$86)+1) -> 0
A88: ='[01_Entry.xlsx]Book'!A88 | B88: ='[01_Entry.xlsx]Book'!B88 | C88: ='[01_Entry.xlsx]Book'!D88 | D88: ='[01_Entry.xlsx]Book'!E88 | E88: ='[01_Entry.xlsx]Book'!O88 | F88: ='[01_Entry.xlsx]Book'!N88 | G88: ='[01_Entry.xlsx]Book'!L88 | H88: ='[01_Entry.xlsx]Book'!M88 | I88: ='[01_Entry.xlsx]Book'!K88 | J88: ='[01_Entry.xlsx]Book'!P88 | K88: ='[01_Entry.xlsx]Book'!F88 | L88: ='[01_Entry.xlsx]Book'!G88 | M88: ='[01_Entry.xlsx]Book'!I88 | N88: =IF($A88="","",MID($A88,6,2)) -> 0 | O88: =IF(OR($C88="",$C88<>'Inv'!$D$12),"",N(O$87)+1) -> 0
A89: ='[01_Entry.xlsx]Book'!A89 | B89: ='[01_Entry.xlsx]Book'!B89 | C89: ='[01_Entry.xlsx]Book'!D89 | D89: ='[01_Entry.xlsx]Book'!E89 | E89: ='[01_Entry.xlsx]Book'!O89 | F89: ='[01_Entry.xlsx]Book'!N89 | G89: ='[01_Entry.xlsx]Book'!L89 | H89: ='[01_Entry.xlsx]Book'!M89 | I89: ='[01_Entry.xlsx]Book'!K89 | J89: ='[01_Entry.xlsx]Book'!P89 | K89: ='[01_Entry.xlsx]Book'!F89 | L89: ='[01_Entry.xlsx]Book'!G89 | M89: ='[01_Entry.xlsx]Book'!I89 | N89: =IF($A89="","",MID($A89,6,2)) -> 0 | O89: =IF(OR($C89="",$C89<>'Inv'!$D$12),"",N(O$88)+1) -> 0
A90: ='[01_Entry.xlsx]Book'!A90 | B90: ='[01_Entry.xlsx]Book'!B90 | C90: ='[01_Entry.xlsx]Book'!D90 | D90: ='[01_Entry.xlsx]Book'!E90 | E90: ='[01_Entry.xlsx]Book'!O90 | F90: ='[01_Entry.xlsx]Book'!N90 | G90: ='[01_Entry.xlsx]Book'!L90 | H90: ='[01_Entry.xlsx]Book'!M90 | I90: ='[01_Entry.xlsx]Book'!K90 | J90: ='[01_Entry.xlsx]Book'!P90 | K90: ='[01_Entry.xlsx]Book'!F90 | L90: ='[01_Entry.xlsx]Book'!G90 | M90: ='[01_Entry.xlsx]Book'!I90 | N90: =IF($A90="","",MID($A90,6,2)) -> 0 | O90: =IF(OR($C90="",$C90<>'Inv'!$D$12),"",N(O$89)+1) -> 0
A91: ='[01_Entry.xlsx]Book'!A91 | B91: ='[01_Entry.xlsx]Book'!B91 | C91: ='[01_Entry.xlsx]Book'!D91 | D91: ='[01_Entry.xlsx]Book'!E91 | E91: ='[01_Entry.xlsx]Book'!O91 | F91: ='[01_Entry.xlsx]Book'!N91 | G91: ='[01_Entry.xlsx]Book'!L91 | H91: ='[01_Entry.xlsx]Book'!M91 | I91: ='[01_Entry.xlsx]Book'!K91 | J91: ='[01_Entry.xlsx]Book'!P91 | K91: ='[01_Entry.xlsx]Book'!F91 | L91: ='[01_Entry.xlsx]Book'!G91 | M91: ='[01_Entry.xlsx]Book'!I91 | N91: =IF($A91="","",MID($A91,6,2)) -> 0 | O91: =IF(OR($C91="",$C91<>'Inv'!$D$12),"",N(O$90)+1) -> 0
A92: ='[01_Entry.xlsx]Book'!A92 | B92: ='[01_Entry.xlsx]Book'!B92 | C92: ='[01_Entry.xlsx]Book'!D92 | D92: ='[01_Entry.xlsx]Book'!E92 | E92: ='[01_Entry.xlsx]Book'!O92 | F92: ='[01_Entry.xlsx]Book'!N92 | G92: ='[01_Entry.xlsx]Book'!L92 | H92: ='[01_Entry.xlsx]Book'!M92 | I92: ='[01_Entry.xlsx]Book'!K92 | J92: ='[01_Entry.xlsx]Book'!P92 | K92: ='[01_Entry.xlsx]Book'!F92 | L92: ='[01_Entry.xlsx]Book'!G92 | M92: ='[01_Entry.xlsx]Book'!I92 | N92: =IF($A92="","",MID($A92,6,2)) -> 0 | O92: =IF(OR($C92="",$C92<>'Inv'!$D$12),"",N(O$91)+1) -> 0
A93: ='[01_Entry.xlsx]Book'!A93 | B93: ='[01_Entry.xlsx]Book'!B93 | C93: ='[01_Entry.xlsx]Book'!D93 | D93: ='[01_Entry.xlsx]Book'!E93 | E93: ='[01_Entry.xlsx]Book'!O93 | F93: ='[01_Entry.xlsx]Book'!N93 | G93: ='[01_Entry.xlsx]Book'!L93 | H93: ='[01_Entry.xlsx]Book'!M93 | I93: ='[01_Entry.xlsx]Book'!K93 | J93: ='[01_Entry.xlsx]Book'!P93 | K93: ='[01_Entry.xlsx]Book'!F93 | L93: ='[01_Entry.xlsx]Book'!G93 | M93: ='[01_Entry.xlsx]Book'!I93 | N93: =IF($A93="","",MID($A93,6,2)) -> 0 | O93: =IF(OR($C93="",$C93<>'Inv'!$D$12),"",N(O$92)+1) -> 0
A94: ='[01_Entry.xlsx]Book'!A94 | B94: ='[01_Entry.xlsx]Book'!B94 | C94: ='[01_Entry.xlsx]Book'!D94 | D94: ='[01_Entry.xlsx]Book'!E94 | E94: ='[01_Entry.xlsx]Book'!O94 | F94: ='[01_Entry.xlsx]Book'!N94 | G94: ='[01_Entry.xlsx]Book'!L94 | H94: ='[01_Entry.xlsx]Book'!M94 | I94: ='[01_Entry.xlsx]Book'!K94 | J94: ='[01_Entry.xlsx]Book'!P94 | K94: ='[01_Entry.xlsx]Book'!F94 | L94: ='[01_Entry.xlsx]Book'!G94 | M94: ='[01_Entry.xlsx]Book'!I94 | N94: =IF($A94="","",MID($A94,6,2)) -> 0 | O94: =IF(OR($C94="",$C94<>'Inv'!$D$12),"",N(O$93)+1) -> 0
A95: ='[01_Entry.xlsx]Book'!A95 | B95: ='[01_Entry.xlsx]Book'!B95 | C95: ='[01_Entry.xlsx]Book'!D95 | D95: ='[01_Entry.xlsx]Book'!E95 | E95: ='[01_Entry.xlsx]Book'!O95 | F95: ='[01_Entry.xlsx]Book'!N95 | G95: ='[01_Entry.xlsx]Book'!L95 | H95: ='[01_Entry.xlsx]Book'!M95 | I95: ='[01_Entry.xlsx]Book'!K95 | J95: ='[01_Entry.xlsx]Book'!P95 | K95: ='[01_Entry.xlsx]Book'!F95 | L95: ='[01_Entry.xlsx]Book'!G95 | M95: ='[01_Entry.xlsx]Book'!I95 | N95: =IF($A95="","",MID($A95,6,2)) -> 0 | O95: =IF(OR($C95="",$C95<>'Inv'!$D$12),"",N(O$94)+1) -> 0
A96: ='[01_Entry.xlsx]Book'!A96 | B96: ='[01_Entry.xlsx]Book'!B96 | C96: ='[01_Entry.xlsx]Book'!D96 | D96: ='[01_Entry.xlsx]Book'!E96 | E96: ='[01_Entry.xlsx]Book'!O96 | F96: ='[01_Entry.xlsx]Book'!N96 | G96: ='[01_Entry.xlsx]Book'!L96 | H96: ='[01_Entry.xlsx]Book'!M96 | I96: ='[01_Entry.xlsx]Book'!K96 | J96: ='[01_Entry.xlsx]Book'!P96 | K96: ='[01_Entry.xlsx]Book'!F96 | L96: ='[01_Entry.xlsx]Book'!G96 | M96: ='[01_Entry.xlsx]Book'!I96 | N96: =IF($A96="","",MID($A96,6,2)) -> 0 | O96: =IF(OR($C96="",$C96<>'Inv'!$D$12),"",N(O$95)+1) -> 0
A97: ='[01_Entry.xlsx]Book'!A97 | B97: ='[01_Entry.xlsx]Book'!B97 | C97: ='[01_Entry.xlsx]Book'!D97 | D97: ='[01_Entry.xlsx]Book'!E97 | E97: ='[01_Entry.xlsx]Book'!O97 | F97: ='[01_Entry.xlsx]Book'!N97 | G97: ='[01_Entry.xlsx]Book'!L97 | H97: ='[01_Entry.xlsx]Book'!M97 | I97: ='[01_Entry.xlsx]Book'!K97 | J97: ='[01_Entry.xlsx]Book'!P97 | K97: ='[01_Entry.xlsx]Book'!F97 | L97: ='[01_Entry.xlsx]Book'!G97 | M97: ='[01_Entry.xlsx]Book'!I97 | N97: =IF($A97="","",MID($A97,6,2)) -> 0 | O97: =IF(OR($C97="",$C97<>'Inv'!$D$12),"",N(O$96)+1) -> 0
A98: ='[01_Entry.xlsx]Book'!A98 | B98: ='[01_Entry.xlsx]Book'!B98 | C98: ='[01_Entry.xlsx]Book'!D98 | D98: ='[01_Entry.xlsx]Book'!E98 | E98: ='[01_Entry.xlsx]Book'!O98 | F98: ='[01_Entry.xlsx]Book'!N98 | G98: ='[01_Entry.xlsx]Book'!L98 | H98: ='[01_Entry.xlsx]Book'!M98 | I98: ='[01_Entry.xlsx]Book'!K98 | J98: ='[01_Entry.xlsx]Book'!P98 | K98: ='[01_Entry.xlsx]Book'!F98 | L98: ='[01_Entry.xlsx]Book'!G98 | M98: ='[01_Entry.xlsx]Book'!I98 | N98: =IF($A98="","",MID($A98,6,2)) -> 0 | O98: =IF(OR($C98="",$C98<>'Inv'!$D$12),"",N(O$97)+1) -> 0
A99: ='[01_Entry.xlsx]Book'!A99 | B99: ='[01_Entry.xlsx]Book'!B99 | C99: ='[01_Entry.xlsx]Book'!D99 | D99: ='[01_Entry.xlsx]Book'!E99 | E99: ='[01_Entry.xlsx]Book'!O99 | F99: ='[01_Entry.xlsx]Book'!N99 | G99: ='[01_Entry.xlsx]Book'!L99 | H99: ='[01_Entry.xlsx]Book'!M99 | I99: ='[01_Entry.xlsx]Book'!K99 | J99: ='[01_Entry.xlsx]Book'!P99 | K99: ='[01_Entry.xlsx]Book'!F99 | L99: ='[01_Entry.xlsx]Book'!G99 | M99: ='[01_Entry.xlsx]Book'!I99 | N99: =IF($A99="","",MID($A99,6,2)) -> 0 | O99: =IF(OR($C99="",$C99<>'Inv'!$D$12),"",N(O$98)+1) -> 0
A100: ='[01_Entry.xlsx]Book'!A100 | B100: ='[01_Entry.xlsx]Book'!B100 | C100: ='[01_Entry.xlsx]Book'!D100 | D100: ='[01_Entry.xlsx]Book'!E100 | E100: ='[01_Entry.xlsx]Book'!O100 | F100: ='[01_Entry.xlsx]Book'!N100 | G100: ='[01_Entry.xlsx]Book'!L100 | H100: ='[01_Entry.xlsx]Book'!M100 | I100: ='[01_Entry.xlsx]Book'!K100 | J100: ='[01_Entry.xlsx]Book'!P100 | K100: ='[01_Entry.xlsx]Book'!F100 | L100: ='[01_Entry.xlsx]Book'!G100 | M100: ='[01_Entry.xlsx]Book'!I100 | N100: =IF($A100="","",MID($A100,6,2)) -> 0 | O100: =IF(OR($C100="",$C100<>'Inv'!$D$12),"",N(O$99)+1) -> 0
A101: ='[01_Entry.xlsx]Book'!A101 | B101: ='[01_Entry.xlsx]Book'!B101 | C101: ='[01_Entry.xlsx]Book'!D101 | D101: ='[01_Entry.xlsx]Book'!E101 | E101: ='[01_Entry.xlsx]Book'!O101 | F101: ='[01_Entry.xlsx]Book'!N101 | G101: ='[01_Entry.xlsx]Book'!L101 | H101: ='[01_Entry.xlsx]Book'!M101 | I101: ='[01_Entry.xlsx]Book'!K101 | J101: ='[01_Entry.xlsx]Book'!P101 | K101: ='[01_Entry.xlsx]Book'!F101 | L101: ='[01_Entry.xlsx]Book'!G101 | M101: ='[01_Entry.xlsx]Book'!I101 | N101: =IF($A101="","",MID($A101,6,2)) -> 0 | O101: =IF(OR($C101="",$C101<>'Inv'!$D$12),"",N(O$100)+1) -> 0
A102: ='[01_Entry.xlsx]Book'!A102 | B102: ='[01_Entry.xlsx]Book'!B102 | C102: ='[01_Entry.xlsx]Book'!D102 | D102: ='[01_Entry.xlsx]Book'!E102 | E102: ='[01_Entry.xlsx]Book'!O102 | F102: ='[01_Entry.xlsx]Book'!N102 | G102: ='[01_Entry.xlsx]Book'!L102 | H102: ='[01_Entry.xlsx]Book'!M102 | I102: ='[01_Entry.xlsx]Book'!K102 | J102: ='[01_Entry.xlsx]Book'!P102 | K102: ='[01_Entry.xlsx]Book'!F102 | L102: ='[01_Entry.xlsx]Book'!G102 | M102: ='[01_Entry.xlsx]Book'!I102 | N102: =IF($A102="","",MID($A102,6,2)) -> 0 | O102: =IF(OR($C102="",$C102<>'Inv'!$D$12),"",N(O$101)+1) -> 0
A103: ='[01_Entry.xlsx]Book'!A103 | B103: ='[01_Entry.xlsx]Book'!B103 | C103: ='[01_Entry.xlsx]Book'!D103 | D103: ='[01_Entry.xlsx]Book'!E103 | E103: ='[01_Entry.xlsx]Book'!O103 | F103: ='[01_Entry.xlsx]Book'!N103 | G103: ='[01_Entry.xlsx]Book'!L103 | H103: ='[01_Entry.xlsx]Book'!M103 | I103: ='[01_Entry.xlsx]Book'!K103 | J103: ='[01_Entry.xlsx]Book'!P103 | K103: ='[01_Entry.xlsx]Book'!F103 | L103: ='[01_Entry.xlsx]Book'!G103 | M103: ='[01_Entry.xlsx]Book'!I103 | N103: =IF($A103="","",MID($A103,6,2)) -> 0 | O103: =IF(OR($C103="",$C103<>'Inv'!$D$12),"",N(O$102)+1) -> 0
A104: ='[01_Entry.xlsx]Book'!A104 | B104: ='[01_Entry.xlsx]Book'!B104 | C104: ='[01_Entry.xlsx]Book'!D104 | D104: ='[01_Entry.xlsx]Book'!E104 | E104: ='[01_Entry.xlsx]Book'!O104 | F104: ='[01_Entry.xlsx]Book'!N104 | G104: ='[01_Entry.xlsx]Book'!L104 | H104: ='[01_Entry.xlsx]Book'!M104 | I104: ='[01_Entry.xlsx]Book'!K104 | J104: ='[01_Entry.xlsx]Book'!P104 | K104: ='[01_Entry.xlsx]Book'!F104 | L104: ='[01_Entry.xlsx]Book'!G104 | M104: ='[01_Entry.xlsx]Book'!I104 | N104: =IF($A104="","",MID($A104,6,2)) -> 0 | O104: =IF(OR($C104="",$C104<>'Inv'!$D$12),"",N(O$103)+1) -> 0
A105: ='[01_Entry.xlsx]Book'!A105 | B105: ='[01_Entry.xlsx]Book'!B105 | C105: ='[01_Entry.xlsx]Book'!D105 | D105: ='[01_Entry.xlsx]Book'!E105 | E105: ='[01_Entry.xlsx]Book'!O105 | F105: ='[01_Entry.xlsx]Book'!N105 | G105: ='[01_Entry.xlsx]Book'!L105 | H105: ='[01_Entry.xlsx]Book'!M105 | I105: ='[01_Entry.xlsx]Book'!K105 | J105: ='[01_Entry.xlsx]Book'!P105 | K105: ='[01_Entry.xlsx]Book'!F105 | L105: ='[01_Entry.xlsx]Book'!G105 | M105: ='[01_Entry.xlsx]Book'!I105 | N105: =IF($A105="","",MID($A105,6,2)) -> 0 | O105: =IF(OR($C105="",$C105<>'Inv'!$D$12),"",N(O$104)+1) -> 0
A106: ='[01_Entry.xlsx]Book'!A106 | B106: ='[01_Entry.xlsx]Book'!B106 | C106: ='[01_Entry.xlsx]Book'!D106 | D106: ='[01_Entry.xlsx]Book'!E106 | E106: ='[01_Entry.xlsx]Book'!O106 | F106: ='[01_Entry.xlsx]Book'!N106 | G106: ='[01_Entry.xlsx]Book'!L106 | H106: ='[01_Entry.xlsx]Book'!M106 | I106: ='[01_Entry.xlsx]Book'!K106 | J106: ='[01_Entry.xlsx]Book'!P106 | K106: ='[01_Entry.xlsx]Book'!F106 | L106: ='[01_Entry.xlsx]Book'!G106 | M106: ='[01_Entry.xlsx]Book'!I106 | N106: =IF($A106="","",MID($A106,6,2)) -> 0 | O106: =IF(OR($C106="",$C106<>'Inv'!$D$12),"",N(O$105)+1) -> 0
A107: ='[01_Entry.xlsx]Book'!A107 | B107: ='[01_Entry.xlsx]Book'!B107 | C107: ='[01_Entry.xlsx]Book'!D107 | D107: ='[01_Entry.xlsx]Book'!E107 | E107: ='[01_Entry.xlsx]Book'!O107 | F107: ='[01_Entry.xlsx]Book'!N107 | G107: ='[01_Entry.xlsx]Book'!L107 | H107: ='[01_Entry.xlsx]Book'!M107 | I107: ='[01_Entry.xlsx]Book'!K107 | J107: ='[01_Entry.xlsx]Book'!P107 | K107: ='[01_Entry.xlsx]Book'!F107 | L107: ='[01_Entry.xlsx]Book'!G107 | M107: ='[01_Entry.xlsx]Book'!I107 | N107: =IF($A107="","",MID($A107,6,2)) -> 0 | O107: =IF(OR($C107="",$C107<>'Inv'!$D$12),"",N(O$106)+1) -> 0
A108: ='[01_Entry.xlsx]Book'!A108 | B108: ='[01_Entry.xlsx]Book'!B108 | C108: ='[01_Entry.xlsx]Book'!D108 | D108: ='[01_Entry.xlsx]Book'!E108 | E108: ='[01_Entry.xlsx]Book'!O108 | F108: ='[01_Entry.xlsx]Book'!N108 | G108: ='[01_Entry.xlsx]Book'!L108 | H108: ='[01_Entry.xlsx]Book'!M108 | I108: ='[01_Entry.xlsx]Book'!K108 | J108: ='[01_Entry.xlsx]Book'!P108 | K108: ='[01_Entry.xlsx]Book'!F108 | L108: ='[01_Entry.xlsx]Book'!G108 | M108: ='[01_Entry.xlsx]Book'!I108 | N108: =IF($A108="","",MID($A108,6,2)) -> 0 | O108: =IF(OR($C108="",$C108<>'Inv'!$D$12),"",N(O$107)+1) -> 0
...

Sheet Inv
A2: مازندشت — سورتینگ و بسته‌بندی مرکبات | H2: MAZANDASHT · INVOICE
A3: صورت‌حساب / فاکتور طرف حساب
A4: کد حساب را انتخاب کنید، سطرهای موردنظر را تیک بزنید؛ جمع فاکتور خودکار حساب می‌شود.
B6: کد حساب | E6: شماره فاکتور | G6: تاریخ | I6: =IFERROR(VLOOKUP($C$6,AcctTbl,2,0),"—") -> 0
A7: =IF($C$6="","برای شروع، کد حساب را در کادر بالا انتخاب کنید.","گروه: "&IFERROR(VLOOKUP($C$6,AcctTbl,3,0),"")&" · "&IFERROR(VLOOKUP($C$6,AcctTbl,4,0),"")) -> 0
A9: نمایش | B9: تاریخ | C9: سند | D9: شرح | E9: سبد | F9: وزن خالص | G9: بدهکار | H9: بستانکار | I9: مبلغ
B10: =IF($K$10="","",INDEX(Data!$A$10:$A$1807,$K$10)) -> 0 | C10: =IF($K$10="","",INDEX(Data!$B$10:$B$1807,$K$10)) -> 0 | D10: =IF($K$10="","",INDEX(Data!$D$10:$D$1807,$K$10)) -> 0 | E10: =IF($K$10="","",INDEX(Data!$L$10:$L$1807,$K$10)) -> 0 | F10: =IF($K$10="","",INDEX(Data!$M$10:$M$1807,$K$10)) -> 0 | G10: =IF($K$10="","",INDEX(Data!$G$10:$G$1807,$K$10)) -> 0 | H10: =IF($K$10="","",INDEX(Data!$H$10:$H$1807,$K$10)) -> 0 | I10: =IF($K$10="","",INDEX(Data!$I$10:$I$1807,$K$10)) -> 0 | K10: =IFERROR(MATCH(1,Data!$O$10:$O$1807,0),"") -> 0
B11: =IF($K$11="","",INDEX(Data!$A$10:$A$1807,$K$11)) -> 0 | C11: =IF($K$11="","",INDEX(Data!$B$10:$B$1807,$K$11)) -> 0 | D11: =IF($K$11="","",INDEX(Data!$D$10:$D$1807,$K$11)) -> 0 | E11: =IF($K$11="","",INDEX(Data!$L$10:$L$1807,$K$11)) -> 0 | F11: =IF($K$11="","",INDEX(Data!$M$10:$M$1807,$K$11)) -> 0 | G11: =IF($K$11="","",INDEX(Data!$G$10:$G$1807,$K$11)) -> 0 | H11: =IF($K$11="","",INDEX(Data!$H$10:$H$1807,$K$11)) -> 0 | I11: =IF($K$11="","",INDEX(Data!$I$10:$I$1807,$K$11)) -> 0 | K11: =IFERROR(MATCH(2,Data!$O$10:$O$1807,0),"") -> 0
B12: =IF($K$12="","",INDEX(Data!$A$10:$A$1807,$K$12)) -> 0 | C12: =IF($K$12="","",INDEX(Data!$B$10:$B$1807,$K$12)) -> 0 | D12: =IF($K$12="","",INDEX(Data!$D$10:$D$1807,$K$12)) -> 0 | E12: =IF($K$12="","",INDEX(Data!$L$10:$L$1807,$K$12)) -> 0 | F12: =IF($K$12="","",INDEX(Data!$M$10:$M$1807,$K$12)) -> 0 | G12: =IF($K$12="","",INDEX(Data!$G$10:$G$1807,$K$12)) -> 0 | H12: =IF($K$12="","",INDEX(Data!$H$10:$H$1807,$K$12)) -> 0 | I12: =IF($K$12="","",INDEX(Data!$I$10:$I$1807,$K$12)) -> 0 | K12: =IFERROR(MATCH(3,Data!$O$10:$O$1807,0),"") -> 0
B13: =IF($K$13="","",INDEX(Data!$A$10:$A$1807,$K$13)) -> 0 | C13: =IF($K$13="","",INDEX(Data!$B$10:$B$1807,$K$13)) -> 0 | D13: =IF($K$13="","",INDEX(Data!$D$10:$D$1807,$K$13)) -> 0 | E13: =IF($K$13="","",INDEX(Data!$L$10:$L$1807,$K$13)) -> 0 | F13: =IF($K$13="","",INDEX(Data!$M$10:$M$1807,$K$13)) -> 0 | G13: =IF($K$13="","",INDEX(Data!$G$10:$G$1807,$K$13)) -> 0 | H13: =IF($K$13="","",INDEX(Data!$H$10:$H$1807,$K$13)) -> 0 | I13: =IF($K$13="","",INDEX(Data!$I$10:$I$1807,$K$13)) -> 0 | K13: =IFERROR(MATCH(4,Data!$O$10:$O$1807,0),"") -> 0
B14: =IF($K$14="","",INDEX(Data!$A$10:$A$1807,$K$14)) -> 0 | C14: =IF($K$14="","",INDEX(Data!$B$10:$B$1807,$K$14)) -> 0 | D14: =IF($K$14="","",INDEX(Data!$D$10:$D$1807,$K$14)) -> 0 | E14: =IF($K$14="","",INDEX(Data!$L$10:$L$1807,$K$14)) -> 0 | F14: =IF($K$14="","",INDEX(Data!$M$10:$M$1807,$K$14)) -> 0 | G14: =IF($K$14="","",INDEX(Data!$G$10:$G$1807,$K$14)) -> 0 | H14: =IF($K$14="","",INDEX(Data!$H$10:$H$1807,$K$14)) -> 0 | I14: =IF($K$14="","",INDEX(Data!$I$10:$I$1807,$K$14)) -> 0 | K14: =IFERROR(MATCH(5,Data!$O$10:$O$1807,0),"") -> 0
B15: =IF($K$15="","",INDEX(Data!$A$10:$A$1807,$K$15)) -> 0 | C15: =IF($K$15="","",INDEX(Data!$B$10:$B$1807,$K$15)) -> 0 | D15: =IF($K$15="","",INDEX(Data!$D$10:$D$1807,$K$15)) -> 0 | E15: =IF($K$15="","",INDEX(Data!$L$10:$L$1807,$K$15)) -> 0 | F15: =IF($K$15="","",INDEX(Data!$M$10:$M$1807,$K$15)) -> 0 | G15: =IF($K$15="","",INDEX(Data!$G$10:$G$1807,$K$15)) -> 0 | H15: =IF($K$15="","",INDEX(Data!$H$10:$H$1807,$K$15)) -> 0 | I15: =IF($K$15="","",INDEX(Data!$I$10:$I$1807,$K$15)) -> 0 | K15: =IFERROR(MATCH(6,Data!$O$10:$O$1807,0),"") -> 0
B16: =IF($K$16="","",INDEX(Data!$A$10:$A$1807,$K$16)) -> 0 | C16: =IF($K$16="","",INDEX(Data!$B$10:$B$1807,$K$16)) -> 0 | D16: =IF($K$16="","",INDEX(Data!$D$10:$D$1807,$K$16)) -> 0 | E16: =IF($K$16="","",INDEX(Data!$L$10:$L$1807,$K$16)) -> 0 | F16: =IF($K$16="","",INDEX(Data!$M$10:$M$1807,$K$16)) -> 0 | G16: =IF($K$16="","",INDEX(Data!$G$10:$G$1807,$K$16)) -> 0 | H16: =IF($K$16="","",INDEX(Data!$H$10:$H$1807,$K$16)) -> 0 | I16: =IF($K$16="","",INDEX(Data!$I$10:$I$1807,$K$16)) -> 0 | K16: =IFERROR(MATCH(7,Data!$O$10:$O$1807,0),"") -> 0
B17: =IF($K$17="","",INDEX(Data!$A$10:$A$1807,$K$17)) -> 0 | C17: =IF($K$17="","",INDEX(Data!$B$10:$B$1807,$K$17)) -> 0 | D17: =IF($K$17="","",INDEX(Data!$D$10:$D$1807,$K$17)) -> 0 | E17: =IF($K$17="","",INDEX(Data!$L$10:$L$1807,$K$17)) -> 0 | F17: =IF($K$17="","",INDEX(Data!$M$10:$M$1807,$K$17)) -> 0 | G17: =IF($K$17="","",INDEX(Data!$G$10:$G$1807,$K$17)) -> 0 | H17: =IF($K$17="","",INDEX(Data!$H$10:$H$1807,$K$17)) -> 0 | I17: =IF($K$17="","",INDEX(Data!$I$10:$I$1807,$K$17)) -> 0 | K17: =IFERROR(MATCH(8,Data!$O$10:$O$1807,0),"") -> 0
B18: =IF($K$18="","",INDEX(Data!$A$10:$A$1807,$K$18)) -> 0 | C18: =IF($K$18="","",INDEX(Data!$B$10:$B$1807,$K$18)) -> 0 | D18: =IF($K$18="","",INDEX(Data!$D$10:$D$1807,$K$18)) -> 0 | E18: =IF($K$18="","",INDEX(Data!$L$10:$L$1807,$K$18)) -> 0 | F18: =IF($K$18="","",INDEX(Data!$M$10:$M$1807,$K$18)) -> 0 | G18: =IF($K$18="","",INDEX(Data!$G$10:$G$1807,$K$18)) -> 0 | H18: =IF($K$18="","",INDEX(Data!$H$10:$H$1807,$K$18)) -> 0 | I18: =IF($K$18="","",INDEX(Data!$I$10:$I$1807,$K$18)) -> 0 | K18: =IFERROR(MATCH(9,Data!$O$10:$O$1807,0),"") -> 0
B19: =IF($K$19="","",INDEX(Data!$A$10:$A$1807,$K$19)) -> 0 | C19: =IF($K$19="","",INDEX(Data!$B$10:$B$1807,$K$19)) -> 0 | D19: =IF($K$19="","",INDEX(Data!$D$10:$D$1807,$K$19)) -> 0 | E19: =IF($K$19="","",INDEX(Data!$L$10:$L$1807,$K$19)) -> 0 | F19: =IF($K$19="","",INDEX(Data!$M$10:$M$1807,$K$19)) -> 0 | G19: =IF($K$19="","",INDEX(Data!$G$10:$G$1807,$K$19)) -> 0 | H19: =IF($K$19="","",INDEX(Data!$H$10:$H$1807,$K$19)) -> 0 | I19: =IF($K$19="","",INDEX(Data!$I$10:$I$1807,$K$19)) -> 0 | K19: =IFERROR(MATCH(10,Data!$O$10:$O$1807,0),"") -> 0
B20: =IF($K$20="","",INDEX(Data!$A$10:$A$1807,$K$20)) -> 0 | C20: =IF($K$20="","",INDEX(Data!$B$10:$B$1807,$K$20)) -> 0 | D20: =IF($K$20="","",INDEX(Data!$D$10:$D$1807,$K$20)) -> 0 | E20: =IF($K$20="","",INDEX(Data!$L$10:$L$1807,$K$20)) -> 0 | F20: =IF($K$20="","",INDEX(Data!$M$10:$M$1807,$K$20)) -> 0 | G20: =IF($K$20="","",INDEX(Data!$G$10:$G$1807,$K$20)) -> 0 | H20: =IF($K$20="","",INDEX(Data!$H$10:$H$1807,$K$20)) -> 0 | I20: =IF($K$20="","",INDEX(Data!$I$10:$I$1807,$K$20)) -> 0 | K20: =IFERROR(MATCH(11,Data!$O$10:$O$1807,0),"") -> 0
B21: =IF($K$21="","",INDEX(Data!$A$10:$A$1807,$K$21)) -> 0 | C21: =IF($K$21="","",INDEX(Data!$B$10:$B$1807,$K$21)) -> 0 | D21: =IF($K$21="","",INDEX(Data!$D$10:$D$1807,$K$21)) -> 0 | E21: =IF($K$21="","",INDEX(Data!$L$10:$L$1807,$K$21)) -> 0 | F21: =IF($K$21="","",INDEX(Data!$M$10:$M$1807,$K$21)) -> 0 | G21: =IF($K$21="","",INDEX(Data!$G$10:$G$1807,$K$21)) -> 0 | H21: =IF($K$21="","",INDEX(Data!$H$10:$H$1807,$K$21)) -> 0 | I21: =IF($K$21="","",INDEX(Data!$I$10:$I$1807,$K$21)) -> 0 | K21: =IFERROR(MATCH(12,Data!$O$10:$O$1807,0),"") -> 0
B22: =IF($K$22="","",INDEX(Data!$A$10:$A$1807,$K$22)) -> 0 | C22: =IF($K$22="","",INDEX(Data!$B$10:$B$1807,$K$22)) -> 0 | D22: =IF($K$22="","",INDEX(Data!$D$10:$D$1807,$K$22)) -> 0 | E22: =IF($K$22="","",INDEX(Data!$L$10:$L$1807,$K$22)) -> 0 | F22: =IF($K$22="","",INDEX(Data!$M$10:$M$1807,$K$22)) -> 0 | G22: =IF($K$22="","",INDEX(Data!$G$10:$G$1807,$K$22)) -> 0 | H22: =IF($K$22="","",INDEX(Data!$H$10:$H$1807,$K$22)) -> 0 | I22: =IF($K$22="","",INDEX(Data!$I$10:$I$1807,$K$22)) -> 0 | K22: =IFERROR(MATCH(13,Data!$O$10:$O$1807,0),"") -> 0
B23: =IF($K$23="","",INDEX(Data!$A$10:$A$1807,$K$23)) -> 0 | C23: =IF($K$23="","",INDEX(Data!$B$10:$B$1807,$K$23)) -> 0 | D23: =IF($K$23="","",INDEX(Data!$D$10:$D$1807,$K$23)) -> 0 | E23: =IF($K$23="","",INDEX(Data!$L$10:$L$1807,$K$23)) -> 0 | F23: =IF($K$23="","",INDEX(Data!$M$10:$M$1807,$K$23)) -> 0 | G23: =IF($K$23="","",INDEX(Data!$G$10:$G$1807,$K$23)) -> 0 | H23: =IF($K$23="","",INDEX(Data!$H$10:$H$1807,$K$23)) -> 0 | I23: =IF($K$23="","",INDEX(Data!$I$10:$I$1807,$K$23)) -> 0 | K23: =IFERROR(MATCH(14,Data!$O$10:$O$1807,0),"") -> 0
B24: =IF($K$24="","",INDEX(Data!$A$10:$A$1807,$K$24)) -> 0 | C24: =IF($K$24="","",INDEX(Data!$B$10:$B$1807,$K$24)) -> 0 | D24: =IF($K$24="","",INDEX(Data!$D$10:$D$1807,$K$24)) -> 0 | E24: =IF($K$24="","",INDEX(Data!$L$10:$L$1807,$K$24)) -> 0 | F24: =IF($K$24="","",INDEX(Data!$M$10:$M$1807,$K$24)) -> 0 | G24: =IF($K$24="","",INDEX(Data!$G$10:$G$1807,$K$24)) -> 0 | H24: =IF($K$24="","",INDEX(Data!$H$10:$H$1807,$K$24)) -> 0 | I24: =IF($K$24="","",INDEX(Data!$I$10:$I$1807,$K$24)) -> 0 | K24: =IFERROR(MATCH(15,Data!$O$10:$O$1807,0),"") -> 0
B25: =IF($K$25="","",INDEX(Data!$A$10:$A$1807,$K$25)) -> 0 | C25: =IF($K$25="","",INDEX(Data!$B$10:$B$1807,$K$25)) -> 0 | D25: =IF($K$25="","",INDEX(Data!$D$10:$D$1807,$K$25)) -> 0 | E25: =IF($K$25="","",INDEX(Data!$L$10:$L$1807,$K$25)) -> 0 | F25: =IF($K$25="","",INDEX(Data!$M$10:$M$1807,$K$25)) -> 0 | G25: =IF($K$25="","",INDEX(Data!$G$10:$G$1807,$K$25)) -> 0 | H25: =IF($K$25="","",INDEX(Data!$H$10:$H$1807,$K$25)) -> 0 | I25: =IF($K$25="","",INDEX(Data!$I$10:$I$1807,$K$25)) -> 0 | K25: =IFERROR(MATCH(16,Data!$O$10:$O$1807,0),"") -> 0
B26: =IF($K$26="","",INDEX(Data!$A$10:$A$1807,$K$26)) -> 0 | C26: =IF($K$26="","",INDEX(Data!$B$10:$B$1807,$K$26)) -> 0 | D26: =IF($K$26="","",INDEX(Data!$D$10:$D$1807,$K$26)) -> 0 | E26: =IF($K$26="","",INDEX(Data!$L$10:$L$1807,$K$26)) -> 0 | F26: =IF($K$26="","",INDEX(Data!$M$10:$M$1807,$K$26)) -> 0 | G26: =IF($K$26="","",INDEX(Data!$G$10:$G$1807,$K$26)) -> 0 | H26: =IF($K$26="","",INDEX(Data!$H$10:$H$1807,$K$26)) -> 0 | I26: =IF($K$26="","",INDEX(Data!$I$10:$I$1807,$K$26)) -> 0 | K26: =IFERROR(MATCH(17,Data!$O$10:$O$1807,0),"") -> 0
B27: =IF($K$27="","",INDEX(Data!$A$10:$A$1807,$K$27)) -> 0 | C27: =IF($K$27="","",INDEX(Data!$B$10:$B$1807,$K$27)) -> 0 | D27: =IF($K$27="","",INDEX(Data!$D$10:$D$1807,$K$27)) -> 0 | E27: =IF($K$27="","",INDEX(Data!$L$10:$L$1807,$K$27)) -> 0 | F27: =IF($K$27="","",INDEX(Data!$M$10:$M$1807,$K$27)) -> 0 | G27: =IF($K$27="","",INDEX(Data!$G$10:$G$1807,$K$27)) -> 0 | H27: =IF($K$27="","",INDEX(Data!$H$10:$H$1807,$K$27)) -> 0 | I27: =IF($K$27="","",INDEX(Data!$I$10:$I$1807,$K$27)) -> 0 | K27: =IFERROR(MATCH(18,Data!$O$10:$O$1807,0),"") -> 0
B28: =IF($K$28="","",INDEX(Data!$A$10:$A$1807,$K$28)) -> 0 | C28: =IF($K$28="","",INDEX(Data!$B$10:$B$1807,$K$28)) -> 0 | D28: =IF($K$28="","",INDEX(Data!$D$10:$D$1807,$K$28)) -> 0 | E28: =IF($K$28="","",INDEX(Data!$L$10:$L$1807,$K$28)) -> 0 | F28: =IF($K$28="","",INDEX(Data!$M$10:$M$1807,$K$28)) -> 0 | G28: =IF($K$28="","",INDEX(Data!$G$10:$G$1807,$K$28)) -> 0 | H28: =IF($K$28="","",INDEX(Data!$H$10:$H$1807,$K$28)) -> 0 | I28: =IF($K$28="","",INDEX(Data!$I$10:$I$1807,$K$28)) -> 0 | K28: =IFERROR(MATCH(19,Data!$O$10:$O$1807,0),"") -> 0
B29: =IF($K$29="","",INDEX(Data!$A$10:$A$1807,$K$29)) -> 0 | C29: =IF($K$29="","",INDEX(Data!$B$10:$B$1807,$K$29)) -> 0 | D29: =IF($K$29="","",INDEX(Data!$D$10:$D$1807,$K$29)) -> 0 | E29: =IF($K$29="","",INDEX(Data!$L$10:$L$1807,$K$29)) -> 0 | F29: =IF($K$29="","",INDEX(Data!$M$10:$M$1807,$K$29)) -> 0 | G29: =IF($K$29="","",INDEX(Data!$G$10:$G$1807,$K$29)) -> 0 | H29: =IF($K$29="","",INDEX(Data!$H$10:$H$1807,$K$29)) -> 0 | I29: =IF($K$29="","",INDEX(Data!$I$10:$I$1807,$K$29)) -> 0 | K29: =IFERROR(MATCH(20,Data!$O$10:$O$1807,0),"") -> 0
B30: =IF($K$30="","",INDEX(Data!$A$10:$A$1807,$K$30)) -> 0 | C30: =IF($K$30="","",INDEX(Data!$B$10:$B$1807,$K$30)) -> 0 | D30: =IF($K$30="","",INDEX(Data!$D$10:$D$1807,$K$30)) -> 0 | E30: =IF($K$30="","",INDEX(Data!$L$10:$L$1807,$K$30)) -> 0 | F30: =IF($K$30="","",INDEX(Data!$M$10:$M$1807,$K$30)) -> 0 | G30: =IF($K$30="","",INDEX(Data!$G$10:$G$1807,$K$30)) -> 0 | H30: =IF($K$30="","",INDEX(Data!$H$10:$H$1807,$K$30)) -> 0 | I30: =IF($K$30="","",INDEX(Data!$I$10:$I$1807,$K$30)) -> 0 | K30: =IFERROR(MATCH(21,Data!$O$10:$O$1807,0),"") -> 0
B31: =IF($K$31="","",INDEX(Data!$A$10:$A$1807,$K$31)) -> 0 | C31: =IF($K$31="","",INDEX(Data!$B$10:$B$1807,$K$31)) -> 0 | D31: =IF($K$31="","",INDEX(Data!$D$10:$D$1807,$K$31)) -> 0 | E31: =IF($K$31="","",INDEX(Data!$L$10:$L$1807,$K$31)) -> 0 | F31: =IF($K$31="","",INDEX(Data!$M$10:$M$1807,$K$31)) -> 0 | G31: =IF($K$31="","",INDEX(Data!$G$10:$G$1807,$K$31)) -> 0 | H31: =IF($K$31="","",INDEX(Data!$H$10:$H$1807,$K$31)) -> 0 | I31: =IF($K$31="","",INDEX(Data!$I$10:$I$1807,$K$31)) -> 0 | K31: =IFERROR(MATCH(22,Data!$O$10:$O$1807,0),"") -> 0
B32: =IF($K$32="","",INDEX(Data!$A$10:$A$1807,$K$32)) -> 0 | C32: =IF($K$32="","",INDEX(Data!$B$10:$B$1807,$K$32)) -> 0 | D32: =IF($K$32="","",INDEX(Data!$D$10:$D$1807,$K$32)) -> 0 | E32: =IF($K$32="","",INDEX(Data!$L$10:$L$1807,$K$32)) -> 0 | F32: =IF($K$32="","",INDEX(Data!$M$10:$M$1807,$K$32)) -> 0 | G32: =IF($K$32="","",INDEX(Data!$G$10:$G$1807,$K$32)) -> 0 | H32: =IF($K$32="","",INDEX(Data!$H$10:$H$1807,$K$32)) -> 0 | I32: =IF($K$32="","",INDEX(Data!$I$10:$I$1807,$K$32)) -> 0 | K32: =IFERROR(MATCH(23,Data!$O$10:$O$1807,0),"") -> 0
B33: =IF($K$33="","",INDEX(Data!$A$10:$A$1807,$K$33)) -> 0 | C33: =IF($K$33="","",INDEX(Data!$B$10:$B$1807,$K$33)) -> 0 | D33: =IF($K$33="","",INDEX(Data!$D$10:$D$1807,$K$33)) -> 0 | E33: =IF($K$33="","",INDEX(Data!$L$10:$L$1807,$K$33)) -> 0 | F33: =IF($K$33="","",INDEX(Data!$M$10:$M$1807,$K$33)) -> 0 | G33: =IF($K$33="","",INDEX(Data!$G$10:$G$1807,$K$33)) -> 0 | H33: =IF($K$33="","",INDEX(Data!$H$10:$H$1807,$K$33)) -> 0 | I33: =IF($K$33="","",INDEX(Data!$I$10:$I$1807,$K$33)) -> 0 | K33: =IFERROR(MATCH(24,Data!$O$10:$O$1807,0),"") -> 0
B34: =IF($K$34="","",INDEX(Data!$A$10:$A$1807,$K$34)) -> 0 | C34: =IF($K$34="","",INDEX(Data!$B$10:$B$1807,$K$34)) -> 0 | D34: =IF($K$34="","",INDEX(Data!$D$10:$D$1807,$K$34)) -> 0 | E34: =IF($K$34="","",INDEX(Data!$L$10:$L$1807,$K$34)) -> 0 | F34: =IF($K$34="","",INDEX(Data!$M$10:$M$1807,$K$34)) -> 0 | G34: =IF($K$34="","",INDEX(Data!$G$10:$G$1807,$K$34)) -> 0 | H34: =IF($K$34="","",INDEX(Data!$H$10:$H$1807,$K$34)) -> 0 | I34: =IF($K$34="","",INDEX(Data!$I$10:$I$1807,$K$34)) -> 0 | K34: =IFERROR(MATCH(25,Data!$O$10:$O$1807,0),"") -> 0
B35: =IF($K$35="","",INDEX(Data!$A$10:$A$1807,$K$35)) -> 0 | C35: =IF($K$35="","",INDEX(Data!$B$10:$B$1807,$K$35)) -> 0 | D35: =IF($K$35="","",INDEX(Data!$D$10:$D$1807,$K$35)) -> 0 | E35: =IF($K$35="","",INDEX(Data!$L$10:$L$1807,$K$35)) -> 0 | F35: =IF($K$35="","",INDEX(Data!$M$10:$M$1807,$K$35)) -> 0 | G35: =IF($K$35="","",INDEX(Data!$G$10:$G$1807,$K$35)) -> 0 | H35: =IF($K$35="","",INDEX(Data!$H$10:$H$1807,$K$35)) -> 0 | I35: =IF($K$35="","",INDEX(Data!$I$10:$I$1807,$K$35)) -> 0 | K35: =IFERROR(MATCH(26,Data!$O$10:$O$1807,0),"") -> 0
B36: =IF($K$36="","",INDEX(Data!$A$10:$A$1807,$K$36)) -> 0 | C36: =IF($K$36="","",INDEX(Data!$B$10:$B$1807,$K$36)) -> 0 | D36: =IF($K$36="","",INDEX(Data!$D$10:$D$1807,$K$36)) -> 0 | E36: =IF($K$36="","",INDEX(Data!$L$10:$L$1807,$K$36)) -> 0 | F36: =IF($K$36="","",INDEX(Data!$M$10:$M$1807,$K$36)) -> 0 | G36: =IF($K$36="","",INDEX(Data!$G$10:$G$1807,$K$36)) -> 0 | H36: =IF($K$36="","",INDEX(Data!$H$10:$H$1807,$K$36)) -> 0 | I36: =IF($K$36="","",INDEX(Data!$I$10:$I$1807,$K$36)) -> 0 | K36: =IFERROR(MATCH(27,Data!$O$10:$O$1807,0),"") -> 0
B37: =IF($K$37="","",INDEX(Data!$A$10:$A$1807,$K$37)) -> 0 | C37: =IF($K$37="","",INDEX(Data!$B$10:$B$1807,$K$37)) -> 0 | D37: =IF($K$37="","",INDEX(Data!$D$10:$D$1807,$K$37)) -> 0 | E37: =IF($K$37="","",INDEX(Data!$L$10:$L$1807,$K$37)) -> 0 | F37: =IF($K$37="","",INDEX(Data!$M$10:$M$1807,$K$37)) -> 0 | G37: =IF($K$37="","",INDEX(Data!$G$10:$G$1807,$K$37)) -> 0 | H37: =IF($K$37="","",INDEX(Data!$H$10:$H$1807,$K$37)) -> 0 | I37: =IF($K$37="","",INDEX(Data!$I$10:$I$1807,$K$37)) -> 0 | K37: =IFERROR(MATCH(28,Data!$O$10:$O$1807,0),"") -> 0
B38: =IF($K$38="","",INDEX(Data!$A$10:$A$1807,$K$38)) -> 0 | C38: =IF($K$38="","",INDEX(Data!$B$10:$B$1807,$K$38)) -> 0 | D38: =IF($K$38="","",INDEX(Data!$D$10:$D$1807,$K$38)) -> 0 | E38: =IF($K$38="","",INDEX(Data!$L$10:$L$1807,$K$38)) -> 0 | F38: =IF($K$38="","",INDEX(Data!$M$10:$M$1807,$K$38)) -> 0 | G38: =IF($K$38="","",INDEX(Data!$G$10:$G$1807,$K$38)) -> 0 | H38: =IF($K$38="","",INDEX(Data!$H$10:$H$1807,$K$38)) -> 0 | I38: =IF($K$38="","",INDEX(Data!$I$10:$I$1807,$K$38)) -> 0 | K38: =IFERROR(MATCH(29,Data!$O$10:$O$1807,0),"") -> 0
B39: =IF($K$39="","",INDEX(Data!$A$10:$A$1807,$K$39)) -> 0 | C39: =IF($K$39="","",INDEX(Data!$B$10:$B$1807,$K$39)) -> 0 | D39: =IF($K$39="","",INDEX(Data!$D$10:$D$1807,$K$39)) -> 0 | E39: =IF($K$39="","",INDEX(Data!$L$10:$L$1807,$K$39)) -> 0 | F39: =IF($K$39="","",INDEX(Data!$M$10:$M$1807,$K$39)) -> 0 | G39: =IF($K$39="","",INDEX(Data!$G$10:$G$1807,$K$39)) -> 0 | H39: =IF($K$39="","",INDEX(Data!$H$10:$H$1807,$K$39)) -> 0 | I39: =IF($K$39="","",INDEX(Data!$I$10:$I$1807,$K$39)) -> 0 | K39: =IFERROR(MATCH(30,Data!$O$10:$O$1807,0),"") -> 0
B40: =IF($K$40="","",INDEX(Data!$A$10:$A$1807,$K$40)) -> 0 | C40: =IF($K$40="","",INDEX(Data!$B$10:$B$1807,$K$40)) -> 0 | D40: =IF($K$40="","",INDEX(Data!$D$10:$D$1807,$K$40)) -> 0 | E40: =IF($K$40="","",INDEX(Data!$L$10:$L$1807,$K$40)) -> 0 | F40: =IF($K$40="","",INDEX(Data!$M$10:$M$1807,$K$40)) -> 0 | G40: =IF($K$40="","",INDEX(Data!$G$10:$G$1807,$K$40)) -> 0 | H40: =IF($K$40="","",INDEX(Data!$H$10:$H$1807,$K$40)) -> 0 | I40: =IF($K$40="","",INDEX(Data!$I$10:$I$1807,$K$40)) -> 0 | K40: =IFERROR(MATCH(31,Data!$O$10:$O$1807,0),"") -> 0
B41: =IF($K$41="","",INDEX(Data!$A$10:$A$1807,$K$41)) -> 0 | C41: =IF($K$41="","",INDEX(Data!$B$10:$B$1807,$K$41)) -> 0 | D41: =IF($K$41="","",INDEX(Data!$D$10:$D$1807,$K$41)) -> 0 | E41: =IF($K$41="","",INDEX(Data!$L$10:$L$1807,$K$41)) -> 0 | F41: =IF($K$41="","",INDEX(Data!$M$10:$M$1807,$K$41)) -> 0 | G41: =IF($K$41="","",INDEX(Data!$G$10:$G$1807,$K$41)) -> 0 | H41: =IF($K$41="","",INDEX(Data!$H$10:$H$1807,$K$41)) -> 0 | I41: =IF($K$41="","",INDEX(Data!$I$10:$I$1807,$K$41)) -> 0 | K41: =IFERROR(MATCH(32,Data!$O$10:$O$1807,0),"") -> 0
B42: =IF($K$42="","",INDEX(Data!$A$10:$A$1807,$K$42)) -> 0 | C42: =IF($K$42="","",INDEX(Data!$B$10:$B$1807,$K$42)) -> 0 | D42: =IF($K$42="","",INDEX(Data!$D$10:$D$1807,$K$42)) -> 0 | E42: =IF($K$42="","",INDEX(Data!$L$10:$L$1807,$K$42)) -> 0 | F42: =IF($K$42="","",INDEX(Data!$M$10:$M$1807,$K$42)) -> 0 | G42: =IF($K$42="","",INDEX(Data!$G$10:$G$1807,$K$42)) -> 0 | H42: =IF($K$42="","",INDEX(Data!$H$10:$H$1807,$K$42)) -> 0 | I42: =IF($K$42="","",INDEX(Data!$I$10:$I$1807,$K$42)) -> 0 | K42: =IFERROR(MATCH(33,Data!$O$10:$O$1807,0),"") -> 0
B43: =IF($K$43="","",INDEX(Data!$A$10:$A$1807,$K$43)) -> 0 | C43: =IF($K$43="","",INDEX(Data!$B$10:$B$1807,$K$43)) -> 0 | D43: =IF($K$43="","",INDEX(Data!$D$10:$D$1807,$K$43)) -> 0 | E43: =IF($K$43="","",INDEX(Data!$L$10:$L$1807,$K$43)) -> 0 | F43: =IF($K$43="","",INDEX(Data!$M$10:$M$1807,$K$43)) -> 0 | G43: =IF($K$43="","",INDEX(Data!$G$10:$G$1807,$K$43)) -> 0 | H43: =IF($K$43="","",INDEX(Data!$H$10:$H$1807,$K$43)) -> 0 | I43: =IF($K$43="","",INDEX(Data!$I$10:$I$1807,$K$43)) -> 0 | K43: =IFERROR(MATCH(34,Data!$O$10:$O$1807,0),"") -> 0
B44: =IF($K$44="","",INDEX(Data!$A$10:$A$1807,$K$44)) -> 0 | C44: =IF($K$44="","",INDEX(Data!$B$10:$B$1807,$K$44)) -> 0 | D44: =IF($K$44="","",INDEX(Data!$D$10:$D$1807,$K$44)) -> 0 | E44: =IF($K$44="","",INDEX(Data!$L$10:$L$1807,$K$44)) -> 0 | F44: =IF($K$44="","",INDEX(Data!$M$10:$M$1807,$K$44)) -> 0 | G44: =IF($K$44="","",INDEX(Data!$G$10:$G$1807,$K$44)) -> 0 | H44: =IF($K$44="","",INDEX(Data!$H$10:$H$1807,$K$44)) -> 0 | I44: =IF($K$44="","",INDEX(Data!$I$10:$I$1807,$K$44)) -> 0 | K44: =IFERROR(MATCH(35,Data!$O$10:$O$1807,0),"") -> 0
B45: =IF($K$45="","",INDEX(Data!$A$10:$A$1807,$K$45)) -> 0 | C45: =IF($K$45="","",INDEX(Data!$B$10:$B$1807,$K$45)) -> 0 | D45: =IF($K$45="","",INDEX(Data!$D$10:$D$1807,$K$45)) -> 0 | E45: =IF($K$45="","",INDEX(Data!$L$10:$L$1807,$K$45)) -> 0 | F45: =IF($K$45="","",INDEX(Data!$M$10:$M$1807,$K$45)) -> 0 | G45: =IF($K$45="","",INDEX(Data!$G$10:$G$1807,$K$45)) -> 0 | H45: =IF($K$45="","",INDEX(Data!$H$10:$H$1807,$K$45)) -> 0 | I45: =IF($K$45="","",INDEX(Data!$I$10:$I$1807,$K$45)) -> 0 | K45: =IFERROR(MATCH(36,Data!$O$10:$O$1807,0),"") -> 0
B46: =IF($K$46="","",INDEX(Data!$A$10:$A$1807,$K$46)) -> 0 | C46: =IF($K$46="","",INDEX(Data!$B$10:$B$1807,$K$46)) -> 0 | D46: =IF($K$46="","",INDEX(Data!$D$10:$D$1807,$K$46)) -> 0 | E46: =IF($K$46="","",INDEX(Data!$L$10:$L$1807,$K$46)) -> 0 | F46: =IF($K$46="","",INDEX(Data!$M$10:$M$1807,$K$46)) -> 0 | G46: =IF($K$46="","",INDEX(Data!$G$10:$G$1807,$K$46)) -> 0 | H46: =IF($K$46="","",INDEX(Data!$H$10:$H$1807,$K$46)) -> 0 | I46: =IF($K$46="","",INDEX(Data!$I$10:$I$1807,$K$46)) -> 0 | K46: =IFERROR(MATCH(37,Data!$O$10:$O$1807,0),"") -> 0
B47: =IF($K$47="","",INDEX(Data!$A$10:$A$1807,$K$47)) -> 0 | C47: =IF($K$47="","",INDEX(Data!$B$10:$B$1807,$K$47)) -> 0 | D47: =IF($K$47="","",INDEX(Data!$D$10:$D$1807,$K$47)) -> 0 | E47: =IF($K$47="","",INDEX(Data!$L$10:$L$1807,$K$47)) -> 0 | F47: =IF($K$47="","",INDEX(Data!$M$10:$M$1807,$K$47)) -> 0 | G47: =IF($K$47="","",INDEX(Data!$G$10:$G$1807,$K$47)) -> 0 | H47: =IF($K$47="","",INDEX(Data!$H$10:$H$1807,$K$47)) -> 0 | I47: =IF($K$47="","",INDEX(Data!$I$10:$I$1807,$K$47)) -> 0 | K47: =IFERROR(MATCH(38,Data!$O$10:$O$1807,0),"") -> 0
B48: =IF($K$48="","",INDEX(Data!$A$10:$A$1807,$K$48)) -> 0 | C48: =IF($K$48="","",INDEX(Data!$B$10:$B$1807,$K$48)) -> 0 | D48: =IF($K$48="","",INDEX(Data!$D$10:$D$1807,$K$48)) -> 0 | E48: =IF($K$48="","",INDEX(Data!$L$10:$L$1807,$K$48)) -> 0 | F48: =IF($K$48="","",INDEX(Data!$M$10:$M$1807,$K$48)) -> 0 | G48: =IF($K$48="","",INDEX(Data!$G$10:$G$1807,$K$48)) -> 0 | H48: =IF($K$48="","",INDEX(Data!$H$10:$H$1807,$K$48)) -> 0 | I48: =IF($K$48="","",INDEX(Data!$I$10:$I$1807,$K$48)) -> 0 | K48: =IFERROR(MATCH(39,Data!$O$10:$O$1807,0),"") -> 0
B49: =IF($K$49="","",INDEX(Data!$A$10:$A$1807,$K$49)) -> 0 | C49: =IF($K$49="","",INDEX(Data!$B$10:$B$1807,$K$49)) -> 0 | D49: =IF($K$49="","",INDEX(Data!$D$10:$D$1807,$K$49)) -> 0 | E49: =IF($K$49="","",INDEX(Data!$L$10:$L$1807,$K$49)) -> 0 | F49: =IF($K$49="","",INDEX(Data!$M$10:$M$1807,$K$49)) -> 0 | G49: =IF($K$49="","",INDEX(Data!$G$10:$G$1807,$K$49)) -> 0 | H49: =IF($K$49="","",INDEX(Data!$H$10:$H$1807,$K$49)) -> 0 | I49: =IF($K$49="","",INDEX(Data!$I$10:$I$1807,$K$49)) -> 0 | K49: =IFERROR(MATCH(40,Data!$O$10:$O$1807,0),"") -> 0
B50: =IF($K$50="","",INDEX(Data!$A$10:$A$1807,$K$50)) -> 0 | C50: =IF($K$50="","",INDEX(Data!$B$10:$B$1807,$K$50)) -> 0 | D50: =IF($K$50="","",INDEX(Data!$D$10:$D$1807,$K$50)) -> 0 | E50: =IF($K$50="","",INDEX(Data!$L$10:$L$1807,$K$50)) -> 0 | F50: =IF($K$50="","",INDEX(Data!$M$10:$M$1807,$K$50)) -> 0 | G50: =IF($K$50="","",INDEX(Data!$G$10:$G$1807,$K$50)) -> 0 | H50: =IF($K$50="","",INDEX(Data!$H$10:$H$1807,$K$50)) -> 0 | I50: =IF($K$50="","",INDEX(Data!$I$10:$I$1807,$K$50)) -> 0 | K50: =IFERROR(MATCH(41,Data!$O$10:$O$1807,0),"") -> 0
B51: =IF($K$51="","",INDEX(Data!$A$10:$A$1807,$K$51)) -> 0 | C51: =IF($K$51="","",INDEX(Data!$B$10:$B$1807,$K$51)) -> 0 | D51: =IF($K$51="","",INDEX(Data!$D$10:$D$1807,$K$51)) -> 0 | E51: =IF($K$51="","",INDEX(Data!$L$10:$L$1807,$K$51)) -> 0 | F51: =IF($K$51="","",INDEX(Data!$M$10:$M$1807,$K$51)) -> 0 | G51: =IF($K$51="","",INDEX(Data!$G$10:$G$1807,$K$51)) -> 0 | H51: =IF($K$51="","",INDEX(Data!$H$10:$H$1807,$K$51)) -> 0 | I51: =IF($K$51="","",INDEX(Data!$I$10:$I$1807,$K$51)) -> 0 | K51: =IFERROR(MATCH(42,Data!$O$10:$O$1807,0),"") -> 0
B52: =IF($K$52="","",INDEX(Data!$A$10:$A$1807,$K$52)) -> 0 | C52: =IF($K$52="","",INDEX(Data!$B$10:$B$1807,$K$52)) -> 0 | D52: =IF($K$52="","",INDEX(Data!$D$10:$D$1807,$K$52)) -> 0 | E52: =IF($K$52="","",INDEX(Data!$L$10:$L$1807,$K$52)) -> 0 | F52: =IF($K$52="","",INDEX(Data!$M$10:$M$1807,$K$52)) -> 0 | G52: =IF($K$52="","",INDEX(Data!$G$10:$G$1807,$K$52)) -> 0 | H52: =IF($K$52="","",INDEX(Data!$H$10:$H$1807,$K$52)) -> 0 | I52: =IF($K$52="","",INDEX(Data!$I$10:$I$1807,$K$52)) -> 0 | K52: =IFERROR(MATCH(43,Data!$O$10:$O$1807,0),"") -> 0
B53: =IF($K$53="","",INDEX(Data!$A$10:$A$1807,$K$53)) -> 0 | C53: =IF($K$53="","",INDEX(Data!$B$10:$B$1807,$K$53)) -> 0 | D53: =IF($K$53="","",INDEX(Data!$D$10:$D$1807,$K$53)) -> 0 | E53: =IF($K$53="","",INDEX(Data!$L$10:$L$1807,$K$53)) -> 0 | F53: =IF($K$53="","",INDEX(Data!$M$10:$M$1807,$K$53)) -> 0 | G53: =IF($K$53="","",INDEX(Data!$G$10:$G$1807,$K$53)) -> 0 | H53: =IF($K$53="","",INDEX(Data!$H$10:$H$1807,$K$53)) -> 0 | I53: =IF($K$53="","",INDEX(Data!$I$10:$I$1807,$K$53)) -> 0 | K53: =IFERROR(MATCH(44,Data!$O$10:$O$1807,0),"") -> 0
B54: =IF($K$54="","",INDEX(Data!$A$10:$A$1807,$K$54)) -> 0 | C54: =IF($K$54="","",INDEX(Data!$B$10:$B$1807,$K$54)) -> 0 | D54: =IF($K$54="","",INDEX(Data!$D$10:$D$1807,$K$54)) -> 0 | E54: =IF($K$54="","",INDEX(Data!$L$10:$L$1807,$K$54)) -> 0 | F54: =IF($K$54="","",INDEX(Data!$M$10:$M$1807,$K$54)) -> 0 | G54: =IF($K$54="","",INDEX(Data!$G$10:$G$1807,$K$54)) -> 0 | H54: =IF($K$54="","",INDEX(Data!$H$10:$H$1807,$K$54)) -> 0 | I54: =IF($K$54="","",INDEX(Data!$I$10:$I$1807,$K$54)) -> 0 | K54: =IFERROR(MATCH(45,Data!$O$10:$O$1807,0),"") -> 0
A56: جمع سطرهای انتخاب‌شده | G56: =SUMIF($A$10:$A$54,1,$G$10:$G$54) -> 0 | H56: =SUMIF($A$10:$A$54,1,$H$10:$H$54) -> 0 | I56: =SUMIF($A$10:$A$54,1,$I$10:$I$54) -> 0
A57: مانده نهایی حساب (کل گردش، نه فقط انتخاب‌شده‌ها) | I57: =SUM(G10:G54)-SUM(H10:H54) -> 0
A59: مهر و امضای فروشنده | F59: امضای خریدار

Sheet Sync
A1: داده‌های ثابت — کپی کامل از 00_Master.xlsx (بدون وابستگی)
A2: این شیت فقط نمایش است و قفل شده. همه کشوها و فرمول‌ها از همین‌جا می‌خوانند؛ برای تغییر، 00_Master.xlsx را ویرایش کنید و سپس این فایل را (با اسکریپت ساخت یا کپی ستون‌ها) دوباره همگام کنید. هیچ فرمولی به فایل مادر وابسته نیست، پس فایل همیشه سالم باز می‌شود. — فاکتور از دفتر ثبت روزانه می‌خواند.
A3: MAZANDASHT · INFO MASTER DATA (READ ONLY)
B8: حساب‌ها — کد، نام، گروه، زیرگروه، نوع و مانده اولیه | I8: عملیات — قاعده بدهکار/بستانکار | Y8: سبدها — برچسب، کد، نام، تار، ظرفیت، خرید، فروش، موجودی | AH8: محصولات | AK8: بانک‌ها — کد، عنوان، مانده، حساب معین | AO8: پارامترها | AR8: گروه‌ها و زیرگروه‌ها | AU8: گروه‌های اصلی | AW8: عملیات سبد | AX8: باسکول دیگران | AZ8: عملیات باسکول
B9: ACCOUNTS | I9: OPERATIONS | Y9: BASKETS | AH9: PRODUCTS | AK9: BANKS | AO9: PARAMS | AR9: GROUPS | AU9: GROUP LIST | AW9: BASKET OPS | AX9: OTHER SCALES | AZ9: BASKOL OPS
B10: C001 | C10: زینب زاهدی | D10: باغدار | E10: عمده | F10: طرف حساب | G10: 0 | I10: خرید مرکبات | J10: ورود | K10: خرید | L10: بله | M10: بله | N10: وزن | O10: بستانکار | P10: X004 | Q10: بدهکار | R10: افزودن | S10: — | W10: بله | Y10: BK01 – ۶ک مشکی | Z10: BK01 | AA10: ۶ک مشکی | AB10: 1.5 | AC10: 6 | AD10: 45000 | AE10: 55000 | AF10: 1200 | AH10: پرتقال تامسون | AI10: پرتقال | AK10: BANK01 | AL10: صادرات ۹۰۰۹ — جاری اصلی | AM10: 500000000 | AN10: BN01 | AO10: P01 | AP10: 1.5 | AR10: باغدار | AS10: سردرختی | AU10: باغدار | AW10: خرید سبد | AX10: BD001 | AZ10: خرید مرکبات | CA10: کیلوگرم | CB10: پرتقال | CC10: ورود | CD10: بله | CE10: طرف حساب | CF10: نقد | CG10: در جریان | CH10: ☑ | CI10: افزودن | CJ10: بدهکار | CK10: بدهکار | CL10: خرید | CM10: ✓ | CN10: Growers | CO10: وزن | CP10: mint | CQ10: بهار | CR10: پرداخت
B11: C002 | C11: سید عباس موسوی | D11: باغدار | E11: صادراتی | F11: طرف حساب | G11: 0 | I11: فروش بار (بارفروش) | J11: خروج | K11: فروش | L11: بله | M11: بله | N11: وزن | O11: بدهکار | P11: X006 | Q11: بستانکار | R11: پوز | S11: بدهکار | T11: BANK02 | U11: X002 | W11: بله | Y11: BK02 – درب‌۶ک | Z11: BK02 | AA11: درب‌۶ک | AB11: 1.5 | AC11: 6 | AD11: 48000 | AE11: 58000 | AF11: 400 | AH11: پرتقال خونی | AI11: پرتقال | AK11: BANK02 | AL11: صادرات ۲۰۰۶ — پوز باسکول | AM11: 0 | AN11: BN02 | AO11: P02 | AP11: 1 | AR11: باغدار | AS11: انباری | AU11: بارفروش | AW11: فروش سبد | AX11: BD002 | AZ11: فروش بار (بارفروش) | CA11: سبد | CB11: نارنگی | CC11: خروج | CD11: خیر | CE11: معین | CF11: چک | CG11: پاس شده | CH11: ☐ | CI11: پوز | CJ11: بستانکار | CK11: بستانکار | CL11: فروش | CM11: ⚠ | CN11: LoadBuyers | CO11: مبلغ | CP11: sky | CQ11: تابستان | CR11: دریافت
B12: C003 | C12: حاج احمد عیسی پور | D12: باغدار | E12: خرده‌فروش | F12: طرف حساب | G12: 0 | I12: فروش متفرقه / صادراتی | J12: خروج | K12: فروش | L12: بله | M12: بله | N12: وزن | O12: بدهکار | P12: X006 | Q12: بستانکار | R12: پوز | S12: بدهکار | T12: BANK02 | U12: X002 | W12: بله | Y12: BK03 – ۹ک مشکی | Z12: BK03 | AA12: ۹ک مشکی | AB12: 1.9 | AC12: 9 | AD12: 62000 | AE12: 75000 | AF12: 800 | AH12: پرتقال کاراکارا | AI12: پرتقال | AK12: BANK03 | AL12: ملت | AM12: 0 | AN12: BN03 | AO12: P03 | AP12: 1000 | AR12: باغدار | AS12: عمده | AU12: فروشنده سبد | AW12: مرجوعی خرید سبد | AX12: BD003 | AZ12: فروش متفرقه / صادراتی | CA12: جعبه | CB12: لیمو | CC12: — | CF12: انتقال بانکی | CG12: برگشتی | CI12: هیچ | CJ12: — | CK12: خودکار | CL12: آبگیری | CN12: BasketSellers | CO12: هیچ | CP12: lavender | CQ12: پاییز
B13: C004 | C13: امید زاهدی | D13: باغدار | F13: طرف حساب | G13: 0 | I13: آبگیری | J13: خروج | K13: آبگیری | L13: بله | M13: بله | N13: مبلغ | O13: خودکار | P13: X008 | Q13: خودکار | R13: هیچ | S13: — | W13: بله | Y13: BK04 – ریلی کوچک آبی | Z13: BK04 | AA13: ریلی کوچک آبی | AB13: 1.3 | AC13: 5 | AD13: 40000 | AE13: 50000 | AF13: 300 | AH13: پرتقال بیروتی | AI13: پرتقال | AK13: BANK04 | AL13: کشاورزی | AM13: 0 | AN13: BN04 | AO13: P04 | AP13: 1405 | AR13: باغدار | AS13: خرده‌فروش | AU13: تأمین‌کننده | AW13: مرجوعی فروش سبد | AX13: BD004 | AZ13: آبگیری | CA13: تن | CB13: گریپ‌فرویت | CF13: کارت/پوز | CG13: باطل | CI13: — | CK13: — | CL13: انعام | CN13: Suppliers | CO13: — | CP13: rose | CQ13: زمستان
B14: C005 | C14: بار شخصی قاسم زاهدی | D14: باغدار | F14: طرف حساب | G14: 0 | I14: انعام مصطفی | J14: — | K14: انعام | L14: خیر | M14: خیر | N14: مبلغ | O14: بستانکار | P14: BANK02 | Q14: بدهکار | R14: هیچ | S14: — | V14: X001 | W14: بله | Y14: BK05 – تک‌رج آبی بزرگ | Z14: BK05 | AA14: تک‌رج آبی بزرگ | AB14: 2 | AC14: 10 | AD14: 70000 | AE14: 85000 | AF14: 250 | AH14: پرتقال یافا | AI14: پرتقال | AK14: BANK05 | AL14: سپه | AM14: 0 | AN14: BN05 | AO14: P05 | AP14: 100 | AR14: باغدار | AS14: صادراتی | AU14: کارمند | AW14: انتقال سبد بین انبار | AX14: BD005 | AZ14: انعام مصطفی | CA14: عدد | CB14: سایر | CF14: پاس چک | CL14: باسکول دیگران | CN14: Staff | CP14: sand
B15: C006 | C15: هوشنگ عیسی پور | D15: باغدار | F15: طرف حساب | G15: 0 | I15: باسکول دیگران | J15: — | K15: باسکول دیگران | L15: خیر | M15: بله | N15: مبلغ | O15: بدهکار | P15: X002 | Q15: بستانکار | R15: هیچ | S15: — | W15: بله | Y15: BK06 – آبی ۲۵×۲۰ | Z15: BK06 | AA15: آبی ۲۵×۲۰ | AB15: 1.1 | AC15: 4 | AD15: 35000 | AE15: 45000 | AF15: 150 | AH15: نارنگی پیچ | AI15: نارنگی | AK15: BANK06 | AL15: مهر ایران | AM15: 0 | AN15: BN06 | AO15: P06 | AP15: 0 | AR15: باغدار | AS15: میدان بار | AU15: سایر حساب | AX15: BD006 | AZ15: باسکول دیگران | CA15: ریال | CF15: انتقال داخلی | CL15: درآمد | CN15: Other | CP15: grey
B16: C007 | C16: علی آهنگر | D16: باغدار | F16: طرف حساب | G16: 0 | I16: درآمد پوز باسکول (بدون طرف) | J16: — | K16: درآمد | L16: خیر | M16: خیر | N16: مبلغ | O16: — | Q16: — | R16: پوز | S16: بدهکار | T16: BANK02 | U16: X002 | W16: بله | Y16: BK07 – ۸ک مشکی | Z16: BK07 | AA16: ۸ک مشکی | AB16: 1.8 | AC16: 8 | AD16: 58000 | AE16: 70000 | AF16: 200 | AH16: نارنگی ژاپنی | AI16: نارنگی | AK16: BANK07 | AL16: تجارت | AM16: 0 | AN16: BN07 | AO16: P07 | AP16: خرید- | AR16: بارفروش | AS16: میدان بار شهرستان | AU16: باسکول دیگران | AX16: BD007 | AZ16: درآمد پوز باسکول (بدون طرف) | CL16: هزینه | CN16: OtherScales | CP16: teal
B17: C008 | C17: صفدر مسلمی | D17: باغدار | F17: طرف حساب | G17: 0 | I17: مرجوعی خرید | J17: خروج | K17: خرید | L17: بله | M17: بله | N17: وزن | O17: بدهکار | P17: X004 | Q17: بستانکار | R17: افزودن | S17: — | W17: بله | Y17: BK08 – | Z17: BK08 | AB17: 1.5 | AC17: 6 | AD17: 0 | AE17: 0 | AF17: 0 | AH17: نارنگی اونشو | AI17: نارنگی | AK17: BANK08 | AL17: پاسارگاد | AM17: 0 | AN17: BN08 | AO17: P08 | AP17: فروش- | AR17: بارفروش | AS17: حجره‌دار | AU17: دارایی ثابت | AX17: BD008 | AZ17: مرجوعی خرید | CL17: انتقال | CN17: Assets | CP17: peach
B18: C009 | C18: همایون بابایی | D18: باغدار | F18: طرف حساب | G18: 0 | I18: مرجوعی فروش | J18: ورود | K18: فروش | L18: بله | M18: بله | N18: وزن | O18: بستانکار | P18: X006 | Q18: بدهکار | R18: هیچ | S18: — | W18: بله | Y18: BK09 – | Z18: BK09 | AB18: 1.5 | AC18: 6 | AD18: 0 | AE18: 0 | AF18: 0 | AH18: نارنگی یافا | AI18: نارنگی | AK18: BANK09 | AL18: رفاه | AM18: 0 | AN18: BN09 | AO18: P09 | AP18: 500000000 | AR18: بارفروش | AS18: صادراتی | AU18: وام و تسهیلات | AX18: BD009 | AZ18: مرجوعی فروش | CL18: سایر | CN18: Liabilities
B19: C010 | C19: دبیر فرجی | D19: باغدار | F19: طرف حساب | G19: 0 | I19: ضایعات / افت انبار | J19: خروج | K19: هزینه | L19: بله | M19: بله | N19: وزن | O19: بستانکار | P19: X009 | Q19: بدهکار | R19: هیچ | S19: — | V19: X004 | W19: بله | Y19: BK10 – | Z19: BK10 | AB19: 1.5 | AC19: 6 | AD19: 0 | AE19: 0 | AF19: 0 | AH19: لیمو شیرین | AI19: لیمو | AK19: BANK10 | AL19: قرض‌الحسنه | AM19: 0 | AN19: BN10 | AO19: P10 | AP19: 30 | AR19: بارفروش | AS19: واسطه | AU19: سرمایه و آورده صاحبان | AX19: BD010 | AZ19: ضایعات / افت انبار | CL19: تعدیل | CN19: Equity
B20: C011 | C20: محمود علیجانی | D20: باغدار | F20: طرف حساب | G20: 0 | I20: انتقال بین انبار | J20: خروج | K20: انتقال | L20: بله | M20: خیر | N20: هیچ | O20: — | Q20: — | R20: هیچ | S20: — | W20: بله | Y20: BK11 – | Z20: BK11 | AB20: 1.5 | AC20: 6 | AD20: 0 | AE20: 0 | AF20: 0 | AH20: لیمو ترش | AI20: لیمو | AO20: P11 | AP20: ریال | AR20: بارفروش | AS20: نقدی | AU20: بانک و صندوق | AX20: BD011 | AZ20: انتقال بین انبار
B21: C012 | C21: افشین بشتکار | D21: باغدار | F21: طرف حساب | G21: 0 | I21: سایر ورود | J21: ورود | K21: سایر | L21: بله | M21: بله | N21: وزن | O21: بستانکار | P21: X011 | Q21: بدهکار | R21: افزودن | S21: — | W21: بله | Y21: BK12 – | Z21: BK12 | AB21: 1.5 | AC21: 6 | AD21: 0 | AE21: 0 | AF21: 0 | AH21: کامکوات | AI21: سایر | AO21: P12 | AP21: خیر | AR21: فروشنده سبد | AS21: سبد پلاستیکی | AX21: BD012 | AZ21: سایر ورود
B22: C013 | C22: میرقربان موسویان | D22: باغدار | F22: طرف حساب | G22: 0 | I22: سایر خروج | J22: خروج | K22: سایر | L22: بله | M22: بله | N22: وزن | O22: بدهکار | P22: X011 | Q22: بستانکار | R22: هیچ | S22: — | W22: بله | AH22: گریپ‌فرویت | AI22: گریپ‌فرویت | AR22: فروشنده سبد | AS22: سبد چوبی | AX22: BD013 | AZ22: سایر خروج
B23: C014 | C23: باباجانی (تراجیکلا) | D23: باغدار | F23: طرف حساب | G23: 0 | I23: هزینه باسکول نقدی (درآمد) | J23: — | K23: درآمد | L23: خیر | M23: خیر | N23: مبلغ | O23: — | Q23: — | R23: پوز | S23: بدهکار | T23: BANK02 | U23: X002 | W23: بله | AH23: خرمالو | AI23: سایر | AR23: فروشنده سبد | AS23: سبد مقوایی | AX23: BD014 | AZ23: هزینه باسکول نقدی (درآمد)
B24: C015 | C24: کاظم میرزازاده | D24: باغدار | F24: طرف حساب | G24: 0 | I24: خرید سبد | J24: ورود | K24: خرید | L24: خیر | M24: بله | N24: مبلغ | O24: بستانکار | P24: X005 | Q24: بدهکار | R24: هیچ | S24: — | W24: خیر | AH24: نارنج | AI24: سایر | AR24: فروشنده سبد | AS24: سایر | AX24: BD015
B25: C016 | C25: علی جانبرارپور | D25: باغدار | F25: طرف حساب | G25: 0 | I25: فروش سبد | J25: خروج | K25: فروش | L25: خیر | M25: بله | N25: مبلغ | O25: بدهکار | P25: X007 | Q25: بستانکار | R25: هیچ | S25: — | W25: خیر | AR25: تأمین‌کننده | AS25: مواد بسته‌بندی | AX25: BD016
B26: C017 | C26: لیلا محمودنیا | D26: باغدار | F26: طرف حساب | G26: 0 | I26: مرجوعی خرید سبد | J26: خروج | K26: خرید | L26: خیر | M26: بله | N26: مبلغ | O26: بدهکار | P26: X005 | Q26: بستانکار | R26: هیچ | S26: — | W26: خیر | AR26: تأمین‌کننده | AS26: واکس و رنگ | AX26: BD017
B27: C018 | C27: اسماعیل خانیا | D27: باغدار | F27: طرف حساب | G27: 0 | I27: مرجوعی فروش سبد | J27: ورود | K27: فروش | L27: خیر | M27: بله | N27: مبلغ | O27: بستانکار | P27: X007 | Q27: بدهکار | R27: هیچ | S27: — | W27: خیر | AR27: تأمین‌کننده | AS27: حمل‌ونقل | AX27: BD018
B28: C019 | C28: یوسف یوسف نژاد | D28: باغدار | F28: طرف حساب | G28: 0 | I28: انتقال سبد بین انبار | J28: خروج | K28: انتقال | L28: خیر | M28: خیر | N28: هیچ | O28: — | Q28: — | R28: هیچ | S28: — | W28: خیر | AR28: تأمین‌کننده | AS28: خدمات | AX28: BD019
B29: C020 | C29: علی نوایی | D29: باغدار | F29: طرف حساب | G29: 0 | AR29: کارمند | AS29: مدیرعامل | AX29: BD020
B30: C021 | C30: دومیری | D30: باغدار | F30: طرف حساب | G30: 0 | AR30: کارمند | AS30: حسابدار
B31: C022 | C31: شمسعلی علیجانی | D31: باغدار | F31: طرف حساب | G31: 0 | AR31: کارمند | AS31: فروشنده
B32: C023 | C32: یوسف نیا (موزیج) | D32: باغدار | F32: طرف حساب | G32: 0 | AR32: کارمند | AS32: انباردار
B33: C024 | C33: کاظم ذبیح پور | D33: باغدار | F33: طرف حساب | G33: 0 | AR33: کارمند | AS33: سرپرست خط
B34: C025 | C34: علی غلام رضاپور | D34: باغدار | F34: طرف حساب | G34: 0 | AR34: کارمند | AS34: کارگر
B35: C026 | C35: حسین شکرالله نیا | D35: باغدار | F35: طرف حساب | G35: 0 | AR35: سایر حساب | AS35: صندوق
B36: C027 | C36: سید مهدی حسینی (دوست حاج هوشنگ) | D36: باغدار | F36: طرف حساب | G36: 0 | AR36: سایر حساب | AS36: موجودی
B37: C028 | C37: آقای عزیزی | D37: باغدار | F37: طرف حساب | G37: 0 | AR37: سایر حساب | AS37: درآمد
B38: C029 | C38: آقای حبیبی (بانک صادرات) | D38: باغدار | F38: طرف حساب | G38: 0 | AR38: سایر حساب | AS38: هزینه
B39: C030 | C39: محمد علی اصغرزاده | D39: باغدار | F39: طرف حساب | G39: 0 | AR39: سایر حساب | AS39: انعام و پاداش
B40: C031 | C40: فغان پور | D40: باغدار | F40: طرف حساب | G40: 0 | AR40: سایر حساب | AS40: چک پرداختی
B41: C032 | C41: عباس پور (بهنمیر) | D41: باغدار | F41: طرف حساب | G41: 0 | AR41: سایر حساب | AS41: حساب واسط
... B51: C042 | C51: مغداد طلایی | D51: باغدار | F51: طرف حساب | G51: 0 | AR51: سرمایه و آورده صاحبان | AS51: برداشت سرمایه
B52: C043 | C52: سید عبدالله میراقازاده | D52: باغدار | F52: طرف حساب | G52: 0
B53: C044 | C53: رجب پور | D53: باغدار | F53: طرف حساب | G53: 0
B54: C045 | C54: سعید بابایی | D54: باغدار | F54: طرف حساب | G54: 0
B55: C046 | C55: مطلب عیسی پور | D55: باغدار | F55: طرف حساب | G55: 0
B56: C047 | C56: عزیز زاده | D56: باغدار | F56: طرف حساب | G56: 0
B57: C048 | C57: تقی اصغرنیا | D57: باغدار | F57: طرف حساب | G57: 0
B58: C049 | C58: مدانلو | D58: باغدار | F58: طرف حساب | G58: 0
B59: C050 | C59: خدیجه اصغرنیا | D59: باغدار | F59: طرف حساب | G59: 0
B60: C051 | C60: اصغر عزیزی | D60: باغدار | F60: طرف حساب | G60: 0
B61: C052 | C61: غلامی | D61: باغدار | F61: طرف حساب | G61: 0
B62: C053 | C62: علی عزیزنژاد | D62: باغدار | F62: طرف حساب | G62: 0
B63: C054 | C63: حسن عیسی پور | D63: باغدار | F63: طرف حساب | G63: 0
... B66: C057 | C66: کبری اصغرنیا | D66: باغدار | F66: طرف حساب | G66: 0
B67: SL001 | C67: قم — سید حسین حسینی | D67: بارفروش | E67: میدان بار شهرستان | F67: طرف حساب | G67: 0
B68: SL002 | C68: مشهد — محمد توکلی | D68: بارفروش | E68: میدان بار شهرستان | F68: طرف حساب | G68: 0
B69: SL003 | C69: اراک — پوریا خوش‌نمکیان | D69: بارفروش | E69: میدان بار شهرستان | F69: طرف حساب | G69: 0
B70: SL004 | C70: تبریز — نورزاده | D70: بارفروش | E70: میدان بار شهرستان | F70: طرف حساب | G70: 0
B71: SL005 | C71: زنجان — خانی | D71: بارفروش | E71: میدان بار شهرستان | F71: طرف حساب | G71: 0
B72: S001 | C72: حسن کوچک‌زاده | D72: فروشنده سبد | E72: سبد پلاستیکی | F72: طرف حساب | G72: 0
B73: S002 | C73: سید محمد موسویان | D73: فروشنده سبد | E73: سبد پلاستیکی | F73: طرف حساب | G73: 0
B74: S003 | C74: سید ربیع موسویان | D74: فروشنده سبد | E74: سبد پلاستیکی | F74: طرف حساب | G74: 0
B75: E001 | C75: قاسم زاهدی تیر | D75: کارمند | E75: مدیرعامل | F75: طرف حساب | G75: 0
B76: E002 | C76: (نام حسابدار) | D76: کارمند | E76: حسابدار | F76: طرف حساب | G76: 0
B77: E003 | C77: (نام فروشنده ۱) | D77: کارمند | E77: فروشنده | F77: طرف حساب | G77: 0
B78: E004 | C78: (نام انباردار) | D78: کارمند | E78: انباردار | F78: طرف حساب | G78: 0
... B116: BN10 | C116: قرض‌الحسنه | D116: بانک و صندوق | E116: حساب‌های بانکی | F116: بانک | G116: 0
B117: C058 | G117: 0
B118: C059 | G118: 0
B119: C060 | G119: 0
B120: C061 | G120: 0
B121: C062 | G121: 0
B122: C063 | G122: 0
B123: C064 | G123: 0
B124: C065 | G124: 0
B125: C066 | G125: 0
B126: C067 | G126: 0
B127: C068 | G127: 0
B128: C069 | G128: 0
... B259: BD020 | G259: 0

Sheet Help
A1: مازندشت — سورتینگ و بسته‌بندی مرکبات | E1: MAZANDASHT · CITRUS SORTING & PACKING
A2: راهنمای فاکتور
A3: چطور یک فاکتور تمیز و قابل چاپ بسازم
A4: راهنما | B4: ورود دستی | C4: خودکار | D4: ورود | E4: خروج | F4: هشدار | G4: ستون‌های زرد = ورود شما | ستون‌های خاکستری = محاسبه خودکار | روی سرستون‌ها بایستید تا راهنما باز شود
B11: • | C11: گام ۱ — کد حساب
A12: کد حساب را در کادر «کد حساب» انتخاب کنید. همه گردش‌های آن حساب — خرید، پرداخت، چک، برگشت — به ترتیب تاریخ پایین می‌آید.
B14: • | C14: گام ۲ — تیک بزنید
A15: ستون «نمایش»: ۱ یعنی این سطر در فاکتور حساب شود، ۰ یعنی حذف. جمع پایین صفحه فقط سطرهای تیک‌خورده را جمع می‌زند.
B17: • | C17: گام ۳ — چاپ
A18: Ctrl+P. صفحه برای A4 افقی تنظیم شده و همه ستون‌ها در یک صفحه جا می‌شوند. سربرگ شرکت و محل امضا آماده است.
B20: • | C20: نکته
A21: مبلغ‌ها به ریال و بدون اعشار است. اگر اعداد صفر بود: Data ← Edit Links ← Update Values.
B23: • | C23: مانده حساب
A24: «مانده نهایی» کل گردش حساب است؛ با جمع سطرهای انتخاب‌شده اشتباه نشود.
A27: برای ویرایش داده‌ها به ثبت روزانه برگردید.
