Workbook
Name AcctCodes: Sync!$B$10:$B$259
Name AcctTbl: Sync!$B$10:$G$259
Name BankCodes: Sync!$AK$10:$AK$19
Name BankTbl: Sync!$AK$10:$AN$19
Name BasketCodeCol: Sync!$Z$10:$Z$21
Name BasketTbl: Sync!$Y$10:$AF$21
Name GroupTbl: Sync!$AR$10:$AS$51
Name ListAllCodes: OFFSET(Sync!$B$10,0,0,MAX(COUNTIF(Sync!$C$10:$C$259,"?*"),1),1)
Name ListBasketOps: OFFSET(Sync!$AW$10,0,0,MAX(COUNTIF(Sync!$AW$10:$AW$14,"?*"),1),1)
Name ListBaskets: OFFSET(Sync!$Y$10,0,0,MAX(COUNTIF(Sync!$Y$10:$Y$21,"?*"),1),1)
Name ListBasketSellerCodes: OFFSET(Sync!$B$72,0,0,MAX(COUNTIF(Sync!$C$72:$C$74,"?*"),1),1)
Name ListBaskolOps: OFFSET(Sync!$AZ$10,0,0,MAX(COUNTIF(Sync!$AZ$10:$AZ$23,"?*"),1),1)
Name ListCategories: OFFSET(Sync!$CB$10,0,0,MAX(COUNTIF(Sync!$CB$10:$CB$29,"?*"),1),1)
Name ListChequeStatus: OFFSET(Sync!$CG$10,0,0,MAX(COUNTIF(Sync!$CG$10:$CG$29,"?*"),1),1)
Name ListColorKeys: OFFSET(Sync!$CP$10,0,0,MAX(COUNTIF(Sync!$CP$10:$CP$29,"?*"),1),1)
Name ListDirections: OFFSET(Sync!$CC$10,0,0,MAX(COUNTIF(Sync!$CC$10:$CC$29,"?*"),1),1)
Name ListGroups: Sync!$AU$10:$AU$19
Name ListGrowerCodes: OFFSET(Sync!$B$10,0,0,MAX(COUNTIF(Sync!$C$10:$C$66,"?*"),1),1)
Name ListInclude: OFFSET(Sync!$CH$10,0,0,MAX(COUNTIF(Sync!$CH$10:$CH$29,"?*"),1),1)
Name ListLoadBuyerCodes: OFFSET(Sync!$B$67,0,0,MAX(COUNTIF(Sync!$C$67:$C$71,"?*"),1),1)
Name ListManualRoles: OFFSET(Sync!$CI$10,0,0,MAX(COUNTIF(Sync!$CI$10:$CI$29,"?*"),1),1)
Name ListOpCategories: OFFSET(Sync!$CL$10,0,0,MAX(COUNTIF(Sync!$CL$10:$CL$29,"?*"),1),1)
Name ListOps: OFFSET(Sync!$I$10,0,0,MAX(COUNTIF(Sync!$I$10:$I$33,"?*"),1),1)
Name ListOtherScaleCodes: Sync!$AX$10:$AX$29
Name ListPartyBasis: OFFSET(Sync!$CO$10,0,0,MAX(COUNTIF(Sync!$CO$10:$CO$29,"?*"),1),1)
Name ListPartyTypes: OFFSET(Sync!$CE$10,0,0,MAX(COUNTIF(Sync!$CE$10:$CE$29,"?*"),1),1)
Name ListPayMethods: OFFSET(Sync!$CF$10,0,0,MAX(COUNTIF(Sync!$CF$10:$CF$29,"?*"),1),1)
Name ListPosEffects: OFFSET(Sync!$CJ$10,0,0,MAX(COUNTIF(Sync!$CJ$10:$CJ$29,"?*"),1),1)
Name ListProducts: OFFSET(Sync!$AH$10,0,0,MAX(COUNTIF(Sync!$AH$10:$AH$29,"?*"),1),1)
Name ListReportSheets: OFFSET(Sync!$CN$10,0,0,MAX(COUNTIF(Sync!$CN$10:$CN$29,"?*"),1),1)
Name ListSeasons: OFFSET(Sync!$CQ$10,0,0,MAX(COUNTIF(Sync!$CQ$10:$CQ$29,"?*"),1),1)
Name ListSides: OFFSET(Sync!$CK$10,0,0,MAX(COUNTIF(Sync!$CK$10:$CK$29,"?*"),1),1)
Name ListStatus: OFFSET(Sync!$CM$10,0,0,MAX(COUNTIF(Sync!$CM$10:$CM$29,"?*"),1),1)
Name ListSubgroups: OFFSET(Sync!$AR$10,0,0,MAX(COUNTIF(Sync!$AS$10:$AS$51,"?*"),1),1)
Name ListTxnDirections: OFFSET(Sync!$CR$10,0,0,MAX(COUNTIF(Sync!$CR$10:$CR$29,"?*"),1),1)
Name ListUnits: OFFSET(Sync!$CA$10,0,0,MAX(COUNTIF(Sync!$CA$10:$CA$29,"?*"),1),1)
Name ListYesNo: OFFSET(Sync!$CD$10,0,0,MAX(COUNTIF(Sync!$CD$10:$CD$29,"?*"),1),1)
Name OpTbl: Sync!$I$10:$W$33
Name ParamTbl: Sync!$AO$10:$AP$21
Name ProductTbl: Sync!$AH$10:$AI$29
Name ListBanks: Sync!$AK$10:$AK$19

Sheet Home
A1: مازندشت — سورتینگ و بسته‌بندی مرکبات | G1: MAZANDASHT · CITRUS SORTING & PACKING
A2: ثبت روزانه — باسکول، سبد و پرداخت
A3: تنها فایل ورود داده · همه گزارش‌ها و ترازنامه‌ها از همین‌جا می‌خوانند · نسخه ۰۱
A5: توزین‌های ثبت‌شده | C5: جمع خالص ورود (kg) | E5: جمع خالص خروج (kg) | G5: جمع مبالغ (ریال) | I5: وضعیت تراز
A6: =COUNTA(Scale!$B$10:$B$309) | C6: =SUMIF(Scale!$F$10:$F$309,"ورود",Scale!$N$10:$N$309) | E6: =SUMIF(Scale!$F$10:$F$309,"خروج",Scale!$N$10:$N$309) | G6: =SUM(Book!$K$10:$K$1808) | I6: =IF(ROUND(SUM(Book!$L$10:$L$1808)-SUM(Book!$M$10:$M$1808),0)=0,"✓ تراز","⚠ ناتراز")
A8: ۰۱ | B8: شیت‌های این فایل — روی هر کارت کلیک کنید
A9: باسکول | D9: سبد | G9: پرداخت
A10: ثبت ورود/خروج بار، خرید باغدار، فروش بارفروش، آبگیری، انعام و باسکول دیگران | D10: خرید، فروش و مرجوعی سبد به‌همراه موجودی خودکار | G10: پرداخت و دریافت نقدی/بانکی/چک، پاس چک و انتقال داخلی
A12: دفتر معین | D12: خلاصه | G12: راهنما
A13: همه گردش‌های طرف حساب‌ها یک‌جا — منبع گزارش‌ها | D13: تراز دفتر، گردش گروه‌ها، موجودی سبد و آمار ماهانه | G13: آموزش کامل این فایل و قواعد بدهکار/بستانکار
A18: ۰۲ | B18: شروع سریع — پنج گام — هر روز همین ترتیب را برو
A19: ۱ | B19: اول INFO را باز کنید و اگر حساب/عملیات جدیدی دارید اضافه کنید؛ بعد Update Links.
A20: ۲ | B20: در شیت باسکول، نوع عملیات را انتخاب کنید؛ جهت، نام و گروه خودکار می‌آید.
A21: ۳ | B21: وزن باسکول، تعداد سبد و فی را وارد کنید؛ وزن خالص و مبلغ خودکار محاسبه می‌شود.
A22: ۴ | B22: پول‌ها را در شیت پرداخت ثبت کنید (نقد، بانک، چک، پاس چک).
A23: ۵ | B23: شیت خلاصه را ببینید؛ اگر تراز سبز بود، گزارش/فاکتور/ترازنامه را باز کنید.
A25: ۰۳ | B25: رنگ‌ها و معنی آن‌ها
A26: خرید مرکبات | C26: فروش بار | E26: آبگیری | G26: انعام مصطفی
A27: باسکول دیگران | C27: مرجوعی/ضایعات | E27: درآمد پوز | G27: ⚠ ناتراز
A30: این فایل هیچ تعریفی از خودش ندارد: کد حساب‌ها، عملیات، وزن سبد و پارامترها همه از INFO می‌آیند. اگر فایلی را جابه‌جا کردید، هر دو فایل را با هم جابه‌جا کنید و در Excel: Data ← Edit Links ← Update Values.
A31: باز کردن فایل مادر INFO
A33: ۰۴ | B33: فایل‌های دیگر مجموعه — همه در همین پوشه · داده‌ها از همین فایل خوانده می‌شود
A34: بانک · 02_Bank.xlsx | D34: گزارش · 03_Report.xlsx | G34: فاکتور · 04_Inv.xlsx
A35: تراکنش بانکی، چک، مغایرت‌گیری | D35: صورت‌حساب باغدار و بارفروش | G35: تیک زدن سطرها و چاپ فاکتور
A36: ترازنامه · 05_Bal.xlsx | D36: بارفروشان · 06_Buyers.xlsx | G36: نمونه · 07_Demo.xlsx
A37: تراز ۴ و ۶ ستونی و کنترل | D37: ریز بار، ماهانه و مانده | G37: نمونه ساده برای یادگیری
A39: شیت POS · کنترل روزانه پز باسکول در برابر واریزی روز بعد به حساب ۲۰۰۶ صادرات؛ اگر تراز نباشد، هشدار ⚠ می‌دهد.
A40: قاعده جدید: هر مبلغی که برای خروج بار ثبت شود درآمد باسکول است و به ۲۰۰۶ می‌رود؛ برای فروش متفرقه، ستون «کد حساب / مقصد وجه» همان حسابی است که پول به آن واریز شده.

Sheet Scale
A1: مازندشت — سورتینگ و بسته‌بندی مرکبات | P1: MAZANDASHT · CITRUS SORTING & PACKING
A2: دفتر باسکول — ثبت ورود و خروج بار
A3: هر ردیف یک توزین · ابتدا نوع عملیات، بعد کد حساب، وزن، تعداد سبد و فی · ستون‌های خاکستری خودکارند
A4: راهنما | B4: ورود دستی | C4: خودکار | D4: ورود | E4: خروج | F4: هشدار | G4: ستون‌های زرد = ورود شما | ستون‌های خاکستری = محاسبه خودکار | روی سرستون‌ها بایستید تا راهنما باز شود
A5: تعداد توزین | E5: جمع خالص ورود (kg) | I5: جمع خالص خروج (kg) | M5: جمع مبالغ (ریال) | Q5: ردیف‌های ناتراز
A6: =COUNTA($B$10:$B$309) | E6: =SUMIF($F$10:$F$309,"ورود",$N$10:$N$309) | I6: =SUMIF($F$10:$F$309,"خروج",$N$10:$N$309) | M6: =SUM($P$10:$P$309) | Q6: =COUNTIF($AI$10:$AI$309,"⚠")
A7: ردیف | B7: تاریخ و سند | E7: عملیات | G7: طرف حساب | J7: بار و وزن | P7: مبلغ | R7: سمت / وضعیت / توضیح
A8: ردیف | B8: تاریخ | C8: ساعت | D8: شماره سند | E8: نوع عملیات | F8: جهت | G8: کد حساب / مقصد وجه | H8: نام حساب | I8: گروه | J8: محصول | K8: سبد | L8: وزن باسکول | M8: تعداد سبد | N8: وزن خالص | O8: فی خرید | P8: مبلغ محاسبه | Q8: مبلغ پوز/باسکول (درآمد) | R8: سمت حساب | S8: وضعیت | T8: توضیحات
A9: No. | B9: Date | C9: Time | D9: Doc | E9: Operation | F9: Direction | G9: Account / Money-to | H9: Account Name | I9: Group | J9: Product | K9: Basket | L9: Scale kg | M9: Baskets | N9: Net kg | O9: Price | P9: Amount | Q9: POS / Fee amount | R9: Side | S9: Status | T9: Notes
A10: =IF($B10="","",COUNTA($B$10:$B10)) | B10: 1405/07/01 | C10: 07:45 | D10: BS-001 | E10: خرید مرکبات | F10: =IF($E10="","",IFERROR(VLOOKUP($E10,OpTbl,2,0),"")) | G10: C001 | H10: =IF($U10="","",IFERROR(VLOOKUP($U10,AcctTbl,2,0),"کد ناشناخته")) | I10: =IF($U10="","",IFERROR(VLOOKUP($U10,AcctTbl,3,0),"")) | J10: نارنگی پیچ | K10: BK03 – ۹ک مشکی | L10: 2290 | M10: 139 | N10: =IF(OR($E10="",$L10=""),"",IFERROR(($L10-IF($M10="",0,$M10)*IFERROR(VLOOKUP($K10,BasketTbl,4,0),IFERROR(INDEX(BasketTbl,MATCH($K10,BasketCodeCol,0),4),VLOOKUP("P01",ParamTbl,2,0))))*(1-IF(VLOOKUP($E10,OpTbl,3,0)="خرید",VLOOKUP("P02",ParamTbl,2,0),0)/100),"")) | O10: 32000 | P10: =IF(OR($E10="",$L10=""),"",IFERROR(IF(VLOOKUP($E10,OpTbl,6,0)="وزن",ROUND($N10*$O10,-3),IF(VLOOKUP($E10,OpTbl,6,0)="مبلغ",ROUND($L10*$O10,-3),0)),"")) | Q10: 0 | S10: =IF($E10="","",IF($AI10="⚠","⚠ ناتراز",IF(AND(IFERROR(VLOOKUP($E10,OpTbl,4,0),"")="بله",$L10=""),"⚠ وزن",IF(AND(IFERROR(VLOOKUP($E10,OpTbl,5,0),"")="بله",$U10=""),"⚠ حساب",IF(AND(IFERROR(VLOOKUP($E10,OpTbl,6,0),"")="مبلغ",$Q10=""),"⚠ مبلغ","✓"))))) | U10: =IF($E10="","",IFERROR(IF(VLOOKUP($E10,OpTbl,14,0)<>"",VLOOKUP($E10,OpTbl,14,0),$G10),"")) | V10: =IF(OR($AJ10="",$AJ10=0,$AL10<>"بدهکار"),"",$AJ10) | W10: =IF(OR($AJ10="",$AJ10=0,$AL10<>"بستانکار"),"",$AJ10) | X10: =IF($E10="","",IFERROR(VLOOKUP($E10,OpTbl,8,0),"")) | Y10: =IF(OR($X10="",$AJ10="",$AJ10=0,$AM10<>"بدهکار"),"",$AJ10) | Z10: =IF(OR($X10="",$AJ10="",$AJ10=0,$AM10<>"بستانکار"),"",$AJ10) | AA10: =IF(OR($E10="",$AN10="—",$AN10=""),"",IFERROR(VLOOKUP($E10,OpTbl,12,0),"")) | AB10: =IF(OR($AA10="",$Q10="",$Q10=0,$AN10<>"بدهکار"),"",$Q10) | AC10: =IF(OR($AA10="",$Q10="",$Q10=0,$AN10<>"بستانکار"),"",$Q10) | AD10: =IF($AA10="","",IFERROR(VLOOKUP($E10,OpTbl,13,0),"")) | AE10: =IF(OR($AD10="",$Q10="",$Q10=0,$AN10<>"بستانکار"),"",$Q10) | AF10: =IF(OR($AD10="",$Q10="",$Q10=0,$AN10<>"بدهکار"),"",$Q10) | AG10: =SUM($V10,$Y10,$AB10,$AE10) | AH10: =SUM($W10,$Z10,$AC10,$AF10) | AI10: =IF($E10="","",IF(ROUND($AG10-$AH10,0)=0,"✓","⚠")) | AJ10: =IF(OR($E10="",$U10=""),"",IFERROR(IF(VLOOKUP($E10,OpTbl,6,0)="وزن",IF($P10="",0,$P10),IF(VLOOKUP($E10,OpTbl,6,0)="مبلغ",IF(AND($Q10<>"",$Q10<>0),$Q10,$P10),0))+IF(VLOOKUP($E10,OpTbl,10,0)="افزودن",IF($Q10="",0,$Q10),0),0)) | AK10: =IF($E10="","",IFERROR(VLOOKUP($E10,OpTbl,10,0),"")) | AL10: =IF(OR($E10="",$U10=""),"",IFERROR(IF(VLOOKUP($E10,OpTbl,7,0)="خودکار",$R10,VLOOKUP($E10,OpTbl,7,0)),"")) | AM10: =IF(OR($E10="",$X10=""),"",IFERROR(IF(VLOOKUP($E10,OpTbl,9,0)="خودکار",IF($AL10="بدهکار","بستانکار",IF($AL10="بستانکار","بدهکار","")),VLOOKUP($E10,OpTbl,9,0)),"")) | AN10: =IF($E10="","",IFERROR(VLOOKUP($E10,OpTbl,11,0),"")) | AO10: =IF($B10="","",MID($B10,6,2)) | AP10: =IF($B10="",0,1)
A11: =IF($B11="","",COUNTA($B$10:$B11)) | B11: 1405/07/01 | C11: 09:10 | D11: BS-002 | E11: خرید مرکبات | F11: =IF($E11="","",IFERROR(VLOOKUP($E11,OpTbl,2,0),"")) | G11: C003 | H11: =IF($U11="","",IFERROR(VLOOKUP($U11,AcctTbl,2,0),"کد ناشناخته")) | I11: =IF($U11="","",IFERROR(VLOOKUP($U11,AcctTbl,3,0),"")) | J11: پرتقال تامسون | K11: BK01 – ۶ک مشکی | L11: 910 | M11: 53 | N11: =IF(OR($E11="",$L11=""),"",IFERROR(($L11-IF($M11="",0,$M11)*IFERROR(VLOOKUP($K11,BasketTbl,4,0),IFERROR(INDEX(BasketTbl,MATCH($K11,BasketCodeCol,0),4),VLOOKUP("P01",ParamTbl,2,0))))*(1-IF(VLOOKUP($E11,OpTbl,3,0)="خرید",VLOOKUP("P02",ParamTbl,2,0),0)/100),"")) | O11: 35000 | P11: =IF(OR($E11="",$L11=""),"",IFERROR(IF(VLOOKUP($E11,OpTbl,6,0)="وزن",ROUND($N11*$O11,-3),IF(VLOOKUP($E11,OpTbl,6,0)="مبلغ",ROUND($L11*$O11,-3),0)),"")) | Q11: 0 | S11: =IF($E11="","",IF($AI11="⚠","⚠ ناتراز",IF(AND(IFERROR(VLOOKUP($E11,OpTbl,4,0),"")="بله",$L11=""),"⚠ وزن",IF(AND(IFERROR(VLOOKUP($E11,OpTbl,5,0),"")="بله",$U11=""),"⚠ حساب",IF(AND(IFERROR(VLOOKUP($E11,OpTbl,6,0),"")="مبلغ",$Q11=""),"⚠ مبلغ","✓"))))) | U11: =IF($E11="","",IFERROR(IF(VLOOKUP($E11,OpTbl,14,0)<>"",VLOOKUP($E11,OpTbl,14,0),$G11),"")) | V11: =IF(OR($AJ11="",$AJ11=0,$AL11<>"بدهکار"),"",$AJ11) | W11: =IF(OR($AJ11="",$AJ11=0,$AL11<>"بستانکار"),"",$AJ11) | X11: =IF($E11="","",IFERROR(VLOOKUP($E11,OpTbl,8,0),"")) | Y11: =IF(OR($X11="",$AJ11="",$AJ11=0,$AM11<>"بدهکار"),"",$AJ11) | Z11: =IF(OR($X11="",$AJ11="",$AJ11=0,$AM11<>"بستانکار"),"",$AJ11) | AA11: =IF(OR($E11="",$AN11="—",$AN11=""),"",IFERROR(VLOOKUP($E11,OpTbl,12,0),"")) | AB11: =IF(OR($AA11="",$Q11="",$Q11=0,$AN11<>"بدهکار"),"",$Q11) | AC11: =IF(OR($AA11="",$Q11="",$Q11=0,$AN11<>"بستانکار"),"",$Q11) | AD11: =IF($AA11="","",IFERROR(VLOOKUP($E11,OpTbl,13,0),"")) | AE11: =IF(OR($AD11="",$Q11="",$Q11=0,$AN11<>"بستانکار"),"",$Q11) | AF11: =IF(OR($AD11="",$Q11="",$Q11=0,$AN11<>"بدهکار"),"",$Q11) | AG11: =SUM($V11,$Y11,$AB11,$AE11) | AH11: =SUM($W11,$Z11,$AC11,$AF11) | AI11: =IF($E11="","",IF(ROUND($AG11-$AH11,0)=0,"✓","⚠")) | AJ11: =IF(OR($E11="",$U11=""),"",IFERROR(IF(VLOOKUP($E11,OpTbl,6,0)="وزن",IF($P11="",0,$P11),IF(VLOOKUP($E11,OpTbl,6,0)="مبلغ",IF(AND($Q11<>"",$Q11<>0),$Q11,$P11),0))+IF(VLOOKUP($E11,OpTbl,10,0)="افزودن",IF($Q11="",0,$Q11),0),0)) | AK11: =IF($E11="","",IFERROR(VLOOKUP($E11,OpTbl,10,0),"")) | AL11: =IF(OR($E11="",$U11=""),"",IFERROR(IF(VLOOKUP($E11,OpTbl,7,0)="خودکار",$R11,VLOOKUP($E11,OpTbl,7,0)),"")) | AM11: =IF(OR($E11="",$X11=""),"",IFERROR(IF(VLOOKUP($E11,OpTbl,9,0)="خودکار",IF($AL11="بدهکار","بستانکار",IF($AL11="بستانکار","بدهکار","")),VLOOKUP($E11,OpTbl,9,0)),"")) | AN11: =IF($E11="","",IFERROR(VLOOKUP($E11,OpTbl,11,0),"")) | AO11: =IF($B11="","",MID($B11,6,2)) | AP11: =IF($B11="",0,1)
A12: =IF($B12="","",COUNTA($B$10:$B12)) | B12: 1405/07/02 | C12: 08:20 | D12: BS-003 | E12: خرید مرکبات | F12: =IF($E12="","",IFERROR(VLOOKUP($E12,OpTbl,2,0),"")) | G12: C006 | H12: =IF($U12="","",IFERROR(VLOOKUP($U12,AcctTbl,2,0),"کد ناشناخته")) | I12: =IF($U12="","",IFERROR(VLOOKUP($U12,AcctTbl,3,0),"")) | J12: نارنگی اونشو | K12: BK01 – ۶ک مشکی | L12: 1385 | M12: 85 | N12: =IF(OR($E12="",$L12=""),"",IFERROR(($L12-IF($M12="",0,$M12)*IFERROR(VLOOKUP($K12,BasketTbl,4,0),IFERROR(INDEX(BasketTbl,MATCH($K12,BasketCodeCol,0),4),VLOOKUP("P01",ParamTbl,2,0))))*(1-IF(VLOOKUP($E12,OpTbl,3,0)="خرید",VLOOKUP("P02",ParamTbl,2,0),0)/100),"")) | O12: 30000 | P12: =IF(OR($E12="",$L12=""),"",IFERROR(IF(VLOOKUP($E12,OpTbl,6,0)="وزن",ROUND($N12*$O12,-3),IF(VLOOKUP($E12,OpTbl,6,0)="مبلغ",ROUND($L12*$O12,-3),0)),"")) | Q12: 500000 | S12: =IF($E12="","",IF($AI12="⚠","⚠ ناتراز",IF(AND(IFERROR(VLOOKUP($E12,OpTbl,4,0),"")="بله",$L12=""),"⚠ وزن",IF(AND(IFERROR(VLOOKUP($E12,OpTbl,5,0),"")="بله",$U12=""),"⚠ حساب",IF(AND(IFERROR(VLOOKUP($E12,OpTbl,6,0),"")="مبلغ",$Q12=""),"⚠ مبلغ","✓"))))) | T12: کرایه حمل ۵۰۰٬۰۰۰ | U12: =IF($E12="","",IFERROR(IF(VLOOKUP($E12,OpTbl,14,0)<>"",VLOOKUP($E12,OpTbl,14,0),$G12),"")) | V12: =IF(OR($AJ12="",$AJ12=0,$AL12<>"بدهکار"),"",$AJ12) | W12: =IF(OR($AJ12="",$AJ12=0,$AL12<>"بستانکار"),"",$AJ12) | X12: =IF($E12="","",IFERROR(VLOOKUP($E12,OpTbl,8,0),"")) | Y12: =IF(OR($X12="",$AJ12="",$AJ12=0,$AM12<>"بدهکار"),"",$AJ12) | Z12: =IF(OR($X12="",$AJ12="",$AJ12=0,$AM12<>"بستانکار"),"",$AJ12) | AA12: =IF(OR($E12="",$AN12="—",$AN12=""),"",IFERROR(VLOOKUP($E12,OpTbl,12,0),"")) | AB12: =IF(OR($AA12="",$Q12="",$Q12=0,$AN12<>"بدهکار"),"",$Q12) | AC12: =IF(OR($AA12="",$Q12="",$Q12=0,$AN12<>"بستانکار"),"",$Q12) | AD12: =IF($AA12="","",IFERROR(VLOOKUP($E12,OpTbl,13,0),"")) | AE12: =IF(OR($AD12="",$Q12="",$Q12=0,$AN12<>"بستانکار"),"",$Q12) | AF12: =IF(OR($AD12="",$Q12="",$Q12=0,$AN12<>"بدهکار"),"",$Q12) | AG12: =SUM($V12,$Y12,$AB12,$AE12) | AH12: =SUM($W12,$Z12,$AC12,$AF12) | AI12: =IF($E12="","",IF(ROUND($AG12-$AH12,0)=0,"✓","⚠")) | AJ12: =IF(OR($E12="",$U12=""),"",IFERROR(IF(VLOOKUP($E12,OpTbl,6,0)="وزن",IF($P12="",0,$P12),IF(VLOOKUP($E12,OpTbl,6,0)="مبلغ",IF(AND($Q12<>"",$Q12<>0),$Q12,$P12),0))+IF(VLOOKUP($E12,OpTbl,10,0)="افزودن",IF($Q12="",0,$Q12),0),0)) | AK12: =IF($E12="","",IFERROR(VLOOKUP($E12,OpTbl,10,0),"")) | AL12: =IF(OR($E12="",$U12=""),"",IFERROR(IF(VLOOKUP($E12,OpTbl,7,0)="خودکار",$R12,VLOOKUP($E12,OpTbl,7,0)),"")) | AM12: =IF(OR($E12="",$X12=""),"",IFERROR(IF(VLOOKUP($E12,OpTbl,9,0)="خودکار",IF($AL12="بدهکار","بستانکار",IF($AL12="بستانکار","بدهکار","")),VLOOKUP($E12,OpTbl,9,0)),"")) | AN12: =IF($E12="","",IFERROR(VLOOKUP($E12,OpTbl,11,0),"")) | AO12: =IF($B12="","",MID($B12,6,2)) | AP12: =IF($B12="",0,1)
A13: =IF($B13="","",COUNTA($B$10:$B13)) | B13: 1405/07/02 | C13: 11:30 | D13: BS-004 | E13: خرید مرکبات | F13: =IF($E13="","",IFERROR(VLOOKUP($E13,OpTbl,2,0),"")) | G13: C002 | H13: =IF($U13="","",IFERROR(VLOOKUP($U13,AcctTbl,2,0),"کد ناشناخته")) | I13: =IF($U13="","",IFERROR(VLOOKUP($U13,AcctTbl,3,0),"")) | J13: پرتقال خونی | K13: BK03 – ۹ک مشکی | L13: 605 | M13: 36 | N13: =IF(OR($E13="",$L13=""),"",IFERROR(($L13-IF($M13="",0,$M13)*IFERROR(VLOOKUP($K13,BasketTbl,4,0),IFERROR(INDEX(BasketTbl,MATCH($K13,BasketCodeCol,0),4),VLOOKUP("P01",ParamTbl,2,0))))*(1-IF(VLOOKUP($E13,OpTbl,3,0)="خرید",VLOOKUP("P02",ParamTbl,2,0),0)/100),"")) | O13: 38000 | P13: =IF(OR($E13="",$L13=""),"",IFERROR(IF(VLOOKUP($E13,OpTbl,6,0)="وزن",ROUND($N13*$O13,-3),IF(VLOOKUP($E13,OpTbl,6,0)="مبلغ",ROUND($L13*$O13,-3),0)),"")) | Q13: 0 | S13: =IF($E13="","",IF($AI13="⚠","⚠ ناتراز",IF(AND(IFERROR(VLOOKUP($E13,OpTbl,4,0),"")="بله",$L13=""),"⚠ وزن",IF(AND(IFERROR(VLOOKUP($E13,OpTbl,5,0),"")="بله",$U13=""),"⚠ حساب",IF(AND(IFERROR(VLOOKUP($E13,OpTbl,6,0),"")="مبلغ",$Q13=""),"⚠ مبلغ","✓"))))) | U13: =IF($E13="","",IFERROR(IF(VLOOKUP($E13,OpTbl,14,0)<>"",VLOOKUP($E13,OpTbl,14,0),$G13),"")) | V13: =IF(OR($AJ13="",$AJ13=0,$AL13<>"بدهکار"),"",$AJ13) | W13: =IF(OR($AJ13="",$AJ13=0,$AL13<>"بستانکار"),"",$AJ13) | X13: =IF($E13="","",IFERROR(VLOOKUP($E13,OpTbl,8,0),"")) | Y13: =IF(OR($X13="",$AJ13="",$AJ13=0,$AM13<>"بدهکار"),"",$AJ13) | Z13: =IF(OR($X13="",$AJ13="",$AJ13=0,$AM13<>"بستانکار"),"",$AJ13) | AA13: =IF(OR($E13="",$AN13="—",$AN13=""),"",IFERROR(VLOOKUP($E13,OpTbl,12,0),"")) | AB13: =IF(OR($AA13="",$Q13="",$Q13=0,$AN13<>"بدهکار"),"",$Q13) | AC13: =IF(OR($AA13="",$Q13="",$Q13=0,$AN13<>"بستانکار"),"",$Q13) | AD13: =IF($AA13="","",IFERROR(VLOOKUP($E13,OpTbl,13,0),"")) | AE13: =IF(OR($AD13="",$Q13="",$Q13=0,$AN13<>"بستانکار"),"",$Q13) | AF13: =IF(OR($AD13="",$Q13="",$Q13=0,$AN13<>"بدهکار"),"",$Q13) | AG13: =SUM($V13,$Y13,$AB13,$AE13) | AH13: =SUM($W13,$Z13,$AC13,$AF13) | AI13: =IF($E13="","",IF(ROUND($AG13-$AH13,0)=0,"✓","⚠")) | AJ13: =IF(OR($E13="",$U13=""),"",IFERROR(IF(VLOOKUP($E13,OpTbl,6,0)="وزن",IF($P13="",0,$P13),IF(VLOOKUP($E13,OpTbl,6,0)="مبلغ",IF(AND($Q13<>"",$Q13<>0),$Q13,$P13),0))+IF(VLOOKUP($E13,OpTbl,10,0)="افزودن",IF($Q13="",0,$Q13),0),0)) | AK13: =IF($E13="","",IFERROR(VLOOKUP($E13,OpTbl,10,0),"")) | AL13: =IF(OR($E13="",$U13=""),"",IFERROR(IF(VLOOKUP($E13,OpTbl,7,0)="خودکار",$R13,VLOOKUP($E13,OpTbl,7,0)),"")) | AM13: =IF(OR($E13="",$X13=""),"",IFERROR(IF(VLOOKUP($E13,OpTbl,9,0)="خودکار",IF($AL13="بدهکار","بستانکار",IF($AL13="بستانکار","بدهکار","")),VLOOKUP($E13,OpTbl,9,0)),"")) | AN13: =IF($E13="","",IFERROR(VLOOKUP($E13,OpTbl,11,0),"")) | AO13: =IF($B13="","",MID($B13,6,2)) | AP13: =IF($B13="",0,1)
A14: =IF($B14="","",COUNTA($B$10:$B14)) | B14: 1405/07/03 | C14: 07:50 | D14: BS-005 | E14: خرید مرکبات | F14: =IF($E14="","",IFERROR(VLOOKUP($E14,OpTbl,2,0),"")) | G14: C008 | H14: =IF($U14="","",IFERROR(VLOOKUP($U14,AcctTbl,2,0),"کد ناشناخته")) | I14: =IF($U14="","",IFERROR(VLOOKUP($U14,AcctTbl,3,0),"")) | J14: نارنگی ژاپنی | K14: BK07 – ۸ک مشکی | L14: 1762 | M14: 108 | N14: =IF(OR($E14="",$L14=""),"",IFERROR(($L14-IF($M14="",0,$M14)*IFERROR(VLOOKUP($K14,BasketTbl,4,0),IFERROR(INDEX(BasketTbl,MATCH($K14,BasketCodeCol,0),4),VLOOKUP("P01",ParamTbl,2,0))))*(1-IF(VLOOKUP($E14,OpTbl,3,0)="خرید",VLOOKUP("P02",ParamTbl,2,0),0)/100),"")) | O14: 31000 | P14: =IF(OR($E14="",$L14=""),"",IFERROR(IF(VLOOKUP($E14,OpTbl,6,0)="وزن",ROUND($N14*$O14,-3),IF(VLOOKUP($E14,OpTbl,6,0)="مبلغ",ROUND($L14*$O14,-3),0)),"")) | Q14: 0 | S14: =IF($E14="","",IF($AI14="⚠","⚠ ناتراز",IF(AND(IFERROR(VLOOKUP($E14,OpTbl,4,0),"")="بله",$L14=""),"⚠ وزن",IF(AND(IFERROR(VLOOKUP($E14,OpTbl,5,0),"")="بله",$U14=""),"⚠ حساب",IF(AND(IFERROR(VLOOKUP($E14,OpTbl,6,0),"")="مبلغ",$Q14=""),"⚠ مبلغ","✓"))))) | U14: =IF($E14="","",IFERROR(IF(VLOOKUP($E14,OpTbl,14,0)<>"",VLOOKUP($E14,OpTbl,14,0),$G14),"")) | V14: =IF(OR($AJ14="",$AJ14=0,$AL14<>"بدهکار"),"",$AJ14) | W14: =IF(OR($AJ14="",$AJ14=0,$AL14<>"بستانکار"),"",$AJ14) | X14: =IF($E14="","",IFERROR(VLOOKUP($E14,OpTbl,8,0),"")) | Y14: =IF(OR($X14="",$AJ14="",$AJ14=0,$AM14<>"بدهکار"),"",$AJ14) | Z14: =IF(OR($X14="",$AJ14="",$AJ14=0,$AM14<>"بستانکار"),"",$AJ14) | AA14: =IF(OR($E14="",$AN14="—",$AN14=""),"",IFERROR(VLOOKUP($E14,OpTbl,12,0),"")) | AB14: =IF(OR($AA14="",$Q14="",$Q14=0,$AN14<>"بدهکار"),"",$Q14) | AC14: =IF(OR($AA14="",$Q14="",$Q14=0,$AN14<>"بستانکار"),"",$Q14) | AD14: =IF($AA14="","",IFERROR(VLOOKUP($E14,OpTbl,13,0),"")) | AE14: =IF(OR($AD14="",$Q14="",$Q14=0,$AN14<>"بستانکار"),"",$Q14) | AF14: =IF(OR($AD14="",$Q14="",$Q14=0,$AN14<>"بدهکار"),"",$Q14) | AG14: =SUM($V14,$Y14,$AB14,$AE14) | AH14: =SUM($W14,$Z14,$AC14,$AF14) | AI14: =IF($E14="","",IF(ROUND($AG14-$AH14,0)=0,"✓","⚠")) | AJ14: =IF(OR($E14="",$U14=""),"",IFERROR(IF(VLOOKUP($E14,OpTbl,6,0)="وزن",IF($P14="",0,$P14),IF(VLOOKUP($E14,OpTbl,6,0)="مبلغ",IF(AND($Q14<>"",$Q14<>0),$Q14,$P14),0))+IF(VLOOKUP($E14,OpTbl,10,0)="افزودن",IF($Q14="",0,$Q14),0),0)) | AK14: =IF($E14="","",IFERROR(VLOOKUP($E14,OpTbl,10,0),"")) | AL14: =IF(OR($E14="",$U14=""),"",IFERROR(IF(VLOOKUP($E14,OpTbl,7,0)="خودکار",$R14,VLOOKUP($E14,OpTbl,7,0)),"")) | AM14: =IF(OR($E14="",$X14=""),"",IFERROR(IF(VLOOKUP($E14,OpTbl,9,0)="خودکار",IF($AL14="بدهکار","بستانکار",IF($AL14="بستانکار","بدهکار","")),VLOOKUP($E14,OpTbl,9,0)),"")) | AN14: =IF($E14="","",IFERROR(VLOOKUP($E14,OpTbl,11,0),"")) | AO14: =IF($B14="","",MID($B14,6,2)) | AP14: =IF($B14="",0,1)
A15: =IF($B15="","",COUNTA($B$10:$B15)) | B15: 1405/07/03 | C15: 10:15 | D15: BS-006 | E15: فروش بار (بارفروش) | F15: =IF($E15="","",IFERROR(VLOOKUP($E15,OpTbl,2,0),"")) | G15: SL001 | H15: =IF($U15="","",IFERROR(VLOOKUP($U15,AcctTbl,2,0),"کد ناشناخته")) | I15: =IF($U15="","",IFERROR(VLOOKUP($U15,AcctTbl,3,0),"")) | J15: پرتقال تامسون | K15: BK03 – ۹ک مشکی | L15: 2500 | M15: 0 | N15: =IF(OR($E15="",$L15=""),"",IFERROR(($L15-IF($M15="",0,$M15)*IFERROR(VLOOKUP($K15,BasketTbl,4,0),IFERROR(INDEX(BasketTbl,MATCH($K15,BasketCodeCol,0),4),VLOOKUP("P01",ParamTbl,2,0))))*(1-IF(VLOOKUP($E15,OpTbl,3,0)="خرید",VLOOKUP("P02",ParamTbl,2,0),0)/100),"")) | O15: 58000 | P15: =IF(OR($E15="",$L15=""),"",IFERROR(IF(VLOOKUP($E15,OpTbl,6,0)="وزن",ROUND($N15*$O15,-3),IF(VLOOKUP($E15,OpTbl,6,0)="مبلغ",ROUND($L15*$O15,-3),0)),"")) | Q15: 120000 | S15: =IF($E15="","",IF($AI15="⚠","⚠ ناتراز",IF(AND(IFERROR(VLOOKUP($E15,OpTbl,4,0),"")="بله",$L15=""),"⚠ وزن",IF(AND(IFERROR(VLOOKUP($E15,OpTbl,5,0),"")="بله",$U15=""),"⚠ حساب",IF(AND(IFERROR(VLOOKUP($E15,OpTbl,6,0),"")="مبلغ",$Q15=""),"⚠ مبلغ","✓"))))) | T15: هزینه باسکول پوز | U15: =IF($E15="","",IFERROR(IF(VLOOKUP($E15,OpTbl,14,0)<>"",VLOOKUP($E15,OpTbl,14,0),$G15),"")) | V15: =IF(OR($AJ15="",$AJ15=0,$AL15<>"بدهکار"),"",$AJ15) | W15: =IF(OR($AJ15="",$AJ15=0,$AL15<>"بستانکار"),"",$AJ15) | X15: =IF($E15="","",IFERROR(VLOOKUP($E15,OpTbl,8,0),"")) | Y15: =IF(OR($X15="",$AJ15="",$AJ15=0,$AM15<>"بدهکار"),"",$AJ15) | Z15: =IF(OR($X15="",$AJ15="",$AJ15=0,$AM15<>"بستانکار"),"",$AJ15) | AA15: =IF(OR($E15="",$AN15="—",$AN15=""),"",IFERROR(VLOOKUP($E15,OpTbl,12,0),"")) | AB15: =IF(OR($AA15="",$Q15="",$Q15=0,$AN15<>"بدهکار"),"",$Q15) | AC15: =IF(OR($AA15="",$Q15="",$Q15=0,$AN15<>"بستانکار"),"",$Q15) | AD15: =IF($AA15="","",IFERROR(VLOOKUP($E15,OpTbl,13,0),"")) | AE15: =IF(OR($AD15="",$Q15="",$Q15=0,$AN15<>"بستانکار"),"",$Q15) | AF15: =IF(OR($AD15="",$Q15="",$Q15=0,$AN15<>"بدهکار"),"",$Q15) | AG15: =SUM($V15,$Y15,$AB15,$AE15) | AH15: =SUM($W15,$Z15,$AC15,$AF15) | AI15: =IF($E15="","",IF(ROUND($AG15-$AH15,0)=0,"✓","⚠")) | AJ15: =IF(OR($E15="",$U15=""),"",IFERROR(IF(VLOOKUP($E15,OpTbl,6,0)="وزن",IF($P15="",0,$P15),IF(VLOOKUP($E15,OpTbl,6,0)="مبلغ",IF(AND($Q15<>"",$Q15<>0),$Q15,$P15),0))+IF(VLOOKUP($E15,OpTbl,10,0)="افزودن",IF($Q15="",0,$Q15),0),0)) | AK15: =IF($E15="","",IFERROR(VLOOKUP($E15,OpTbl,10,0),"")) | AL15: =IF(OR($E15="",$U15=""),"",IFERROR(IF(VLOOKUP($E15,OpTbl,7,0)="خودکار",$R15,VLOOKUP($E15,OpTbl,7,0)),"")) | AM15: =IF(OR($E15="",$X15=""),"",IFERROR(IF(VLOOKUP($E15,OpTbl,9,0)="خودکار",IF($AL15="بدهکار","بستانکار",IF($AL15="بستانکار","بدهکار","")),VLOOKUP($E15,OpTbl,9,0)),"")) | AN15: =IF($E15="","",IFERROR(VLOOKUP($E15,OpTbl,11,0),"")) | AO15: =IF($B15="","",MID($B15,6,2)) | AP15: =IF($B15="",0,1)
A16: =IF($B16="","",COUNTA($B$10:$B16)) | B16: 1405/07/04 | C16: 09:00 | D16: BS-007 | E16: خرید مرکبات | F16: =IF($E16="","",IFERROR(VLOOKUP($E16,OpTbl,2,0),"")) | G16: C004 | H16: =IF($U16="","",IFERROR(VLOOKUP($U16,AcctTbl,2,0),"کد ناشناخته")) | I16: =IF($U16="","",IFERROR(VLOOKUP($U16,AcctTbl,3,0),"")) | J16: نارنگی پیچ | K16: BK01 – ۶ک مشکی | L16: 640 | M16: 38 | N16: =IF(OR($E16="",$L16=""),"",IFERROR(($L16-IF($M16="",0,$M16)*IFERROR(VLOOKUP($K16,BasketTbl,4,0),IFERROR(INDEX(BasketTbl,MATCH($K16,BasketCodeCol,0),4),VLOOKUP("P01",ParamTbl,2,0))))*(1-IF(VLOOKUP($E16,OpTbl,3,0)="خرید",VLOOKUP("P02",ParamTbl,2,0),0)/100),"")) | O16: 33000 | P16: =IF(OR($E16="",$L16=""),"",IFERROR(IF(VLOOKUP($E16,OpTbl,6,0)="وزن",ROUND($N16*$O16,-3),IF(VLOOKUP($E16,OpTbl,6,0)="مبلغ",ROUND($L16*$O16,-3),0)),"")) | Q16: 0 | S16: =IF($E16="","",IF($AI16="⚠","⚠ ناتراز",IF(AND(IFERROR(VLOOKUP($E16,OpTbl,4,0),"")="بله",$L16=""),"⚠ وزن",IF(AND(IFERROR(VLOOKUP($E16,OpTbl,5,0),"")="بله",$U16=""),"⚠ حساب",IF(AND(IFERROR(VLOOKUP($E16,OpTbl,6,0),"")="مبلغ",$Q16=""),"⚠ مبلغ","✓"))))) | U16: =IF($E16="","",IFERROR(IF(VLOOKUP($E16,OpTbl,14,0)<>"",VLOOKUP($E16,OpTbl,14,0),$G16),"")) | V16: =IF(OR($AJ16="",$AJ16=0,$AL16<>"بدهکار"),"",$AJ16) | W16: =IF(OR($AJ16="",$AJ16=0,$AL16<>"بستانکار"),"",$AJ16) | X16: =IF($E16="","",IFERROR(VLOOKUP($E16,OpTbl,8,0),"")) | Y16: =IF(OR($X16="",$AJ16="",$AJ16=0,$AM16<>"بدهکار"),"",$AJ16) | Z16: =IF(OR($X16="",$AJ16="",$AJ16=0,$AM16<>"بستانکار"),"",$AJ16) | AA16: =IF(OR($E16="",$AN16="—",$AN16=""),"",IFERROR(VLOOKUP($E16,OpTbl,12,0),"")) | AB16: =IF(OR($AA16="",$Q16="",$Q16=0,$AN16<>"بدهکار"),"",$Q16) | AC16: =IF(OR($AA16="",$Q16="",$Q16=0,$AN16<>"بستانکار"),"",$Q16) | AD16: =IF($AA16="","",IFERROR(VLOOKUP($E16,OpTbl,13,0),"")) | AE16: =IF(OR($AD16="",$Q16="",$Q16=0,$AN16<>"بستانکار"),"",$Q16) | AF16: =IF(OR($AD16="",$Q16="",$Q16=0,$AN16<>"بدهکار"),"",$Q16) | AG16: =SUM($V16,$Y16,$AB16,$AE16) | AH16: =SUM($W16,$Z16,$AC16,$AF16) | AI16: =IF($E16="","",IF(ROUND($AG16-$AH16,0)=0,"✓","⚠")) | AJ16: =IF(OR($E16="",$U16=""),"",IFERROR(IF(VLOOKUP($E16,OpTbl,6,0)="وزن",IF($P16="",0,$P16),IF(VLOOKUP($E16,OpTbl,6,0)="مبلغ",IF(AND($Q16<>"",$Q16<>0),$Q16,$P16),0))+IF(VLOOKUP($E16,OpTbl,10,0)="افزودن",IF($Q16="",0,$Q16),0),0)) | AK16: =IF($E16="","",IFERROR(VLOOKUP($E16,OpTbl,10,0),"")) | AL16: =IF(OR($E16="",$U16=""),"",IFERROR(IF(VLOOKUP($E16,OpTbl,7,0)="خودکار",$R16,VLOOKUP($E16,OpTbl,7,0)),"")) | AM16: =IF(OR($E16="",$X16=""),"",IFERROR(IF(VLOOKUP($E16,OpTbl,9,0)="خودکار",IF($AL16="بدهکار","بستانکار",IF($AL16="بستانکار","بدهکار","")),VLOOKUP($E16,OpTbl,9,0)),"")) | AN16: =IF($E16="","",IFERROR(VLOOKUP($E16,OpTbl,11,0),"")) | AO16: =IF($B16="","",MID($B16,6,2)) | AP16: =IF($B16="",0,1)
A17: =IF($B17="","",COUNTA($B$10:$B17)) | B17: 1405/07/04 | C17: 13:20 | D17: BS-008 | E17: فروش بار (بارفروش) | F17: =IF($E17="","",IFERROR(VLOOKUP($E17,OpTbl,2,0),"")) | G17: SL002 | H17: =IF($U17="","",IFERROR(VLOOKUP($U17,AcctTbl,2,0),"کد ناشناخته")) | I17: =IF($U17="","",IFERROR(VLOOKUP($U17,AcctTbl,3,0),"")) | J17: نارنگی اونشو | K17: BK03 – ۹ک مشکی | L17: 1800 | M17: 0 | N17: =IF(OR($E17="",$L17=""),"",IFERROR(($L17-IF($M17="",0,$M17)*IFERROR(VLOOKUP($K17,BasketTbl,4,0),IFERROR(INDEX(BasketTbl,MATCH($K17,BasketCodeCol,0),4),VLOOKUP("P01",ParamTbl,2,0))))*(1-IF(VLOOKUP($E17,OpTbl,3,0)="خرید",VLOOKUP("P02",ParamTbl,2,0),0)/100),"")) | O17: 52000 | P17: =IF(OR($E17="",$L17=""),"",IFERROR(IF(VLOOKUP($E17,OpTbl,6,0)="وزن",ROUND($N17*$O17,-3),IF(VLOOKUP($E17,OpTbl,6,0)="مبلغ",ROUND($L17*$O17,-3),0)),"")) | Q17: 90000 | S17: =IF($E17="","",IF($AI17="⚠","⚠ ناتراز",IF(AND(IFERROR(VLOOKUP($E17,OpTbl,4,0),"")="بله",$L17=""),"⚠ وزن",IF(AND(IFERROR(VLOOKUP($E17,OpTbl,5,0),"")="بله",$U17=""),"⚠ حساب",IF(AND(IFERROR(VLOOKUP($E17,OpTbl,6,0),"")="مبلغ",$Q17=""),"⚠ مبلغ","✓"))))) | T17: هزینه باسکول پوز | U17: =IF($E17="","",IFERROR(IF(VLOOKUP($E17,OpTbl,14,0)<>"",VLOOKUP($E17,OpTbl,14,0),$G17),"")) | V17: =IF(OR($AJ17="",$AJ17=0,$AL17<>"بدهکار"),"",$AJ17) | W17: =IF(OR($AJ17="",$AJ17=0,$AL17<>"بستانکار"),"",$AJ17) | X17: =IF($E17="","",IFERROR(VLOOKUP($E17,OpTbl,8,0),"")) | Y17: =IF(OR($X17="",$AJ17="",$AJ17=0,$AM17<>"بدهکار"),"",$AJ17) | Z17: =IF(OR($X17="",$AJ17="",$AJ17=0,$AM17<>"بستانکار"),"",$AJ17) | AA17: =IF(OR($E17="",$AN17="—",$AN17=""),"",IFERROR(VLOOKUP($E17,OpTbl,12,0),"")) | AB17: =IF(OR($AA17="",$Q17="",$Q17=0,$AN17<>"بدهکار"),"",$Q17) | AC17: =IF(OR($AA17="",$Q17="",$Q17=0,$AN17<>"بستانکار"),"",$Q17) | AD17: =IF($AA17="","",IFERROR(VLOOKUP($E17,OpTbl,13,0),"")) | AE17: =IF(OR($AD17="",$Q17="",$Q17=0,$AN17<>"بستانکار"),"",$Q17) | AF17: =IF(OR($AD17="",$Q17="",$Q17=0,$AN17<>"بدهکار"),"",$Q17) | AG17: =SUM($V17,$Y17,$AB17,$AE17) | AH17: =SUM($W17,$Z17,$AC17,$AF17) | AI17: =IF($E17="","",IF(ROUND($AG17-$AH17,0)=0,"✓","⚠")) | AJ17: =IF(OR($E17="",$U17=""),"",IFERROR(IF(VLOOKUP($E17,OpTbl,6,0)="وزن",IF($P17="",0,$P17),IF(VLOOKUP($E17,OpTbl,6,0)="مبلغ",IF(AND($Q17<>"",$Q17<>0),$Q17,$P17),0))+IF(VLOOKUP($E17,OpTbl,10,0)="افزودن",IF($Q17="",0,$Q17),0),0)) | AK17: =IF($E17="","",IFERROR(VLOOKUP($E17,OpTbl,10,0),"")) | AL17: =IF(OR($E17="",$U17=""),"",IFERROR(IF(VLOOKUP($E17,OpTbl,7,0)="خودکار",$R17,VLOOKUP($E17,OpTbl,7,0)),"")) | AM17: =IF(OR($E17="",$X17=""),"",IFERROR(IF(VLOOKUP($E17,OpTbl,9,0)="خودکار",IF($AL17="بدهکار","بستانکار",IF($AL17="بستانکار","بدهکار","")),VLOOKUP($E17,OpTbl,9,0)),"")) | AN17: =IF($E17="","",IFERROR(VLOOKUP($E17,OpTbl,11,0),"")) | AO17: =IF($B17="","",MID($B17,6,2)) | AP17: =IF($B17="",0,1)
A18: =IF($B18="","",COUNTA($B$10:$B18)) | B18: 1405/07/05 | C18: 08:05 | D18: BS-009 | E18: آبگیری | F18: =IF($E18="","",IFERROR(VLOOKUP($E18,OpTbl,2,0),"")) | G18: C007 | H18: =IF($U18="","",IFERROR(VLOOKUP($U18,AcctTbl,2,0),"کد ناشناخته")) | I18: =IF($U18="","",IFERROR(VLOOKUP($U18,AcctTbl,3,0),"")) | J18: نارنگی پیچ | K18: BK01 – ۶ک مشکی | L18: 800 | M18: 0 | N18: =IF(OR($E18="",$L18=""),"",IFERROR(($L18-IF($M18="",0,$M18)*IFERROR(VLOOKUP($K18,BasketTbl,4,0),IFERROR(INDEX(BasketTbl,MATCH($K18,BasketCodeCol,0),4),VLOOKUP("P01",ParamTbl,2,0))))*(1-IF(VLOOKUP($E18,OpTbl,3,0)="خرید",VLOOKUP("P02",ParamTbl,2,0),0)/100),"")) | O18: 0 | P18: =IF(OR($E18="",$L18=""),"",IFERROR(IF(VLOOKUP($E18,OpTbl,6,0)="وزن",ROUND($N18*$O18,-3),IF(VLOOKUP($E18,OpTbl,6,0)="مبلغ",ROUND($L18*$O18,-3),0)),"")) | Q18: 12000000 | R18: بستانکار | S18: =IF($E18="","",IF($AI18="⚠","⚠ ناتراز",IF(AND(IFERROR(VLOOKUP($E18,OpTbl,4,0),"")="بله",$L18=""),"⚠ وزن",IF(AND(IFERROR(VLOOKUP($E18,OpTbl,5,0),"")="بله",$U18=""),"⚠ حساب",IF(AND(IFERROR(VLOOKUP($E18,OpTbl,6,0),"")="مبلغ",$Q18=""),"⚠ مبلغ","✓"))))) | T18: آبگیری — طرف حساب بستانکار | U18: =IF($E18="","",IFERROR(IF(VLOOKUP($E18,OpTbl,14,0)<>"",VLOOKUP($E18,OpTbl,14,0),$G18),"")) | V18: =IF(OR($AJ18="",$AJ18=0,$AL18<>"بدهکار"),"",$AJ18) | W18: =IF(OR($AJ18="",$AJ18=0,$AL18<>"بستانکار"),"",$AJ18) | X18: =IF($E18="","",IFERROR(VLOOKUP($E18,OpTbl,8,0),"")) | Y18: =IF(OR($X18="",$AJ18="",$AJ18=0,$AM18<>"بدهکار"),"",$AJ18) | Z18: =IF(OR($X18="",$AJ18="",$AJ18=0,$AM18<>"بستانکار"),"",$AJ18) | AA18: =IF(OR($E18="",$AN18="—",$AN18=""),"",IFERROR(VLOOKUP($E18,OpTbl,12,0),"")) | AB18: =IF(OR($AA18="",$Q18="",$Q18=0,$AN18<>"بدهکار"),"",$Q18) | AC18: =IF(OR($AA18="",$Q18="",$Q18=0,$AN18<>"بستانکار"),"",$Q18) | AD18: =IF($AA18="","",IFERROR(VLOOKUP($E18,OpTbl,13,0),"")) | AE18: =IF(OR($AD18="",$Q18="",$Q18=0,$AN18<>"بستانکار"),"",$Q18) | AF18: =IF(OR($AD18="",$Q18="",$Q18=0,$AN18<>"بدهکار"),"",$Q18) | AG18: =SUM($V18,$Y18,$AB18,$AE18) | AH18: =SUM($W18,$Z18,$AC18,$AF18) | AI18: =IF($E18="","",IF(ROUND($AG18-$AH18,0)=0,"✓","⚠")) | AJ18: =IF(OR($E18="",$U18=""),"",IFERROR(IF(VLOOKUP($E18,OpTbl,6,0)="وزن",IF($P18="",0,$P18),IF(VLOOKUP($E18,OpTbl,6,0)="مبلغ",IF(AND($Q18<>"",$Q18<>0),$Q18,$P18),0))+IF(VLOOKUP($E18,OpTbl,10,0)="افزودن",IF($Q18="",0,$Q18),0),0)) | AK18: =IF($E18="","",IFERROR(VLOOKUP($E18,OpTbl,10,0),"")) | AL18: =IF(OR($E18="",$U18=""),"",IFERROR(IF(VLOOKUP($E18,OpTbl,7,0)="خودکار",$R18,VLOOKUP($E18,OpTbl,7,0)),"")) | AM18: =IF(OR($E18="",$X18=""),"",IFERROR(IF(VLOOKUP($E18,OpTbl,9,0)="خودکار",IF($AL18="بدهکار","بستانکار",IF($AL18="بستانکار","بدهکار","")),VLOOKUP($E18,OpTbl,9,0)),"")) | AN18: =IF($E18="","",IFERROR(VLOOKUP($E18,OpTbl,11,0),"")) | AO18: =IF($B18="","",MID($B18,6,2)) | AP18: =IF($B18="",0,1)
A19: =IF($B19="","",COUNTA($B$10:$B19)) | B19: 1405/07/05 | C19: 10:40 | D19: BS-010 | E19: انعام مصطفی | F19: =IF($E19="","",IFERROR(VLOOKUP($E19,OpTbl,2,0),"")) | H19: =IF($U19="","",IFERROR(VLOOKUP($U19,AcctTbl,2,0),"کد ناشناخته")) | I19: =IF($U19="","",IFERROR(VLOOKUP($U19,AcctTbl,3,0),"")) | L19: 0 | M19: 0 | N19: =IF(OR($E19="",$L19=""),"",IFERROR(($L19-IF($M19="",0,$M19)*IFERROR(VLOOKUP($K19,BasketTbl,4,0),IFERROR(INDEX(BasketTbl,MATCH($K19,BasketCodeCol,0),4),VLOOKUP("P01",ParamTbl,2,0))))*(1-IF(VLOOKUP($E19,OpTbl,3,0)="خرید",VLOOKUP("P02",ParamTbl,2,0),0)/100),"")) | O19: 0 | P19: =IF(OR($E19="",$L19=""),"",IFERROR(IF(VLOOKUP($E19,OpTbl,6,0)="وزن",ROUND($N19*$O19,-3),IF(VLOOKUP($E19,OpTbl,6,0)="مبلغ",ROUND($L19*$O19,-3),0)),"")) | Q19: 500000 | S19: =IF($E19="","",IF($AI19="⚠","⚠ ناتراز",IF(AND(IFERROR(VLOOKUP($E19,OpTbl,4,0),"")="بله",$L19=""),"⚠ وزن",IF(AND(IFERROR(VLOOKUP($E19,OpTbl,5,0),"")="بله",$U19=""),"⚠ حساب",IF(AND(IFERROR(VLOOKUP($E19,OpTbl,6,0),"")="مبلغ",$Q19=""),"⚠ مبلغ","✓"))))) | T19: انعام از پوز باسکول | U19: =IF($E19="","",IFERROR(IF(VLOOKUP($E19,OpTbl,14,0)<>"",VLOOKUP($E19,OpTbl,14,0),$G19),"")) | V19: =IF(OR($AJ19="",$AJ19=0,$AL19<>"بدهکار"),"",$AJ19) | W19: =IF(OR($AJ19="",$AJ19=0,$AL19<>"بستانکار"),"",$AJ19) | X19: =IF($E19="","",IFERROR(VLOOKUP($E19,OpTbl,8,0),"")) | Y19: =IF(OR($X19="",$AJ19="",$AJ19=0,$AM19<>"بدهکار"),"",$AJ19) | Z19: =IF(OR($X19="",$AJ19="",$AJ19=0,$AM19<>"بستانکار"),"",$AJ19) | AA19: =IF(OR($E19="",$AN19="—",$AN19=""),"",IFERROR(VLOOKUP($E19,OpTbl,12,0),"")) | AB19: =IF(OR($AA19="",$Q19="",$Q19=0,$AN19<>"بدهکار"),"",$Q19) | AC19: =IF(OR($AA19="",$Q19="",$Q19=0,$AN19<>"بستانکار"),"",$Q19) | AD19: =IF($AA19="","",IFERROR(VLOOKUP($E19,OpTbl,13,0),"")) | AE19: =IF(OR($AD19="",$Q19="",$Q19=0,$AN19<>"بستانکار"),"",$Q19) | AF19: =IF(OR($AD19="",$Q19="",$Q19=0,$AN19<>"بدهکار"),"",$Q19) | AG19: =SUM($V19,$Y19,$AB19,$AE19) | AH19: =SUM($W19,$Z19,$AC19,$AF19) | AI19: =IF($E19="","",IF(ROUND($AG19-$AH19,0)=0,"✓","⚠")) | AJ19: =IF(OR($E19="",$U19=""),"",IFERROR(IF(VLOOKUP($E19,OpTbl,6,0)="وزن",IF($P19="",0,$P19),IF(VLOOKUP($E19,OpTbl,6,0)="مبلغ",IF(AND($Q19<>"",$Q19<>0),$Q19,$P19),0))+IF(VLOOKUP($E19,OpTbl,10,0)="افزودن",IF($Q19="",0,$Q19),0),0)) | AK19: =IF($E19="","",IFERROR(VLOOKUP($E19,OpTbl,10,0),"")) | AL19: =IF(OR($E19="",$U19=""),"",IFERROR(IF(VLOOKUP($E19,OpTbl,7,0)="خودکار",$R19,VLOOKUP($E19,OpTbl,7,0)),"")) | AM19: =IF(OR($E19="",$X19=""),"",IFERROR(IF(VLOOKUP($E19,OpTbl,9,0)="خودکار",IF($AL19="بدهکار","بستانکار",IF($AL19="بستانکار","بدهکار","")),VLOOKUP($E19,OpTbl,9,0)),"")) | AN19: =IF($E19="","",IFERROR(VLOOKUP($E19,OpTbl,11,0),"")) | AO19: =IF($B19="","",MID($B19,6,2)) | AP19: =IF($B19="",0,1)
A20: =IF($B20="","",COUNTA($B$10:$B20)) | B20: 1405/07/06 | C20: 09:15 | D20: BS-011 | E20: باسکول دیگران | F20: =IF($E20="","",IFERROR(VLOOKUP($E20,OpTbl,2,0),"")) | G20: BD001 | H20: =IF($U20="","",IFERROR(VLOOKUP($U20,AcctTbl,2,0),"کد ناشناخته")) | I20: =IF($U20="","",IFERROR(VLOOKUP($U20,AcctTbl,3,0),"")) | L20: 0 | M20: 0 | N20: =IF(OR($E20="",$L20=""),"",IFERROR(($L20-IF($M20="",0,$M20)*IFERROR(VLOOKUP($K20,BasketTbl,4,0),IFERROR(INDEX(BasketTbl,MATCH($K20,BasketCodeCol,0),4),VLOOKUP("P01",ParamTbl,2,0))))*(1-IF(VLOOKUP($E20,OpTbl,3,0)="خرید",VLOOKUP("P02",ParamTbl,2,0),0)/100),"")) | O20: 0 | P20: =IF(OR($E20="",$L20=""),"",IFERROR(IF(VLOOKUP($E20,OpTbl,6,0)="وزن",ROUND($N20*$O20,-3),IF(VLOOKUP($E20,OpTbl,6,0)="مبلغ",ROUND($L20*$O20,-3),0)),"")) | Q20: 150000 | S20: =IF($E20="","",IF($AI20="⚠","⚠ ناتراز",IF(AND(IFERROR(VLOOKUP($E20,OpTbl,4,0),"")="بله",$L20=""),"⚠ وزن",IF(AND(IFERROR(VLOOKUP($E20,OpTbl,5,0),"")="بله",$U20=""),"⚠ حساب",IF(AND(IFERROR(VLOOKUP($E20,OpTbl,6,0),"")="مبلغ",$Q20=""),"⚠ مبلغ","✓"))))) | T20: هزینه باسکول مهمان | U20: =IF($E20="","",IFERROR(IF(VLOOKUP($E20,OpTbl,14,0)<>"",VLOOKUP($E20,OpTbl,14,0),$G20),"")) | V20: =IF(OR($AJ20="",$AJ20=0,$AL20<>"بدهکار"),"",$AJ20) | W20: =IF(OR($AJ20="",$AJ20=0,$AL20<>"بستانکار"),"",$AJ20) | X20: =IF($E20="","",IFERROR(VLOOKUP($E20,OpTbl,8,0),"")) | Y20: =IF(OR($X20="",$AJ20="",$AJ20=0,$AM20<>"بدهکار"),"",$AJ20) | Z20: =IF(OR($X20="",$AJ20="",$AJ20=0,$AM20<>"بستانکار"),"",$AJ20) | AA20: =IF(OR($E20="",$AN20="—",$AN20=""),"",IFERROR(VLOOKUP($E20,OpTbl,12,0),"")) | AB20: =IF(OR($AA20="",$Q20="",$Q20=0,$AN20<>"بدهکار"),"",$Q20) | AC20: =IF(OR($AA20="",$Q20="",$Q20=0,$AN20<>"بستانکار"),"",$Q20) | AD20: =IF($AA20="","",IFERROR(VLOOKUP($E20,OpTbl,13,0),"")) | AE20: =IF(OR($AD20="",$Q20="",$Q20=0,$AN20<>"بستانکار"),"",$Q20) | AF20: =IF(OR($AD20="",$Q20="",$Q20=0,$AN20<>"بدهکار"),"",$Q20) | AG20: =SUM($V20,$Y20,$AB20,$AE20) | AH20: =SUM($W20,$Z20,$AC20,$AF20) | AI20: =IF($E20="","",IF(ROUND($AG20-$AH20,0)=0,"✓","⚠")) | AJ20: =IF(OR($E20="",$U20=""),"",IFERROR(IF(VLOOKUP($E20,OpTbl,6,0)="وزن",IF($P20="",0,$P20),IF(VLOOKUP($E20,OpTbl,6,0)="مبلغ",IF(AND($Q20<>"",$Q20<>0),$Q20,$P20),0))+IF(VLOOKUP($E20,OpTbl,10,0)="افزودن",IF($Q20="",0,$Q20),0),0)) | AK20: =IF($E20="","",IFERROR(VLOOKUP($E20,OpTbl,10,0),"")) | AL20: =IF(OR($E20="",$U20=""),"",IFERROR(IF(VLOOKUP($E20,OpTbl,7,0)="خودکار",$R20,VLOOKUP($E20,OpTbl,7,0)),"")) | AM20: =IF(OR($E20="",$X20=""),"",IFERROR(IF(VLOOKUP($E20,OpTbl,9,0)="خودکار",IF($AL20="بدهکار","بستانکار",IF($AL20="بستانکار","بدهکار","")),VLOOKUP($E20,OpTbl,9,0)),"")) | AN20: =IF($E20="","",IFERROR(VLOOKUP($E20,OpTbl,11,0),"")) | AO20: =IF($B20="","",MID($B20,6,2)) | AP20: =IF($B20="",0,1)
A21: =IF($B21="","",COUNTA($B$10:$B21)) | B21: 1405/07/06 | C21: 12:00 | D21: BS-012 | E21: خرید مرکبات | F21: =IF($E21="","",IFERROR(VLOOKUP($E21,OpTbl,2,0),"")) | G21: C005 | H21: =IF($U21="","",IFERROR(VLOOKUP($U21,AcctTbl,2,0),"کد ناشناخته")) | I21: =IF($U21="","",IFERROR(VLOOKUP($U21,AcctTbl,3,0),"")) | J21: پرتقال یافا | K21: BK03 – ۹ک مشکی | L21: 3200 | M21: 195 | N21: =IF(OR($E21="",$L21=""),"",IFERROR(($L21-IF($M21="",0,$M21)*IFERROR(VLOOKUP($K21,BasketTbl,4,0),IFERROR(INDEX(BasketTbl,MATCH($K21,BasketCodeCol,0),4),VLOOKUP("P01",ParamTbl,2,0))))*(1-IF(VLOOKUP($E21,OpTbl,3,0)="خرید",VLOOKUP("P02",ParamTbl,2,0),0)/100),"")) | O21: 29000 | P21: =IF(OR($E21="",$L21=""),"",IFERROR(IF(VLOOKUP($E21,OpTbl,6,0)="وزن",ROUND($N21*$O21,-3),IF(VLOOKUP($E21,OpTbl,6,0)="مبلغ",ROUND($L21*$O21,-3),0)),"")) | Q21: 0 | S21: =IF($E21="","",IF($AI21="⚠","⚠ ناتراز",IF(AND(IFERROR(VLOOKUP($E21,OpTbl,4,0),"")="بله",$L21=""),"⚠ وزن",IF(AND(IFERROR(VLOOKUP($E21,OpTbl,5,0),"")="بله",$U21=""),"⚠ حساب",IF(AND(IFERROR(VLOOKUP($E21,OpTbl,6,0),"")="مبلغ",$Q21=""),"⚠ مبلغ","✓"))))) | U21: =IF($E21="","",IFERROR(IF(VLOOKUP($E21,OpTbl,14,0)<>"",VLOOKUP($E21,OpTbl,14,0),$G21),"")) | V21: =IF(OR($AJ21="",$AJ21=0,$AL21<>"بدهکار"),"",$AJ21) | W21: =IF(OR($AJ21="",$AJ21=0,$AL21<>"بستانکار"),"",$AJ21) | X21: =IF($E21="","",IFERROR(VLOOKUP($E21,OpTbl,8,0),"")) | Y21: =IF(OR($X21="",$AJ21="",$AJ21=0,$AM21<>"بدهکار"),"",$AJ21) | Z21: =IF(OR($X21="",$AJ21="",$AJ21=0,$AM21<>"بستانکار"),"",$AJ21) | AA21: =IF(OR($E21="",$AN21="—",$AN21=""),"",IFERROR(VLOOKUP($E21,OpTbl,12,0),"")) | AB21: =IF(OR($AA21="",$Q21="",$Q21=0,$AN21<>"بدهکار"),"",$Q21) | AC21: =IF(OR($AA21="",$Q21="",$Q21=0,$AN21<>"بستانکار"),"",$Q21) | AD21: =IF($AA21="","",IFERROR(VLOOKUP($E21,OpTbl,13,0),"")) | AE21: =IF(OR($AD21="",$Q21="",$Q21=0,$AN21<>"بستانکار"),"",$Q21) | AF21: =IF(OR($AD21="",$Q21="",$Q21=0,$AN21<>"بدهکار"),"",$Q21) | AG21: =SUM($V21,$Y21,$AB21,$AE21) | AH21: =SUM($W21,$Z21,$AC21,$AF21) | AI21: =IF($E21="","",IF(ROUND($AG21-$AH21,0)=0,"✓","⚠")) | AJ21: =IF(OR($E21="",$U21=""),"",IFERROR(IF(VLOOKUP($E21,OpTbl,6,0)="وزن",IF($P21="",0,$P21),IF(VLOOKUP($E21,OpTbl,6,0)="مبلغ",IF(AND($Q21<>"",$Q21<>0),$Q21,$P21),0))+IF(VLOOKUP($E21,OpTbl,10,0)="افزودن",IF($Q21="",0,$Q21),0),0)) | AK21: =IF($E21="","",IFERROR(VLOOKUP($E21,OpTbl,10,0),"")) | AL21: =IF(OR($E21="",$U21=""),"",IFERROR(IF(VLOOKUP($E21,OpTbl,7,0)="خودکار",$R21,VLOOKUP($E21,OpTbl,7,0)),"")) | AM21: =IF(OR($E21="",$X21=""),"",IFERROR(IF(VLOOKUP($E21,OpTbl,9,0)="خودکار",IF($AL21="بدهکار","بستانکار",IF($AL21="بستانکار","بدهکار","")),VLOOKUP($E21,OpTbl,9,0)),"")) | AN21: =IF($E21="","",IFERROR(VLOOKUP($E21,OpTbl,11,0),"")) | AO21: =IF($B21="","",MID($B21,6,2)) | AP21: =IF($B21="",0,1)
A22: =IF($B22="","",COUNTA($B$10:$B22)) | B22: 1405/07/07 | C22: 08:30 | D22: BS-013 | E22: مرجوعی خرید | F22: =IF($E22="","",IFERROR(VLOOKUP($E22,OpTbl,2,0),"")) | G22: C001 | H22: =IF($U22="","",IFERROR(VLOOKUP($U22,AcctTbl,2,0),"کد ناشناخته")) | I22: =IF($U22="","",IFERROR(VLOOKUP($U22,AcctTbl,3,0),"")) | J22: نارنگی پیچ | K22: BK01 – ۶ک مشکی | L22: 220 | M22: 12 | N22: =IF(OR($E22="",$L22=""),"",IFERROR(($L22-IF($M22="",0,$M22)*IFERROR(VLOOKUP($K22,BasketTbl,4,0),IFERROR(INDEX(BasketTbl,MATCH($K22,BasketCodeCol,0),4),VLOOKUP("P01",ParamTbl,2,0))))*(1-IF(VLOOKUP($E22,OpTbl,3,0)="خرید",VLOOKUP("P02",ParamTbl,2,0),0)/100),"")) | O22: 32000 | P22: =IF(OR($E22="",$L22=""),"",IFERROR(IF(VLOOKUP($E22,OpTbl,6,0)="وزن",ROUND($N22*$O22,-3),IF(VLOOKUP($E22,OpTbl,6,0)="مبلغ",ROUND($L22*$O22,-3),0)),"")) | Q22: 0 | S22: =IF($E22="","",IF($AI22="⚠","⚠ ناتراز",IF(AND(IFERROR(VLOOKUP($E22,OpTbl,4,0),"")="بله",$L22=""),"⚠ وزن",IF(AND(IFERROR(VLOOKUP($E22,OpTbl,5,0),"")="بله",$U22=""),"⚠ حساب",IF(AND(IFERROR(VLOOKUP($E22,OpTbl,6,0),"")="مبلغ",$Q22=""),"⚠ مبلغ","✓"))))) | T22: برگشت ۱۲ سبد | U22: =IF($E22="","",IFERROR(IF(VLOOKUP($E22,OpTbl,14,0)<>"",VLOOKUP($E22,OpTbl,14,0),$G22),"")) | V22: =IF(OR($AJ22="",$AJ22=0,$AL22<>"بدهکار"),"",$AJ22) | W22: =IF(OR($AJ22="",$AJ22=0,$AL22<>"بستانکار"),"",$AJ22) | X22: =IF($E22="","",IFERROR(VLOOKUP($E22,OpTbl,8,0),"")) | Y22: =IF(OR($X22="",$AJ22="",$AJ22=0,$AM22<>"بدهکار"),"",$AJ22) | Z22: =IF(OR($X22="",$AJ22="",$AJ22=0,$AM22<>"بستانکار"),"",$AJ22) | AA22: =IF(OR($E22="",$AN22="—",$AN22=""),"",IFERROR(VLOOKUP($E22,OpTbl,12,0),"")) | AB22: =IF(OR($AA22="",$Q22="",$Q22=0,$AN22<>"بدهکار"),"",$Q22) | AC22: =IF(OR($AA22="",$Q22="",$Q22=0,$AN22<>"بستانکار"),"",$Q22) | AD22: =IF($AA22="","",IFERROR(VLOOKUP($E22,OpTbl,13,0),"")) | AE22: =IF(OR($AD22="",$Q22="",$Q22=0,$AN22<>"بستانکار"),"",$Q22) | AF22: =IF(OR($AD22="",$Q22="",$Q22=0,$AN22<>"بدهکار"),"",$Q22) | AG22: =SUM($V22,$Y22,$AB22,$AE22) | AH22: =SUM($W22,$Z22,$AC22,$AF22) | AI22: =IF($E22="","",IF(ROUND($AG22-$AH22,0)=0,"✓","⚠")) | AJ22: =IF(OR($E22="",$U22=""),"",IFERROR(IF(VLOOKUP($E22,OpTbl,6,0)="وزن",IF($P22="",0,$P22),IF(VLOOKUP($E22,OpTbl,6,0)="مبلغ",IF(AND($Q22<>"",$Q22<>0),$Q22,$P22),0))+IF(VLOOKUP($E22,OpTbl,10,0)="افزودن",IF($Q22="",0,$Q22),0),0)) | AK22: =IF($E22="","",IFERROR(VLOOKUP($E22,OpTbl,10,0),"")) | AL22: =IF(OR($E22="",$U22=""),"",IFERROR(IF(VLOOKUP($E22,OpTbl,7,0)="خودکار",$R22,VLOOKUP($E22,OpTbl,7,0)),"")) | AM22: =IF(OR($E22="",$X22=""),"",IFERROR(IF(VLOOKUP($E22,OpTbl,9,0)="خودکار",IF($AL22="بدهکار","بستانکار",IF($AL22="بستانکار","بدهکار","")),VLOOKUP($E22,OpTbl,9,0)),"")) | AN22: =IF($E22="","",IFERROR(VLOOKUP($E22,OpTbl,11,0),"")) | AO22: =IF($B22="","",MID($B22,6,2)) | AP22: =IF($B22="",0,1)
A23: =IF($B23="","",COUNTA($B$10:$B23)) | B23: 1405/07/08 | C23: 09:50 | D23: BS-014 | E23: خرید مرکبات | F23: =IF($E23="","",IFERROR(VLOOKUP($E23,OpTbl,2,0),"")) | G23: C009 | H23: =IF($U23="","",IFERROR(VLOOKUP($U23,AcctTbl,2,0),"کد ناشناخته")) | I23: =IF($U23="","",IFERROR(VLOOKUP($U23,AcctTbl,3,0),"")) | J23: نارنگی ژاپنی | K23: BK07 – ۸ک مشکی | L23: 1450 | M23: 92 | N23: =IF(OR($E23="",$L23=""),"",IFERROR(($L23-IF($M23="",0,$M23)*IFERROR(VLOOKUP($K23,BasketTbl,4,0),IFERROR(INDEX(BasketTbl,MATCH($K23,BasketCodeCol,0),4),VLOOKUP("P01",ParamTbl,2,0))))*(1-IF(VLOOKUP($E23,OpTbl,3,0)="خرید",VLOOKUP("P02",ParamTbl,2,0),0)/100),"")) | O23: 30500 | P23: =IF(OR($E23="",$L23=""),"",IFERROR(IF(VLOOKUP($E23,OpTbl,6,0)="وزن",ROUND($N23*$O23,-3),IF(VLOOKUP($E23,OpTbl,6,0)="مبلغ",ROUND($L23*$O23,-3),0)),"")) | Q23: 0 | S23: =IF($E23="","",IF($AI23="⚠","⚠ ناتراز",IF(AND(IFERROR(VLOOKUP($E23,OpTbl,4,0),"")="بله",$L23=""),"⚠ وزن",IF(AND(IFERROR(VLOOKUP($E23,OpTbl,5,0),"")="بله",$U23=""),"⚠ حساب",IF(AND(IFERROR(VLOOKUP($E23,OpTbl,6,0),"")="مبلغ",$Q23=""),"⚠ مبلغ","✓"))))) | U23: =IF($E23="","",IFERROR(IF(VLOOKUP($E23,OpTbl,14,0)<>"",VLOOKUP($E23,OpTbl,14,0),$G23),"")) | V23: =IF(OR($AJ23="",$AJ23=0,$AL23<>"بدهکار"),"",$AJ23) | W23: =IF(OR($AJ23="",$AJ23=0,$AL23<>"بستانکار"),"",$AJ23) | X23: =IF($E23="","",IFERROR(VLOOKUP($E23,OpTbl,8,0),"")) | Y23: =IF(OR($X23="",$AJ23="",$AJ23=0,$AM23<>"بدهکار"),"",$AJ23) | Z23: =IF(OR($X23="",$AJ23="",$AJ23=0,$AM23<>"بستانکار"),"",$AJ23) | AA23: =IF(OR($E23="",$AN23="—",$AN23=""),"",IFERROR(VLOOKUP($E23,OpTbl,12,0),"")) | AB23: =IF(OR($AA23="",$Q23="",$Q23=0,$AN23<>"بدهکار"),"",$Q23) | AC23: =IF(OR($AA23="",$Q23="",$Q23=0,$AN23<>"بستانکار"),"",$Q23) | AD23: =IF($AA23="","",IFERROR(VLOOKUP($E23,OpTbl,13,0),"")) | AE23: =IF(OR($AD23="",$Q23="",$Q23=0,$AN23<>"بستانکار"),"",$Q23) | AF23: =IF(OR($AD23="",$Q23="",$Q23=0,$AN23<>"بدهکار"),"",$Q23) | AG23: =SUM($V23,$Y23,$AB23,$AE23) | AH23: =SUM($W23,$Z23,$AC23,$AF23) | AI23: =IF($E23="","",IF(ROUND($AG23-$AH23,0)=0,"✓","⚠")) | AJ23: =IF(OR($E23="",$U23=""),"",IFERROR(IF(VLOOKUP($E23,OpTbl,6,0)="وزن",IF($P23="",0,$P23),IF(VLOOKUP($E23,OpTbl,6,0)="مبلغ",IF(AND($Q23<>"",$Q23<>0),$Q23,$P23),0))+IF(VLOOKUP($E23,OpTbl,10,0)="افزودن",IF($Q23="",0,$Q23),0),0)) | AK23: =IF($E23="","",IFERROR(VLOOKUP($E23,OpTbl,10,0),"")) | AL23: =IF(OR($E23="",$U23=""),"",IFERROR(IF(VLOOKUP($E23,OpTbl,7,0)="خودکار",$R23,VLOOKUP($E23,OpTbl,7,0)),"")) | AM23: =IF(OR($E23="",$X23=""),"",IFERROR(IF(VLOOKUP($E23,OpTbl,9,0)="خودکار",IF($AL23="بدهکار","بستانکار",IF($AL23="بستانکار","بدهکار","")),VLOOKUP($E23,OpTbl,9,0)),"")) | AN23: =IF($E23="","",IFERROR(VLOOKUP($E23,OpTbl,11,0),"")) | AO23: =IF($B23="","",MID($B23,6,2)) | AP23: =IF($B23="",0,1)
A24: =IF($B24="","",COUNTA($B$10:$B24)) | B24: 1405/07/09 | C24: 11:10 | D24: BS-015 | E24: فروش بار (بارفروش) | F24: =IF($E24="","",IFERROR(VLOOKUP($E24,OpTbl,2,0),"")) | G24: SL001 | H24: =IF($U24="","",IFERROR(VLOOKUP($U24,AcctTbl,2,0),"کد ناشناخته")) | I24: =IF($U24="","",IFERROR(VLOOKUP($U24,AcctTbl,3,0),"")) | J24: پرتقال تامسون | K24: BK03 – ۹ک مشکی | L24: 1600 | M24: 0 | N24: =IF(OR($E24="",$L24=""),"",IFERROR(($L24-IF($M24="",0,$M24)*IFERROR(VLOOKUP($K24,BasketTbl,4,0),IFERROR(INDEX(BasketTbl,MATCH($K24,BasketCodeCol,0),4),VLOOKUP("P01",ParamTbl,2,0))))*(1-IF(VLOOKUP($E24,OpTbl,3,0)="خرید",VLOOKUP("P02",ParamTbl,2,0),0)/100),"")) | O24: 60000 | P24: =IF(OR($E24="",$L24=""),"",IFERROR(IF(VLOOKUP($E24,OpTbl,6,0)="وزن",ROUND($N24*$O24,-3),IF(VLOOKUP($E24,OpTbl,6,0)="مبلغ",ROUND($L24*$O24,-3),0)),"")) | Q24: 80000 | S24: =IF($E24="","",IF($AI24="⚠","⚠ ناتراز",IF(AND(IFERROR(VLOOKUP($E24,OpTbl,4,0),"")="بله",$L24=""),"⚠ وزن",IF(AND(IFERROR(VLOOKUP($E24,OpTbl,5,0),"")="بله",$U24=""),"⚠ حساب",IF(AND(IFERROR(VLOOKUP($E24,OpTbl,6,0),"")="مبلغ",$Q24=""),"⚠ مبلغ","✓"))))) | T24: هزینه باسکول پوز | U24: =IF($E24="","",IFERROR(IF(VLOOKUP($E24,OpTbl,14,0)<>"",VLOOKUP($E24,OpTbl,14,0),$G24),"")) | V24: =IF(OR($AJ24="",$AJ24=0,$AL24<>"بدهکار"),"",$AJ24) | W24: =IF(OR($AJ24="",$AJ24=0,$AL24<>"بستانکار"),"",$AJ24) | X24: =IF($E24="","",IFERROR(VLOOKUP($E24,OpTbl,8,0),"")) | Y24: =IF(OR($X24="",$AJ24="",$AJ24=0,$AM24<>"بدهکار"),"",$AJ24) | Z24: =IF(OR($X24="",$AJ24="",$AJ24=0,$AM24<>"بستانکار"),"",$AJ24) | AA24: =IF(OR($E24="",$AN24="—",$AN24=""),"",IFERROR(VLOOKUP($E24,OpTbl,12,0),"")) | AB24: =IF(OR($AA24="",$Q24="",$Q24=0,$AN24<>"بدهکار"),"",$Q24) | AC24: =IF(OR($AA24="",$Q24="",$Q24=0,$AN24<>"بستانکار"),"",$Q24) | AD24: =IF($AA24="","",IFERROR(VLOOKUP($E24,OpTbl,13,0),"")) | AE24: =IF(OR($AD24="",$Q24="",$Q24=0,$AN24<>"بستانکار"),"",$Q24) | AF24: =IF(OR($AD24="",$Q24="",$Q24=0,$AN24<>"بدهکار"),"",$Q24) | AG24: =SUM($V24,$Y24,$AB24,$AE24) | AH24: =SUM($W24,$Z24,$AC24,$AF24) | AI24: =IF($E24="","",IF(ROUND($AG24-$AH24,0)=0,"✓","⚠")) | AJ24: =IF(OR($E24="",$U24=""),"",IFERROR(IF(VLOOKUP($E24,OpTbl,6,0)="وزن",IF($P24="",0,$P24),IF(VLOOKUP($E24,OpTbl,6,0)="مبلغ",IF(AND($Q24<>"",$Q24<>0),$Q24,$P24),0))+IF(VLOOKUP($E24,OpTbl,10,0)="افزودن",IF($Q24="",0,$Q24),0),0)) | AK24: =IF($E24="","",IFERROR(VLOOKUP($E24,OpTbl,10,0),"")) | AL24: =IF(OR($E24="",$U24=""),"",IFERROR(IF(VLOOKUP($E24,OpTbl,7,0)="خودکار",$R24,VLOOKUP($E24,OpTbl,7,0)),"")) | AM24: =IF(OR($E24="",$X24=""),"",IFERROR(IF(VLOOKUP($E24,OpTbl,9,0)="خودکار",IF($AL24="بدهکار","بستانکار",IF($AL24="بستانکار","بدهکار","")),VLOOKUP($E24,OpTbl,9,0)),"")) | AN24: =IF($E24="","",IFERROR(VLOOKUP($E24,OpTbl,11,0),"")) | AO24: =IF($B24="","",MID($B24,6,2)) | AP24: =IF($B24="",0,1)
A25: =IF($B25="","",COUNTA($B$10:$B25)) | B25: 1405/07/10 | C25: 07:30 | D25: BS-016 | E25: خرید مرکبات | F25: =IF($E25="","",IFERROR(VLOOKUP($E25,OpTbl,2,0),"")) | G25: C010 | H25: =IF($U25="","",IFERROR(VLOOKUP($U25,AcctTbl,2,0),"کد ناشناخته")) | I25: =IF($U25="","",IFERROR(VLOOKUP($U25,AcctTbl,3,0),"")) | J25: پرتقال کاراکارا | K25: BK03 – ۹ک مشکی | L25: 950 | M25: 58 | N25: =IF(OR($E25="",$L25=""),"",IFERROR(($L25-IF($M25="",0,$M25)*IFERROR(VLOOKUP($K25,BasketTbl,4,0),IFERROR(INDEX(BasketTbl,MATCH($K25,BasketCodeCol,0),4),VLOOKUP("P01",ParamTbl,2,0))))*(1-IF(VLOOKUP($E25,OpTbl,3,0)="خرید",VLOOKUP("P02",ParamTbl,2,0),0)/100),"")) | O25: 36000 | P25: =IF(OR($E25="",$L25=""),"",IFERROR(IF(VLOOKUP($E25,OpTbl,6,0)="وزن",ROUND($N25*$O25,-3),IF(VLOOKUP($E25,OpTbl,6,0)="مبلغ",ROUND($L25*$O25,-3),0)),"")) | Q25: 0 | S25: =IF($E25="","",IF($AI25="⚠","⚠ ناتراز",IF(AND(IFERROR(VLOOKUP($E25,OpTbl,4,0),"")="بله",$L25=""),"⚠ وزن",IF(AND(IFERROR(VLOOKUP($E25,OpTbl,5,0),"")="بله",$U25=""),"⚠ حساب",IF(AND(IFERROR(VLOOKUP($E25,OpTbl,6,0),"")="مبلغ",$Q25=""),"⚠ مبلغ","✓"))))) | U25: =IF($E25="","",IFERROR(IF(VLOOKUP($E25,OpTbl,14,0)<>"",VLOOKUP($E25,OpTbl,14,0),$G25),"")) | V25: =IF(OR($AJ25="",$AJ25=0,$AL25<>"بدهکار"),"",$AJ25) | W25: =IF(OR($AJ25="",$AJ25=0,$AL25<>"بستانکار"),"",$AJ25) | X25: =IF($E25="","",IFERROR(VLOOKUP($E25,OpTbl,8,0),"")) | Y25: =IF(OR($X25="",$AJ25="",$AJ25=0,$AM25<>"بدهکار"),"",$AJ25) | Z25: =IF(OR($X25="",$AJ25="",$AJ25=0,$AM25<>"بستانکار"),"",$AJ25) | AA25: =IF(OR($E25="",$AN25="—",$AN25=""),"",IFERROR(VLOOKUP($E25,OpTbl,12,0),"")) | AB25: =IF(OR($AA25="",$Q25="",$Q25=0,$AN25<>"بدهکار"),"",$Q25) | AC25: =IF(OR($AA25="",$Q25="",$Q25=0,$AN25<>"بستانکار"),"",$Q25) | AD25: =IF($AA25="","",IFERROR(VLOOKUP($E25,OpTbl,13,0),"")) | AE25: =IF(OR($AD25="",$Q25="",$Q25=0,$AN25<>"بستانکار"),"",$Q25) | AF25: =IF(OR($AD25="",$Q25="",$Q25=0,$AN25<>"بدهکار"),"",$Q25) | AG25: =SUM($V25,$Y25,$AB25,$AE25) | AH25: =SUM($W25,$Z25,$AC25,$AF25) | AI25: =IF($E25="","",IF(ROUND($AG25-$AH25,0)=0,"✓","⚠")) | AJ25: =IF(OR($E25="",$U25=""),"",IFERROR(IF(VLOOKUP($E25,OpTbl,6,0)="وزن",IF($P25="",0,$P25),IF(VLOOKUP($E25,OpTbl,6,0)="مبلغ",IF(AND($Q25<>"",$Q25<>0),$Q25,$P25),0))+IF(VLOOKUP($E25,OpTbl,10,0)="افزودن",IF($Q25="",0,$Q25),0),0)) | AK25: =IF($E25="","",IFERROR(VLOOKUP($E25,OpTbl,10,0),"")) | AL25: =IF(OR($E25="",$U25=""),"",IFERROR(IF(VLOOKUP($E25,OpTbl,7,0)="خودکار",$R25,VLOOKUP($E25,OpTbl,7,0)),"")) | AM25: =IF(OR($E25="",$X25=""),"",IFERROR(IF(VLOOKUP($E25,OpTbl,9,0)="خودکار",IF($AL25="بدهکار","بستانکار",IF($AL25="بستانکار","بدهکار","")),VLOOKUP($E25,OpTbl,9,0)),"")) | AN25: =IF($E25="","",IFERROR(VLOOKUP($E25,OpTbl,11,0),"")) | AO25: =IF($B25="","",MID($B25,6,2)) | AP25: =IF($B25="",0,1)
A26: =IF($B26="","",COUNTA($B$10:$B26)) | B26: 1405/07/11 | C26: 10:05 | D26: BS-017 | E26: درآمد پوز باسکول (بدون طرف) | F26: =IF($E26="","",IFERROR(VLOOKUP($E26,OpTbl,2,0),"")) | H26: =IF($U26="","",IFERROR(VLOOKUP($U26,AcctTbl,2,0),"کد ناشناخته")) | I26: =IF($U26="","",IFERROR(VLOOKUP($U26,AcctTbl,3,0),"")) | L26: 0 | M26: 0 | N26: =IF(OR($E26="",$L26=""),"",IFERROR(($L26-IF($M26="",0,$M26)*IFERROR(VLOOKUP($K26,BasketTbl,4,0),IFERROR(INDEX(BasketTbl,MATCH($K26,BasketCodeCol,0),4),VLOOKUP("P01",ParamTbl,2,0))))*(1-IF(VLOOKUP($E26,OpTbl,3,0)="خرید",VLOOKUP("P02",ParamTbl,2,0),0)/100),"")) | O26: 0 | P26: =IF(OR($E26="",$L26=""),"",IFERROR(IF(VLOOKUP($E26,OpTbl,6,0)="وزن",ROUND($N26*$O26,-3),IF(VLOOKUP($E26,OpTbl,6,0)="مبلغ",ROUND($L26*$O26,-3),0)),"")) | Q26: 300000 | S26: =IF($E26="","",IF($AI26="⚠","⚠ ناتراز",IF(AND(IFERROR(VLOOKUP($E26,OpTbl,4,0),"")="بله",$L26=""),"⚠ وزن",IF(AND(IFERROR(VLOOKUP($E26,OpTbl,5,0),"")="بله",$U26=""),"⚠ حساب",IF(AND(IFERROR(VLOOKUP($E26,OpTbl,6,0),"")="مبلغ",$Q26=""),"⚠ مبلغ","✓"))))) | T26: هزینه باسکول نقدی | U26: =IF($E26="","",IFERROR(IF(VLOOKUP($E26,OpTbl,14,0)<>"",VLOOKUP($E26,OpTbl,14,0),$G26),"")) | V26: =IF(OR($AJ26="",$AJ26=0,$AL26<>"بدهکار"),"",$AJ26) | W26: =IF(OR($AJ26="",$AJ26=0,$AL26<>"بستانکار"),"",$AJ26) | X26: =IF($E26="","",IFERROR(VLOOKUP($E26,OpTbl,8,0),"")) | Y26: =IF(OR($X26="",$AJ26="",$AJ26=0,$AM26<>"بدهکار"),"",$AJ26) | Z26: =IF(OR($X26="",$AJ26="",$AJ26=0,$AM26<>"بستانکار"),"",$AJ26) | AA26: =IF(OR($E26="",$AN26="—",$AN26=""),"",IFERROR(VLOOKUP($E26,OpTbl,12,0),"")) | AB26: =IF(OR($AA26="",$Q26="",$Q26=0,$AN26<>"بدهکار"),"",$Q26) | AC26: =IF(OR($AA26="",$Q26="",$Q26=0,$AN26<>"بستانکار"),"",$Q26) | AD26: =IF($AA26="","",IFERROR(VLOOKUP($E26,OpTbl,13,0),"")) | AE26: =IF(OR($AD26="",$Q26="",$Q26=0,$AN26<>"بستانکار"),"",$Q26) | AF26: =IF(OR($AD26="",$Q26="",$Q26=0,$AN26<>"بدهکار"),"",$Q26) | AG26: =SUM($V26,$Y26,$AB26,$AE26) | AH26: =SUM($W26,$Z26,$AC26,$AF26) | AI26: =IF($E26="","",IF(ROUND($AG26-$AH26,0)=0,"✓","⚠")) | AJ26: =IF(OR($E26="",$U26=""),"",IFERROR(IF(VLOOKUP($E26,OpTbl,6,0)="وزن",IF($P26="",0,$P26),IF(VLOOKUP($E26,OpTbl,6,0)="مبلغ",IF(AND($Q26<>"",$Q26<>0),$Q26,$P26),0))+IF(VLOOKUP($E26,OpTbl,10,0)="افزودن",IF($Q26="",0,$Q26),0),0)) | AK26: =IF($E26="","",IFERROR(VLOOKUP($E26,OpTbl,10,0),"")) | AL26: =IF(OR($E26="",$U26=""),"",IFERROR(IF(VLOOKUP($E26,OpTbl,7,0)="خودکار",$R26,VLOOKUP($E26,OpTbl,7,0)),"")) | AM26: =IF(OR($E26="",$X26=""),"",IFERROR(IF(VLOOKUP($E26,OpTbl,9,0)="خودکار",IF($AL26="بدهکار","بستانکار",IF($AL26="بستانکار","بدهکار","")),VLOOKUP($E26,OpTbl,9,0)),"")) | AN26: =IF($E26="","",IFERROR(VLOOKUP($E26,OpTbl,11,0),"")) | AO26: =IF($B26="","",MID($B26,6,2)) | AP26: =IF($B26="",0,1)
A27: =IF($B27="","",COUNTA($B$10:$B27)) | B27: 1405/07/12 | C27: 08:45 | D27: BS-018 | E27: خرید مرکبات | F27: =IF($E27="","",IFERROR(VLOOKUP($E27,OpTbl,2,0),"")) | G27: C011 | H27: =IF($U27="","",IFERROR(VLOOKUP($U27,AcctTbl,2,0),"کد ناشناخته")) | I27: =IF($U27="","",IFERROR(VLOOKUP($U27,AcctTbl,3,0),"")) | J27: پرتقال بیروتی | K27: BK01 – ۶ک مشکی | L27: 1200 | M27: 72 | N27: =IF(OR($E27="",$L27=""),"",IFERROR(($L27-IF($M27="",0,$M27)*IFERROR(VLOOKUP($K27,BasketTbl,4,0),IFERROR(INDEX(BasketTbl,MATCH($K27,BasketCodeCol,0),4),VLOOKUP("P01",ParamTbl,2,0))))*(1-IF(VLOOKUP($E27,OpTbl,3,0)="خرید",VLOOKUP("P02",ParamTbl,2,0),0)/100),"")) | O27: 34000 | P27: =IF(OR($E27="",$L27=""),"",IFERROR(IF(VLOOKUP($E27,OpTbl,6,0)="وزن",ROUND($N27*$O27,-3),IF(VLOOKUP($E27,OpTbl,6,0)="مبلغ",ROUND($L27*$O27,-3),0)),"")) | Q27: 0 | S27: =IF($E27="","",IF($AI27="⚠","⚠ ناتراز",IF(AND(IFERROR(VLOOKUP($E27,OpTbl,4,0),"")="بله",$L27=""),"⚠ وزن",IF(AND(IFERROR(VLOOKUP($E27,OpTbl,5,0),"")="بله",$U27=""),"⚠ حساب",IF(AND(IFERROR(VLOOKUP($E27,OpTbl,6,0),"")="مبلغ",$Q27=""),"⚠ مبلغ","✓"))))) | U27: =IF($E27="","",IFERROR(IF(VLOOKUP($E27,OpTbl,14,0)<>"",VLOOKUP($E27,OpTbl,14,0),$G27),"")) | V27: =IF(OR($AJ27="",$AJ27=0,$AL27<>"بدهکار"),"",$AJ27) | W27: =IF(OR($AJ27="",$AJ27=0,$AL27<>"بستانکار"),"",$AJ27) | X27: =IF($E27="","",IFERROR(VLOOKUP($E27,OpTbl,8,0),"")) | Y27: =IF(OR($X27="",$AJ27="",$AJ27=0,$AM27<>"بدهکار"),"",$AJ27) | Z27: =IF(OR($X27="",$AJ27="",$AJ27=0,$AM27<>"بستانکار"),"",$AJ27) | AA27: =IF(OR($E27="",$AN27="—",$AN27=""),"",IFERROR(VLOOKUP($E27,OpTbl,12,0),"")) | AB27: =IF(OR($AA27="",$Q27="",$Q27=0,$AN27<>"بدهکار"),"",$Q27) | AC27: =IF(OR($AA27="",$Q27="",$Q27=0,$AN27<>"بستانکار"),"",$Q27) | AD27: =IF($AA27="","",IFERROR(VLOOKUP($E27,OpTbl,13,0),"")) | AE27: =IF(OR($AD27="",$Q27="",$Q27=0,$AN27<>"بستانکار"),"",$Q27) | AF27: =IF(OR($AD27="",$Q27="",$Q27=0,$AN27<>"بدهکار"),"",$Q27) | AG27: =SUM($V27,$Y27,$AB27,$AE27) | AH27: =SUM($W27,$Z27,$AC27,$AF27) | AI27: =IF($E27="","",IF(ROUND($AG27-$AH27,0)=0,"✓","⚠")) | AJ27: =IF(OR($E27="",$U27=""),"",IFERROR(IF(VLOOKUP($E27,OpTbl,6,0)="وزن",IF($P27="",0,$P27),IF(VLOOKUP($E27,OpTbl,6,0)="مبلغ",IF(AND($Q27<>"",$Q27<>0),$Q27,$P27),0))+IF(VLOOKUP($E27,OpTbl,10,0)="افزودن",IF($Q27="",0,$Q27),0),0)) | AK27: =IF($E27="","",IFERROR(VLOOKUP($E27,OpTbl,10,0),"")) | AL27: =IF(OR($E27="",$U27=""),"",IFERROR(IF(VLOOKUP($E27,OpTbl,7,0)="خودکار",$R27,VLOOKUP($E27,OpTbl,7,0)),"")) | AM27: =IF(OR($E27="",$X27=""),"",IFERROR(IF(VLOOKUP($E27,OpTbl,9,0)="خودکار",IF($AL27="بدهکار","بستانکار",IF($AL27="بستانکار","بدهکار","")),VLOOKUP($E27,OpTbl,9,0)),"")) | AN27: =IF($E27="","",IFERROR(VLOOKUP($E27,OpTbl,11,0),"")) | AO27: =IF($B27="","",MID($B27,6,2)) | AP27: =IF($B27="",0,1)
A28: =IF($B28="","",COUNTA($B$10:$B28)) | F28: =IF($E28="","",IFERROR(VLOOKUP($E28,OpTbl,2,0),"")) | H28: =IF($U28="","",IFERROR(VLOOKUP($U28,AcctTbl,2,0),"کد ناشناخته")) | I28: =IF($U28="","",IFERROR(VLOOKUP($U28,AcctTbl,3,0),"")) | N28: =IF(OR($E28="",$L28=""),"",IFERROR(($L28-IF($M28="",0,$M28)*IFERROR(VLOOKUP($K28,BasketTbl,4,0),IFERROR(INDEX(BasketTbl,MATCH($K28,BasketCodeCol,0),4),VLOOKUP("P01",ParamTbl,2,0))))*(1-IF(VLOOKUP($E28,OpTbl,3,0)="خرید",VLOOKUP("P02",ParamTbl,2,0),0)/100),"")) | P28: =IF(OR($E28="",$L28=""),"",IFERROR(IF(VLOOKUP($E28,OpTbl,6,0)="وزن",ROUND($N28*$O28,-3),IF(VLOOKUP($E28,OpTbl,6,0)="مبلغ",ROUND($L28*$O28,-3),0)),"")) | S28: =IF($E28="","",IF($AI28="⚠","⚠ ناتراز",IF(AND(IFERROR(VLOOKUP($E28,OpTbl,4,0),"")="بله",$L28=""),"⚠ وزن",IF(AND(IFERROR(VLOOKUP($E28,OpTbl,5,0),"")="بله",$U28=""),"⚠ حساب",IF(AND(IFERROR(VLOOKUP($E28,OpTbl,6,0),"")="مبلغ",$Q28=""),"⚠ مبلغ","✓"))))) | U28: =IF($E28="","",IFERROR(IF(VLOOKUP($E28,OpTbl,14,0)<>"",VLOOKUP($E28,OpTbl,14,0),$G28),"")) | V28: =IF(OR($AJ28="",$AJ28=0,$AL28<>"بدهکار"),"",$AJ28) | W28: =IF(OR($AJ28="",$AJ28=0,$AL28<>"بستانکار"),"",$AJ28) | X28: =IF($E28="","",IFERROR(VLOOKUP($E28,OpTbl,8,0),"")) | Y28: =IF(OR($X28="",$AJ28="",$AJ28=0,$AM28<>"بدهکار"),"",$AJ28) | Z28: =IF(OR($X28="",$AJ28="",$AJ28=0,$AM28<>"بستانکار"),"",$AJ28) | AA28: =IF(OR($E28="",$AN28="—",$AN28=""),"",IFERROR(VLOOKUP($E28,OpTbl,12,0),"")) | AB28: =IF(OR($AA28="",$Q28="",$Q28=0,$AN28<>"بدهکار"),"",$Q28) | AC28: =IF(OR($AA28="",$Q28="",$Q28=0,$AN28<>"بستانکار"),"",$Q28) | AD28: =IF($AA28="","",IFERROR(VLOOKUP($E28,OpTbl,13,0),"")) | AE28: =IF(OR($AD28="",$Q28="",$Q28=0,$AN28<>"بستانکار"),"",$Q28) | AF28: =IF(OR($AD28="",$Q28="",$Q28=0,$AN28<>"بدهکار"),"",$Q28) | AG28: =SUM($V28,$Y28,$AB28,$AE28) | AH28: =SUM($W28,$Z28,$AC28,$AF28) | AI28: =IF($E28="","",IF(ROUND($AG28-$AH28,0)=0,"✓","⚠")) | AJ28: =IF(OR($E28="",$U28=""),"",IFERROR(IF(VLOOKUP($E28,OpTbl,6,0)="وزن",IF($P28="",0,$P28),IF(VLOOKUP($E28,OpTbl,6,0)="مبلغ",IF(AND($Q28<>"",$Q28<>0),$Q28,$P28),0))+IF(VLOOKUP($E28,OpTbl,10,0)="افزودن",IF($Q28="",0,$Q28),0),0)) | AK28: =IF($E28="","",IFERROR(VLOOKUP($E28,OpTbl,10,0),"")) | AL28: =IF(OR($E28="",$U28=""),"",IFERROR(IF(VLOOKUP($E28,OpTbl,7,0)="خودکار",$R28,VLOOKUP($E28,OpTbl,7,0)),"")) | AM28: =IF(OR($E28="",$X28=""),"",IFERROR(IF(VLOOKUP($E28,OpTbl,9,0)="خودکار",IF($AL28="بدهکار","بستانکار",IF($AL28="بستانکار","بدهکار","")),VLOOKUP($E28,OpTbl,9,0)),"")) | AN28: =IF($E28="","",IFERROR(VLOOKUP($E28,OpTbl,11,0),"")) | AO28: =IF($B28="","",MID($B28,6,2)) | AP28: =IF($B28="",0,1)
A29: =IF($B29="","",COUNTA($B$10:$B29)) | F29: =IF($E29="","",IFERROR(VLOOKUP($E29,OpTbl,2,0),"")) | H29: =IF($U29="","",IFERROR(VLOOKUP($U29,AcctTbl,2,0),"کد ناشناخته")) | I29: =IF($U29="","",IFERROR(VLOOKUP($U29,AcctTbl,3,0),"")) | N29: =IF(OR($E29="",$L29=""),"",IFERROR(($L29-IF($M29="",0,$M29)*IFERROR(VLOOKUP($K29,BasketTbl,4,0),IFERROR(INDEX(BasketTbl,MATCH($K29,BasketCodeCol,0),4),VLOOKUP("P01",ParamTbl,2,0))))*(1-IF(VLOOKUP($E29,OpTbl,3,0)="خرید",VLOOKUP("P02",ParamTbl,2,0),0)/100),"")) | P29: =IF(OR($E29="",$L29=""),"",IFERROR(IF(VLOOKUP($E29,OpTbl,6,0)="وزن",ROUND($N29*$O29,-3),IF(VLOOKUP($E29,OpTbl,6,0)="مبلغ",ROUND($L29*$O29,-3),0)),"")) | S29: =IF($E29="","",IF($AI29="⚠","⚠ ناتراز",IF(AND(IFERROR(VLOOKUP($E29,OpTbl,4,0),"")="بله",$L29=""),"⚠ وزن",IF(AND(IFERROR(VLOOKUP($E29,OpTbl,5,0),"")="بله",$U29=""),"⚠ حساب",IF(AND(IFERROR(VLOOKUP($E29,OpTbl,6,0),"")="مبلغ",$Q29=""),"⚠ مبلغ","✓"))))) | U29: =IF($E29="","",IFERROR(IF(VLOOKUP($E29,OpTbl,14,0)<>"",VLOOKUP($E29,OpTbl,14,0),$G29),"")) | V29: =IF(OR($AJ29="",$AJ29=0,$AL29<>"بدهکار"),"",$AJ29) | W29: =IF(OR($AJ29="",$AJ29=0,$AL29<>"بستانکار"),"",$AJ29) | X29: =IF($E29="","",IFERROR(VLOOKUP($E29,OpTbl,8,0),"")) | Y29: =IF(OR($X29="",$AJ29="",$AJ29=0,$AM29<>"بدهکار"),"",$AJ29) | Z29: =IF(OR($X29="",$AJ29="",$AJ29=0,$AM29<>"بستانکار"),"",$AJ29) | AA29: =IF(OR($E29="",$AN29="—",$AN29=""),"",IFERROR(VLOOKUP($E29,OpTbl,12,0),"")) | AB29: =IF(OR($AA29="",$Q29="",$Q29=0,$AN29<>"بدهکار"),"",$Q29) | AC29: =IF(OR($AA29="",$Q29="",$Q29=0,$AN29<>"بستانکار"),"",$Q29) | AD29: =IF($AA29="","",IFERROR(VLOOKUP($E29,OpTbl,13,0),"")) | AE29: =IF(OR($AD29="",$Q29="",$Q29=0,$AN29<>"بستانکار"),"",$Q29) | AF29: =IF(OR($AD29="",$Q29="",$Q29=0,$AN29<>"بدهکار"),"",$Q29) | AG29: =SUM($V29,$Y29,$AB29,$AE29) | AH29: =SUM($W29,$Z29,$AC29,$AF29) | AI29: =IF($E29="","",IF(ROUND($AG29-$AH29,0)=0,"✓","⚠")) | AJ29: =IF(OR($E29="",$U29=""),"",IFERROR(IF(VLOOKUP($E29,OpTbl,6,0)="وزن",IF($P29="",0,$P29),IF(VLOOKUP($E29,OpTbl,6,0)="مبلغ",IF(AND($Q29<>"",$Q29<>0),$Q29,$P29),0))+IF(VLOOKUP($E29,OpTbl,10,0)="افزودن",IF($Q29="",0,$Q29),0),0)) | AK29: =IF($E29="","",IFERROR(VLOOKUP($E29,OpTbl,10,0),"")) | AL29: =IF(OR($E29="",$U29=""),"",IFERROR(IF(VLOOKUP($E29,OpTbl,7,0)="خودکار",$R29,VLOOKUP($E29,OpTbl,7,0)),"")) | AM29: =IF(OR($E29="",$X29=""),"",IFERROR(IF(VLOOKUP($E29,OpTbl,9,0)="خودکار",IF($AL29="بدهکار","بستانکار",IF($AL29="بستانکار","بدهکار","")),VLOOKUP($E29,OpTbl,9,0)),"")) | AN29: =IF($E29="","",IFERROR(VLOOKUP($E29,OpTbl,11,0),"")) | AO29: =IF($B29="","",MID($B29,6,2)) | AP29: =IF($B29="",0,1)
A30: =IF($B30="","",COUNTA($B$10:$B30)) | F30: =IF($E30="","",IFERROR(VLOOKUP($E30,OpTbl,2,0),"")) | H30: =IF($U30="","",IFERROR(VLOOKUP($U30,AcctTbl,2,0),"کد ناشناخته")) | I30: =IF($U30="","",IFERROR(VLOOKUP($U30,AcctTbl,3,0),"")) | N30: =IF(OR($E30="",$L30=""),"",IFERROR(($L30-IF($M30="",0,$M30)*IFERROR(VLOOKUP($K30,BasketTbl,4,0),IFERROR(INDEX(BasketTbl,MATCH($K30,BasketCodeCol,0),4),VLOOKUP("P01",ParamTbl,2,0))))*(1-IF(VLOOKUP($E30,OpTbl,3,0)="خرید",VLOOKUP("P02",ParamTbl,2,0),0)/100),"")) | P30: =IF(OR($E30="",$L30=""),"",IFERROR(IF(VLOOKUP($E30,OpTbl,6,0)="وزن",ROUND($N30*$O30,-3),IF(VLOOKUP($E30,OpTbl,6,0)="مبلغ",ROUND($L30*$O30,-3),0)),"")) | S30: =IF($E30="","",IF($AI30="⚠","⚠ ناتراز",IF(AND(IFERROR(VLOOKUP($E30,OpTbl,4,0),"")="بله",$L30=""),"⚠ وزن",IF(AND(IFERROR(VLOOKUP($E30,OpTbl,5,0),"")="بله",$U30=""),"⚠ حساب",IF(AND(IFERROR(VLOOKUP($E30,OpTbl,6,0),"")="مبلغ",$Q30=""),"⚠ مبلغ","✓"))))) | U30: =IF($E30="","",IFERROR(IF(VLOOKUP($E30,OpTbl,14,0)<>"",VLOOKUP($E30,OpTbl,14,0),$G30),"")) | V30: =IF(OR($AJ30="",$AJ30=0,$AL30<>"بدهکار"),"",$AJ30) | W30: =IF(OR($AJ30="",$AJ30=0,$AL30<>"بستانکار"),"",$AJ30) | X30: =IF($E30="","",IFERROR(VLOOKUP($E30,OpTbl,8,0),"")) | Y30: =IF(OR($X30="",$AJ30="",$AJ30=0,$AM30<>"بدهکار"),"",$AJ30) | Z30: =IF(OR($X30="",$AJ30="",$AJ30=0,$AM30<>"بستانکار"),"",$AJ30) | AA30: =IF(OR($E30="",$AN30="—",$AN30=""),"",IFERROR(VLOOKUP($E30,OpTbl,12,0),"")) | AB30: =IF(OR($AA30="",$Q30="",$Q30=0,$AN30<>"بدهکار"),"",$Q30) | AC30: =IF(OR($AA30="",$Q30="",$Q30=0,$AN30<>"بستانکار"),"",$Q30) | AD30: =IF($AA30="","",IFERROR(VLOOKUP($E30,OpTbl,13,0),"")) | AE30: =IF(OR($AD30="",$Q30="",$Q30=0,$AN30<>"بستانکار"),"",$Q30) | AF30: =IF(OR($AD30="",$Q30="",$Q30=0,$AN30<>"بدهکار"),"",$Q30) | AG30: =SUM($V30,$Y30,$AB30,$AE30) | AH30: =SUM($W30,$Z30,$AC30,$AF30) | AI30: =IF($E30="","",IF(ROUND($AG30-$AH30,0)=0,"✓","⚠")) | AJ30: =IF(OR($E30="",$U30=""),"",IFERROR(IF(VLOOKUP($E30,OpTbl,6,0)="وزن",IF($P30="",0,$P30),IF(VLOOKUP($E30,OpTbl,6,0)="مبلغ",IF(AND($Q30<>"",$Q30<>0),$Q30,$P30),0))+IF(VLOOKUP($E30,OpTbl,10,0)="افزودن",IF($Q30="",0,$Q30),0),0)) | AK30: =IF($E30="","",IFERROR(VLOOKUP($E30,OpTbl,10,0),"")) | AL30: =IF(OR($E30="",$U30=""),"",IFERROR(IF(VLOOKUP($E30,OpTbl,7,0)="خودکار",$R30,VLOOKUP($E30,OpTbl,7,0)),"")) | AM30: =IF(OR($E30="",$X30=""),"",IFERROR(IF(VLOOKUP($E30,OpTbl,9,0)="خودکار",IF($AL30="بدهکار","بستانکار",IF($AL30="بستانکار","بدهکار","")),VLOOKUP($E30,OpTbl,9,0)),"")) | AN30: =IF($E30="","",IFERROR(VLOOKUP($E30,OpTbl,11,0),"")) | AO30: =IF($B30="","",MID($B30,6,2)) | AP30: =IF($B30="",0,1)
A31: =IF($B31="","",COUNTA($B$10:$B31)) | F31: =IF($E31="","",IFERROR(VLOOKUP($E31,OpTbl,2,0),"")) | H31: =IF($U31="","",IFERROR(VLOOKUP($U31,AcctTbl,2,0),"کد ناشناخته")) | I31: =IF($U31="","",IFERROR(VLOOKUP($U31,AcctTbl,3,0),"")) | N31: =IF(OR($E31="",$L31=""),"",IFERROR(($L31-IF($M31="",0,$M31)*IFERROR(VLOOKUP($K31,BasketTbl,4,0),IFERROR(INDEX(BasketTbl,MATCH($K31,BasketCodeCol,0),4),VLOOKUP("P01",ParamTbl,2,0))))*(1-IF(VLOOKUP($E31,OpTbl,3,0)="خرید",VLOOKUP("P02",ParamTbl,2,0),0)/100),"")) | P31: =IF(OR($E31="",$L31=""),"",IFERROR(IF(VLOOKUP($E31,OpTbl,6,0)="وزن",ROUND($N31*$O31,-3),IF(VLOOKUP($E31,OpTbl,6,0)="مبلغ",ROUND($L31*$O31,-3),0)),"")) | S31: =IF($E31="","",IF($AI31="⚠","⚠ ناتراز",IF(AND(IFERROR(VLOOKUP($E31,OpTbl,4,0),"")="بله",$L31=""),"⚠ وزن",IF(AND(IFERROR(VLOOKUP($E31,OpTbl,5,0),"")="بله",$U31=""),"⚠ حساب",IF(AND(IFERROR(VLOOKUP($E31,OpTbl,6,0),"")="مبلغ",$Q31=""),"⚠ مبلغ","✓"))))) | U31: =IF($E31="","",IFERROR(IF(VLOOKUP($E31,OpTbl,14,0)<>"",VLOOKUP($E31,OpTbl,14,0),$G31),"")) | V31: =IF(OR($AJ31="",$AJ31=0,$AL31<>"بدهکار"),"",$AJ31) | W31: =IF(OR($AJ31="",$AJ31=0,$AL31<>"بستانکار"),"",$AJ31) | X31: =IF($E31="","",IFERROR(VLOOKUP($E31,OpTbl,8,0),"")) | Y31: =IF(OR($X31="",$AJ31="",$AJ31=0,$AM31<>"بدهکار"),"",$AJ31) | Z31: =IF(OR($X31="",$AJ31="",$AJ31=0,$AM31<>"بستانکار"),"",$AJ31) | AA31: =IF(OR($E31="",$AN31="—",$AN31=""),"",IFERROR(VLOOKUP($E31,OpTbl,12,0),"")) | AB31: =IF(OR($AA31="",$Q31="",$Q31=0,$AN31<>"بدهکار"),"",$Q31) | AC31: =IF(OR($AA31="",$Q31="",$Q31=0,$AN31<>"بستانکار"),"",$Q31) | AD31: =IF($AA31="","",IFERROR(VLOOKUP($E31,OpTbl,13,0),"")) | AE31: =IF(OR($AD31="",$Q31="",$Q31=0,$AN31<>"بستانکار"),"",$Q31) | AF31: =IF(OR($AD31="",$Q31="",$Q31=0,$AN31<>"بدهکار"),"",$Q31) | AG31: =SUM($V31,$Y31,$AB31,$AE31) | AH31: =SUM($W31,$Z31,$AC31,$AF31) | AI31: =IF($E31="","",IF(ROUND($AG31-$AH31,0)=0,"✓","⚠")) | AJ31: =IF(OR($E31="",$U31=""),"",IFERROR(IF(VLOOKUP($E31,OpTbl,6,0)="وزن",IF($P31="",0,$P31),IF(VLOOKUP($E31,OpTbl,6,0)="مبلغ",IF(AND($Q31<>"",$Q31<>0),$Q31,$P31),0))+IF(VLOOKUP($E31,OpTbl,10,0)="افزودن",IF($Q31="",0,$Q31),0),0)) | AK31: =IF($E31="","",IFERROR(VLOOKUP($E31,OpTbl,10,0),"")) | AL31: =IF(OR($E31="",$U31=""),"",IFERROR(IF(VLOOKUP($E31,OpTbl,7,0)="خودکار",$R31,VLOOKUP($E31,OpTbl,7,0)),"")) | AM31: =IF(OR($E31="",$X31=""),"",IFERROR(IF(VLOOKUP($E31,OpTbl,9,0)="خودکار",IF($AL31="بدهکار","بستانکار",IF($AL31="بستانکار","بدهکار","")),VLOOKUP($E31,OpTbl,9,0)),"")) | AN31: =IF($E31="","",IFERROR(VLOOKUP($E31,OpTbl,11,0),"")) | AO31: =IF($B31="","",MID($B31,6,2)) | AP31: =IF($B31="",0,1)
A32: =IF($B32="","",COUNTA($B$10:$B32)) | F32: =IF($E32="","",IFERROR(VLOOKUP($E32,OpTbl,2,0),"")) | H32: =IF($U32="","",IFERROR(VLOOKUP($U32,AcctTbl,2,0),"کد ناشناخته")) | I32: =IF($U32="","",IFERROR(VLOOKUP($U32,AcctTbl,3,0),"")) | N32: =IF(OR($E32="",$L32=""),"",IFERROR(($L32-IF($M32="",0,$M32)*IFERROR(VLOOKUP($K32,BasketTbl,4,0),IFERROR(INDEX(BasketTbl,MATCH($K32,BasketCodeCol,0),4),VLOOKUP("P01",ParamTbl,2,0))))*(1-IF(VLOOKUP($E32,OpTbl,3,0)="خرید",VLOOKUP("P02",ParamTbl,2,0),0)/100),"")) | P32: =IF(OR($E32="",$L32=""),"",IFERROR(IF(VLOOKUP($E32,OpTbl,6,0)="وزن",ROUND($N32*$O32,-3),IF(VLOOKUP($E32,OpTbl,6,0)="مبلغ",ROUND($L32*$O32,-3),0)),"")) | S32: =IF($E32="","",IF($AI32="⚠","⚠ ناتراز",IF(AND(IFERROR(VLOOKUP($E32,OpTbl,4,0),"")="بله",$L32=""),"⚠ وزن",IF(AND(IFERROR(VLOOKUP($E32,OpTbl,5,0),"")="بله",$U32=""),"⚠ حساب",IF(AND(IFERROR(VLOOKUP($E32,OpTbl,6,0),"")="مبلغ",$Q32=""),"⚠ مبلغ","✓"))))) | U32: =IF($E32="","",IFERROR(IF(VLOOKUP($E32,OpTbl,14,0)<>"",VLOOKUP($E32,OpTbl,14,0),$G32),"")) | V32: =IF(OR($AJ32="",$AJ32=0,$AL32<>"بدهکار"),"",$AJ32) | W32: =IF(OR($AJ32="",$AJ32=0,$AL32<>"بستانکار"),"",$AJ32) | X32: =IF($E32="","",IFERROR(VLOOKUP($E32,OpTbl,8,0),"")) | Y32: =IF(OR($X32="",$AJ32="",$AJ32=0,$AM32<>"بدهکار"),"",$AJ32) | Z32: =IF(OR($X32="",$AJ32="",$AJ32=0,$AM32<>"بستانکار"),"",$AJ32) | AA32: =IF(OR($E32="",$AN32="—",$AN32=""),"",IFERROR(VLOOKUP($E32,OpTbl,12,0),"")) | AB32: =IF(OR($AA32="",$Q32="",$Q32=0,$AN32<>"بدهکار"),"",$Q32) | AC32: =IF(OR($AA32="",$Q32="",$Q32=0,$AN32<>"بستانکار"),"",$Q32) | AD32: =IF($AA32="","",IFERROR(VLOOKUP($E32,OpTbl,13,0),"")) | AE32: =IF(OR($AD32="",$Q32="",$Q32=0,$AN32<>"بستانکار"),"",$Q32) | AF32: =IF(OR($AD32="",$Q32="",$Q32=0,$AN32<>"بدهکار"),"",$Q32) | AG32: =SUM($V32,$Y32,$AB32,$AE32) | AH32: =SUM($W32,$Z32,$AC32,$AF32) | AI32: =IF($E32="","",IF(ROUND($AG32-$AH32,0)=0,"✓","⚠")) | AJ32: =IF(OR($E32="",$U32=""),"",IFERROR(IF(VLOOKUP($E32,OpTbl,6,0)="وزن",IF($P32="",0,$P32),IF(VLOOKUP($E32,OpTbl,6,0)="مبلغ",IF(AND($Q32<>"",$Q32<>0),$Q32,$P32),0))+IF(VLOOKUP($E32,OpTbl,10,0)="افزودن",IF($Q32="",0,$Q32),0),0)) | AK32: =IF($E32="","",IFERROR(VLOOKUP($E32,OpTbl,10,0),"")) | AL32: =IF(OR($E32="",$U32=""),"",IFERROR(IF(VLOOKUP($E32,OpTbl,7,0)="خودکار",$R32,VLOOKUP($E32,OpTbl,7,0)),"")) | AM32: =IF(OR($E32="",$X32=""),"",IFERROR(IF(VLOOKUP($E32,OpTbl,9,0)="خودکار",IF($AL32="بدهکار","بستانکار",IF($AL32="بستانکار","بدهکار","")),VLOOKUP($E32,OpTbl,9,0)),"")) | AN32: =IF($E32="","",IFERROR(VLOOKUP($E32,OpTbl,11,0),"")) | AO32: =IF($B32="","",MID($B32,6,2)) | AP32: =IF($B32="",0,1)
A33: =IF($B33="","",COUNTA($B$10:$B33)) | F33: =IF($E33="","",IFERROR(VLOOKUP($E33,OpTbl,2,0),"")) | H33: =IF($U33="","",IFERROR(VLOOKUP($U33,AcctTbl,2,0),"کد ناشناخته")) | I33: =IF($U33="","",IFERROR(VLOOKUP($U33,AcctTbl,3,0),"")) | N33: =IF(OR($E33="",$L33=""),"",IFERROR(($L33-IF($M33="",0,$M33)*IFERROR(VLOOKUP($K33,BasketTbl,4,0),IFERROR(INDEX(BasketTbl,MATCH($K33,BasketCodeCol,0),4),VLOOKUP("P01",ParamTbl,2,0))))*(1-IF(VLOOKUP($E33,OpTbl,3,0)="خرید",VLOOKUP("P02",ParamTbl,2,0),0)/100),"")) | P33: =IF(OR($E33="",$L33=""),"",IFERROR(IF(VLOOKUP($E33,OpTbl,6,0)="وزن",ROUND($N33*$O33,-3),IF(VLOOKUP($E33,OpTbl,6,0)="مبلغ",ROUND($L33*$O33,-3),0)),"")) | S33: =IF($E33="","",IF($AI33="⚠","⚠ ناتراز",IF(AND(IFERROR(VLOOKUP($E33,OpTbl,4,0),"")="بله",$L33=""),"⚠ وزن",IF(AND(IFERROR(VLOOKUP($E33,OpTbl,5,0),"")="بله",$U33=""),"⚠ حساب",IF(AND(IFERROR(VLOOKUP($E33,OpTbl,6,0),"")="مبلغ",$Q33=""),"⚠ مبلغ","✓"))))) | U33: =IF($E33="","",IFERROR(IF(VLOOKUP($E33,OpTbl,14,0)<>"",VLOOKUP($E33,OpTbl,14,0),$G33),"")) | V33: =IF(OR($AJ33="",$AJ33=0,$AL33<>"بدهکار"),"",$AJ33) | W33: =IF(OR($AJ33="",$AJ33=0,$AL33<>"بستانکار"),"",$AJ33) | X33: =IF($E33="","",IFERROR(VLOOKUP($E33,OpTbl,8,0),"")) | Y33: =IF(OR($X33="",$AJ33="",$AJ33=0,$AM33<>"بدهکار"),"",$AJ33) | Z33: =IF(OR($X33="",$AJ33="",$AJ33=0,$AM33<>"بستانکار"),"",$AJ33) | AA33: =IF(OR($E33="",$AN33="—",$AN33=""),"",IFERROR(VLOOKUP($E33,OpTbl,12,0),"")) | AB33: =IF(OR($AA33="",$Q33="",$Q33=0,$AN33<>"بدهکار"),"",$Q33) | AC33: =IF(OR($AA33="",$Q33="",$Q33=0,$AN33<>"بستانکار"),"",$Q33) | AD33: =IF($AA33="","",IFERROR(VLOOKUP($E33,OpTbl,13,0),"")) | AE33: =IF(OR($AD33="",$Q33="",$Q33=0,$AN33<>"بستانکار"),"",$Q33) | AF33: =IF(OR($AD33="",$Q33="",$Q33=0,$AN33<>"بدهکار"),"",$Q33) | AG33: =SUM($V33,$Y33,$AB33,$AE33) | AH33: =SUM($W33,$Z33,$AC33,$AF33) | AI33: =IF($E33="","",IF(ROUND($AG33-$AH33,0)=0,"✓","⚠")) | AJ33: =IF(OR($E33="",$U33=""),"",IFERROR(IF(VLOOKUP($E33,OpTbl,6,0)="وزن",IF($P33="",0,$P33),IF(VLOOKUP($E33,OpTbl,6,0)="مبلغ",IF(AND($Q33<>"",$Q33<>0),$Q33,$P33),0))+IF(VLOOKUP($E33,OpTbl,10,0)="افزودن",IF($Q33="",0,$Q33),0),0)) | AK33: =IF($E33="","",IFERROR(VLOOKUP($E33,OpTbl,10,0),"")) | AL33: =IF(OR($E33="",$U33=""),"",IFERROR(IF(VLOOKUP($E33,OpTbl,7,0)="خودکار",$R33,VLOOKUP($E33,OpTbl,7,0)),"")) | AM33: =IF(OR($E33="",$X33=""),"",IFERROR(IF(VLOOKUP($E33,OpTbl,9,0)="خودکار",IF($AL33="بدهکار","بستانکار",IF($AL33="بستانکار","بدهکار","")),VLOOKUP($E33,OpTbl,9,0)),"")) | AN33: =IF($E33="","",IFERROR(VLOOKUP($E33,OpTbl,11,0),"")) | AO33: =IF($B33="","",MID($B33,6,2)) | AP33: =IF($B33="",0,1)
A34: =IF($B34="","",COUNTA($B$10:$B34)) | F34: =IF($E34="","",IFERROR(VLOOKUP($E34,OpTbl,2,0),"")) | H34: =IF($U34="","",IFERROR(VLOOKUP($U34,AcctTbl,2,0),"کد ناشناخته")) | I34: =IF($U34="","",IFERROR(VLOOKUP($U34,AcctTbl,3,0),"")) | N34: =IF(OR($E34="",$L34=""),"",IFERROR(($L34-IF($M34="",0,$M34)*IFERROR(VLOOKUP($K34,BasketTbl,4,0),IFERROR(INDEX(BasketTbl,MATCH($K34,BasketCodeCol,0),4),VLOOKUP("P01",ParamTbl,2,0))))*(1-IF(VLOOKUP($E34,OpTbl,3,0)="خرید",VLOOKUP("P02",ParamTbl,2,0),0)/100),"")) | P34: =IF(OR($E34="",$L34=""),"",IFERROR(IF(VLOOKUP($E34,OpTbl,6,0)="وزن",ROUND($N34*$O34,-3),IF(VLOOKUP($E34,OpTbl,6,0)="مبلغ",ROUND($L34*$O34,-3),0)),"")) | S34: =IF($E34="","",IF($AI34="⚠","⚠ ناتراز",IF(AND(IFERROR(VLOOKUP($E34,OpTbl,4,0),"")="بله",$L34=""),"⚠ وزن",IF(AND(IFERROR(VLOOKUP($E34,OpTbl,5,0),"")="بله",$U34=""),"⚠ حساب",IF(AND(IFERROR(VLOOKUP($E34,OpTbl,6,0),"")="مبلغ",$Q34=""),"⚠ مبلغ","✓"))))) | U34: =IF($E34="","",IFERROR(IF(VLOOKUP($E34,OpTbl,14,0)<>"",VLOOKUP($E34,OpTbl,14,0),$G34),"")) | V34: =IF(OR($AJ34="",$AJ34=0,$AL34<>"بدهکار"),"",$AJ34) | W34: =IF(OR($AJ34="",$AJ34=0,$AL34<>"بستانکار"),"",$AJ34) | X34: =IF($E34="","",IFERROR(VLOOKUP($E34,OpTbl,8,0),"")) | Y34: =IF(OR($X34="",$AJ34="",$AJ34=0,$AM34<>"بدهکار"),"",$AJ34) | Z34: =IF(OR($X34="",$AJ34="",$AJ34=0,$AM34<>"بستانکار"),"",$AJ34) | AA34: =IF(OR($E34="",$AN34="—",$AN34=""),"",IFERROR(VLOOKUP($E34,OpTbl,12,0),"")) | AB34: =IF(OR($AA34="",$Q34="",$Q34=0,$AN34<>"بدهکار"),"",$Q34) | AC34: =IF(OR($AA34="",$Q34="",$Q34=0,$AN34<>"بستانکار"),"",$Q34) | AD34: =IF($AA34="","",IFERROR(VLOOKUP($E34,OpTbl,13,0),"")) | AE34: =IF(OR($AD34="",$Q34="",$Q34=0,$AN34<>"بستانکار"),"",$Q34) | AF34: =IF(OR($AD34="",$Q34="",$Q34=0,$AN34<>"بدهکار"),"",$Q34) | AG34: =SUM($V34,$Y34,$AB34,$AE34) | AH34: =SUM($W34,$Z34,$AC34,$AF34) | AI34: =IF($E34="","",IF(ROUND($AG34-$AH34,0)=0,"✓","⚠")) | AJ34: =IF(OR($E34="",$U34=""),"",IFERROR(IF(VLOOKUP($E34,OpTbl,6,0)="وزن",IF($P34="",0,$P34),IF(VLOOKUP($E34,OpTbl,6,0)="مبلغ",IF(AND($Q34<>"",$Q34<>0),$Q34,$P34),0))+IF(VLOOKUP($E34,OpTbl,10,0)="افزودن",IF($Q34="",0,$Q34),0),0)) | AK34: =IF($E34="","",IFERROR(VLOOKUP($E34,OpTbl,10,0),"")) | AL34: =IF(OR($E34="",$U34=""),"",IFERROR(IF(VLOOKUP($E34,OpTbl,7,0)="خودکار",$R34,VLOOKUP($E34,OpTbl,7,0)),"")) | AM34: =IF(OR($E34="",$X34=""),"",IFERROR(IF(VLOOKUP($E34,OpTbl,9,0)="خودکار",IF($AL34="بدهکار","بستانکار",IF($AL34="بستانکار","بدهکار","")),VLOOKUP($E34,OpTbl,9,0)),"")) | AN34: =IF($E34="","",IFERROR(VLOOKUP($E34,OpTbl,11,0),"")) | AO34: =IF($B34="","",MID($B34,6,2)) | AP34: =IF($B34="",0,1)
A35: =IF($B35="","",COUNTA($B$10:$B35)) | F35: =IF($E35="","",IFERROR(VLOOKUP($E35,OpTbl,2,0),"")) | H35: =IF($U35="","",IFERROR(VLOOKUP($U35,AcctTbl,2,0),"کد ناشناخته")) | I35: =IF($U35="","",IFERROR(VLOOKUP($U35,AcctTbl,3,0),"")) | N35: =IF(OR($E35="",$L35=""),"",IFERROR(($L35-IF($M35="",0,$M35)*IFERROR(VLOOKUP($K35,BasketTbl,4,0),IFERROR(INDEX(BasketTbl,MATCH($K35,BasketCodeCol,0),4),VLOOKUP("P01",ParamTbl,2,0))))*(1-IF(VLOOKUP($E35,OpTbl,3,0)="خرید",VLOOKUP("P02",ParamTbl,2,0),0)/100),"")) | P35: =IF(OR($E35="",$L35=""),"",IFERROR(IF(VLOOKUP($E35,OpTbl,6,0)="وزن",ROUND($N35*$O35,-3),IF(VLOOKUP($E35,OpTbl,6,0)="مبلغ",ROUND($L35*$O35,-3),0)),"")) | S35: =IF($E35="","",IF($AI35="⚠","⚠ ناتراز",IF(AND(IFERROR(VLOOKUP($E35,OpTbl,4,0),"")="بله",$L35=""),"⚠ وزن",IF(AND(IFERROR(VLOOKUP($E35,OpTbl,5,0),"")="بله",$U35=""),"⚠ حساب",IF(AND(IFERROR(VLOOKUP($E35,OpTbl,6,0),"")="مبلغ",$Q35=""),"⚠ مبلغ","✓"))))) | U35: =IF($E35="","",IFERROR(IF(VLOOKUP($E35,OpTbl,14,0)<>"",VLOOKUP($E35,OpTbl,14,0),$G35),"")) | V35: =IF(OR($AJ35="",$AJ35=0,$AL35<>"بدهکار"),"",$AJ35) | W35: =IF(OR($AJ35="",$AJ35=0,$AL35<>"بستانکار"),"",$AJ35) | X35: =IF($E35="","",IFERROR(VLOOKUP($E35,OpTbl,8,0),"")) | Y35: =IF(OR($X35="",$AJ35="",$AJ35=0,$AM35<>"بدهکار"),"",$AJ35) | Z35: =IF(OR($X35="",$AJ35="",$AJ35=0,$AM35<>"بستانکار"),"",$AJ35) | AA35: =IF(OR($E35="",$AN35="—",$AN35=""),"",IFERROR(VLOOKUP($E35,OpTbl,12,0),"")) | AB35: =IF(OR($AA35="",$Q35="",$Q35=0,$AN35<>"بدهکار"),"",$Q35) | AC35: =IF(OR($AA35="",$Q35="",$Q35=0,$AN35<>"بستانکار"),"",$Q35) | AD35: =IF($AA35="","",IFERROR(VLOOKUP($E35,OpTbl,13,0),"")) | AE35: =IF(OR($AD35="",$Q35="",$Q35=0,$AN35<>"بستانکار"),"",$Q35) | AF35: =IF(OR($AD35="",$Q35="",$Q35=0,$AN35<>"بدهکار"),"",$Q35) | AG35: =SUM($V35,$Y35,$AB35,$AE35) | AH35: =SUM($W35,$Z35,$AC35,$AF35) | AI35: =IF($E35="","",IF(ROUND($AG35-$AH35,0)=0,"✓","⚠")) | AJ35: =IF(OR($E35="",$U35=""),"",IFERROR(IF(VLOOKUP($E35,OpTbl,6,0)="وزن",IF($P35="",0,$P35),IF(VLOOKUP($E35,OpTbl,6,0)="مبلغ",IF(AND($Q35<>"",$Q35<>0),$Q35,$P35),0))+IF(VLOOKUP($E35,OpTbl,10,0)="افزودن",IF($Q35="",0,$Q35),0),0)) | AK35: =IF($E35="","",IFERROR(VLOOKUP($E35,OpTbl,10,0),"")) | AL35: =IF(OR($E35="",$U35=""),"",IFERROR(IF(VLOOKUP($E35,OpTbl,7,0)="خودکار",$R35,VLOOKUP($E35,OpTbl,7,0)),"")) | AM35: =IF(OR($E35="",$X35=""),"",IFERROR(IF(VLOOKUP($E35,OpTbl,9,0)="خودکار",IF($AL35="بدهکار","بستانکار",IF($AL35="بستانکار","بدهکار","")),VLOOKUP($E35,OpTbl,9,0)),"")) | AN35: =IF($E35="","",IFERROR(VLOOKUP($E35,OpTbl,11,0),"")) | AO35: =IF($B35="","",MID($B35,6,2)) | AP35: =IF($B35="",0,1)
A36: =IF($B36="","",COUNTA($B$10:$B36)) | F36: =IF($E36="","",IFERROR(VLOOKUP($E36,OpTbl,2,0),"")) | H36: =IF($U36="","",IFERROR(VLOOKUP($U36,AcctTbl,2,0),"کد ناشناخته")) | I36: =IF($U36="","",IFERROR(VLOOKUP($U36,AcctTbl,3,0),"")) | N36: =IF(OR($E36="",$L36=""),"",IFERROR(($L36-IF($M36="",0,$M36)*IFERROR(VLOOKUP($K36,BasketTbl,4,0),IFERROR(INDEX(BasketTbl,MATCH($K36,BasketCodeCol,0),4),VLOOKUP("P01",ParamTbl,2,0))))*(1-IF(VLOOKUP($E36,OpTbl,3,0)="خرید",VLOOKUP("P02",ParamTbl,2,0),0)/100),"")) | P36: =IF(OR($E36="",$L36=""),"",IFERROR(IF(VLOOKUP($E36,OpTbl,6,0)="وزن",ROUND($N36*$O36,-3),IF(VLOOKUP($E36,OpTbl,6,0)="مبلغ",ROUND($L36*$O36,-3),0)),"")) | S36: =IF($E36="","",IF($AI36="⚠","⚠ ناتراز",IF(AND(IFERROR(VLOOKUP($E36,OpTbl,4,0),"")="بله",$L36=""),"⚠ وزن",IF(AND(IFERROR(VLOOKUP($E36,OpTbl,5,0),"")="بله",$U36=""),"⚠ حساب",IF(AND(IFERROR(VLOOKUP($E36,OpTbl,6,0),"")="مبلغ",$Q36=""),"⚠ مبلغ","✓"))))) | U36: =IF($E36="","",IFERROR(IF(VLOOKUP($E36,OpTbl,14,0)<>"",VLOOKUP($E36,OpTbl,14,0),$G36),"")) | V36: =IF(OR($AJ36="",$AJ36=0,$AL36<>"بدهکار"),"",$AJ36) | W36: =IF(OR($AJ36="",$AJ36=0,$AL36<>"بستانکار"),"",$AJ36) | X36: =IF($E36="","",IFERROR(VLOOKUP($E36,OpTbl,8,0),"")) | Y36: =IF(OR($X36="",$AJ36="",$AJ36=0,$AM36<>"بدهکار"),"",$AJ36) | Z36: =IF(OR($X36="",$AJ36="",$AJ36=0,$AM36<>"بستانکار"),"",$AJ36) | AA36: =IF(OR($E36="",$AN36="—",$AN36=""),"",IFERROR(VLOOKUP($E36,OpTbl,12,0),"")) | AB36: =IF(OR($AA36="",$Q36="",$Q36=0,$AN36<>"بدهکار"),"",$Q36) | AC36: =IF(OR($AA36="",$Q36="",$Q36=0,$AN36<>"بستانکار"),"",$Q36) | AD36: =IF($AA36="","",IFERROR(VLOOKUP($E36,OpTbl,13,0),"")) | AE36: =IF(OR($AD36="",$Q36="",$Q36=0,$AN36<>"بستانکار"),"",$Q36) | AF36: =IF(OR($AD36="",$Q36="",$Q36=0,$AN36<>"بدهکار"),"",$Q36) | AG36: =SUM($V36,$Y36,$AB36,$AE36) | AH36: =SUM($W36,$Z36,$AC36,$AF36) | AI36: =IF($E36="","",IF(ROUND($AG36-$AH36,0)=0,"✓","⚠")) | AJ36: =IF(OR($E36="",$U36=""),"",IFERROR(IF(VLOOKUP($E36,OpTbl,6,0)="وزن",IF($P36="",0,$P36),IF(VLOOKUP($E36,OpTbl,6,0)="مبلغ",IF(AND($Q36<>"",$Q36<>0),$Q36,$P36),0))+IF(VLOOKUP($E36,OpTbl,10,0)="افزودن",IF($Q36="",0,$Q36),0),0)) | AK36: =IF($E36="","",IFERROR(VLOOKUP($E36,OpTbl,10,0),"")) | AL36: =IF(OR($E36="",$U36=""),"",IFERROR(IF(VLOOKUP($E36,OpTbl,7,0)="خودکار",$R36,VLOOKUP($E36,OpTbl,7,0)),"")) | AM36: =IF(OR($E36="",$X36=""),"",IFERROR(IF(VLOOKUP($E36,OpTbl,9,0)="خودکار",IF($AL36="بدهکار","بستانکار",IF($AL36="بستانکار","بدهکار","")),VLOOKUP($E36,OpTbl,9,0)),"")) | AN36: =IF($E36="","",IFERROR(VLOOKUP($E36,OpTbl,11,0),"")) | AO36: =IF($B36="","",MID($B36,6,2)) | AP36: =IF($B36="",0,1)
A37: =IF($B37="","",COUNTA($B$10:$B37)) | F37: =IF($E37="","",IFERROR(VLOOKUP($E37,OpTbl,2,0),"")) | H37: =IF($U37="","",IFERROR(VLOOKUP($U37,AcctTbl,2,0),"کد ناشناخته")) | I37: =IF($U37="","",IFERROR(VLOOKUP($U37,AcctTbl,3,0),"")) | N37: =IF(OR($E37="",$L37=""),"",IFERROR(($L37-IF($M37="",0,$M37)*IFERROR(VLOOKUP($K37,BasketTbl,4,0),IFERROR(INDEX(BasketTbl,MATCH($K37,BasketCodeCol,0),4),VLOOKUP("P01",ParamTbl,2,0))))*(1-IF(VLOOKUP($E37,OpTbl,3,0)="خرید",VLOOKUP("P02",ParamTbl,2,0),0)/100),"")) | P37: =IF(OR($E37="",$L37=""),"",IFERROR(IF(VLOOKUP($E37,OpTbl,6,0)="وزن",ROUND($N37*$O37,-3),IF(VLOOKUP($E37,OpTbl,6,0)="مبلغ",ROUND($L37*$O37,-3),0)),"")) | S37: =IF($E37="","",IF($AI37="⚠","⚠ ناتراز",IF(AND(IFERROR(VLOOKUP($E37,OpTbl,4,0),"")="بله",$L37=""),"⚠ وزن",IF(AND(IFERROR(VLOOKUP($E37,OpTbl,5,0),"")="بله",$U37=""),"⚠ حساب",IF(AND(IFERROR(VLOOKUP($E37,OpTbl,6,0),"")="مبلغ",$Q37=""),"⚠ مبلغ","✓"))))) | U37: =IF($E37="","",IFERROR(IF(VLOOKUP($E37,OpTbl,14,0)<>"",VLOOKUP($E37,OpTbl,14,0),$G37),"")) | V37: =IF(OR($AJ37="",$AJ37=0,$AL37<>"بدهکار"),"",$AJ37) | W37: =IF(OR($AJ37="",$AJ37=0,$AL37<>"بستانکار"),"",$AJ37) | X37: =IF($E37="","",IFERROR(VLOOKUP($E37,OpTbl,8,0),"")) | Y37: =IF(OR($X37="",$AJ37="",$AJ37=0,$AM37<>"بدهکار"),"",$AJ37) | Z37: =IF(OR($X37="",$AJ37="",$AJ37=0,$AM37<>"بستانکار"),"",$AJ37) | AA37: =IF(OR($E37="",$AN37="—",$AN37=""),"",IFERROR(VLOOKUP($E37,OpTbl,12,0),"")) | AB37: =IF(OR($AA37="",$Q37="",$Q37=0,$AN37<>"بدهکار"),"",$Q37) | AC37: =IF(OR($AA37="",$Q37="",$Q37=0,$AN37<>"بستانکار"),"",$Q37) | AD37: =IF($AA37="","",IFERROR(VLOOKUP($E37,OpTbl,13,0),"")) | AE37: =IF(OR($AD37="",$Q37="",$Q37=0,$AN37<>"بستانکار"),"",$Q37) | AF37: =IF(OR($AD37="",$Q37="",$Q37=0,$AN37<>"بدهکار"),"",$Q37) | AG37: =SUM($V37,$Y37,$AB37,$AE37) | AH37: =SUM($W37,$Z37,$AC37,$AF37) | AI37: =IF($E37="","",IF(ROUND($AG37-$AH37,0)=0,"✓","⚠")) | AJ37: =IF(OR($E37="",$U37=""),"",IFERROR(IF(VLOOKUP($E37,OpTbl,6,0)="وزن",IF($P37="",0,$P37),IF(VLOOKUP($E37,OpTbl,6,0)="مبلغ",IF(AND($Q37<>"",$Q37<>0),$Q37,$P37),0))+IF(VLOOKUP($E37,OpTbl,10,0)="افزودن",IF($Q37="",0,$Q37),0),0)) | AK37: =IF($E37="","",IFERROR(VLOOKUP($E37,OpTbl,10,0),"")) | AL37: =IF(OR($E37="",$U37=""),"",IFERROR(IF(VLOOKUP($E37,OpTbl,7,0)="خودکار",$R37,VLOOKUP($E37,OpTbl,7,0)),"")) | AM37: =IF(OR($E37="",$X37=""),"",IFERROR(IF(VLOOKUP($E37,OpTbl,9,0)="خودکار",IF($AL37="بدهکار","بستانکار",IF($AL37="بستانکار","بدهکار","")),VLOOKUP($E37,OpTbl,9,0)),"")) | AN37: =IF($E37="","",IFERROR(VLOOKUP($E37,OpTbl,11,0),"")) | AO37: =IF($B37="","",MID($B37,6,2)) | AP37: =IF($B37="",0,1)
A38: =IF($B38="","",COUNTA($B$10:$B38)) | F38: =IF($E38="","",IFERROR(VLOOKUP($E38,OpTbl,2,0),"")) | H38: =IF($U38="","",IFERROR(VLOOKUP($U38,AcctTbl,2,0),"کد ناشناخته")) | I38: =IF($U38="","",IFERROR(VLOOKUP($U38,AcctTbl,3,0),"")) | N38: =IF(OR($E38="",$L38=""),"",IFERROR(($L38-IF($M38="",0,$M38)*IFERROR(VLOOKUP($K38,BasketTbl,4,0),IFERROR(INDEX(BasketTbl,MATCH($K38,BasketCodeCol,0),4),VLOOKUP("P01",ParamTbl,2,0))))*(1-IF(VLOOKUP($E38,OpTbl,3,0)="خرید",VLOOKUP("P02",ParamTbl,2,0),0)/100),"")) | P38: =IF(OR($E38="",$L38=""),"",IFERROR(IF(VLOOKUP($E38,OpTbl,6,0)="وزن",ROUND($N38*$O38,-3),IF(VLOOKUP($E38,OpTbl,6,0)="مبلغ",ROUND($L38*$O38,-3),0)),"")) | S38: =IF($E38="","",IF($AI38="⚠","⚠ ناتراز",IF(AND(IFERROR(VLOOKUP($E38,OpTbl,4,0),"")="بله",$L38=""),"⚠ وزن",IF(AND(IFERROR(VLOOKUP($E38,OpTbl,5,0),"")="بله",$U38=""),"⚠ حساب",IF(AND(IFERROR(VLOOKUP($E38,OpTbl,6,0),"")="مبلغ",$Q38=""),"⚠ مبلغ","✓"))))) | U38: =IF($E38="","",IFERROR(IF(VLOOKUP($E38,OpTbl,14,0)<>"",VLOOKUP($E38,OpTbl,14,0),$G38),"")) | V38: =IF(OR($AJ38="",$AJ38=0,$AL38<>"بدهکار"),"",$AJ38) | W38: =IF(OR($AJ38="",$AJ38=0,$AL38<>"بستانکار"),"",$AJ38) | X38: =IF($E38="","",IFERROR(VLOOKUP($E38,OpTbl,8,0),"")) | Y38: =IF(OR($X38="",$AJ38="",$AJ38=0,$AM38<>"بدهکار"),"",$AJ38) | Z38: =IF(OR($X38="",$AJ38="",$AJ38=0,$AM38<>"بستانکار"),"",$AJ38) | AA38: =IF(OR($E38="",$AN38="—",$AN38=""),"",IFERROR(VLOOKUP($E38,OpTbl,12,0),"")) | AB38: =IF(OR($AA38="",$Q38="",$Q38=0,$AN38<>"بدهکار"),"",$Q38) | AC38: =IF(OR($AA38="",$Q38="",$Q38=0,$AN38<>"بستانکار"),"",$Q38) | AD38: =IF($AA38="","",IFERROR(VLOOKUP($E38,OpTbl,13,0),"")) | AE38: =IF(OR($AD38="",$Q38="",$Q38=0,$AN38<>"بستانکار"),"",$Q38) | AF38: =IF(OR($AD38="",$Q38="",$Q38=0,$AN38<>"بدهکار"),"",$Q38) | AG38: =SUM($V38,$Y38,$AB38,$AE38) | AH38: =SUM($W38,$Z38,$AC38,$AF38) | AI38: =IF($E38="","",IF(ROUND($AG38-$AH38,0)=0,"✓","⚠")) | AJ38: =IF(OR($E38="",$U38=""),"",IFERROR(IF(VLOOKUP($E38,OpTbl,6,0)="وزن",IF($P38="",0,$P38),IF(VLOOKUP($E38,OpTbl,6,0)="مبلغ",IF(AND($Q38<>"",$Q38<>0),$Q38,$P38),0))+IF(VLOOKUP($E38,OpTbl,10,0)="افزودن",IF($Q38="",0,$Q38),0),0)) | AK38: =IF($E38="","",IFERROR(VLOOKUP($E38,OpTbl,10,0),"")) | AL38: =IF(OR($E38="",$U38=""),"",IFERROR(IF(VLOOKUP($E38,OpTbl,7,0)="خودکار",$R38,VLOOKUP($E38,OpTbl,7,0)),"")) | AM38: =IF(OR($E38="",$X38=""),"",IFERROR(IF(VLOOKUP($E38,OpTbl,9,0)="خودکار",IF($AL38="بدهکار","بستانکار",IF($AL38="بستانکار","بدهکار","")),VLOOKUP($E38,OpTbl,9,0)),"")) | AN38: =IF($E38="","",IFERROR(VLOOKUP($E38,OpTbl,11,0),"")) | AO38: =IF($B38="","",MID($B38,6,2)) | AP38: =IF($B38="",0,1)
A39: =IF($B39="","",COUNTA($B$10:$B39)) | F39: =IF($E39="","",IFERROR(VLOOKUP($E39,OpTbl,2,0),"")) | H39: =IF($U39="","",IFERROR(VLOOKUP($U39,AcctTbl,2,0),"کد ناشناخته")) | I39: =IF($U39="","",IFERROR(VLOOKUP($U39,AcctTbl,3,0),"")) | N39: =IF(OR($E39="",$L39=""),"",IFERROR(($L39-IF($M39="",0,$M39)*IFERROR(VLOOKUP($K39,BasketTbl,4,0),IFERROR(INDEX(BasketTbl,MATCH($K39,BasketCodeCol,0),4),VLOOKUP("P01",ParamTbl,2,0))))*(1-IF(VLOOKUP($E39,OpTbl,3,0)="خرید",VLOOKUP("P02",ParamTbl,2,0),0)/100),"")) | P39: =IF(OR($E39="",$L39=""),"",IFERROR(IF(VLOOKUP($E39,OpTbl,6,0)="وزن",ROUND($N39*$O39,-3),IF(VLOOKUP($E39,OpTbl,6,0)="مبلغ",ROUND($L39*$O39,-3),0)),"")) | S39: =IF($E39="","",IF($AI39="⚠","⚠ ناتراز",IF(AND(IFERROR(VLOOKUP($E39,OpTbl,4,0),"")="بله",$L39=""),"⚠ وزن",IF(AND(IFERROR(VLOOKUP($E39,OpTbl,5,0),"")="بله",$U39=""),"⚠ حساب",IF(AND(IFERROR(VLOOKUP($E39,OpTbl,6,0),"")="مبلغ",$Q39=""),"⚠ مبلغ","✓"))))) | U39: =IF($E39="","",IFERROR(IF(VLOOKUP($E39,OpTbl,14,0)<>"",VLOOKUP($E39,OpTbl,14,0),$G39),"")) | V39: =IF(OR($AJ39="",$AJ39=0,$AL39<>"بدهکار"),"",$AJ39) | W39: =IF(OR($AJ39="",$AJ39=0,$AL39<>"بستانکار"),"",$AJ39) | X39: =IF($E39="","",IFERROR(VLOOKUP($E39,OpTbl,8,0),"")) | Y39: =IF(OR($X39="",$AJ39="",$AJ39=0,$AM39<>"بدهکار"),"",$AJ39) | Z39: =IF(OR($X39="",$AJ39="",$AJ39=0,$AM39<>"بستانکار"),"",$AJ39) | AA39: =IF(OR($E39="",$AN39="—",$AN39=""),"",IFERROR(VLOOKUP($E39,OpTbl,12,0),"")) | AB39: =IF(OR($AA39="",$Q39="",$Q39=0,$AN39<>"بدهکار"),"",$Q39) | AC39: =IF(OR($AA39="",$Q39="",$Q39=0,$AN39<>"بستانکار"),"",$Q39) | AD39: =IF($AA39="","",IFERROR(VLOOKUP($E39,OpTbl,13,0),"")) | AE39: =IF(OR($AD39="",$Q39="",$Q39=0,$AN39<>"بستانکار"),"",$Q39) | AF39: =IF(OR($AD39="",$Q39="",$Q39=0,$AN39<>"بدهکار"),"",$Q39) | AG39: =SUM($V39,$Y39,$AB39,$AE39) | AH39: =SUM($W39,$Z39,$AC39,$AF39) | AI39: =IF($E39="","",IF(ROUND($AG39-$AH39,0)=0,"✓","⚠")) | AJ39: =IF(OR($E39="",$U39=""),"",IFERROR(IF(VLOOKUP($E39,OpTbl,6,0)="وزن",IF($P39="",0,$P39),IF(VLOOKUP($E39,OpTbl,6,0)="مبلغ",IF(AND($Q39<>"",$Q39<>0),$Q39,$P39),0))+IF(VLOOKUP($E39,OpTbl,10,0)="افزودن",IF($Q39="",0,$Q39),0),0)) | AK39: =IF($E39="","",IFERROR(VLOOKUP($E39,OpTbl,10,0),"")) | AL39: =IF(OR($E39="",$U39=""),"",IFERROR(IF(VLOOKUP($E39,OpTbl,7,0)="خودکار",$R39,VLOOKUP($E39,OpTbl,7,0)),"")) | AM39: =IF(OR($E39="",$X39=""),"",IFERROR(IF(VLOOKUP($E39,OpTbl,9,0)="خودکار",IF($AL39="بدهکار","بستانکار",IF($AL39="بستانکار","بدهکار","")),VLOOKUP($E39,OpTbl,9,0)),"")) | AN39: =IF($E39="","",IFERROR(VLOOKUP($E39,OpTbl,11,0),"")) | AO39: =IF($B39="","",MID($B39,6,2)) | AP39: =IF($B39="",0,1)
... A309: =IF($B309="","",COUNTA($B$10:$B309)) | F309: =IF($E309="","",IFERROR(VLOOKUP($E309,OpTbl,2,0),"")) | H309: =IF($U309="","",IFERROR(VLOOKUP($U309,AcctTbl,2,0),"کد ناشناخته")) | I309: =IF($U309="","",IFERROR(VLOOKUP($U309,AcctTbl,3,0),"")) | N309: =IF(OR($E309="",$L309=""),"",IFERROR(($L309-IF($M309="",0,$M309)*IFERROR(VLOOKUP($K309,BasketTbl,4,0),IFERROR(INDEX(BasketTbl,MATCH($K309,BasketCodeCol,0),4),VLOOKUP("P01",ParamTbl,2,0))))*(1-IF(VLOOKUP($E309,OpTbl,3,0)="خرید",VLOOKUP("P02",ParamTbl,2,0),0)/100),"")) | P309: =IF(OR($E309="",$L309=""),"",IFERROR(IF(VLOOKUP($E309,OpTbl,6,0)="وزن",ROUND($N309*$O309,-3),IF(VLOOKUP($E309,OpTbl,6,0)="مبلغ",ROUND($L309*$O309,-3),0)),"")) | S309: =IF($E309="","",IF($AI309="⚠","⚠ ناتراز",IF(AND(IFERROR(VLOOKUP($E309,OpTbl,4,0),"")="بله",$L309=""),"⚠ وزن",IF(AND(IFERROR(VLOOKUP($E309,OpTbl,5,0),"")="بله",$U309=""),"⚠ حساب",IF(AND(IFERROR(VLOOKUP($E309,OpTbl,6,0),"")="مبلغ",$Q309=""),"⚠ مبلغ","✓"))))) | U309: =IF($E309="","",IFERROR(IF(VLOOKUP($E309,OpTbl,14,0)<>"",VLOOKUP($E309,OpTbl,14,0),$G309),"")) | V309: =IF(OR($AJ309="",$AJ309=0,$AL309<>"بدهکار"),"",$AJ309) | W309: =IF(OR($AJ309="",$AJ309=0,$AL309<>"بستانکار"),"",$AJ309) | X309: =IF($E309="","",IFERROR(VLOOKUP($E309,OpTbl,8,0),"")) | Y309: =IF(OR($X309="",$AJ309="",$AJ309=0,$AM309<>"بدهکار"),"",$AJ309) | Z309: =IF(OR($X309="",$AJ309="",$AJ309=0,$AM309<>"بستانکار"),"",$AJ309) | AA309: =IF(OR($E309="",$AN309="—",$AN309=""),"",IFERROR(VLOOKUP($E309,OpTbl,12,0),"")) | AB309: =IF(OR($AA309="",$Q309="",$Q309=0,$AN309<>"بدهکار"),"",$Q309) | AC309: =IF(OR($AA309="",$Q309="",$Q309=0,$AN309<>"بستانکار"),"",$Q309) | AD309: =IF($AA309="","",IFERROR(VLOOKUP($E309,OpTbl,13,0),"")) | AE309: =IF(OR($AD309="",$Q309="",$Q309=0,$AN309<>"بستانکار"),"",$Q309) | AF309: =IF(OR($AD309="",$Q309="",$Q309=0,$AN309<>"بدهکار"),"",$Q309) | AG309: =SUM($V309,$Y309,$AB309,$AE309) | AH309: =SUM($W309,$Z309,$AC309,$AF309) | AI309: =IF($E309="","",IF(ROUND($AG309-$AH309,0)=0,"✓","⚠")) | AJ309: =IF(OR($E309="",$U309=""),"",IFERROR(IF(VLOOKUP($E309,OpTbl,6,0)="وزن",IF($P309="",0,$P309),IF(VLOOKUP($E309,OpTbl,6,0)="مبلغ",IF(AND($Q309<>"",$Q309<>0),$Q309,$P309),0))+IF(VLOOKUP($E309,OpTbl,10,0)="افزودن",IF($Q309="",0,$Q309),0),0)) | AK309: =IF($E309="","",IFERROR(VLOOKUP($E309,OpTbl,10,0),"")) | AL309: =IF(OR($E309="",$U309=""),"",IFERROR(IF(VLOOKUP($E309,OpTbl,7,0)="خودکار",$R309,VLOOKUP($E309,OpTbl,7,0)),"")) | AM309: =IF(OR($E309="",$X309=""),"",IFERROR(IF(VLOOKUP($E309,OpTbl,9,0)="خودکار",IF($AL309="بدهکار","بستانکار",IF($AL309="بستانکار","بدهکار","")),VLOOKUP($E309,OpTbl,9,0)),"")) | AN309: =IF($E309="","",IFERROR(VLOOKUP($E309,OpTbl,11,0),"")) | AO309: =IF($B309="","",MID($B309,6,2)) | AP309: =IF($B309="",0,1)

Sheet Crate
A1: مازندشت — سورتینگ و بسته‌بندی مرکبات | I1: MAZANDASHT · CITRUS SORTING & PACKING
A2: ثبت سبد — خرید، فروش و مرجوعی
A3: هر ردیف یک حرکت سبد است · موجودی سبد در شیت خلاصه خودکار محاسبه می‌شود
A4: راهنما | B4: ورود دستی | C4: خودکار | D4: ورود | E4: خروج | F4: هشدار | G4: ستون‌های زرد = ورود شما | ستون‌های خاکستری = محاسبه خودکار | روی سرستون‌ها بایستید تا راهنما باز شود
A5: ردیف‌ها | D5: خرید سبد (عدد) | G5: فروش سبد (عدد) | J5: مبلغ خرید | M5: مبلغ فروش
A6: =COUNTA($B$10:$B$159) | D6: =SUMIF($D$10:$D$159,"خرید سبد",$I$10:$I$159) | G6: =SUMIF($D$10:$D$159,"فروش سبد",$I$10:$I$159) | J6: =SUMIF($D$10:$D$159,"خرید سبد",$K$10:$K$159) | M6: =SUMIF($D$10:$D$159,"فروش سبد",$K$10:$K$159)
A7: شناسه | D7: عملیات و طرف | I7: مقدار و مبلغ | L7: وضعیت
A8: ردیف | B8: تاریخ | C8: شماره سند | D8: نوع عملیات | E8: کد طرف حساب | F8: نام حساب | G8: گروه | H8: نوع سبد | I8: تعداد | J8: فی / قیمت واحد | K8: مبلغ | L8: وضعیت | M8: توضیحات
A9: No. | B9: Date | C9: Doc | D9: Operation | E9: Account | F9: Account Name | G9: Group | H9: Basket | I9: Qty | J9: Unit Price | K9: Amount | L9: Status | M9: Notes
A10: =IF($B10="","",COUNTA($B$10:$B10)) | B10: 1405/07/01 | C10: BK-001 | D10: خرید سبد | E10: S001 | F10: =IF($E10="","",IFERROR(VLOOKUP($E10,AcctTbl,2,0),"کد ناشناخته")) | G10: =IF($E10="","",IFERROR(VLOOKUP($E10,AcctTbl,3,0),"")) | H10: BK01 – ۶ک مشکی | I10: 500 | J10: 45000 | K10: =IF(OR($I10="",$J10=""),0,ROUND($I10*$J10,-3)) | L10: =IF($D10="","",IF($U10="⚠","⚠ ناتراز",IF($E10="","⚠ حساب","✓"))) | N10: =IF(OR($E10="",$K10=0),0,IF(IFERROR(VLOOKUP($D10,OpTbl,7,0),"")="بدهکار",$K10,0)) | O10: =IF(OR($E10="",$K10=0),0,IF(IFERROR(VLOOKUP($D10,OpTbl,7,0),"")="بستانکار",$K10,0)) | P10: =IF($D10="","",IFERROR(VLOOKUP($D10,OpTbl,8,0),"")) | Q10: =IF(OR($P10="",$K10=0),0,IF(IFERROR(VLOOKUP($D10,OpTbl,9,0),"")="بدهکار",$K10,0)) | R10: =IF(OR($P10="",$K10=0),0,IF(IFERROR(VLOOKUP($D10,OpTbl,9,0),"")="بستانکار",$K10,0)) | S10: =SUM($N10,$Q10) | T10: =SUM($O10,$R10) | U10: =IF($D10="","",IF(ROUND($S10-$T10,0)=0,"✓","⚠")) | V10: =IF($E10="","",$K10)
A11: =IF($B11="","",COUNTA($B$10:$B11)) | B11: 1405/07/02 | C11: BK-002 | D11: خرید سبد | E11: S002 | F11: =IF($E11="","",IFERROR(VLOOKUP($E11,AcctTbl,2,0),"کد ناشناخته")) | G11: =IF($E11="","",IFERROR(VLOOKUP($E11,AcctTbl,3,0),"")) | H11: BK03 – ۹ک مشکی | I11: 300 | J11: 62000 | K11: =IF(OR($I11="",$J11=""),0,ROUND($I11*$J11,-3)) | L11: =IF($D11="","",IF($U11="⚠","⚠ ناتراز",IF($E11="","⚠ حساب","✓"))) | N11: =IF(OR($E11="",$K11=0),0,IF(IFERROR(VLOOKUP($D11,OpTbl,7,0),"")="بدهکار",$K11,0)) | O11: =IF(OR($E11="",$K11=0),0,IF(IFERROR(VLOOKUP($D11,OpTbl,7,0),"")="بستانکار",$K11,0)) | P11: =IF($D11="","",IFERROR(VLOOKUP($D11,OpTbl,8,0),"")) | Q11: =IF(OR($P11="",$K11=0),0,IF(IFERROR(VLOOKUP($D11,OpTbl,9,0),"")="بدهکار",$K11,0)) | R11: =IF(OR($P11="",$K11=0),0,IF(IFERROR(VLOOKUP($D11,OpTbl,9,0),"")="بستانکار",$K11,0)) | S11: =SUM($N11,$Q11) | T11: =SUM($O11,$R11) | U11: =IF($D11="","",IF(ROUND($S11-$T11,0)=0,"✓","⚠")) | V11: =IF($E11="","",$K11)
A12: =IF($B12="","",COUNTA($B$10:$B12)) | B12: 1405/07/04 | C12: BK-003 | D12: فروش سبد | E12: C003 | F12: =IF($E12="","",IFERROR(VLOOKUP($E12,AcctTbl,2,0),"کد ناشناخته")) | G12: =IF($E12="","",IFERROR(VLOOKUP($E12,AcctTbl,3,0),"")) | H12: BK01 – ۶ک مشکی | I12: 150 | J12: 58000 | K12: =IF(OR($I12="",$J12=""),0,ROUND($I12*$J12,-3)) | L12: =IF($D12="","",IF($U12="⚠","⚠ ناتراز",IF($E12="","⚠ حساب","✓"))) | N12: =IF(OR($E12="",$K12=0),0,IF(IFERROR(VLOOKUP($D12,OpTbl,7,0),"")="بدهکار",$K12,0)) | O12: =IF(OR($E12="",$K12=0),0,IF(IFERROR(VLOOKUP($D12,OpTbl,7,0),"")="بستانکار",$K12,0)) | P12: =IF($D12="","",IFERROR(VLOOKUP($D12,OpTbl,8,0),"")) | Q12: =IF(OR($P12="",$K12=0),0,IF(IFERROR(VLOOKUP($D12,OpTbl,9,0),"")="بدهکار",$K12,0)) | R12: =IF(OR($P12="",$K12=0),0,IF(IFERROR(VLOOKUP($D12,OpTbl,9,0),"")="بستانکار",$K12,0)) | S12: =SUM($N12,$Q12) | T12: =SUM($O12,$R12) | U12: =IF($D12="","",IF(ROUND($S12-$T12,0)=0,"✓","⚠")) | V12: =IF($E12="","",$K12)
A13: =IF($B13="","",COUNTA($B$10:$B13)) | B13: 1405/07/06 | C13: BK-004 | D13: فروش سبد | E13: C006 | F13: =IF($E13="","",IFERROR(VLOOKUP($E13,AcctTbl,2,0),"کد ناشناخته")) | G13: =IF($E13="","",IFERROR(VLOOKUP($E13,AcctTbl,3,0),"")) | H13: BK03 – ۹ک مشکی | I13: 80 | J13: 80000 | K13: =IF(OR($I13="",$J13=""),0,ROUND($I13*$J13,-3)) | L13: =IF($D13="","",IF($U13="⚠","⚠ ناتراز",IF($E13="","⚠ حساب","✓"))) | N13: =IF(OR($E13="",$K13=0),0,IF(IFERROR(VLOOKUP($D13,OpTbl,7,0),"")="بدهکار",$K13,0)) | O13: =IF(OR($E13="",$K13=0),0,IF(IFERROR(VLOOKUP($D13,OpTbl,7,0),"")="بستانکار",$K13,0)) | P13: =IF($D13="","",IFERROR(VLOOKUP($D13,OpTbl,8,0),"")) | Q13: =IF(OR($P13="",$K13=0),0,IF(IFERROR(VLOOKUP($D13,OpTbl,9,0),"")="بدهکار",$K13,0)) | R13: =IF(OR($P13="",$K13=0),0,IF(IFERROR(VLOOKUP($D13,OpTbl,9,0),"")="بستانکار",$K13,0)) | S13: =SUM($N13,$Q13) | T13: =SUM($O13,$R13) | U13: =IF($D13="","",IF(ROUND($S13-$T13,0)=0,"✓","⚠")) | V13: =IF($E13="","",$K13)
A14: =IF($B14="","",COUNTA($B$10:$B14)) | B14: 1405/07/08 | C14: BK-005 | D14: خرید سبد | E14: S003 | F14: =IF($E14="","",IFERROR(VLOOKUP($E14,AcctTbl,2,0),"کد ناشناخته")) | G14: =IF($E14="","",IFERROR(VLOOKUP($E14,AcctTbl,3,0),"")) | H14: BK07 – ۸ک مشکی | I14: 200 | J14: 58000 | K14: =IF(OR($I14="",$J14=""),0,ROUND($I14*$J14,-3)) | L14: =IF($D14="","",IF($U14="⚠","⚠ ناتراز",IF($E14="","⚠ حساب","✓"))) | N14: =IF(OR($E14="",$K14=0),0,IF(IFERROR(VLOOKUP($D14,OpTbl,7,0),"")="بدهکار",$K14,0)) | O14: =IF(OR($E14="",$K14=0),0,IF(IFERROR(VLOOKUP($D14,OpTbl,7,0),"")="بستانکار",$K14,0)) | P14: =IF($D14="","",IFERROR(VLOOKUP($D14,OpTbl,8,0),"")) | Q14: =IF(OR($P14="",$K14=0),0,IF(IFERROR(VLOOKUP($D14,OpTbl,9,0),"")="بدهکار",$K14,0)) | R14: =IF(OR($P14="",$K14=0),0,IF(IFERROR(VLOOKUP($D14,OpTbl,9,0),"")="بستانکار",$K14,0)) | S14: =SUM($N14,$Q14) | T14: =SUM($O14,$R14) | U14: =IF($D14="","",IF(ROUND($S14-$T14,0)=0,"✓","⚠")) | V14: =IF($E14="","",$K14)
A15: =IF($B15="","",COUNTA($B$10:$B15)) | B15: 1405/07/10 | C15: BK-006 | D15: مرجوعی خرید سبد | E15: S001 | F15: =IF($E15="","",IFERROR(VLOOKUP($E15,AcctTbl,2,0),"کد ناشناخته")) | G15: =IF($E15="","",IFERROR(VLOOKUP($E15,AcctTbl,3,0),"")) | H15: BK01 – ۶ک مشکی | I15: 20 | J15: 45000 | K15: =IF(OR($I15="",$J15=""),0,ROUND($I15*$J15,-3)) | L15: =IF($D15="","",IF($U15="⚠","⚠ ناتراز",IF($E15="","⚠ حساب","✓"))) | M15: سبد سالم | N15: =IF(OR($E15="",$K15=0),0,IF(IFERROR(VLOOKUP($D15,OpTbl,7,0),"")="بدهکار",$K15,0)) | O15: =IF(OR($E15="",$K15=0),0,IF(IFERROR(VLOOKUP($D15,OpTbl,7,0),"")="بستانکار",$K15,0)) | P15: =IF($D15="","",IFERROR(VLOOKUP($D15,OpTbl,8,0),"")) | Q15: =IF(OR($P15="",$K15=0),0,IF(IFERROR(VLOOKUP($D15,OpTbl,9,0),"")="بدهکار",$K15,0)) | R15: =IF(OR($P15="",$K15=0),0,IF(IFERROR(VLOOKUP($D15,OpTbl,9,0),"")="بستانکار",$K15,0)) | S15: =SUM($N15,$Q15) | T15: =SUM($O15,$R15) | U15: =IF($D15="","",IF(ROUND($S15-$T15,0)=0,"✓","⚠")) | V15: =IF($E15="","",$K15)
A16: =IF($B16="","",COUNTA($B$10:$B16)) | B16: 1405/07/12 | C16: BK-007 | D16: فروش سبد | E16: C001 | F16: =IF($E16="","",IFERROR(VLOOKUP($E16,AcctTbl,2,0),"کد ناشناخته")) | G16: =IF($E16="","",IFERROR(VLOOKUP($E16,AcctTbl,3,0),"")) | H16: BK03 – ۹ک مشکی | I16: 60 | J16: 82000 | K16: =IF(OR($I16="",$J16=""),0,ROUND($I16*$J16,-3)) | L16: =IF($D16="","",IF($U16="⚠","⚠ ناتراز",IF($E16="","⚠ حساب","✓"))) | N16: =IF(OR($E16="",$K16=0),0,IF(IFERROR(VLOOKUP($D16,OpTbl,7,0),"")="بدهکار",$K16,0)) | O16: =IF(OR($E16="",$K16=0),0,IF(IFERROR(VLOOKUP($D16,OpTbl,7,0),"")="بستانکار",$K16,0)) | P16: =IF($D16="","",IFERROR(VLOOKUP($D16,OpTbl,8,0),"")) | Q16: =IF(OR($P16="",$K16=0),0,IF(IFERROR(VLOOKUP($D16,OpTbl,9,0),"")="بدهکار",$K16,0)) | R16: =IF(OR($P16="",$K16=0),0,IF(IFERROR(VLOOKUP($D16,OpTbl,9,0),"")="بستانکار",$K16,0)) | S16: =SUM($N16,$Q16) | T16: =SUM($O16,$R16) | U16: =IF($D16="","",IF(ROUND($S16-$T16,0)=0,"✓","⚠")) | V16: =IF($E16="","",$K16)
A17: =IF($B17="","",COUNTA($B$10:$B17)) | F17: =IF($E17="","",IFERROR(VLOOKUP($E17,AcctTbl,2,0),"کد ناشناخته")) | G17: =IF($E17="","",IFERROR(VLOOKUP($E17,AcctTbl,3,0),"")) | K17: =IF(OR($I17="",$J17=""),0,ROUND($I17*$J17,-3)) | L17: =IF($D17="","",IF($U17="⚠","⚠ ناتراز",IF($E17="","⚠ حساب","✓"))) | N17: =IF(OR($E17="",$K17=0),0,IF(IFERROR(VLOOKUP($D17,OpTbl,7,0),"")="بدهکار",$K17,0)) | O17: =IF(OR($E17="",$K17=0),0,IF(IFERROR(VLOOKUP($D17,OpTbl,7,0),"")="بستانکار",$K17,0)) | P17: =IF($D17="","",IFERROR(VLOOKUP($D17,OpTbl,8,0),"")) | Q17: =IF(OR($P17="",$K17=0),0,IF(IFERROR(VLOOKUP($D17,OpTbl,9,0),"")="بدهکار",$K17,0)) | R17: =IF(OR($P17="",$K17=0),0,IF(IFERROR(VLOOKUP($D17,OpTbl,9,0),"")="بستانکار",$K17,0)) | S17: =SUM($N17,$Q17) | T17: =SUM($O17,$R17) | U17: =IF($D17="","",IF(ROUND($S17-$T17,0)=0,"✓","⚠")) | V17: =IF($E17="","",$K17)
A18: =IF($B18="","",COUNTA($B$10:$B18)) | F18: =IF($E18="","",IFERROR(VLOOKUP($E18,AcctTbl,2,0),"کد ناشناخته")) | G18: =IF($E18="","",IFERROR(VLOOKUP($E18,AcctTbl,3,0),"")) | K18: =IF(OR($I18="",$J18=""),0,ROUND($I18*$J18,-3)) | L18: =IF($D18="","",IF($U18="⚠","⚠ ناتراز",IF($E18="","⚠ حساب","✓"))) | N18: =IF(OR($E18="",$K18=0),0,IF(IFERROR(VLOOKUP($D18,OpTbl,7,0),"")="بدهکار",$K18,0)) | O18: =IF(OR($E18="",$K18=0),0,IF(IFERROR(VLOOKUP($D18,OpTbl,7,0),"")="بستانکار",$K18,0)) | P18: =IF($D18="","",IFERROR(VLOOKUP($D18,OpTbl,8,0),"")) | Q18: =IF(OR($P18="",$K18=0),0,IF(IFERROR(VLOOKUP($D18,OpTbl,9,0),"")="بدهکار",$K18,0)) | R18: =IF(OR($P18="",$K18=0),0,IF(IFERROR(VLOOKUP($D18,OpTbl,9,0),"")="بستانکار",$K18,0)) | S18: =SUM($N18,$Q18) | T18: =SUM($O18,$R18) | U18: =IF($D18="","",IF(ROUND($S18-$T18,0)=0,"✓","⚠")) | V18: =IF($E18="","",$K18)
A19: =IF($B19="","",COUNTA($B$10:$B19)) | F19: =IF($E19="","",IFERROR(VLOOKUP($E19,AcctTbl,2,0),"کد ناشناخته")) | G19: =IF($E19="","",IFERROR(VLOOKUP($E19,AcctTbl,3,0),"")) | K19: =IF(OR($I19="",$J19=""),0,ROUND($I19*$J19,-3)) | L19: =IF($D19="","",IF($U19="⚠","⚠ ناتراز",IF($E19="","⚠ حساب","✓"))) | N19: =IF(OR($E19="",$K19=0),0,IF(IFERROR(VLOOKUP($D19,OpTbl,7,0),"")="بدهکار",$K19,0)) | O19: =IF(OR($E19="",$K19=0),0,IF(IFERROR(VLOOKUP($D19,OpTbl,7,0),"")="بستانکار",$K19,0)) | P19: =IF($D19="","",IFERROR(VLOOKUP($D19,OpTbl,8,0),"")) | Q19: =IF(OR($P19="",$K19=0),0,IF(IFERROR(VLOOKUP($D19,OpTbl,9,0),"")="بدهکار",$K19,0)) | R19: =IF(OR($P19="",$K19=0),0,IF(IFERROR(VLOOKUP($D19,OpTbl,9,0),"")="بستانکار",$K19,0)) | S19: =SUM($N19,$Q19) | T19: =SUM($O19,$R19) | U19: =IF($D19="","",IF(ROUND($S19-$T19,0)=0,"✓","⚠")) | V19: =IF($E19="","",$K19)
A20: =IF($B20="","",COUNTA($B$10:$B20)) | F20: =IF($E20="","",IFERROR(VLOOKUP($E20,AcctTbl,2,0),"کد ناشناخته")) | G20: =IF($E20="","",IFERROR(VLOOKUP($E20,AcctTbl,3,0),"")) | K20: =IF(OR($I20="",$J20=""),0,ROUND($I20*$J20,-3)) | L20: =IF($D20="","",IF($U20="⚠","⚠ ناتراز",IF($E20="","⚠ حساب","✓"))) | N20: =IF(OR($E20="",$K20=0),0,IF(IFERROR(VLOOKUP($D20,OpTbl,7,0),"")="بدهکار",$K20,0)) | O20: =IF(OR($E20="",$K20=0),0,IF(IFERROR(VLOOKUP($D20,OpTbl,7,0),"")="بستانکار",$K20,0)) | P20: =IF($D20="","",IFERROR(VLOOKUP($D20,OpTbl,8,0),"")) | Q20: =IF(OR($P20="",$K20=0),0,IF(IFERROR(VLOOKUP($D20,OpTbl,9,0),"")="بدهکار",$K20,0)) | R20: =IF(OR($P20="",$K20=0),0,IF(IFERROR(VLOOKUP($D20,OpTbl,9,0),"")="بستانکار",$K20,0)) | S20: =SUM($N20,$Q20) | T20: =SUM($O20,$R20) | U20: =IF($D20="","",IF(ROUND($S20-$T20,0)=0,"✓","⚠")) | V20: =IF($E20="","",$K20)
A21: =IF($B21="","",COUNTA($B$10:$B21)) | F21: =IF($E21="","",IFERROR(VLOOKUP($E21,AcctTbl,2,0),"کد ناشناخته")) | G21: =IF($E21="","",IFERROR(VLOOKUP($E21,AcctTbl,3,0),"")) | K21: =IF(OR($I21="",$J21=""),0,ROUND($I21*$J21,-3)) | L21: =IF($D21="","",IF($U21="⚠","⚠ ناتراز",IF($E21="","⚠ حساب","✓"))) | N21: =IF(OR($E21="",$K21=0),0,IF(IFERROR(VLOOKUP($D21,OpTbl,7,0),"")="بدهکار",$K21,0)) | O21: =IF(OR($E21="",$K21=0),0,IF(IFERROR(VLOOKUP($D21,OpTbl,7,0),"")="بستانکار",$K21,0)) | P21: =IF($D21="","",IFERROR(VLOOKUP($D21,OpTbl,8,0),"")) | Q21: =IF(OR($P21="",$K21=0),0,IF(IFERROR(VLOOKUP($D21,OpTbl,9,0),"")="بدهکار",$K21,0)) | R21: =IF(OR($P21="",$K21=0),0,IF(IFERROR(VLOOKUP($D21,OpTbl,9,0),"")="بستانکار",$K21,0)) | S21: =SUM($N21,$Q21) | T21: =SUM($O21,$R21) | U21: =IF($D21="","",IF(ROUND($S21-$T21,0)=0,"✓","⚠")) | V21: =IF($E21="","",$K21)
A22: =IF($B22="","",COUNTA($B$10:$B22)) | F22: =IF($E22="","",IFERROR(VLOOKUP($E22,AcctTbl,2,0),"کد ناشناخته")) | G22: =IF($E22="","",IFERROR(VLOOKUP($E22,AcctTbl,3,0),"")) | K22: =IF(OR($I22="",$J22=""),0,ROUND($I22*$J22,-3)) | L22: =IF($D22="","",IF($U22="⚠","⚠ ناتراز",IF($E22="","⚠ حساب","✓"))) | N22: =IF(OR($E22="",$K22=0),0,IF(IFERROR(VLOOKUP($D22,OpTbl,7,0),"")="بدهکار",$K22,0)) | O22: =IF(OR($E22="",$K22=0),0,IF(IFERROR(VLOOKUP($D22,OpTbl,7,0),"")="بستانکار",$K22,0)) | P22: =IF($D22="","",IFERROR(VLOOKUP($D22,OpTbl,8,0),"")) | Q22: =IF(OR($P22="",$K22=0),0,IF(IFERROR(VLOOKUP($D22,OpTbl,9,0),"")="بدهکار",$K22,0)) | R22: =IF(OR($P22="",$K22=0),0,IF(IFERROR(VLOOKUP($D22,OpTbl,9,0),"")="بستانکار",$K22,0)) | S22: =SUM($N22,$Q22) | T22: =SUM($O22,$R22) | U22: =IF($D22="","",IF(ROUND($S22-$T22,0)=0,"✓","⚠")) | V22: =IF($E22="","",$K22)
A23: =IF($B23="","",COUNTA($B$10:$B23)) | F23: =IF($E23="","",IFERROR(VLOOKUP($E23,AcctTbl,2,0),"کد ناشناخته")) | G23: =IF($E23="","",IFERROR(VLOOKUP($E23,AcctTbl,3,0),"")) | K23: =IF(OR($I23="",$J23=""),0,ROUND($I23*$J23,-3)) | L23: =IF($D23="","",IF($U23="⚠","⚠ ناتراز",IF($E23="","⚠ حساب","✓"))) | N23: =IF(OR($E23="",$K23=0),0,IF(IFERROR(VLOOKUP($D23,OpTbl,7,0),"")="بدهکار",$K23,0)) | O23: =IF(OR($E23="",$K23=0),0,IF(IFERROR(VLOOKUP($D23,OpTbl,7,0),"")="بستانکار",$K23,0)) | P23: =IF($D23="","",IFERROR(VLOOKUP($D23,OpTbl,8,0),"")) | Q23: =IF(OR($P23="",$K23=0),0,IF(IFERROR(VLOOKUP($D23,OpTbl,9,0),"")="بدهکار",$K23,0)) | R23: =IF(OR($P23="",$K23=0),0,IF(IFERROR(VLOOKUP($D23,OpTbl,9,0),"")="بستانکار",$K23,0)) | S23: =SUM($N23,$Q23) | T23: =SUM($O23,$R23) | U23: =IF($D23="","",IF(ROUND($S23-$T23,0)=0,"✓","⚠")) | V23: =IF($E23="","",$K23)
A24: =IF($B24="","",COUNTA($B$10:$B24)) | F24: =IF($E24="","",IFERROR(VLOOKUP($E24,AcctTbl,2,0),"کد ناشناخته")) | G24: =IF($E24="","",IFERROR(VLOOKUP($E24,AcctTbl,3,0),"")) | K24: =IF(OR($I24="",$J24=""),0,ROUND($I24*$J24,-3)) | L24: =IF($D24="","",IF($U24="⚠","⚠ ناتراز",IF($E24="","⚠ حساب","✓"))) | N24: =IF(OR($E24="",$K24=0),0,IF(IFERROR(VLOOKUP($D24,OpTbl,7,0),"")="بدهکار",$K24,0)) | O24: =IF(OR($E24="",$K24=0),0,IF(IFERROR(VLOOKUP($D24,OpTbl,7,0),"")="بستانکار",$K24,0)) | P24: =IF($D24="","",IFERROR(VLOOKUP($D24,OpTbl,8,0),"")) | Q24: =IF(OR($P24="",$K24=0),0,IF(IFERROR(VLOOKUP($D24,OpTbl,9,0),"")="بدهکار",$K24,0)) | R24: =IF(OR($P24="",$K24=0),0,IF(IFERROR(VLOOKUP($D24,OpTbl,9,0),"")="بستانکار",$K24,0)) | S24: =SUM($N24,$Q24) | T24: =SUM($O24,$R24) | U24: =IF($D24="","",IF(ROUND($S24-$T24,0)=0,"✓","⚠")) | V24: =IF($E24="","",$K24)
A25: =IF($B25="","",COUNTA($B$10:$B25)) | F25: =IF($E25="","",IFERROR(VLOOKUP($E25,AcctTbl,2,0),"کد ناشناخته")) | G25: =IF($E25="","",IFERROR(VLOOKUP($E25,AcctTbl,3,0),"")) | K25: =IF(OR($I25="",$J25=""),0,ROUND($I25*$J25,-3)) | L25: =IF($D25="","",IF($U25="⚠","⚠ ناتراز",IF($E25="","⚠ حساب","✓"))) | N25: =IF(OR($E25="",$K25=0),0,IF(IFERROR(VLOOKUP($D25,OpTbl,7,0),"")="بدهکار",$K25,0)) | O25: =IF(OR($E25="",$K25=0),0,IF(IFERROR(VLOOKUP($D25,OpTbl,7,0),"")="بستانکار",$K25,0)) | P25: =IF($D25="","",IFERROR(VLOOKUP($D25,OpTbl,8,0),"")) | Q25: =IF(OR($P25="",$K25=0),0,IF(IFERROR(VLOOKUP($D25,OpTbl,9,0),"")="بدهکار",$K25,0)) | R25: =IF(OR($P25="",$K25=0),0,IF(IFERROR(VLOOKUP($D25,OpTbl,9,0),"")="بستانکار",$K25,0)) | S25: =SUM($N25,$Q25) | T25: =SUM($O25,$R25) | U25: =IF($D25="","",IF(ROUND($S25-$T25,0)=0,"✓","⚠")) | V25: =IF($E25="","",$K25)
A26: =IF($B26="","",COUNTA($B$10:$B26)) | F26: =IF($E26="","",IFERROR(VLOOKUP($E26,AcctTbl,2,0),"کد ناشناخته")) | G26: =IF($E26="","",IFERROR(VLOOKUP($E26,AcctTbl,3,0),"")) | K26: =IF(OR($I26="",$J26=""),0,ROUND($I26*$J26,-3)) | L26: =IF($D26="","",IF($U26="⚠","⚠ ناتراز",IF($E26="","⚠ حساب","✓"))) | N26: =IF(OR($E26="",$K26=0),0,IF(IFERROR(VLOOKUP($D26,OpTbl,7,0),"")="بدهکار",$K26,0)) | O26: =IF(OR($E26="",$K26=0),0,IF(IFERROR(VLOOKUP($D26,OpTbl,7,0),"")="بستانکار",$K26,0)) | P26: =IF($D26="","",IFERROR(VLOOKUP($D26,OpTbl,8,0),"")) | Q26: =IF(OR($P26="",$K26=0),0,IF(IFERROR(VLOOKUP($D26,OpTbl,9,0),"")="بدهکار",$K26,0)) | R26: =IF(OR($P26="",$K26=0),0,IF(IFERROR(VLOOKUP($D26,OpTbl,9,0),"")="بستانکار",$K26,0)) | S26: =SUM($N26,$Q26) | T26: =SUM($O26,$R26) | U26: =IF($D26="","",IF(ROUND($S26-$T26,0)=0,"✓","⚠")) | V26: =IF($E26="","",$K26)
A27: =IF($B27="","",COUNTA($B$10:$B27)) | F27: =IF($E27="","",IFERROR(VLOOKUP($E27,AcctTbl,2,0),"کد ناشناخته")) | G27: =IF($E27="","",IFERROR(VLOOKUP($E27,AcctTbl,3,0),"")) | K27: =IF(OR($I27="",$J27=""),0,ROUND($I27*$J27,-3)) | L27: =IF($D27="","",IF($U27="⚠","⚠ ناتراز",IF($E27="","⚠ حساب","✓"))) | N27: =IF(OR($E27="",$K27=0),0,IF(IFERROR(VLOOKUP($D27,OpTbl,7,0),"")="بدهکار",$K27,0)) | O27: =IF(OR($E27="",$K27=0),0,IF(IFERROR(VLOOKUP($D27,OpTbl,7,0),"")="بستانکار",$K27,0)) | P27: =IF($D27="","",IFERROR(VLOOKUP($D27,OpTbl,8,0),"")) | Q27: =IF(OR($P27="",$K27=0),0,IF(IFERROR(VLOOKUP($D27,OpTbl,9,0),"")="بدهکار",$K27,0)) | R27: =IF(OR($P27="",$K27=0),0,IF(IFERROR(VLOOKUP($D27,OpTbl,9,0),"")="بستانکار",$K27,0)) | S27: =SUM($N27,$Q27) | T27: =SUM($O27,$R27) | U27: =IF($D27="","",IF(ROUND($S27-$T27,0)=0,"✓","⚠")) | V27: =IF($E27="","",$K27)
A28: =IF($B28="","",COUNTA($B$10:$B28)) | F28: =IF($E28="","",IFERROR(VLOOKUP($E28,AcctTbl,2,0),"کد ناشناخته")) | G28: =IF($E28="","",IFERROR(VLOOKUP($E28,AcctTbl,3,0),"")) | K28: =IF(OR($I28="",$J28=""),0,ROUND($I28*$J28,-3)) | L28: =IF($D28="","",IF($U28="⚠","⚠ ناتراز",IF($E28="","⚠ حساب","✓"))) | N28: =IF(OR($E28="",$K28=0),0,IF(IFERROR(VLOOKUP($D28,OpTbl,7,0),"")="بدهکار",$K28,0)) | O28: =IF(OR($E28="",$K28=0),0,IF(IFERROR(VLOOKUP($D28,OpTbl,7,0),"")="بستانکار",$K28,0)) | P28: =IF($D28="","",IFERROR(VLOOKUP($D28,OpTbl,8,0),"")) | Q28: =IF(OR($P28="",$K28=0),0,IF(IFERROR(VLOOKUP($D28,OpTbl,9,0),"")="بدهکار",$K28,0)) | R28: =IF(OR($P28="",$K28=0),0,IF(IFERROR(VLOOKUP($D28,OpTbl,9,0),"")="بستانکار",$K28,0)) | S28: =SUM($N28,$Q28) | T28: =SUM($O28,$R28) | U28: =IF($D28="","",IF(ROUND($S28-$T28,0)=0,"✓","⚠")) | V28: =IF($E28="","",$K28)
... A159: =IF($B159="","",COUNTA($B$10:$B159)) | F159: =IF($E159="","",IFERROR(VLOOKUP($E159,AcctTbl,2,0),"کد ناشناخته")) | G159: =IF($E159="","",IFERROR(VLOOKUP($E159,AcctTbl,3,0),"")) | K159: =IF(OR($I159="",$J159=""),0,ROUND($I159*$J159,-3)) | L159: =IF($D159="","",IF($U159="⚠","⚠ ناتراز",IF($E159="","⚠ حساب","✓"))) | N159: =IF(OR($E159="",$K159=0),0,IF(IFERROR(VLOOKUP($D159,OpTbl,7,0),"")="بدهکار",$K159,0)) | O159: =IF(OR($E159="",$K159=0),0,IF(IFERROR(VLOOKUP($D159,OpTbl,7,0),"")="بستانکار",$K159,0)) | P159: =IF($D159="","",IFERROR(VLOOKUP($D159,OpTbl,8,0),"")) | Q159: =IF(OR($P159="",$K159=0),0,IF(IFERROR(VLOOKUP($D159,OpTbl,9,0),"")="بدهکار",$K159,0)) | R159: =IF(OR($P159="",$K159=0),0,IF(IFERROR(VLOOKUP($D159,OpTbl,9,0),"")="بستانکار",$K159,0)) | S159: =SUM($N159,$Q159) | T159: =SUM($O159,$R159) | U159: =IF($D159="","",IF(ROUND($S159-$T159,0)=0,"✓","⚠")) | V159: =IF($E159="","",$K159)

Sheet Pay
A1: مازندشت — سورتینگ و بسته‌بندی مرکبات | N1: MAZANDASHT · CITRUS SORTING & PACKING
A2: پرداخت و دریافت — نقد، بانک، چک و انتقال داخلی
A3: هر ردیف یک تسویه · چک با شماره چک ردیابی می‌شود · انتقال داخلی بین بانک‌های شرکت
A4: راهنما | B4: ورود دستی | C4: خودکار | D4: ورود | E4: خروج | F4: هشدار | G4: ستون‌های زرد = ورود شما | ستون‌های خاکستری = محاسبه خودکار | روی سرستون‌ها بایستید تا راهنما باز شود
A5: تعداد تسویه | E5: جمع پرداخت | I5: جمع دریافت | M5: چک در جریان | Q5: ردیف‌های ناتراز
A6: =COUNTA($B$10:$B$159) | E6: =SUMIF($D$10:$D$159,"پرداخت",$K$10:$K$159) | I6: =SUMIF($D$10:$D$159,"دریافت",$K$10:$K$159) | M6: =COUNTIFS($E$10:$E$159,"چک",$L$10:$L$159,"در جریان") | Q6: =COUNTIF($AA$10:$AA$159,"⚠")
A7: شناسه | D7: نوع و روش | G7: طرف حساب | J7: چک و مبلغ | P7: توضیح و وضعیت
A8: ردیف | B8: تاریخ | C8: شماره سند | D8: نوع | E8: روش | F8: کد حساب | G8: نام حساب | H8: گروه | I8: بانک / مقصد | J8: شماره چک | K8: مبلغ | L8: وضعیت چک | M8: سررسید | N8: بانک مبدأ | O8: سند مرتبط | P8: توضیحات | Q8: منبع | R8: وضعیت
A9: No. | B9: Date | C9: Doc | D9: Type | E9: Method | F9: Account | G9: Account Name | H9: Group | I9: Bank | J9: Cheque No. | K9: Amount | L9: Cheque Status | M9: Due | N9: From Bank | O9: Related | P9: Notes | Q9: Source | R9: Status
A10: =IF($B10="","",COUNTA($B$10:$B10)) | B10: 1405/07/06 | C10: PV-001 | D10: پرداخت | E10: نقد | F10: C001 | G10: =IF($F10="","",IFERROR(VLOOKUP($F10,AcctTbl,2,0),"کد ناشناخته")) | H10: =IF($F10="","",IFERROR(VLOOKUP($F10,AcctTbl,3,0),"")) | K10: 150000000 | P10: علی‌الحساب خرید | R10: =IF($D10="","",IF($AA10="⚠","⚠ ناتراز",IF(AND($D10="پرداخت",$E10="چک",$L10=""),"⚠ وضعیت چک","✓"))) | S10: =IF(OR($D10="",$K10=""),"",IF(AND($D10="پرداخت",$E10<>"انتقال داخلی",$E10<>"پاس چک",$E10<>"برگشت چک"),$K10,0)) | T10: =IF(OR($D10="",$K10=""),"",IF(OR(AND($D10="دریافت",$E10<>"انتقال داخلی"),$E10="برگشت چک"),$K10,0)) | U10: =IF(OR($D10="",$K10=""),"",IF(OR(AND($D10="دریافت",$E10<>"چک"),$E10="انتقال داخلی"),$K10,0)) | V10: =IF(OR($D10="",$K10=""),"",IF(OR(AND($D10="پرداخت",$E10<>"چک",$E10<>"برگشت چک"),$E10="انتقال داخلی"),$K10,0)) | W10: =IF(OR($D10="",$K10=""),"",IF(OR($E10="پاس چک",$E10="برگشت چک",AND($D10="دریافت",$E10="چک")),$K10,0)) | X10: =IF(OR($D10="",$K10=""),"",IF(AND($D10="پرداخت",$E10="چک"),$K10,0)) | Y10: =SUM($S10,$U10,$W10) | Z10: =SUM($T10,$V10,$X10) | AA10: =IF($D10="","",IF(ROUND($Y10-$Z10,0)=0,"✓","⚠")) | AB10: =IF($D10="","",IF($E10="نقد","X003",IF(OR($E10="چک",$E10="پاس چک",$E10="برگشت چک"),"X010",IF($I10="","X003","X011")))) | AC10: =IF($D10="","",IF($E10="انتقال داخلی",IF($N10="","X003",IFERROR(VLOOKUP($N10,BankTbl,4,0),$N10)),IF($I10="","X003",IFERROR(VLOOKUP($I10,BankTbl,4,0),$I10)))) | AD10: =IF($D10="","",IF($E10="پاس چک","X010",IF($E10="برگشت چک",IF($I10="","X003","X011"),IF($E10="انتقال داخلی",IF($I10="","X003","X011"),IF($D10="پرداخت",$F10,IF($E10="چک","X009",IF($I10="","X003","X011"))))))) | AE10: =IF($D10="","",IF($K10="",0,$K10)) | AF10: =IF($D10="","",IF($E10="پاس چک",IF($I10="","X003","X011"),IF($E10="برگشت چک","X010",IF($E10="انتقال داخلی",IF($N10="","X003","X011"),IF($D10="پرداخت",IF($E10="چک","X010",IF($I10="","X003","X011")),$F10))))) | AG10: =IF($D10="","",IF($K10="",0,$K10))
A11: =IF($B11="","",COUNTA($B$10:$B11)) | B11: 1405/07/06 | C11: RV-001 | D11: دریافت | E11: انتقال بانکی | F11: SL001 | G11: =IF($F11="","",IFERROR(VLOOKUP($F11,AcctTbl,2,0),"کد ناشناخته")) | H11: =IF($F11="","",IFERROR(VLOOKUP($F11,AcctTbl,3,0),"")) | I11: BN01 | K11: 300000000 | P11: تسویه بار | R11: =IF($D11="","",IF($AA11="⚠","⚠ ناتراز",IF(AND($D11="پرداخت",$E11="چک",$L11=""),"⚠ وضعیت چک","✓"))) | S11: =IF(OR($D11="",$K11=""),"",IF(AND($D11="پرداخت",$E11<>"انتقال داخلی",$E11<>"پاس چک",$E11<>"برگشت چک"),$K11,0)) | T11: =IF(OR($D11="",$K11=""),"",IF(OR(AND($D11="دریافت",$E11<>"انتقال داخلی"),$E11="برگشت چک"),$K11,0)) | U11: =IF(OR($D11="",$K11=""),"",IF(OR(AND($D11="دریافت",$E11<>"چک"),$E11="انتقال داخلی"),$K11,0)) | V11: =IF(OR($D11="",$K11=""),"",IF(OR(AND($D11="پرداخت",$E11<>"چک",$E11<>"برگشت چک"),$E11="انتقال داخلی"),$K11,0)) | W11: =IF(OR($D11="",$K11=""),"",IF(OR($E11="پاس چک",$E11="برگشت چک",AND($D11="دریافت",$E11="چک")),$K11,0)) | X11: =IF(OR($D11="",$K11=""),"",IF(AND($D11="پرداخت",$E11="چک"),$K11,0)) | Y11: =SUM($S11,$U11,$W11) | Z11: =SUM($T11,$V11,$X11) | AA11: =IF($D11="","",IF(ROUND($Y11-$Z11,0)=0,"✓","⚠")) | AB11: =IF($D11="","",IF($E11="نقد","X003",IF(OR($E11="چک",$E11="پاس چک",$E11="برگشت چک"),"X010",IF($I11="","X003","X011")))) | AC11: =IF($D11="","",IF($E11="انتقال داخلی",IF($N11="","X003",IFERROR(VLOOKUP($N11,BankTbl,4,0),$N11)),IF($I11="","X003",IFERROR(VLOOKUP($I11,BankTbl,4,0),$I11)))) | AD11: =IF($D11="","",IF($E11="پاس چک","X010",IF($E11="برگشت چک",IF($I11="","X003","X011"),IF($E11="انتقال داخلی",IF($I11="","X003","X011"),IF($D11="پرداخت",$F11,IF($E11="چک","X009",IF($I11="","X003","X011"))))))) | AE11: =IF($D11="","",IF($K11="",0,$K11)) | AF11: =IF($D11="","",IF($E11="پاس چک",IF($I11="","X003","X011"),IF($E11="برگشت چک","X010",IF($E11="انتقال داخلی",IF($N11="","X003","X011"),IF($D11="پرداخت",IF($E11="چک","X010",IF($I11="","X003","X011")),$F11))))) | AG11: =IF($D11="","",IF($K11="",0,$K11))
A12: =IF($B12="","",COUNTA($B$10:$B12)) | B12: 1405/07/07 | C12: PV-002 | D12: پرداخت | E12: چک | F12: C002 | G12: =IF($F12="","",IFERROR(VLOOKUP($F12,AcctTbl,2,0),"کد ناشناخته")) | H12: =IF($F12="","",IFERROR(VLOOKUP($F12,AcctTbl,3,0),"")) | I12: BN01 | J12: CHQ-1001 | K12: 200000000 | L12: در جریان | P12: چک ۳۰ روزه | R12: =IF($D12="","",IF($AA12="⚠","⚠ ناتراز",IF(AND($D12="پرداخت",$E12="چک",$L12=""),"⚠ وضعیت چک","✓"))) | S12: =IF(OR($D12="",$K12=""),"",IF(AND($D12="پرداخت",$E12<>"انتقال داخلی",$E12<>"پاس چک",$E12<>"برگشت چک"),$K12,0)) | T12: =IF(OR($D12="",$K12=""),"",IF(OR(AND($D12="دریافت",$E12<>"انتقال داخلی"),$E12="برگشت چک"),$K12,0)) | U12: =IF(OR($D12="",$K12=""),"",IF(OR(AND($D12="دریافت",$E12<>"چک"),$E12="انتقال داخلی"),$K12,0)) | V12: =IF(OR($D12="",$K12=""),"",IF(OR(AND($D12="پرداخت",$E12<>"چک",$E12<>"برگشت چک"),$E12="انتقال داخلی"),$K12,0)) | W12: =IF(OR($D12="",$K12=""),"",IF(OR($E12="پاس چک",$E12="برگشت چک",AND($D12="دریافت",$E12="چک")),$K12,0)) | X12: =IF(OR($D12="",$K12=""),"",IF(AND($D12="پرداخت",$E12="چک"),$K12,0)) | Y12: =SUM($S12,$U12,$W12) | Z12: =SUM($T12,$V12,$X12) | AA12: =IF($D12="","",IF(ROUND($Y12-$Z12,0)=0,"✓","⚠")) | AB12: =IF($D12="","",IF($E12="نقد","X003",IF(OR($E12="چک",$E12="پاس چک",$E12="برگشت چک"),"X010",IF($I12="","X003","X011")))) | AC12: =IF($D12="","",IF($E12="انتقال داخلی",IF($N12="","X003",IFERROR(VLOOKUP($N12,BankTbl,4,0),$N12)),IF($I12="","X003",IFERROR(VLOOKUP($I12,BankTbl,4,0),$I12)))) | AD12: =IF($D12="","",IF($E12="پاس چک","X010",IF($E12="برگشت چک",IF($I12="","X003","X011"),IF($E12="انتقال داخلی",IF($I12="","X003","X011"),IF($D12="پرداخت",$F12,IF($E12="چک","X009",IF($I12="","X003","X011"))))))) | AE12: =IF($D12="","",IF($K12="",0,$K12)) | AF12: =IF($D12="","",IF($E12="پاس چک",IF($I12="","X003","X011"),IF($E12="برگشت چک","X010",IF($E12="انتقال داخلی",IF($N12="","X003","X011"),IF($D12="پرداخت",IF($E12="چک","X010",IF($I12="","X003","X011")),$F12))))) | AG12: =IF($D12="","",IF($K12="",0,$K12))
A13: =IF($B13="","",COUNTA($B$10:$B13)) | B13: 1405/07/08 | C13: PV-003 | D13: پرداخت | E13: انتقال بانکی | F13: C003 | G13: =IF($F13="","",IFERROR(VLOOKUP($F13,AcctTbl,2,0),"کد ناشناخته")) | H13: =IF($F13="","",IFERROR(VLOOKUP($F13,AcctTbl,3,0),"")) | I13: BN02 | K13: 80000000 | R13: =IF($D13="","",IF($AA13="⚠","⚠ ناتراز",IF(AND($D13="پرداخت",$E13="چک",$L13=""),"⚠ وضعیت چک","✓"))) | S13: =IF(OR($D13="",$K13=""),"",IF(AND($D13="پرداخت",$E13<>"انتقال داخلی",$E13<>"پاس چک",$E13<>"برگشت چک"),$K13,0)) | T13: =IF(OR($D13="",$K13=""),"",IF(OR(AND($D13="دریافت",$E13<>"انتقال داخلی"),$E13="برگشت چک"),$K13,0)) | U13: =IF(OR($D13="",$K13=""),"",IF(OR(AND($D13="دریافت",$E13<>"چک"),$E13="انتقال داخلی"),$K13,0)) | V13: =IF(OR($D13="",$K13=""),"",IF(OR(AND($D13="پرداخت",$E13<>"چک",$E13<>"برگشت چک"),$E13="انتقال داخلی"),$K13,0)) | W13: =IF(OR($D13="",$K13=""),"",IF(OR($E13="پاس چک",$E13="برگشت چک",AND($D13="دریافت",$E13="چک")),$K13,0)) | X13: =IF(OR($D13="",$K13=""),"",IF(AND($D13="پرداخت",$E13="چک"),$K13,0)) | Y13: =SUM($S13,$U13,$W13) | Z13: =SUM($T13,$V13,$X13) | AA13: =IF($D13="","",IF(ROUND($Y13-$Z13,0)=0,"✓","⚠")) | AB13: =IF($D13="","",IF($E13="نقد","X003",IF(OR($E13="چک",$E13="پاس چک",$E13="برگشت چک"),"X010",IF($I13="","X003","X011")))) | AC13: =IF($D13="","",IF($E13="انتقال داخلی",IF($N13="","X003",IFERROR(VLOOKUP($N13,BankTbl,4,0),$N13)),IF($I13="","X003",IFERROR(VLOOKUP($I13,BankTbl,4,0),$I13)))) | AD13: =IF($D13="","",IF($E13="پاس چک","X010",IF($E13="برگشت چک",IF($I13="","X003","X011"),IF($E13="انتقال داخلی",IF($I13="","X003","X011"),IF($D13="پرداخت",$F13,IF($E13="چک","X009",IF($I13="","X003","X011"))))))) | AE13: =IF($D13="","",IF($K13="",0,$K13)) | AF13: =IF($D13="","",IF($E13="پاس چک",IF($I13="","X003","X011"),IF($E13="برگشت چک","X010",IF($E13="انتقال داخلی",IF($N13="","X003","X011"),IF($D13="پرداخت",IF($E13="چک","X010",IF($I13="","X003","X011")),$F13))))) | AG13: =IF($D13="","",IF($K13="",0,$K13))
A14: =IF($B14="","",COUNTA($B$10:$B14)) | B14: 1405/07/09 | C14: RV-002 | D14: دریافت | E14: کارت/پوز | F14: SL002 | G14: =IF($F14="","",IFERROR(VLOOKUP($F14,AcctTbl,2,0),"کد ناشناخته")) | H14: =IF($F14="","",IFERROR(VLOOKUP($F14,AcctTbl,3,0),"")) | I14: BN02 | K14: 120000000 | R14: =IF($D14="","",IF($AA14="⚠","⚠ ناتراز",IF(AND($D14="پرداخت",$E14="چک",$L14=""),"⚠ وضعیت چک","✓"))) | S14: =IF(OR($D14="",$K14=""),"",IF(AND($D14="پرداخت",$E14<>"انتقال داخلی",$E14<>"پاس چک",$E14<>"برگشت چک"),$K14,0)) | T14: =IF(OR($D14="",$K14=""),"",IF(OR(AND($D14="دریافت",$E14<>"انتقال داخلی"),$E14="برگشت چک"),$K14,0)) | U14: =IF(OR($D14="",$K14=""),"",IF(OR(AND($D14="دریافت",$E14<>"چک"),$E14="انتقال داخلی"),$K14,0)) | V14: =IF(OR($D14="",$K14=""),"",IF(OR(AND($D14="پرداخت",$E14<>"چک",$E14<>"برگشت چک"),$E14="انتقال داخلی"),$K14,0)) | W14: =IF(OR($D14="",$K14=""),"",IF(OR($E14="پاس چک",$E14="برگشت چک",AND($D14="دریافت",$E14="چک")),$K14,0)) | X14: =IF(OR($D14="",$K14=""),"",IF(AND($D14="پرداخت",$E14="چک"),$K14,0)) | Y14: =SUM($S14,$U14,$W14) | Z14: =SUM($T14,$V14,$X14) | AA14: =IF($D14="","",IF(ROUND($Y14-$Z14,0)=0,"✓","⚠")) | AB14: =IF($D14="","",IF($E14="نقد","X003",IF(OR($E14="چک",$E14="پاس چک",$E14="برگشت چک"),"X010",IF($I14="","X003","X011")))) | AC14: =IF($D14="","",IF($E14="انتقال داخلی",IF($N14="","X003",IFERROR(VLOOKUP($N14,BankTbl,4,0),$N14)),IF($I14="","X003",IFERROR(VLOOKUP($I14,BankTbl,4,0),$I14)))) | AD14: =IF($D14="","",IF($E14="پاس چک","X010",IF($E14="برگشت چک",IF($I14="","X003","X011"),IF($E14="انتقال داخلی",IF($I14="","X003","X011"),IF($D14="پرداخت",$F14,IF($E14="چک","X009",IF($I14="","X003","X011"))))))) | AE14: =IF($D14="","",IF($K14="",0,$K14)) | AF14: =IF($D14="","",IF($E14="پاس چک",IF($I14="","X003","X011"),IF($E14="برگشت چک","X010",IF($E14="انتقال داخلی",IF($N14="","X003","X011"),IF($D14="پرداخت",IF($E14="چک","X010",IF($I14="","X003","X011")),$F14))))) | AG14: =IF($D14="","",IF($K14="",0,$K14))
A15: =IF($B15="","",COUNTA($B$10:$B15)) | B15: 1405/07/10 | C15: PV-004 | D15: پرداخت | E15: پاس چک | F15: X010 | G15: =IF($F15="","",IFERROR(VLOOKUP($F15,AcctTbl,2,0),"کد ناشناخته")) | H15: =IF($F15="","",IFERROR(VLOOKUP($F15,AcctTbl,3,0),"")) | I15: BN01 | J15: CHQ-1001 | K15: 200000000 | L15: پاس شده | P15: پاس شدن چک | R15: =IF($D15="","",IF($AA15="⚠","⚠ ناتراز",IF(AND($D15="پرداخت",$E15="چک",$L15=""),"⚠ وضعیت چک","✓"))) | S15: =IF(OR($D15="",$K15=""),"",IF(AND($D15="پرداخت",$E15<>"انتقال داخلی",$E15<>"پاس چک",$E15<>"برگشت چک"),$K15,0)) | T15: =IF(OR($D15="",$K15=""),"",IF(OR(AND($D15="دریافت",$E15<>"انتقال داخلی"),$E15="برگشت چک"),$K15,0)) | U15: =IF(OR($D15="",$K15=""),"",IF(OR(AND($D15="دریافت",$E15<>"چک"),$E15="انتقال داخلی"),$K15,0)) | V15: =IF(OR($D15="",$K15=""),"",IF(OR(AND($D15="پرداخت",$E15<>"چک",$E15<>"برگشت چک"),$E15="انتقال داخلی"),$K15,0)) | W15: =IF(OR($D15="",$K15=""),"",IF(OR($E15="پاس چک",$E15="برگشت چک",AND($D15="دریافت",$E15="چک")),$K15,0)) | X15: =IF(OR($D15="",$K15=""),"",IF(AND($D15="پرداخت",$E15="چک"),$K15,0)) | Y15: =SUM($S15,$U15,$W15) | Z15: =SUM($T15,$V15,$X15) | AA15: =IF($D15="","",IF(ROUND($Y15-$Z15,0)=0,"✓","⚠")) | AB15: =IF($D15="","",IF($E15="نقد","X003",IF(OR($E15="چک",$E15="پاس چک",$E15="برگشت چک"),"X010",IF($I15="","X003","X011")))) | AC15: =IF($D15="","",IF($E15="انتقال داخلی",IF($N15="","X003",IFERROR(VLOOKUP($N15,BankTbl,4,0),$N15)),IF($I15="","X003",IFERROR(VLOOKUP($I15,BankTbl,4,0),$I15)))) | AD15: =IF($D15="","",IF($E15="پاس چک","X010",IF($E15="برگشت چک",IF($I15="","X003","X011"),IF($E15="انتقال داخلی",IF($I15="","X003","X011"),IF($D15="پرداخت",$F15,IF($E15="چک","X009",IF($I15="","X003","X011"))))))) | AE15: =IF($D15="","",IF($K15="",0,$K15)) | AF15: =IF($D15="","",IF($E15="پاس چک",IF($I15="","X003","X011"),IF($E15="برگشت چک","X010",IF($E15="انتقال داخلی",IF($N15="","X003","X011"),IF($D15="پرداخت",IF($E15="چک","X010",IF($I15="","X003","X011")),$F15))))) | AG15: =IF($D15="","",IF($K15="",0,$K15))
A16: =IF($B16="","",COUNTA($B$10:$B16)) | B16: 1405/07/10 | C16: PV-005 | D16: پرداخت | E16: نقد | F16: C006 | G16: =IF($F16="","",IFERROR(VLOOKUP($F16,AcctTbl,2,0),"کد ناشناخته")) | H16: =IF($F16="","",IFERROR(VLOOKUP($F16,AcctTbl,3,0),"")) | K16: 30000000 | R16: =IF($D16="","",IF($AA16="⚠","⚠ ناتراز",IF(AND($D16="پرداخت",$E16="چک",$L16=""),"⚠ وضعیت چک","✓"))) | S16: =IF(OR($D16="",$K16=""),"",IF(AND($D16="پرداخت",$E16<>"انتقال داخلی",$E16<>"پاس چک",$E16<>"برگشت چک"),$K16,0)) | T16: =IF(OR($D16="",$K16=""),"",IF(OR(AND($D16="دریافت",$E16<>"انتقال داخلی"),$E16="برگشت چک"),$K16,0)) | U16: =IF(OR($D16="",$K16=""),"",IF(OR(AND($D16="دریافت",$E16<>"چک"),$E16="انتقال داخلی"),$K16,0)) | V16: =IF(OR($D16="",$K16=""),"",IF(OR(AND($D16="پرداخت",$E16<>"چک",$E16<>"برگشت چک"),$E16="انتقال داخلی"),$K16,0)) | W16: =IF(OR($D16="",$K16=""),"",IF(OR($E16="پاس چک",$E16="برگشت چک",AND($D16="دریافت",$E16="چک")),$K16,0)) | X16: =IF(OR($D16="",$K16=""),"",IF(AND($D16="پرداخت",$E16="چک"),$K16,0)) | Y16: =SUM($S16,$U16,$W16) | Z16: =SUM($T16,$V16,$X16) | AA16: =IF($D16="","",IF(ROUND($Y16-$Z16,0)=0,"✓","⚠")) | AB16: =IF($D16="","",IF($E16="نقد","X003",IF(OR($E16="چک",$E16="پاس چک",$E16="برگشت چک"),"X010",IF($I16="","X003","X011")))) | AC16: =IF($D16="","",IF($E16="انتقال داخلی",IF($N16="","X003",IFERROR(VLOOKUP($N16,BankTbl,4,0),$N16)),IF($I16="","X003",IFERROR(VLOOKUP($I16,BankTbl,4,0),$I16)))) | AD16: =IF($D16="","",IF($E16="پاس چک","X010",IF($E16="برگشت چک",IF($I16="","X003","X011"),IF($E16="انتقال داخلی",IF($I16="","X003","X011"),IF($D16="پرداخت",$F16,IF($E16="چک","X009",IF($I16="","X003","X011"))))))) | AE16: =IF($D16="","",IF($K16="",0,$K16)) | AF16: =IF($D16="","",IF($E16="پاس چک",IF($I16="","X003","X011"),IF($E16="برگشت چک","X010",IF($E16="انتقال داخلی",IF($N16="","X003","X011"),IF($D16="پرداخت",IF($E16="چک","X010",IF($I16="","X003","X011")),$F16))))) | AG16: =IF($D16="","",IF($K16="",0,$K16))
A17: =IF($B17="","",COUNTA($B$10:$B17)) | B17: 1405/07/11 | C17: RV-003 | D17: دریافت | E17: انتقال بانکی | F17: SL001 | G17: =IF($F17="","",IFERROR(VLOOKUP($F17,AcctTbl,2,0),"کد ناشناخته")) | H17: =IF($F17="","",IFERROR(VLOOKUP($F17,AcctTbl,3,0),"")) | I17: BN02 | K17: 100000000 | R17: =IF($D17="","",IF($AA17="⚠","⚠ ناتراز",IF(AND($D17="پرداخت",$E17="چک",$L17=""),"⚠ وضعیت چک","✓"))) | S17: =IF(OR($D17="",$K17=""),"",IF(AND($D17="پرداخت",$E17<>"انتقال داخلی",$E17<>"پاس چک",$E17<>"برگشت چک"),$K17,0)) | T17: =IF(OR($D17="",$K17=""),"",IF(OR(AND($D17="دریافت",$E17<>"انتقال داخلی"),$E17="برگشت چک"),$K17,0)) | U17: =IF(OR($D17="",$K17=""),"",IF(OR(AND($D17="دریافت",$E17<>"چک"),$E17="انتقال داخلی"),$K17,0)) | V17: =IF(OR($D17="",$K17=""),"",IF(OR(AND($D17="پرداخت",$E17<>"چک",$E17<>"برگشت چک"),$E17="انتقال داخلی"),$K17,0)) | W17: =IF(OR($D17="",$K17=""),"",IF(OR($E17="پاس چک",$E17="برگشت چک",AND($D17="دریافت",$E17="چک")),$K17,0)) | X17: =IF(OR($D17="",$K17=""),"",IF(AND($D17="پرداخت",$E17="چک"),$K17,0)) | Y17: =SUM($S17,$U17,$W17) | Z17: =SUM($T17,$V17,$X17) | AA17: =IF($D17="","",IF(ROUND($Y17-$Z17,0)=0,"✓","⚠")) | AB17: =IF($D17="","",IF($E17="نقد","X003",IF(OR($E17="چک",$E17="پاس چک",$E17="برگشت چک"),"X010",IF($I17="","X003","X011")))) | AC17: =IF($D17="","",IF($E17="انتقال داخلی",IF($N17="","X003",IFERROR(VLOOKUP($N17,BankTbl,4,0),$N17)),IF($I17="","X003",IFERROR(VLOOKUP($I17,BankTbl,4,0),$I17)))) | AD17: =IF($D17="","",IF($E17="پاس چک","X010",IF($E17="برگشت چک",IF($I17="","X003","X011"),IF($E17="انتقال داخلی",IF($I17="","X003","X011"),IF($D17="پرداخت",$F17,IF($E17="چک","X009",IF($I17="","X003","X011"))))))) | AE17: =IF($D17="","",IF($K17="",0,$K17)) | AF17: =IF($D17="","",IF($E17="پاس چک",IF($I17="","X003","X011"),IF($E17="برگشت چک","X010",IF($E17="انتقال داخلی",IF($N17="","X003","X011"),IF($D17="پرداخت",IF($E17="چک","X010",IF($I17="","X003","X011")),$F17))))) | AG17: =IF($D17="","",IF($K17="",0,$K17))
A18: =IF($B18="","",COUNTA($B$10:$B18)) | B18: 1405/07/11 | C18: PV-006 | D18: پرداخت | E18: نقد | F18: X001 | G18: =IF($F18="","",IFERROR(VLOOKUP($F18,AcctTbl,2,0),"کد ناشناخته")) | H18: =IF($F18="","",IFERROR(VLOOKUP($F18,AcctTbl,3,0),"")) | K18: 500000 | P18: تسویه انعام مصطفی | R18: =IF($D18="","",IF($AA18="⚠","⚠ ناتراز",IF(AND($D18="پرداخت",$E18="چک",$L18=""),"⚠ وضعیت چک","✓"))) | S18: =IF(OR($D18="",$K18=""),"",IF(AND($D18="پرداخت",$E18<>"انتقال داخلی",$E18<>"پاس چک",$E18<>"برگشت چک"),$K18,0)) | T18: =IF(OR($D18="",$K18=""),"",IF(OR(AND($D18="دریافت",$E18<>"انتقال داخلی"),$E18="برگشت چک"),$K18,0)) | U18: =IF(OR($D18="",$K18=""),"",IF(OR(AND($D18="دریافت",$E18<>"چک"),$E18="انتقال داخلی"),$K18,0)) | V18: =IF(OR($D18="",$K18=""),"",IF(OR(AND($D18="پرداخت",$E18<>"چک",$E18<>"برگشت چک"),$E18="انتقال داخلی"),$K18,0)) | W18: =IF(OR($D18="",$K18=""),"",IF(OR($E18="پاس چک",$E18="برگشت چک",AND($D18="دریافت",$E18="چک")),$K18,0)) | X18: =IF(OR($D18="",$K18=""),"",IF(AND($D18="پرداخت",$E18="چک"),$K18,0)) | Y18: =SUM($S18,$U18,$W18) | Z18: =SUM($T18,$V18,$X18) | AA18: =IF($D18="","",IF(ROUND($Y18-$Z18,0)=0,"✓","⚠")) | AB18: =IF($D18="","",IF($E18="نقد","X003",IF(OR($E18="چک",$E18="پاس چک",$E18="برگشت چک"),"X010",IF($I18="","X003","X011")))) | AC18: =IF($D18="","",IF($E18="انتقال داخلی",IF($N18="","X003",IFERROR(VLOOKUP($N18,BankTbl,4,0),$N18)),IF($I18="","X003",IFERROR(VLOOKUP($I18,BankTbl,4,0),$I18)))) | AD18: =IF($D18="","",IF($E18="پاس چک","X010",IF($E18="برگشت چک",IF($I18="","X003","X011"),IF($E18="انتقال داخلی",IF($I18="","X003","X011"),IF($D18="پرداخت",$F18,IF($E18="چک","X009",IF($I18="","X003","X011"))))))) | AE18: =IF($D18="","",IF($K18="",0,$K18)) | AF18: =IF($D18="","",IF($E18="پاس چک",IF($I18="","X003","X011"),IF($E18="برگشت چک","X010",IF($E18="انتقال داخلی",IF($N18="","X003","X011"),IF($D18="پرداخت",IF($E18="چک","X010",IF($I18="","X003","X011")),$F18))))) | AG18: =IF($D18="","",IF($K18="",0,$K18))
A19: =IF($B19="","",COUNTA($B$10:$B19)) | B19: 1405/07/12 | C19: PV-007 | D19: پرداخت | E19: انتقال داخلی | F19: BN02 | G19: =IF($F19="","",IFERROR(VLOOKUP($F19,AcctTbl,2,0),"کد ناشناخته")) | H19: =IF($F19="","",IFERROR(VLOOKUP($F19,AcctTbl,3,0),"")) | I19: BN01 | K19: 50000000 | P19: انتقال بین بانکی | R19: =IF($D19="","",IF($AA19="⚠","⚠ ناتراز",IF(AND($D19="پرداخت",$E19="چک",$L19=""),"⚠ وضعیت چک","✓"))) | S19: =IF(OR($D19="",$K19=""),"",IF(AND($D19="پرداخت",$E19<>"انتقال داخلی",$E19<>"پاس چک",$E19<>"برگشت چک"),$K19,0)) | T19: =IF(OR($D19="",$K19=""),"",IF(OR(AND($D19="دریافت",$E19<>"انتقال داخلی"),$E19="برگشت چک"),$K19,0)) | U19: =IF(OR($D19="",$K19=""),"",IF(OR(AND($D19="دریافت",$E19<>"چک"),$E19="انتقال داخلی"),$K19,0)) | V19: =IF(OR($D19="",$K19=""),"",IF(OR(AND($D19="پرداخت",$E19<>"چک",$E19<>"برگشت چک"),$E19="انتقال داخلی"),$K19,0)) | W19: =IF(OR($D19="",$K19=""),"",IF(OR($E19="پاس چک",$E19="برگشت چک",AND($D19="دریافت",$E19="چک")),$K19,0)) | X19: =IF(OR($D19="",$K19=""),"",IF(AND($D19="پرداخت",$E19="چک"),$K19,0)) | Y19: =SUM($S19,$U19,$W19) | Z19: =SUM($T19,$V19,$X19) | AA19: =IF($D19="","",IF(ROUND($Y19-$Z19,0)=0,"✓","⚠")) | AB19: =IF($D19="","",IF($E19="نقد","X003",IF(OR($E19="چک",$E19="پاس چک",$E19="برگشت چک"),"X010",IF($I19="","X003","X011")))) | AC19: =IF($D19="","",IF($E19="انتقال داخلی",IF($N19="","X003",IFERROR(VLOOKUP($N19,BankTbl,4,0),$N19)),IF($I19="","X003",IFERROR(VLOOKUP($I19,BankTbl,4,0),$I19)))) | AD19: =IF($E19="انتقال داخلی","","") | AE19: =IF($D19="","",IF($K19="",0,$K19)) | AF19: =IF($E19="انتقال داخلی","","") | AG19: =IF($D19="","",IF($K19="",0,$K19))
A20: =IF($B20="","",COUNTA($B$10:$B20)) | B20: 1405/07/07 | C20: PV-008 | D20: پرداخت | E20: چک | F20: C004 | G20: =IF($F20="","",IFERROR(VLOOKUP($F20,AcctTbl,2,0),"کد ناشناخته")) | H20: =IF($F20="","",IFERROR(VLOOKUP($F20,AcctTbl,3,0),"")) | I20: BN03 | J20: CHQ-1002 | K20: 60000000 | L20: در جریان | P20: در جریان | R20: =IF($D20="","",IF($AA20="⚠","⚠ ناتراز",IF(AND($D20="پرداخت",$E20="چک",$L20=""),"⚠ وضعیت چک","✓"))) | S20: =IF(OR($D20="",$K20=""),"",IF(AND($D20="پرداخت",$E20<>"انتقال داخلی",$E20<>"پاس چک",$E20<>"برگشت چک"),$K20,0)) | T20: =IF(OR($D20="",$K20=""),"",IF(OR(AND($D20="دریافت",$E20<>"انتقال داخلی"),$E20="برگشت چک"),$K20,0)) | U20: =IF(OR($D20="",$K20=""),"",IF(OR(AND($D20="دریافت",$E20<>"چک"),$E20="انتقال داخلی"),$K20,0)) | V20: =IF(OR($D20="",$K20=""),"",IF(OR(AND($D20="پرداخت",$E20<>"چک",$E20<>"برگشت چک"),$E20="انتقال داخلی"),$K20,0)) | W20: =IF(OR($D20="",$K20=""),"",IF(OR($E20="پاس چک",$E20="برگشت چک",AND($D20="دریافت",$E20="چک")),$K20,0)) | X20: =IF(OR($D20="",$K20=""),"",IF(AND($D20="پرداخت",$E20="چک"),$K20,0)) | Y20: =SUM($S20,$U20,$W20) | Z20: =SUM($T20,$V20,$X20) | AA20: =IF($D20="","",IF(ROUND($Y20-$Z20,0)=0,"✓","⚠")) | AB20: =IF($D20="","",IF($E20="نقد","X003",IF(OR($E20="چک",$E20="پاس چک",$E20="برگشت چک"),"X010",IF($I20="","X003","X011")))) | AC20: =IF($D20="","",IF($E20="انتقال داخلی",IF($N20="","X003",IFERROR(VLOOKUP($N20,BankTbl,4,0),$N20)),IF($I20="","X003",IFERROR(VLOOKUP($I20,BankTbl,4,0),$I20)))) | AD20: =IF($D20="","",IF($E20="پاس چک","X010",IF($E20="برگشت چک",IF($I20="","X003","X011"),IF($E20="انتقال داخلی",IF($I20="","X003","X011"),IF($D20="پرداخت",$F20,IF($E20="چک","X009",IF($I20="","X003","X011"))))))) | AE20: =IF($D20="","",IF($K20="",0,$K20)) | AF20: =IF($D20="","",IF($E20="پاس چک",IF($I20="","X003","X011"),IF($E20="برگشت چک","X010",IF($E20="انتقال داخلی",IF($N20="","X003","X011"),IF($D20="پرداخت",IF($E20="چک","X010",IF($I20="","X003","X011")),$F20))))) | AG20: =IF($D20="","",IF($K20="",0,$K20))
A21: =IF($B21="","",COUNTA($B$10:$B21)) | B21: 1405/07/12 | C21: RV-004 | D21: دریافت | E21: انتقال بانکی | F21: SL002 | G21: =IF($F21="","",IFERROR(VLOOKUP($F21,AcctTbl,2,0),"کد ناشناخته")) | H21: =IF($F21="","",IFERROR(VLOOKUP($F21,AcctTbl,3,0),"")) | I21: BN01 | K21: 50000000 | R21: =IF($D21="","",IF($AA21="⚠","⚠ ناتراز",IF(AND($D21="پرداخت",$E21="چک",$L21=""),"⚠ وضعیت چک","✓"))) | S21: =IF(OR($D21="",$K21=""),"",IF(AND($D21="پرداخت",$E21<>"انتقال داخلی",$E21<>"پاس چک",$E21<>"برگشت چک"),$K21,0)) | T21: =IF(OR($D21="",$K21=""),"",IF(OR(AND($D21="دریافت",$E21<>"انتقال داخلی"),$E21="برگشت چک"),$K21,0)) | U21: =IF(OR($D21="",$K21=""),"",IF(OR(AND($D21="دریافت",$E21<>"چک"),$E21="انتقال داخلی"),$K21,0)) | V21: =IF(OR($D21="",$K21=""),"",IF(OR(AND($D21="پرداخت",$E21<>"چک",$E21<>"برگشت چک"),$E21="انتقال داخلی"),$K21,0)) | W21: =IF(OR($D21="",$K21=""),"",IF(OR($E21="پاس چک",$E21="برگشت چک",AND($D21="دریافت",$E21="چک")),$K21,0)) | X21: =IF(OR($D21="",$K21=""),"",IF(AND($D21="پرداخت",$E21="چک"),$K21,0)) | Y21: =SUM($S21,$U21,$W21) | Z21: =SUM($T21,$V21,$X21) | AA21: =IF($D21="","",IF(ROUND($Y21-$Z21,0)=0,"✓","⚠")) | AB21: =IF($D21="","",IF($E21="نقد","X003",IF(OR($E21="چک",$E21="پاس چک",$E21="برگشت چک"),"X010",IF($I21="","X003","X011")))) | AC21: =IF($D21="","",IF($E21="انتقال داخلی",IF($N21="","X003",IFERROR(VLOOKUP($N21,BankTbl,4,0),$N21)),IF($I21="","X003",IFERROR(VLOOKUP($I21,BankTbl,4,0),$I21)))) | AD21: =IF($D21="","",IF($E21="پاس چک","X010",IF($E21="برگشت چک",IF($I21="","X003","X011"),IF($E21="انتقال داخلی",IF($I21="","X003","X011"),IF($D21="پرداخت",$F21,IF($E21="چک","X009",IF($I21="","X003","X011"))))))) | AE21: =IF($D21="","",IF($K21="",0,$K21)) | AF21: =IF($D21="","",IF($E21="پاس چک",IF($I21="","X003","X011"),IF($E21="برگشت چک","X010",IF($E21="انتقال داخلی",IF($N21="","X003","X011"),IF($D21="پرداخت",IF($E21="چک","X010",IF($I21="","X003","X011")),$F21))))) | AG21: =IF($D21="","",IF($K21="",0,$K21))
A22: =IF($B22="","",COUNTA($B$10:$B22)) | G22: =IF($F22="","",IFERROR(VLOOKUP($F22,AcctTbl,2,0),"کد ناشناخته")) | H22: =IF($F22="","",IFERROR(VLOOKUP($F22,AcctTbl,3,0),"")) | R22: =IF($D22="","",IF($AA22="⚠","⚠ ناتراز",IF(AND($D22="پرداخت",$E22="چک",$L22=""),"⚠ وضعیت چک","✓"))) | S22: =IF(OR($D22="",$K22=""),"",IF(AND($D22="پرداخت",$E22<>"انتقال داخلی",$E22<>"پاس چک",$E22<>"برگشت چک"),$K22,0)) | T22: =IF(OR($D22="",$K22=""),"",IF(OR(AND($D22="دریافت",$E22<>"انتقال داخلی"),$E22="برگشت چک"),$K22,0)) | U22: =IF(OR($D22="",$K22=""),"",IF(OR(AND($D22="دریافت",$E22<>"چک"),$E22="انتقال داخلی"),$K22,0)) | V22: =IF(OR($D22="",$K22=""),"",IF(OR(AND($D22="پرداخت",$E22<>"چک",$E22<>"برگشت چک"),$E22="انتقال داخلی"),$K22,0)) | W22: =IF(OR($D22="",$K22=""),"",IF(OR($E22="پاس چک",$E22="برگشت چک",AND($D22="دریافت",$E22="چک")),$K22,0)) | X22: =IF(OR($D22="",$K22=""),"",IF(AND($D22="پرداخت",$E22="چک"),$K22,0)) | Y22: =SUM($S22,$U22,$W22) | Z22: =SUM($T22,$V22,$X22) | AA22: =IF($D22="","",IF(ROUND($Y22-$Z22,0)=0,"✓","⚠")) | AB22: =IF($D22="","",IF($E22="نقد","X003",IF(OR($E22="چک",$E22="پاس چک",$E22="برگشت چک"),"X010",IF($I22="","X003","X011")))) | AC22: =IF($D22="","",IF($E22="انتقال داخلی",IF($N22="","X003",IFERROR(VLOOKUP($N22,BankTbl,4,0),$N22)),IF($I22="","X003",IFERROR(VLOOKUP($I22,BankTbl,4,0),$I22)))) | AD22: =IF($D22="","",IF($E22="پاس چک","X010",IF($E22="برگشت چک",IF($I22="","X003","X011"),IF($E22="انتقال داخلی",IF($I22="","X003","X011"),IF($D22="پرداخت",$F22,IF($E22="چک","X009",IF($I22="","X003","X011"))))))) | AE22: =IF($D22="","",IF($K22="",0,$K22)) | AF22: =IF($D22="","",IF($E22="پاس چک",IF($I22="","X003","X011"),IF($E22="برگشت چک","X010",IF($E22="انتقال داخلی",IF($N22="","X003","X011"),IF($D22="پرداخت",IF($E22="چک","X010",IF($I22="","X003","X011")),$F22))))) | AG22: =IF($D22="","",IF($K22="",0,$K22))
A23: =IF($B23="","",COUNTA($B$10:$B23)) | G23: =IF($F23="","",IFERROR(VLOOKUP($F23,AcctTbl,2,0),"کد ناشناخته")) | H23: =IF($F23="","",IFERROR(VLOOKUP($F23,AcctTbl,3,0),"")) | R23: =IF($D23="","",IF($AA23="⚠","⚠ ناتراز",IF(AND($D23="پرداخت",$E23="چک",$L23=""),"⚠ وضعیت چک","✓"))) | S23: =IF(OR($D23="",$K23=""),"",IF(AND($D23="پرداخت",$E23<>"انتقال داخلی",$E23<>"پاس چک",$E23<>"برگشت چک"),$K23,0)) | T23: =IF(OR($D23="",$K23=""),"",IF(OR(AND($D23="دریافت",$E23<>"انتقال داخلی"),$E23="برگشت چک"),$K23,0)) | U23: =IF(OR($D23="",$K23=""),"",IF(OR(AND($D23="دریافت",$E23<>"چک"),$E23="انتقال داخلی"),$K23,0)) | V23: =IF(OR($D23="",$K23=""),"",IF(OR(AND($D23="پرداخت",$E23<>"چک",$E23<>"برگشت چک"),$E23="انتقال داخلی"),$K23,0)) | W23: =IF(OR($D23="",$K23=""),"",IF(OR($E23="پاس چک",$E23="برگشت چک",AND($D23="دریافت",$E23="چک")),$K23,0)) | X23: =IF(OR($D23="",$K23=""),"",IF(AND($D23="پرداخت",$E23="چک"),$K23,0)) | Y23: =SUM($S23,$U23,$W23) | Z23: =SUM($T23,$V23,$X23) | AA23: =IF($D23="","",IF(ROUND($Y23-$Z23,0)=0,"✓","⚠")) | AB23: =IF($D23="","",IF($E23="نقد","X003",IF(OR($E23="چک",$E23="پاس چک",$E23="برگشت چک"),"X010",IF($I23="","X003","X011")))) | AC23: =IF($D23="","",IF($E23="انتقال داخلی",IF($N23="","X003",IFERROR(VLOOKUP($N23,BankTbl,4,0),$N23)),IF($I23="","X003",IFERROR(VLOOKUP($I23,BankTbl,4,0),$I23)))) | AD23: =IF($D23="","",IF($E23="پاس چک","X010",IF($E23="برگشت چک",IF($I23="","X003","X011"),IF($E23="انتقال داخلی",IF($I23="","X003","X011"),IF($D23="پرداخت",$F23,IF($E23="چک","X009",IF($I23="","X003","X011"))))))) | AE23: =IF($D23="","",IF($K23="",0,$K23)) | AF23: =IF($D23="","",IF($E23="پاس چک",IF($I23="","X003","X011"),IF($E23="برگشت چک","X010",IF($E23="انتقال داخلی",IF($N23="","X003","X011"),IF($D23="پرداخت",IF($E23="چک","X010",IF($I23="","X003","X011")),$F23))))) | AG23: =IF($D23="","",IF($K23="",0,$K23))
A24: =IF($B24="","",COUNTA($B$10:$B24)) | G24: =IF($F24="","",IFERROR(VLOOKUP($F24,AcctTbl,2,0),"کد ناشناخته")) | H24: =IF($F24="","",IFERROR(VLOOKUP($F24,AcctTbl,3,0),"")) | R24: =IF($D24="","",IF($AA24="⚠","⚠ ناتراز",IF(AND($D24="پرداخت",$E24="چک",$L24=""),"⚠ وضعیت چک","✓"))) | S24: =IF(OR($D24="",$K24=""),"",IF(AND($D24="پرداخت",$E24<>"انتقال داخلی",$E24<>"پاس چک",$E24<>"برگشت چک"),$K24,0)) | T24: =IF(OR($D24="",$K24=""),"",IF(OR(AND($D24="دریافت",$E24<>"انتقال داخلی"),$E24="برگشت چک"),$K24,0)) | U24: =IF(OR($D24="",$K24=""),"",IF(OR(AND($D24="دریافت",$E24<>"چک"),$E24="انتقال داخلی"),$K24,0)) | V24: =IF(OR($D24="",$K24=""),"",IF(OR(AND($D24="پرداخت",$E24<>"چک",$E24<>"برگشت چک"),$E24="انتقال داخلی"),$K24,0)) | W24: =IF(OR($D24="",$K24=""),"",IF(OR($E24="پاس چک",$E24="برگشت چک",AND($D24="دریافت",$E24="چک")),$K24,0)) | X24: =IF(OR($D24="",$K24=""),"",IF(AND($D24="پرداخت",$E24="چک"),$K24,0)) | Y24: =SUM($S24,$U24,$W24) | Z24: =SUM($T24,$V24,$X24) | AA24: =IF($D24="","",IF(ROUND($Y24-$Z24,0)=0,"✓","⚠")) | AB24: =IF($D24="","",IF($E24="نقد","X003",IF(OR($E24="چک",$E24="پاس چک",$E24="برگشت چک"),"X010",IF($I24="","X003","X011")))) | AC24: =IF($D24="","",IF($E24="انتقال داخلی",IF($N24="","X003",IFERROR(VLOOKUP($N24,BankTbl,4,0),$N24)),IF($I24="","X003",IFERROR(VLOOKUP($I24,BankTbl,4,0),$I24)))) | AD24: =IF($D24="","",IF($E24="پاس چک","X010",IF($E24="برگشت چک",IF($I24="","X003","X011"),IF($E24="انتقال داخلی",IF($I24="","X003","X011"),IF($D24="پرداخت",$F24,IF($E24="چک","X009",IF($I24="","X003","X011"))))))) | AE24: =IF($D24="","",IF($K24="",0,$K24)) | AF24: =IF($D24="","",IF($E24="پاس چک",IF($I24="","X003","X011"),IF($E24="برگشت چک","X010",IF($E24="انتقال داخلی",IF($N24="","X003","X011"),IF($D24="پرداخت",IF($E24="چک","X010",IF($I24="","X003","X011")),$F24))))) | AG24: =IF($D24="","",IF($K24="",0,$K24))
A25: =IF($B25="","",COUNTA($B$10:$B25)) | G25: =IF($F25="","",IFERROR(VLOOKUP($F25,AcctTbl,2,0),"کد ناشناخته")) | H25: =IF($F25="","",IFERROR(VLOOKUP($F25,AcctTbl,3,0),"")) | R25: =IF($D25="","",IF($AA25="⚠","⚠ ناتراز",IF(AND($D25="پرداخت",$E25="چک",$L25=""),"⚠ وضعیت چک","✓"))) | S25: =IF(OR($D25="",$K25=""),"",IF(AND($D25="پرداخت",$E25<>"انتقال داخلی",$E25<>"پاس چک",$E25<>"برگشت چک"),$K25,0)) | T25: =IF(OR($D25="",$K25=""),"",IF(OR(AND($D25="دریافت",$E25<>"انتقال داخلی"),$E25="برگشت چک"),$K25,0)) | U25: =IF(OR($D25="",$K25=""),"",IF(OR(AND($D25="دریافت",$E25<>"چک"),$E25="انتقال داخلی"),$K25,0)) | V25: =IF(OR($D25="",$K25=""),"",IF(OR(AND($D25="پرداخت",$E25<>"چک",$E25<>"برگشت چک"),$E25="انتقال داخلی"),$K25,0)) | W25: =IF(OR($D25="",$K25=""),"",IF(OR($E25="پاس چک",$E25="برگشت چک",AND($D25="دریافت",$E25="چک")),$K25,0)) | X25: =IF(OR($D25="",$K25=""),"",IF(AND($D25="پرداخت",$E25="چک"),$K25,0)) | Y25: =SUM($S25,$U25,$W25) | Z25: =SUM($T25,$V25,$X25) | AA25: =IF($D25="","",IF(ROUND($Y25-$Z25,0)=0,"✓","⚠")) | AB25: =IF($D25="","",IF($E25="نقد","X003",IF(OR($E25="چک",$E25="پاس چک",$E25="برگشت چک"),"X010",IF($I25="","X003","X011")))) | AC25: =IF($D25="","",IF($E25="انتقال داخلی",IF($N25="","X003",IFERROR(VLOOKUP($N25,BankTbl,4,0),$N25)),IF($I25="","X003",IFERROR(VLOOKUP($I25,BankTbl,4,0),$I25)))) | AD25: =IF($D25="","",IF($E25="پاس چک","X010",IF($E25="برگشت چک",IF($I25="","X003","X011"),IF($E25="انتقال داخلی",IF($I25="","X003","X011"),IF($D25="پرداخت",$F25,IF($E25="چک","X009",IF($I25="","X003","X011"))))))) | AE25: =IF($D25="","",IF($K25="",0,$K25)) | AF25: =IF($D25="","",IF($E25="پاس چک",IF($I25="","X003","X011"),IF($E25="برگشت چک","X010",IF($E25="انتقال داخلی",IF($N25="","X003","X011"),IF($D25="پرداخت",IF($E25="چک","X010",IF($I25="","X003","X011")),$F25))))) | AG25: =IF($D25="","",IF($K25="",0,$K25))
A26: =IF($B26="","",COUNTA($B$10:$B26)) | G26: =IF($F26="","",IFERROR(VLOOKUP($F26,AcctTbl,2,0),"کد ناشناخته")) | H26: =IF($F26="","",IFERROR(VLOOKUP($F26,AcctTbl,3,0),"")) | R26: =IF($D26="","",IF($AA26="⚠","⚠ ناتراز",IF(AND($D26="پرداخت",$E26="چک",$L26=""),"⚠ وضعیت چک","✓"))) | S26: =IF(OR($D26="",$K26=""),"",IF(AND($D26="پرداخت",$E26<>"انتقال داخلی",$E26<>"پاس چک",$E26<>"برگشت چک"),$K26,0)) | T26: =IF(OR($D26="",$K26=""),"",IF(OR(AND($D26="دریافت",$E26<>"انتقال داخلی"),$E26="برگشت چک"),$K26,0)) | U26: =IF(OR($D26="",$K26=""),"",IF(OR(AND($D26="دریافت",$E26<>"چک"),$E26="انتقال داخلی"),$K26,0)) | V26: =IF(OR($D26="",$K26=""),"",IF(OR(AND($D26="پرداخت",$E26<>"چک",$E26<>"برگشت چک"),$E26="انتقال داخلی"),$K26,0)) | W26: =IF(OR($D26="",$K26=""),"",IF(OR($E26="پاس چک",$E26="برگشت چک",AND($D26="دریافت",$E26="چک")),$K26,0)) | X26: =IF(OR($D26="",$K26=""),"",IF(AND($D26="پرداخت",$E26="چک"),$K26,0)) | Y26: =SUM($S26,$U26,$W26) | Z26: =SUM($T26,$V26,$X26) | AA26: =IF($D26="","",IF(ROUND($Y26-$Z26,0)=0,"✓","⚠")) | AB26: =IF($D26="","",IF($E26="نقد","X003",IF(OR($E26="چک",$E26="پاس چک",$E26="برگشت چک"),"X010",IF($I26="","X003","X011")))) | AC26: =IF($D26="","",IF($E26="انتقال داخلی",IF($N26="","X003",IFERROR(VLOOKUP($N26,BankTbl,4,0),$N26)),IF($I26="","X003",IFERROR(VLOOKUP($I26,BankTbl,4,0),$I26)))) | AD26: =IF($D26="","",IF($E26="پاس چک","X010",IF($E26="برگشت چک",IF($I26="","X003","X011"),IF($E26="انتقال داخلی",IF($I26="","X003","X011"),IF($D26="پرداخت",$F26,IF($E26="چک","X009",IF($I26="","X003","X011"))))))) | AE26: =IF($D26="","",IF($K26="",0,$K26)) | AF26: =IF($D26="","",IF($E26="پاس چک",IF($I26="","X003","X011"),IF($E26="برگشت چک","X010",IF($E26="انتقال داخلی",IF($N26="","X003","X011"),IF($D26="پرداخت",IF($E26="چک","X010",IF($I26="","X003","X011")),$F26))))) | AG26: =IF($D26="","",IF($K26="",0,$K26))
A27: =IF($B27="","",COUNTA($B$10:$B27)) | G27: =IF($F27="","",IFERROR(VLOOKUP($F27,AcctTbl,2,0),"کد ناشناخته")) | H27: =IF($F27="","",IFERROR(VLOOKUP($F27,AcctTbl,3,0),"")) | R27: =IF($D27="","",IF($AA27="⚠","⚠ ناتراز",IF(AND($D27="پرداخت",$E27="چک",$L27=""),"⚠ وضعیت چک","✓"))) | S27: =IF(OR($D27="",$K27=""),"",IF(AND($D27="پرداخت",$E27<>"انتقال داخلی",$E27<>"پاس چک",$E27<>"برگشت چک"),$K27,0)) | T27: =IF(OR($D27="",$K27=""),"",IF(OR(AND($D27="دریافت",$E27<>"انتقال داخلی"),$E27="برگشت چک"),$K27,0)) | U27: =IF(OR($D27="",$K27=""),"",IF(OR(AND($D27="دریافت",$E27<>"چک"),$E27="انتقال داخلی"),$K27,0)) | V27: =IF(OR($D27="",$K27=""),"",IF(OR(AND($D27="پرداخت",$E27<>"چک",$E27<>"برگشت چک"),$E27="انتقال داخلی"),$K27,0)) | W27: =IF(OR($D27="",$K27=""),"",IF(OR($E27="پاس چک",$E27="برگشت چک",AND($D27="دریافت",$E27="چک")),$K27,0)) | X27: =IF(OR($D27="",$K27=""),"",IF(AND($D27="پرداخت",$E27="چک"),$K27,0)) | Y27: =SUM($S27,$U27,$W27) | Z27: =SUM($T27,$V27,$X27) | AA27: =IF($D27="","",IF(ROUND($Y27-$Z27,0)=0,"✓","⚠")) | AB27: =IF($D27="","",IF($E27="نقد","X003",IF(OR($E27="چک",$E27="پاس چک",$E27="برگشت چک"),"X010",IF($I27="","X003","X011")))) | AC27: =IF($D27="","",IF($E27="انتقال داخلی",IF($N27="","X003",IFERROR(VLOOKUP($N27,BankTbl,4,0),$N27)),IF($I27="","X003",IFERROR(VLOOKUP($I27,BankTbl,4,0),$I27)))) | AD27: =IF($D27="","",IF($E27="پاس چک","X010",IF($E27="برگشت چک",IF($I27="","X003","X011"),IF($E27="انتقال داخلی",IF($I27="","X003","X011"),IF($D27="پرداخت",$F27,IF($E27="چک","X009",IF($I27="","X003","X011"))))))) | AE27: =IF($D27="","",IF($K27="",0,$K27)) | AF27: =IF($D27="","",IF($E27="پاس چک",IF($I27="","X003","X011"),IF($E27="برگشت چک","X010",IF($E27="انتقال داخلی",IF($N27="","X003","X011"),IF($D27="پرداخت",IF($E27="چک","X010",IF($I27="","X003","X011")),$F27))))) | AG27: =IF($D27="","",IF($K27="",0,$K27))
A28: =IF($B28="","",COUNTA($B$10:$B28)) | G28: =IF($F28="","",IFERROR(VLOOKUP($F28,AcctTbl,2,0),"کد ناشناخته")) | H28: =IF($F28="","",IFERROR(VLOOKUP($F28,AcctTbl,3,0),"")) | R28: =IF($D28="","",IF($AA28="⚠","⚠ ناتراز",IF(AND($D28="پرداخت",$E28="چک",$L28=""),"⚠ وضعیت چک","✓"))) | S28: =IF(OR($D28="",$K28=""),"",IF(AND($D28="پرداخت",$E28<>"انتقال داخلی",$E28<>"پاس چک",$E28<>"برگشت چک"),$K28,0)) | T28: =IF(OR($D28="",$K28=""),"",IF(OR(AND($D28="دریافت",$E28<>"انتقال داخلی"),$E28="برگشت چک"),$K28,0)) | U28: =IF(OR($D28="",$K28=""),"",IF(OR(AND($D28="دریافت",$E28<>"چک"),$E28="انتقال داخلی"),$K28,0)) | V28: =IF(OR($D28="",$K28=""),"",IF(OR(AND($D28="پرداخت",$E28<>"چک",$E28<>"برگشت چک"),$E28="انتقال داخلی"),$K28,0)) | W28: =IF(OR($D28="",$K28=""),"",IF(OR($E28="پاس چک",$E28="برگشت چک",AND($D28="دریافت",$E28="چک")),$K28,0)) | X28: =IF(OR($D28="",$K28=""),"",IF(AND($D28="پرداخت",$E28="چک"),$K28,0)) | Y28: =SUM($S28,$U28,$W28) | Z28: =SUM($T28,$V28,$X28) | AA28: =IF($D28="","",IF(ROUND($Y28-$Z28,0)=0,"✓","⚠")) | AB28: =IF($D28="","",IF($E28="نقد","X003",IF(OR($E28="چک",$E28="پاس چک",$E28="برگشت چک"),"X010",IF($I28="","X003","X011")))) | AC28: =IF($D28="","",IF($E28="انتقال داخلی",IF($N28="","X003",IFERROR(VLOOKUP($N28,BankTbl,4,0),$N28)),IF($I28="","X003",IFERROR(VLOOKUP($I28,BankTbl,4,0),$I28)))) | AD28: =IF($D28="","",IF($E28="پاس چک","X010",IF($E28="برگشت چک",IF($I28="","X003","X011"),IF($E28="انتقال داخلی",IF($I28="","X003","X011"),IF($D28="پرداخت",$F28,IF($E28="چک","X009",IF($I28="","X003","X011"))))))) | AE28: =IF($D28="","",IF($K28="",0,$K28)) | AF28: =IF($D28="","",IF($E28="پاس چک",IF($I28="","X003","X011"),IF($E28="برگشت چک","X010",IF($E28="انتقال داخلی",IF($N28="","X003","X011"),IF($D28="پرداخت",IF($E28="چک","X010",IF($I28="","X003","X011")),$F28))))) | AG28: =IF($D28="","",IF($K28="",0,$K28))
A29: =IF($B29="","",COUNTA($B$10:$B29)) | G29: =IF($F29="","",IFERROR(VLOOKUP($F29,AcctTbl,2,0),"کد ناشناخته")) | H29: =IF($F29="","",IFERROR(VLOOKUP($F29,AcctTbl,3,0),"")) | R29: =IF($D29="","",IF($AA29="⚠","⚠ ناتراز",IF(AND($D29="پرداخت",$E29="چک",$L29=""),"⚠ وضعیت چک","✓"))) | S29: =IF(OR($D29="",$K29=""),"",IF(AND($D29="پرداخت",$E29<>"انتقال داخلی",$E29<>"پاس چک",$E29<>"برگشت چک"),$K29,0)) | T29: =IF(OR($D29="",$K29=""),"",IF(OR(AND($D29="دریافت",$E29<>"انتقال داخلی"),$E29="برگشت چک"),$K29,0)) | U29: =IF(OR($D29="",$K29=""),"",IF(OR(AND($D29="دریافت",$E29<>"چک"),$E29="انتقال داخلی"),$K29,0)) | V29: =IF(OR($D29="",$K29=""),"",IF(OR(AND($D29="پرداخت",$E29<>"چک",$E29<>"برگشت چک"),$E29="انتقال داخلی"),$K29,0)) | W29: =IF(OR($D29="",$K29=""),"",IF(OR($E29="پاس چک",$E29="برگشت چک",AND($D29="دریافت",$E29="چک")),$K29,0)) | X29: =IF(OR($D29="",$K29=""),"",IF(AND($D29="پرداخت",$E29="چک"),$K29,0)) | Y29: =SUM($S29,$U29,$W29) | Z29: =SUM($T29,$V29,$X29) | AA29: =IF($D29="","",IF(ROUND($Y29-$Z29,0)=0,"✓","⚠")) | AB29: =IF($D29="","",IF($E29="نقد","X003",IF(OR($E29="چک",$E29="پاس چک",$E29="برگشت چک"),"X010",IF($I29="","X003","X011")))) | AC29: =IF($D29="","",IF($E29="انتقال داخلی",IF($N29="","X003",IFERROR(VLOOKUP($N29,BankTbl,4,0),$N29)),IF($I29="","X003",IFERROR(VLOOKUP($I29,BankTbl,4,0),$I29)))) | AD29: =IF($D29="","",IF($E29="پاس چک","X010",IF($E29="برگشت چک",IF($I29="","X003","X011"),IF($E29="انتقال داخلی",IF($I29="","X003","X011"),IF($D29="پرداخت",$F29,IF($E29="چک","X009",IF($I29="","X003","X011"))))))) | AE29: =IF($D29="","",IF($K29="",0,$K29)) | AF29: =IF($D29="","",IF($E29="پاس چک",IF($I29="","X003","X011"),IF($E29="برگشت چک","X010",IF($E29="انتقال داخلی",IF($N29="","X003","X011"),IF($D29="پرداخت",IF($E29="چک","X010",IF($I29="","X003","X011")),$F29))))) | AG29: =IF($D29="","",IF($K29="",0,$K29))
A30: =IF($B30="","",COUNTA($B$10:$B30)) | G30: =IF($F30="","",IFERROR(VLOOKUP($F30,AcctTbl,2,0),"کد ناشناخته")) | H30: =IF($F30="","",IFERROR(VLOOKUP($F30,AcctTbl,3,0),"")) | R30: =IF($D30="","",IF($AA30="⚠","⚠ ناتراز",IF(AND($D30="پرداخت",$E30="چک",$L30=""),"⚠ وضعیت چک","✓"))) | S30: =IF(OR($D30="",$K30=""),"",IF(AND($D30="پرداخت",$E30<>"انتقال داخلی",$E30<>"پاس چک",$E30<>"برگشت چک"),$K30,0)) | T30: =IF(OR($D30="",$K30=""),"",IF(OR(AND($D30="دریافت",$E30<>"انتقال داخلی"),$E30="برگشت چک"),$K30,0)) | U30: =IF(OR($D30="",$K30=""),"",IF(OR(AND($D30="دریافت",$E30<>"چک"),$E30="انتقال داخلی"),$K30,0)) | V30: =IF(OR($D30="",$K30=""),"",IF(OR(AND($D30="پرداخت",$E30<>"چک",$E30<>"برگشت چک"),$E30="انتقال داخلی"),$K30,0)) | W30: =IF(OR($D30="",$K30=""),"",IF(OR($E30="پاس چک",$E30="برگشت چک",AND($D30="دریافت",$E30="چک")),$K30,0)) | X30: =IF(OR($D30="",$K30=""),"",IF(AND($D30="پرداخت",$E30="چک"),$K30,0)) | Y30: =SUM($S30,$U30,$W30) | Z30: =SUM($T30,$V30,$X30) | AA30: =IF($D30="","",IF(ROUND($Y30-$Z30,0)=0,"✓","⚠")) | AB30: =IF($D30="","",IF($E30="نقد","X003",IF(OR($E30="چک",$E30="پاس چک",$E30="برگشت چک"),"X010",IF($I30="","X003","X011")))) | AC30: =IF($D30="","",IF($E30="انتقال داخلی",IF($N30="","X003",IFERROR(VLOOKUP($N30,BankTbl,4,0),$N30)),IF($I30="","X003",IFERROR(VLOOKUP($I30,BankTbl,4,0),$I30)))) | AD30: =IF($D30="","",IF($E30="پاس چک","X010",IF($E30="برگشت چک",IF($I30="","X003","X011"),IF($E30="انتقال داخلی",IF($I30="","X003","X011"),IF($D30="پرداخت",$F30,IF($E30="چک","X009",IF($I30="","X003","X011"))))))) | AE30: =IF($D30="","",IF($K30="",0,$K30)) | AF30: =IF($D30="","",IF($E30="پاس چک",IF($I30="","X003","X011"),IF($E30="برگشت چک","X010",IF($E30="انتقال داخلی",IF($N30="","X003","X011"),IF($D30="پرداخت",IF($E30="چک","X010",IF($I30="","X003","X011")),$F30))))) | AG30: =IF($D30="","",IF($K30="",0,$K30))
A31: =IF($B31="","",COUNTA($B$10:$B31)) | G31: =IF($F31="","",IFERROR(VLOOKUP($F31,AcctTbl,2,0),"کد ناشناخته")) | H31: =IF($F31="","",IFERROR(VLOOKUP($F31,AcctTbl,3,0),"")) | R31: =IF($D31="","",IF($AA31="⚠","⚠ ناتراز",IF(AND($D31="پرداخت",$E31="چک",$L31=""),"⚠ وضعیت چک","✓"))) | S31: =IF(OR($D31="",$K31=""),"",IF(AND($D31="پرداخت",$E31<>"انتقال داخلی",$E31<>"پاس چک",$E31<>"برگشت چک"),$K31,0)) | T31: =IF(OR($D31="",$K31=""),"",IF(OR(AND($D31="دریافت",$E31<>"انتقال داخلی"),$E31="برگشت چک"),$K31,0)) | U31: =IF(OR($D31="",$K31=""),"",IF(OR(AND($D31="دریافت",$E31<>"چک"),$E31="انتقال داخلی"),$K31,0)) | V31: =IF(OR($D31="",$K31=""),"",IF(OR(AND($D31="پرداخت",$E31<>"چک",$E31<>"برگشت چک"),$E31="انتقال داخلی"),$K31,0)) | W31: =IF(OR($D31="",$K31=""),"",IF(OR($E31="پاس چک",$E31="برگشت چک",AND($D31="دریافت",$E31="چک")),$K31,0)) | X31: =IF(OR($D31="",$K31=""),"",IF(AND($D31="پرداخت",$E31="چک"),$K31,0)) | Y31: =SUM($S31,$U31,$W31) | Z31: =SUM($T31,$V31,$X31) | AA31: =IF($D31="","",IF(ROUND($Y31-$Z31,0)=0,"✓","⚠")) | AB31: =IF($D31="","",IF($E31="نقد","X003",IF(OR($E31="چک",$E31="پاس چک",$E31="برگشت چک"),"X010",IF($I31="","X003","X011")))) | AC31: =IF($D31="","",IF($E31="انتقال داخلی",IF($N31="","X003",IFERROR(VLOOKUP($N31,BankTbl,4,0),$N31)),IF($I31="","X003",IFERROR(VLOOKUP($I31,BankTbl,4,0),$I31)))) | AD31: =IF($D31="","",IF($E31="پاس چک","X010",IF($E31="برگشت چک",IF($I31="","X003","X011"),IF($E31="انتقال داخلی",IF($I31="","X003","X011"),IF($D31="پرداخت",$F31,IF($E31="چک","X009",IF($I31="","X003","X011"))))))) | AE31: =IF($D31="","",IF($K31="",0,$K31)) | AF31: =IF($D31="","",IF($E31="پاس چک",IF($I31="","X003","X011"),IF($E31="برگشت چک","X010",IF($E31="انتقال داخلی",IF($N31="","X003","X011"),IF($D31="پرداخت",IF($E31="چک","X010",IF($I31="","X003","X011")),$F31))))) | AG31: =IF($D31="","",IF($K31="",0,$K31))
A32: =IF($B32="","",COUNTA($B$10:$B32)) | G32: =IF($F32="","",IFERROR(VLOOKUP($F32,AcctTbl,2,0),"کد ناشناخته")) | H32: =IF($F32="","",IFERROR(VLOOKUP($F32,AcctTbl,3,0),"")) | R32: =IF($D32="","",IF($AA32="⚠","⚠ ناتراز",IF(AND($D32="پرداخت",$E32="چک",$L32=""),"⚠ وضعیت چک","✓"))) | S32: =IF(OR($D32="",$K32=""),"",IF(AND($D32="پرداخت",$E32<>"انتقال داخلی",$E32<>"پاس چک",$E32<>"برگشت چک"),$K32,0)) | T32: =IF(OR($D32="",$K32=""),"",IF(OR(AND($D32="دریافت",$E32<>"انتقال داخلی"),$E32="برگشت چک"),$K32,0)) | U32: =IF(OR($D32="",$K32=""),"",IF(OR(AND($D32="دریافت",$E32<>"چک"),$E32="انتقال داخلی"),$K32,0)) | V32: =IF(OR($D32="",$K32=""),"",IF(OR(AND($D32="پرداخت",$E32<>"چک",$E32<>"برگشت چک"),$E32="انتقال داخلی"),$K32,0)) | W32: =IF(OR($D32="",$K32=""),"",IF(OR($E32="پاس چک",$E32="برگشت چک",AND($D32="دریافت",$E32="چک")),$K32,0)) | X32: =IF(OR($D32="",$K32=""),"",IF(AND($D32="پرداخت",$E32="چک"),$K32,0)) | Y32: =SUM($S32,$U32,$W32) | Z32: =SUM($T32,$V32,$X32) | AA32: =IF($D32="","",IF(ROUND($Y32-$Z32,0)=0,"✓","⚠")) | AB32: =IF($D32="","",IF($E32="نقد","X003",IF(OR($E32="چک",$E32="پاس چک",$E32="برگشت چک"),"X010",IF($I32="","X003","X011")))) | AC32: =IF($D32="","",IF($E32="انتقال داخلی",IF($N32="","X003",IFERROR(VLOOKUP($N32,BankTbl,4,0),$N32)),IF($I32="","X003",IFERROR(VLOOKUP($I32,BankTbl,4,0),$I32)))) | AD32: =IF($D32="","",IF($E32="پاس چک","X010",IF($E32="برگشت چک",IF($I32="","X003","X011"),IF($E32="انتقال داخلی",IF($I32="","X003","X011"),IF($D32="پرداخت",$F32,IF($E32="چک","X009",IF($I32="","X003","X011"))))))) | AE32: =IF($D32="","",IF($K32="",0,$K32)) | AF32: =IF($D32="","",IF($E32="پاس چک",IF($I32="","X003","X011"),IF($E32="برگشت چک","X010",IF($E32="انتقال داخلی",IF($N32="","X003","X011"),IF($D32="پرداخت",IF($E32="چک","X010",IF($I32="","X003","X011")),$F32))))) | AG32: =IF($D32="","",IF($K32="",0,$K32))
A33: =IF($B33="","",COUNTA($B$10:$B33)) | G33: =IF($F33="","",IFERROR(VLOOKUP($F33,AcctTbl,2,0),"کد ناشناخته")) | H33: =IF($F33="","",IFERROR(VLOOKUP($F33,AcctTbl,3,0),"")) | R33: =IF($D33="","",IF($AA33="⚠","⚠ ناتراز",IF(AND($D33="پرداخت",$E33="چک",$L33=""),"⚠ وضعیت چک","✓"))) | S33: =IF(OR($D33="",$K33=""),"",IF(AND($D33="پرداخت",$E33<>"انتقال داخلی",$E33<>"پاس چک",$E33<>"برگشت چک"),$K33,0)) | T33: =IF(OR($D33="",$K33=""),"",IF(OR(AND($D33="دریافت",$E33<>"انتقال داخلی"),$E33="برگشت چک"),$K33,0)) | U33: =IF(OR($D33="",$K33=""),"",IF(OR(AND($D33="دریافت",$E33<>"چک"),$E33="انتقال داخلی"),$K33,0)) | V33: =IF(OR($D33="",$K33=""),"",IF(OR(AND($D33="پرداخت",$E33<>"چک",$E33<>"برگشت چک"),$E33="انتقال داخلی"),$K33,0)) | W33: =IF(OR($D33="",$K33=""),"",IF(OR($E33="پاس چک",$E33="برگشت چک",AND($D33="دریافت",$E33="چک")),$K33,0)) | X33: =IF(OR($D33="",$K33=""),"",IF(AND($D33="پرداخت",$E33="چک"),$K33,0)) | Y33: =SUM($S33,$U33,$W33) | Z33: =SUM($T33,$V33,$X33) | AA33: =IF($D33="","",IF(ROUND($Y33-$Z33,0)=0,"✓","⚠")) | AB33: =IF($D33="","",IF($E33="نقد","X003",IF(OR($E33="چک",$E33="پاس چک",$E33="برگشت چک"),"X010",IF($I33="","X003","X011")))) | AC33: =IF($D33="","",IF($E33="انتقال داخلی",IF($N33="","X003",IFERROR(VLOOKUP($N33,BankTbl,4,0),$N33)),IF($I33="","X003",IFERROR(VLOOKUP($I33,BankTbl,4,0),$I33)))) | AD33: =IF($D33="","",IF($E33="پاس چک","X010",IF($E33="برگشت چک",IF($I33="","X003","X011"),IF($E33="انتقال داخلی",IF($I33="","X003","X011"),IF($D33="پرداخت",$F33,IF($E33="چک","X009",IF($I33="","X003","X011"))))))) | AE33: =IF($D33="","",IF($K33="",0,$K33)) | AF33: =IF($D33="","",IF($E33="پاس چک",IF($I33="","X003","X011"),IF($E33="برگشت چک","X010",IF($E33="انتقال داخلی",IF($N33="","X003","X011"),IF($D33="پرداخت",IF($E33="چک","X010",IF($I33="","X003","X011")),$F33))))) | AG33: =IF($D33="","",IF($K33="",0,$K33))
... A159: =IF($B159="","",COUNTA($B$10:$B159)) | G159: =IF($F159="","",IFERROR(VLOOKUP($F159,AcctTbl,2,0),"کد ناشناخته")) | H159: =IF($F159="","",IFERROR(VLOOKUP($F159,AcctTbl,3,0),"")) | R159: =IF($D159="","",IF($AA159="⚠","⚠ ناتراز",IF(AND($D159="پرداخت",$E159="چک",$L159=""),"⚠ وضعیت چک","✓"))) | S159: =IF(OR($D159="",$K159=""),"",IF(AND($D159="پرداخت",$E159<>"انتقال داخلی",$E159<>"پاس چک",$E159<>"برگشت چک"),$K159,0)) | T159: =IF(OR($D159="",$K159=""),"",IF(OR(AND($D159="دریافت",$E159<>"انتقال داخلی"),$E159="برگشت چک"),$K159,0)) | U159: =IF(OR($D159="",$K159=""),"",IF(OR(AND($D159="دریافت",$E159<>"چک"),$E159="انتقال داخلی"),$K159,0)) | V159: =IF(OR($D159="",$K159=""),"",IF(OR(AND($D159="پرداخت",$E159<>"چک",$E159<>"برگشت چک"),$E159="انتقال داخلی"),$K159,0)) | W159: =IF(OR($D159="",$K159=""),"",IF(OR($E159="پاس چک",$E159="برگشت چک",AND($D159="دریافت",$E159="چک")),$K159,0)) | X159: =IF(OR($D159="",$K159=""),"",IF(AND($D159="پرداخت",$E159="چک"),$K159,0)) | Y159: =SUM($S159,$U159,$W159) | Z159: =SUM($T159,$V159,$X159) | AA159: =IF($D159="","",IF(ROUND($Y159-$Z159,0)=0,"✓","⚠")) | AB159: =IF($D159="","",IF($E159="نقد","X003",IF(OR($E159="چک",$E159="پاس چک",$E159="برگشت چک"),"X010",IF($I159="","X003","X011")))) | AC159: =IF($D159="","",IF($E159="انتقال داخلی",IF($N159="","X003",IFERROR(VLOOKUP($N159,BankTbl,4,0),$N159)),IF($I159="","X003",IFERROR(VLOOKUP($I159,BankTbl,4,0),$I159)))) | AD159: =IF($D159="","",IF($E159="پاس چک","X010",IF($E159="برگشت چک",IF($I159="","X003","X011"),IF($E159="انتقال داخلی",IF($I159="","X003","X011"),IF($D159="پرداخت",$F159,IF($E159="چک","X009",IF($I159="","X003","X011"))))))) | AE159: =IF($D159="","",IF($K159="",0,$K159)) | AF159: =IF($D159="","",IF($E159="پاس چک",IF($I159="","X003","X011"),IF($E159="برگشت چک","X010",IF($E159="انتقال داخلی",IF($N159="","X003","X011"),IF($D159="پرداخت",IF($E159="چک","X010",IF($I159="","X003","X011")),$F159))))) | AG159: =IF($D159="","",IF($K159="",0,$K159))

Sheet Book
A1: مازندشت — سورتینگ و بسته‌بندی مرکبات | M1: MAZANDASHT · CITRUS SORTING & PACKING
A2: دفتر روزنامه — همه گردش‌ها با طرف مقابل
A3: هر سند دو سطر دارد: حساب طرف و حساب مقابل؛ به همین دلیل جمع بدهکار و بستانکار همیشه برابر است
A4: راهنما | B4: ورود دستی | C4: خودکار | D4: ورود | E4: خروج | F4: هشدار | G4: ستون‌های زرد = ورود شما | ستون‌های خاکستری = محاسبه خودکار | روی سرستون‌ها بایستید تا راهنما باز شود
A5: تعداد سطر | E5: جمع بدهکار | I5: جمع بستانکار | M5: اختلاف | Q5: وضعیت
A6: =COUNTA($A$10:$A$1808) | E6: =SUM($L$10:$L$1808) | I6: =SUM($M$10:$M$1808) | M6: =SUM($L$10:$L$1808)-SUM($M$10:$M$1808) | Q6: =IF(ROUND(SUM($L$10:$L$1808)-SUM($M$10:$M$1808),0)=0,"✓ تراز","⚠ ناتراز")
A7: شناسه سند | D7: حساب و شرح | G7: بار و مبلغ | L7: بدهکار / بستانکار | O7: گروه و پوز
A8: تاریخ | B8: سند | C8: منبع | D8: کد حساب | E8: شرح | F8: محصول | G8: تعداد سبد | H8: وزن باسکول | I8: وزن خالص | J8: فی | K8: مبلغ | L8: بدهکار | M8: بستانکار | N8: عملیات / نوع | O8: گروه | P8: بانک مرجع
A9: Date | B9: Doc | C9: Source | D9: Account | E9: Description | F9: Product | G9: Baskets | H9: Scale | I9: Net | J9: Price | K9: Amount | L9: Debit | M9: Credit | N9: Type | O9: Group | P9: Bank ref.
A10: =IF(OR(Scale!$U10="",Scale!$U10=0),"",Scale!$B10) | B10: =IF(OR(Scale!$U10="",Scale!$U10=0),"",Scale!$D10) | C10: =IF(OR(Scale!$U10="",Scale!$U10=0),"","باسکول") | D10: =IF(OR(Scale!$U10="",Scale!$U10=0),"",Scale!$U10) | E10: =IF(OR(Scale!$U10="",Scale!$U10=0),"",Scale!$T10) | F10: =IF(OR(Scale!$U10="",Scale!$U10=0),"",Scale!$J10) | G10: =IF(OR(Scale!$U10="",Scale!$U10=0),"",Scale!$M10) | H10: =IF(OR(Scale!$U10="",Scale!$U10=0),"",Scale!$L10) | I10: =IF(OR(Scale!$U10="",Scale!$U10=0),"",Scale!$N10) | J10: =IF(OR(Scale!$U10="",Scale!$U10=0),"",Scale!$O10) | K10: =IF(OR(Scale!$U10="",Scale!$U10=0),"",IF(Scale!$V10="",0,Scale!$V10)+IF(Scale!$W10="",0,Scale!$W10)) | L10: =IF(OR(Scale!$U10="",Scale!$U10=0),"",Scale!$V10) | M10: =IF(OR(Scale!$U10="",Scale!$U10=0),"",Scale!$W10) | N10: =IF(OR(Scale!$U10="",Scale!$U10=0),"",Scale!$E10) | O10: =IF(OR(Scale!$U10="",Scale!$U10=0),"",IFERROR(VLOOKUP(Scale!$U10,AcctTbl,3,0),"")) | P10: =IF(Scale!$U10<>"X011","","BN02")
A11: =IF(OR(Scale!$X10="",Scale!$X10=0),"",Scale!$B10) | B11: =IF(OR(Scale!$X10="",Scale!$X10=0),"",Scale!$D10) | C11: =IF(OR(Scale!$X10="",Scale!$X10=0),"","باسکول") | D11: =IF(OR(Scale!$X10="",Scale!$X10=0),"",Scale!$X10) | E11: =IF(OR(Scale!$X10="",Scale!$X10=0),"",IF(Scale!$X10="","","مقابل: "&Scale!$E10)) | K11: =IF(OR(Scale!$X10="",Scale!$X10=0),"",IF(Scale!$Y10="",0,Scale!$Y10)+IF(Scale!$Z10="",0,Scale!$Z10)) | L11: =IF(OR(Scale!$X10="",Scale!$X10=0),"",Scale!$Y10) | M11: =IF(OR(Scale!$X10="",Scale!$X10=0),"",Scale!$Z10) | N11: =IF(OR(Scale!$X10="",Scale!$X10=0),"","مقابل") | O11: =IF(OR(Scale!$X10="",Scale!$X10=0),"",IFERROR(VLOOKUP(Scale!$X10,AcctTbl,3,0),"")) | P11: =IF(Scale!$X10<>"X011","","BN02")
A12: =IF(OR(Scale!$AA10="",Scale!$AA10=0),"",Scale!$B10) | B12: =IF(OR(Scale!$AA10="",Scale!$AA10=0),"",Scale!$D10) | C12: =IF(OR(Scale!$AA10="",Scale!$AA10=0),"","باسکول") | D12: =IF(OR(Scale!$AA10="",Scale!$AA10=0),"",Scale!$AA10) | E12: =IF(OR(Scale!$AA10="",Scale!$AA10=0),"",IF(Scale!$AA10="","","پوز باسکول — "&Scale!$E10)) | K12: =IF(OR(Scale!$AA10="",Scale!$AA10=0),"",IF(Scale!$AB10="",0,Scale!$AB10)+IF(Scale!$AC10="",0,Scale!$AC10)) | L12: =IF(OR(Scale!$AA10="",Scale!$AA10=0),"",Scale!$AB10) | M12: =IF(OR(Scale!$AA10="",Scale!$AA10=0),"",Scale!$AC10) | N12: =IF(OR(Scale!$AA10="",Scale!$AA10=0),"","پوز") | O12: =IF(OR(Scale!$AA10="",Scale!$AA10=0),"",IFERROR(VLOOKUP(Scale!$AA10,AcctTbl,3,0),"")) | P12: =IF(Scale!$AA10<>"X011","","BN02")
A13: =IF(OR(Scale!$AD10="",Scale!$AD10=0),"",Scale!$B10) | B13: =IF(OR(Scale!$AD10="",Scale!$AD10=0),"",Scale!$D10) | C13: =IF(OR(Scale!$AD10="",Scale!$AD10=0),"","باسکول") | D13: =IF(OR(Scale!$AD10="",Scale!$AD10=0),"",Scale!$AD10) | E13: =IF(OR(Scale!$AD10="",Scale!$AD10=0),"",IF(Scale!$AD10="","","مقابل پوز — "&Scale!$E10)) | K13: =IF(OR(Scale!$AD10="",Scale!$AD10=0),"",IF(Scale!$AE10="",0,Scale!$AE10)+IF(Scale!$AF10="",0,Scale!$AF10)) | L13: =IF(OR(Scale!$AD10="",Scale!$AD10=0),"",Scale!$AE10) | M13: =IF(OR(Scale!$AD10="",Scale!$AD10=0),"",Scale!$AF10) | N13: =IF(OR(Scale!$AD10="",Scale!$AD10=0),"","مقابل پوز") | O13: =IF(OR(Scale!$AD10="",Scale!$AD10=0),"",IFERROR(VLOOKUP(Scale!$AD10,AcctTbl,3,0),"")) | P13: =IF(Scale!$AD10<>"X011","","BN02")
A14: =IF(OR(Scale!$U11="",Scale!$U11=0),"",Scale!$B11) | B14: =IF(OR(Scale!$U11="",Scale!$U11=0),"",Scale!$D11) | C14: =IF(OR(Scale!$U11="",Scale!$U11=0),"","باسکول") | D14: =IF(OR(Scale!$U11="",Scale!$U11=0),"",Scale!$U11) | E14: =IF(OR(Scale!$U11="",Scale!$U11=0),"",Scale!$T11) | F14: =IF(OR(Scale!$U11="",Scale!$U11=0),"",Scale!$J11) | G14: =IF(OR(Scale!$U11="",Scale!$U11=0),"",Scale!$M11) | H14: =IF(OR(Scale!$U11="",Scale!$U11=0),"",Scale!$L11) | I14: =IF(OR(Scale!$U11="",Scale!$U11=0),"",Scale!$N11) | J14: =IF(OR(Scale!$U11="",Scale!$U11=0),"",Scale!$O11) | K14: =IF(OR(Scale!$U11="",Scale!$U11=0),"",IF(Scale!$V11="",0,Scale!$V11)+IF(Scale!$W11="",0,Scale!$W11)) | L14: =IF(OR(Scale!$U11="",Scale!$U11=0),"",Scale!$V11) | M14: =IF(OR(Scale!$U11="",Scale!$U11=0),"",Scale!$W11) | N14: =IF(OR(Scale!$U11="",Scale!$U11=0),"",Scale!$E11) | O14: =IF(OR(Scale!$U11="",Scale!$U11=0),"",IFERROR(VLOOKUP(Scale!$U11,AcctTbl,3,0),"")) | P14: =IF(Scale!$U11<>"X011","","BN02")
A15: =IF(OR(Scale!$X11="",Scale!$X11=0),"",Scale!$B11) | B15: =IF(OR(Scale!$X11="",Scale!$X11=0),"",Scale!$D11) | C15: =IF(OR(Scale!$X11="",Scale!$X11=0),"","باسکول") | D15: =IF(OR(Scale!$X11="",Scale!$X11=0),"",Scale!$X11) | E15: =IF(OR(Scale!$X11="",Scale!$X11=0),"",IF(Scale!$X11="","","مقابل: "&Scale!$E11)) | K15: =IF(OR(Scale!$X11="",Scale!$X11=0),"",IF(Scale!$Y11="",0,Scale!$Y11)+IF(Scale!$Z11="",0,Scale!$Z11)) | L15: =IF(OR(Scale!$X11="",Scale!$X11=0),"",Scale!$Y11) | M15: =IF(OR(Scale!$X11="",Scale!$X11=0),"",Scale!$Z11) | N15: =IF(OR(Scale!$X11="",Scale!$X11=0),"","مقابل") | O15: =IF(OR(Scale!$X11="",Scale!$X11=0),"",IFERROR(VLOOKUP(Scale!$X11,AcctTbl,3,0),"")) | P15: =IF(Scale!$X11<>"X011","","BN02")
A16: =IF(OR(Scale!$AA11="",Scale!$AA11=0),"",Scale!$B11) | B16: =IF(OR(Scale!$AA11="",Scale!$AA11=0),"",Scale!$D11) | C16: =IF(OR(Scale!$AA11="",Scale!$AA11=0),"","باسکول") | D16: =IF(OR(Scale!$AA11="",Scale!$AA11=0),"",Scale!$AA11) | E16: =IF(OR(Scale!$AA11="",Scale!$AA11=0),"",IF(Scale!$AA11="","","پوز باسکول — "&Scale!$E11)) | K16: =IF(OR(Scale!$AA11="",Scale!$AA11=0),"",IF(Scale!$AB11="",0,Scale!$AB11)+IF(Scale!$AC11="",0,Scale!$AC11)) | L16: =IF(OR(Scale!$AA11="",Scale!$AA11=0),"",Scale!$AB11) | M16: =IF(OR(Scale!$AA11="",Scale!$AA11=0),"",Scale!$AC11) | N16: =IF(OR(Scale!$AA11="",Scale!$AA11=0),"","پوز") | O16: =IF(OR(Scale!$AA11="",Scale!$AA11=0),"",IFERROR(VLOOKUP(Scale!$AA11,AcctTbl,3,0),"")) | P16: =IF(Scale!$AA11<>"X011","","BN02")
A17: =IF(OR(Scale!$AD11="",Scale!$AD11=0),"",Scale!$B11) | B17: =IF(OR(Scale!$AD11="",Scale!$AD11=0),"",Scale!$D11) | C17: =IF(OR(Scale!$AD11="",Scale!$AD11=0),"","باسکول") | D17: =IF(OR(Scale!$AD11="",Scale!$AD11=0),"",Scale!$AD11) | E17: =IF(OR(Scale!$AD11="",Scale!$AD11=0),"",IF(Scale!$AD11="","","مقابل پوز — "&Scale!$E11)) | K17: =IF(OR(Scale!$AD11="",Scale!$AD11=0),"",IF(Scale!$AE11="",0,Scale!$AE11)+IF(Scale!$AF11="",0,Scale!$AF11)) | L17: =IF(OR(Scale!$AD11="",Scale!$AD11=0),"",Scale!$AE11) | M17: =IF(OR(Scale!$AD11="",Scale!$AD11=0),"",Scale!$AF11) | N17: =IF(OR(Scale!$AD11="",Scale!$AD11=0),"","مقابل پوز") | O17: =IF(OR(Scale!$AD11="",Scale!$AD11=0),"",IFERROR(VLOOKUP(Scale!$AD11,AcctTbl,3,0),"")) | P17: =IF(Scale!$AD11<>"X011","","BN02")
A18: =IF(OR(Scale!$U12="",Scale!$U12=0),"",Scale!$B12) | B18: =IF(OR(Scale!$U12="",Scale!$U12=0),"",Scale!$D12) | C18: =IF(OR(Scale!$U12="",Scale!$U12=0),"","باسکول") | D18: =IF(OR(Scale!$U12="",Scale!$U12=0),"",Scale!$U12) | E18: =IF(OR(Scale!$U12="",Scale!$U12=0),"",Scale!$T12) | F18: =IF(OR(Scale!$U12="",Scale!$U12=0),"",Scale!$J12) | G18: =IF(OR(Scale!$U12="",Scale!$U12=0),"",Scale!$M12) | H18: =IF(OR(Scale!$U12="",Scale!$U12=0),"",Scale!$L12) | I18: =IF(OR(Scale!$U12="",Scale!$U12=0),"",Scale!$N12) | J18: =IF(OR(Scale!$U12="",Scale!$U12=0),"",Scale!$O12) | K18: =IF(OR(Scale!$U12="",Scale!$U12=0),"",IF(Scale!$V12="",0,Scale!$V12)+IF(Scale!$W12="",0,Scale!$W12)) | L18: =IF(OR(Scale!$U12="",Scale!$U12=0),"",Scale!$V12) | M18: =IF(OR(Scale!$U12="",Scale!$U12=0),"",Scale!$W12) | N18: =IF(OR(Scale!$U12="",Scale!$U12=0),"",Scale!$E12) | O18: =IF(OR(Scale!$U12="",Scale!$U12=0),"",IFERROR(VLOOKUP(Scale!$U12,AcctTbl,3,0),"")) | P18: =IF(Scale!$U12<>"X011","","BN02")
A19: =IF(OR(Scale!$X12="",Scale!$X12=0),"",Scale!$B12) | B19: =IF(OR(Scale!$X12="",Scale!$X12=0),"",Scale!$D12) | C19: =IF(OR(Scale!$X12="",Scale!$X12=0),"","باسکول") | D19: =IF(OR(Scale!$X12="",Scale!$X12=0),"",Scale!$X12) | E19: =IF(OR(Scale!$X12="",Scale!$X12=0),"",IF(Scale!$X12="","","مقابل: "&Scale!$E12)) | K19: =IF(OR(Scale!$X12="",Scale!$X12=0),"",IF(Scale!$Y12="",0,Scale!$Y12)+IF(Scale!$Z12="",0,Scale!$Z12)) | L19: =IF(OR(Scale!$X12="",Scale!$X12=0),"",Scale!$Y12) | M19: =IF(OR(Scale!$X12="",Scale!$X12=0),"",Scale!$Z12) | N19: =IF(OR(Scale!$X12="",Scale!$X12=0),"","مقابل") | O19: =IF(OR(Scale!$X12="",Scale!$X12=0),"",IFERROR(VLOOKUP(Scale!$X12,AcctTbl,3,0),"")) | P19: =IF(Scale!$X12<>"X011","","BN02")
A20: =IF(OR(Scale!$AA12="",Scale!$AA12=0),"",Scale!$B12) | B20: =IF(OR(Scale!$AA12="",Scale!$AA12=0),"",Scale!$D12) | C20: =IF(OR(Scale!$AA12="",Scale!$AA12=0),"","باسکول") | D20: =IF(OR(Scale!$AA12="",Scale!$AA12=0),"",Scale!$AA12) | E20: =IF(OR(Scale!$AA12="",Scale!$AA12=0),"",IF(Scale!$AA12="","","پوز باسکول — "&Scale!$E12)) | K20: =IF(OR(Scale!$AA12="",Scale!$AA12=0),"",IF(Scale!$AB12="",0,Scale!$AB12)+IF(Scale!$AC12="",0,Scale!$AC12)) | L20: =IF(OR(Scale!$AA12="",Scale!$AA12=0),"",Scale!$AB12) | M20: =IF(OR(Scale!$AA12="",Scale!$AA12=0),"",Scale!$AC12) | N20: =IF(OR(Scale!$AA12="",Scale!$AA12=0),"","پوز") | O20: =IF(OR(Scale!$AA12="",Scale!$AA12=0),"",IFERROR(VLOOKUP(Scale!$AA12,AcctTbl,3,0),"")) | P20: =IF(Scale!$AA12<>"X011","","BN02")
A21: =IF(OR(Scale!$AD12="",Scale!$AD12=0),"",Scale!$B12) | B21: =IF(OR(Scale!$AD12="",Scale!$AD12=0),"",Scale!$D12) | C21: =IF(OR(Scale!$AD12="",Scale!$AD12=0),"","باسکول") | D21: =IF(OR(Scale!$AD12="",Scale!$AD12=0),"",Scale!$AD12) | E21: =IF(OR(Scale!$AD12="",Scale!$AD12=0),"",IF(Scale!$AD12="","","مقابل پوز — "&Scale!$E12)) | K21: =IF(OR(Scale!$AD12="",Scale!$AD12=0),"",IF(Scale!$AE12="",0,Scale!$AE12)+IF(Scale!$AF12="",0,Scale!$AF12)) | L21: =IF(OR(Scale!$AD12="",Scale!$AD12=0),"",Scale!$AE12) | M21: =IF(OR(Scale!$AD12="",Scale!$AD12=0),"",Scale!$AF12) | N21: =IF(OR(Scale!$AD12="",Scale!$AD12=0),"","مقابل پوز") | O21: =IF(OR(Scale!$AD12="",Scale!$AD12=0),"",IFERROR(VLOOKUP(Scale!$AD12,AcctTbl,3,0),"")) | P21: =IF(Scale!$AD12<>"X011","","BN02")
A22: =IF(OR(Scale!$U13="",Scale!$U13=0),"",Scale!$B13) | B22: =IF(OR(Scale!$U13="",Scale!$U13=0),"",Scale!$D13) | C22: =IF(OR(Scale!$U13="",Scale!$U13=0),"","باسکول") | D22: =IF(OR(Scale!$U13="",Scale!$U13=0),"",Scale!$U13) | E22: =IF(OR(Scale!$U13="",Scale!$U13=0),"",Scale!$T13) | F22: =IF(OR(Scale!$U13="",Scale!$U13=0),"",Scale!$J13) | G22: =IF(OR(Scale!$U13="",Scale!$U13=0),"",Scale!$M13) | H22: =IF(OR(Scale!$U13="",Scale!$U13=0),"",Scale!$L13) | I22: =IF(OR(Scale!$U13="",Scale!$U13=0),"",Scale!$N13) | J22: =IF(OR(Scale!$U13="",Scale!$U13=0),"",Scale!$O13) | K22: =IF(OR(Scale!$U13="",Scale!$U13=0),"",IF(Scale!$V13="",0,Scale!$V13)+IF(Scale!$W13="",0,Scale!$W13)) | L22: =IF(OR(Scale!$U13="",Scale!$U13=0),"",Scale!$V13) | M22: =IF(OR(Scale!$U13="",Scale!$U13=0),"",Scale!$W13) | N22: =IF(OR(Scale!$U13="",Scale!$U13=0),"",Scale!$E13) | O22: =IF(OR(Scale!$U13="",Scale!$U13=0),"",IFERROR(VLOOKUP(Scale!$U13,AcctTbl,3,0),"")) | P22: =IF(Scale!$U13<>"X011","","BN02")
A23: =IF(OR(Scale!$X13="",Scale!$X13=0),"",Scale!$B13) | B23: =IF(OR(Scale!$X13="",Scale!$X13=0),"",Scale!$D13) | C23: =IF(OR(Scale!$X13="",Scale!$X13=0),"","باسکول") | D23: =IF(OR(Scale!$X13="",Scale!$X13=0),"",Scale!$X13) | E23: =IF(OR(Scale!$X13="",Scale!$X13=0),"",IF(Scale!$X13="","","مقابل: "&Scale!$E13)) | K23: =IF(OR(Scale!$X13="",Scale!$X13=0),"",IF(Scale!$Y13="",0,Scale!$Y13)+IF(Scale!$Z13="",0,Scale!$Z13)) | L23: =IF(OR(Scale!$X13="",Scale!$X13=0),"",Scale!$Y13) | M23: =IF(OR(Scale!$X13="",Scale!$X13=0),"",Scale!$Z13) | N23: =IF(OR(Scale!$X13="",Scale!$X13=0),"","مقابل") | O23: =IF(OR(Scale!$X13="",Scale!$X13=0),"",IFERROR(VLOOKUP(Scale!$X13,AcctTbl,3,0),"")) | P23: =IF(Scale!$X13<>"X011","","BN02")
A24: =IF(OR(Scale!$AA13="",Scale!$AA13=0),"",Scale!$B13) | B24: =IF(OR(Scale!$AA13="",Scale!$AA13=0),"",Scale!$D13) | C24: =IF(OR(Scale!$AA13="",Scale!$AA13=0),"","باسکول") | D24: =IF(OR(Scale!$AA13="",Scale!$AA13=0),"",Scale!$AA13) | E24: =IF(OR(Scale!$AA13="",Scale!$AA13=0),"",IF(Scale!$AA13="","","پوز باسکول — "&Scale!$E13)) | K24: =IF(OR(Scale!$AA13="",Scale!$AA13=0),"",IF(Scale!$AB13="",0,Scale!$AB13)+IF(Scale!$AC13="",0,Scale!$AC13)) | L24: =IF(OR(Scale!$AA13="",Scale!$AA13=0),"",Scale!$AB13) | M24: =IF(OR(Scale!$AA13="",Scale!$AA13=0),"",Scale!$AC13) | N24: =IF(OR(Scale!$AA13="",Scale!$AA13=0),"","پوز") | O24: =IF(OR(Scale!$AA13="",Scale!$AA13=0),"",IFERROR(VLOOKUP(Scale!$AA13,AcctTbl,3,0),"")) | P24: =IF(Scale!$AA13<>"X011","","BN02")
A25: =IF(OR(Scale!$AD13="",Scale!$AD13=0),"",Scale!$B13) | B25: =IF(OR(Scale!$AD13="",Scale!$AD13=0),"",Scale!$D13) | C25: =IF(OR(Scale!$AD13="",Scale!$AD13=0),"","باسکول") | D25: =IF(OR(Scale!$AD13="",Scale!$AD13=0),"",Scale!$AD13) | E25: =IF(OR(Scale!$AD13="",Scale!$AD13=0),"",IF(Scale!$AD13="","","مقابل پوز — "&Scale!$E13)) | K25: =IF(OR(Scale!$AD13="",Scale!$AD13=0),"",IF(Scale!$AE13="",0,Scale!$AE13)+IF(Scale!$AF13="",0,Scale!$AF13)) | L25: =IF(OR(Scale!$AD13="",Scale!$AD13=0),"",Scale!$AE13) | M25: =IF(OR(Scale!$AD13="",Scale!$AD13=0),"",Scale!$AF13) | N25: =IF(OR(Scale!$AD13="",Scale!$AD13=0),"","مقابل پوز") | O25: =IF(OR(Scale!$AD13="",Scale!$AD13=0),"",IFERROR(VLOOKUP(Scale!$AD13,AcctTbl,3,0),"")) | P25: =IF(Scale!$AD13<>"X011","","BN02")
A26: =IF(OR(Scale!$U14="",Scale!$U14=0),"",Scale!$B14) | B26: =IF(OR(Scale!$U14="",Scale!$U14=0),"",Scale!$D14) | C26: =IF(OR(Scale!$U14="",Scale!$U14=0),"","باسکول") | D26: =IF(OR(Scale!$U14="",Scale!$U14=0),"",Scale!$U14) | E26: =IF(OR(Scale!$U14="",Scale!$U14=0),"",Scale!$T14) | F26: =IF(OR(Scale!$U14="",Scale!$U14=0),"",Scale!$J14) | G26: =IF(OR(Scale!$U14="",Scale!$U14=0),"",Scale!$M14) | H26: =IF(OR(Scale!$U14="",Scale!$U14=0),"",Scale!$L14) | I26: =IF(OR(Scale!$U14="",Scale!$U14=0),"",Scale!$N14) | J26: =IF(OR(Scale!$U14="",Scale!$U14=0),"",Scale!$O14) | K26: =IF(OR(Scale!$U14="",Scale!$U14=0),"",IF(Scale!$V14="",0,Scale!$V14)+IF(Scale!$W14="",0,Scale!$W14)) | L26: =IF(OR(Scale!$U14="",Scale!$U14=0),"",Scale!$V14) | M26: =IF(OR(Scale!$U14="",Scale!$U14=0),"",Scale!$W14) | N26: =IF(OR(Scale!$U14="",Scale!$U14=0),"",Scale!$E14) | O26: =IF(OR(Scale!$U14="",Scale!$U14=0),"",IFERROR(VLOOKUP(Scale!$U14,AcctTbl,3,0),"")) | P26: =IF(Scale!$U14<>"X011","","BN02")
A27: =IF(OR(Scale!$X14="",Scale!$X14=0),"",Scale!$B14) | B27: =IF(OR(Scale!$X14="",Scale!$X14=0),"",Scale!$D14) | C27: =IF(OR(Scale!$X14="",Scale!$X14=0),"","باسکول") | D27: =IF(OR(Scale!$X14="",Scale!$X14=0),"",Scale!$X14) | E27: =IF(OR(Scale!$X14="",Scale!$X14=0),"",IF(Scale!$X14="","","مقابل: "&Scale!$E14)) | K27: =IF(OR(Scale!$X14="",Scale!$X14=0),"",IF(Scale!$Y14="",0,Scale!$Y14)+IF(Scale!$Z14="",0,Scale!$Z14)) | L27: =IF(OR(Scale!$X14="",Scale!$X14=0),"",Scale!$Y14) | M27: =IF(OR(Scale!$X14="",Scale!$X14=0),"",Scale!$Z14) | N27: =IF(OR(Scale!$X14="",Scale!$X14=0),"","مقابل") | O27: =IF(OR(Scale!$X14="",Scale!$X14=0),"",IFERROR(VLOOKUP(Scale!$X14,AcctTbl,3,0),"")) | P27: =IF(Scale!$X14<>"X011","","BN02")
A28: =IF(OR(Scale!$AA14="",Scale!$AA14=0),"",Scale!$B14) | B28: =IF(OR(Scale!$AA14="",Scale!$AA14=0),"",Scale!$D14) | C28: =IF(OR(Scale!$AA14="",Scale!$AA14=0),"","باسکول") | D28: =IF(OR(Scale!$AA14="",Scale!$AA14=0),"",Scale!$AA14) | E28: =IF(OR(Scale!$AA14="",Scale!$AA14=0),"",IF(Scale!$AA14="","","پوز باسکول — "&Scale!$E14)) | K28: =IF(OR(Scale!$AA14="",Scale!$AA14=0),"",IF(Scale!$AB14="",0,Scale!$AB14)+IF(Scale!$AC14="",0,Scale!$AC14)) | L28: =IF(OR(Scale!$AA14="",Scale!$AA14=0),"",Scale!$AB14) | M28: =IF(OR(Scale!$AA14="",Scale!$AA14=0),"",Scale!$AC14) | N28: =IF(OR(Scale!$AA14="",Scale!$AA14=0),"","پوز") | O28: =IF(OR(Scale!$AA14="",Scale!$AA14=0),"",IFERROR(VLOOKUP(Scale!$AA14,AcctTbl,3,0),"")) | P28: =IF(Scale!$AA14<>"X011","","BN02")
A29: =IF(OR(Scale!$AD14="",Scale!$AD14=0),"",Scale!$B14) | B29: =IF(OR(Scale!$AD14="",Scale!$AD14=0),"",Scale!$D14) | C29: =IF(OR(Scale!$AD14="",Scale!$AD14=0),"","باسکول") | D29: =IF(OR(Scale!$AD14="",Scale!$AD14=0),"",Scale!$AD14) | E29: =IF(OR(Scale!$AD14="",Scale!$AD14=0),"",IF(Scale!$AD14="","","مقابل پوز — "&Scale!$E14)) | K29: =IF(OR(Scale!$AD14="",Scale!$AD14=0),"",IF(Scale!$AE14="",0,Scale!$AE14)+IF(Scale!$AF14="",0,Scale!$AF14)) | L29: =IF(OR(Scale!$AD14="",Scale!$AD14=0),"",Scale!$AE14) | M29: =IF(OR(Scale!$AD14="",Scale!$AD14=0),"",Scale!$AF14) | N29: =IF(OR(Scale!$AD14="",Scale!$AD14=0),"","مقابل پوز") | O29: =IF(OR(Scale!$AD14="",Scale!$AD14=0),"",IFERROR(VLOOKUP(Scale!$AD14,AcctTbl,3,0),"")) | P29: =IF(Scale!$AD14<>"X011","","BN02")
A30: =IF(OR(Scale!$U15="",Scale!$U15=0),"",Scale!$B15) | B30: =IF(OR(Scale!$U15="",Scale!$U15=0),"",Scale!$D15) | C30: =IF(OR(Scale!$U15="",Scale!$U15=0),"","باسکول") | D30: =IF(OR(Scale!$U15="",Scale!$U15=0),"",Scale!$U15) | E30: =IF(OR(Scale!$U15="",Scale!$U15=0),"",Scale!$T15) | F30: =IF(OR(Scale!$U15="",Scale!$U15=0),"",Scale!$J15) | G30: =IF(OR(Scale!$U15="",Scale!$U15=0),"",Scale!$M15) | H30: =IF(OR(Scale!$U15="",Scale!$U15=0),"",Scale!$L15) | I30: =IF(OR(Scale!$U15="",Scale!$U15=0),"",Scale!$N15) | J30: =IF(OR(Scale!$U15="",Scale!$U15=0),"",Scale!$O15) | K30: =IF(OR(Scale!$U15="",Scale!$U15=0),"",IF(Scale!$V15="",0,Scale!$V15)+IF(Scale!$W15="",0,Scale!$W15)) | L30: =IF(OR(Scale!$U15="",Scale!$U15=0),"",Scale!$V15) | M30: =IF(OR(Scale!$U15="",Scale!$U15=0),"",Scale!$W15) | N30: =IF(OR(Scale!$U15="",Scale!$U15=0),"",Scale!$E15) | O30: =IF(OR(Scale!$U15="",Scale!$U15=0),"",IFERROR(VLOOKUP(Scale!$U15,AcctTbl,3,0),"")) | P30: =IF(Scale!$U15<>"X011","","BN02")
A31: =IF(OR(Scale!$X15="",Scale!$X15=0),"",Scale!$B15) | B31: =IF(OR(Scale!$X15="",Scale!$X15=0),"",Scale!$D15) | C31: =IF(OR(Scale!$X15="",Scale!$X15=0),"","باسکول") | D31: =IF(OR(Scale!$X15="",Scale!$X15=0),"",Scale!$X15) | E31: =IF(OR(Scale!$X15="",Scale!$X15=0),"",IF(Scale!$X15="","","مقابل: "&Scale!$E15)) | K31: =IF(OR(Scale!$X15="",Scale!$X15=0),"",IF(Scale!$Y15="",0,Scale!$Y15)+IF(Scale!$Z15="",0,Scale!$Z15)) | L31: =IF(OR(Scale!$X15="",Scale!$X15=0),"",Scale!$Y15) | M31: =IF(OR(Scale!$X15="",Scale!$X15=0),"",Scale!$Z15) | N31: =IF(OR(Scale!$X15="",Scale!$X15=0),"","مقابل") | O31: =IF(OR(Scale!$X15="",Scale!$X15=0),"",IFERROR(VLOOKUP(Scale!$X15,AcctTbl,3,0),"")) | P31: =IF(Scale!$X15<>"X011","","BN02")
A32: =IF(OR(Scale!$AA15="",Scale!$AA15=0),"",Scale!$B15) | B32: =IF(OR(Scale!$AA15="",Scale!$AA15=0),"",Scale!$D15) | C32: =IF(OR(Scale!$AA15="",Scale!$AA15=0),"","باسکول") | D32: =IF(OR(Scale!$AA15="",Scale!$AA15=0),"",Scale!$AA15) | E32: =IF(OR(Scale!$AA15="",Scale!$AA15=0),"",IF(Scale!$AA15="","","پوز باسکول — "&Scale!$E15)) | K32: =IF(OR(Scale!$AA15="",Scale!$AA15=0),"",IF(Scale!$AB15="",0,Scale!$AB15)+IF(Scale!$AC15="",0,Scale!$AC15)) | L32: =IF(OR(Scale!$AA15="",Scale!$AA15=0),"",Scale!$AB15) | M32: =IF(OR(Scale!$AA15="",Scale!$AA15=0),"",Scale!$AC15) | N32: =IF(OR(Scale!$AA15="",Scale!$AA15=0),"","پوز") | O32: =IF(OR(Scale!$AA15="",Scale!$AA15=0),"",IFERROR(VLOOKUP(Scale!$AA15,AcctTbl,3,0),"")) | P32: =IF(Scale!$AA15<>"X011","","BN02")
A33: =IF(OR(Scale!$AD15="",Scale!$AD15=0),"",Scale!$B15) | B33: =IF(OR(Scale!$AD15="",Scale!$AD15=0),"",Scale!$D15) | C33: =IF(OR(Scale!$AD15="",Scale!$AD15=0),"","باسکول") | D33: =IF(OR(Scale!$AD15="",Scale!$AD15=0),"",Scale!$AD15) | E33: =IF(OR(Scale!$AD15="",Scale!$AD15=0),"",IF(Scale!$AD15="","","مقابل پوز — "&Scale!$E15)) | K33: =IF(OR(Scale!$AD15="",Scale!$AD15=0),"",IF(Scale!$AE15="",0,Scale!$AE15)+IF(Scale!$AF15="",0,Scale!$AF15)) | L33: =IF(OR(Scale!$AD15="",Scale!$AD15=0),"",Scale!$AE15) | M33: =IF(OR(Scale!$AD15="",Scale!$AD15=0),"",Scale!$AF15) | N33: =IF(OR(Scale!$AD15="",Scale!$AD15=0),"","مقابل پوز") | O33: =IF(OR(Scale!$AD15="",Scale!$AD15=0),"",IFERROR(VLOOKUP(Scale!$AD15,AcctTbl,3,0),"")) | P33: =IF(Scale!$AD15<>"X011","","BN02")
A34: =IF(OR(Scale!$U16="",Scale!$U16=0),"",Scale!$B16) | B34: =IF(OR(Scale!$U16="",Scale!$U16=0),"",Scale!$D16) | C34: =IF(OR(Scale!$U16="",Scale!$U16=0),"","باسکول") | D34: =IF(OR(Scale!$U16="",Scale!$U16=0),"",Scale!$U16) | E34: =IF(OR(Scale!$U16="",Scale!$U16=0),"",Scale!$T16) | F34: =IF(OR(Scale!$U16="",Scale!$U16=0),"",Scale!$J16) | G34: =IF(OR(Scale!$U16="",Scale!$U16=0),"",Scale!$M16) | H34: =IF(OR(Scale!$U16="",Scale!$U16=0),"",Scale!$L16) | I34: =IF(OR(Scale!$U16="",Scale!$U16=0),"",Scale!$N16) | J34: =IF(OR(Scale!$U16="",Scale!$U16=0),"",Scale!$O16) | K34: =IF(OR(Scale!$U16="",Scale!$U16=0),"",IF(Scale!$V16="",0,Scale!$V16)+IF(Scale!$W16="",0,Scale!$W16)) | L34: =IF(OR(Scale!$U16="",Scale!$U16=0),"",Scale!$V16) | M34: =IF(OR(Scale!$U16="",Scale!$U16=0),"",Scale!$W16) | N34: =IF(OR(Scale!$U16="",Scale!$U16=0),"",Scale!$E16) | O34: =IF(OR(Scale!$U16="",Scale!$U16=0),"",IFERROR(VLOOKUP(Scale!$U16,AcctTbl,3,0),"")) | P34: =IF(Scale!$U16<>"X011","","BN02")
A35: =IF(OR(Scale!$X16="",Scale!$X16=0),"",Scale!$B16) | B35: =IF(OR(Scale!$X16="",Scale!$X16=0),"",Scale!$D16) | C35: =IF(OR(Scale!$X16="",Scale!$X16=0),"","باسکول") | D35: =IF(OR(Scale!$X16="",Scale!$X16=0),"",Scale!$X16) | E35: =IF(OR(Scale!$X16="",Scale!$X16=0),"",IF(Scale!$X16="","","مقابل: "&Scale!$E16)) | K35: =IF(OR(Scale!$X16="",Scale!$X16=0),"",IF(Scale!$Y16="",0,Scale!$Y16)+IF(Scale!$Z16="",0,Scale!$Z16)) | L35: =IF(OR(Scale!$X16="",Scale!$X16=0),"",Scale!$Y16) | M35: =IF(OR(Scale!$X16="",Scale!$X16=0),"",Scale!$Z16) | N35: =IF(OR(Scale!$X16="",Scale!$X16=0),"","مقابل") | O35: =IF(OR(Scale!$X16="",Scale!$X16=0),"",IFERROR(VLOOKUP(Scale!$X16,AcctTbl,3,0),"")) | P35: =IF(Scale!$X16<>"X011","","BN02")
A36: =IF(OR(Scale!$AA16="",Scale!$AA16=0),"",Scale!$B16) | B36: =IF(OR(Scale!$AA16="",Scale!$AA16=0),"",Scale!$D16) | C36: =IF(OR(Scale!$AA16="",Scale!$AA16=0),"","باسکول") | D36: =IF(OR(Scale!$AA16="",Scale!$AA16=0),"",Scale!$AA16) | E36: =IF(OR(Scale!$AA16="",Scale!$AA16=0),"",IF(Scale!$AA16="","","پوز باسکول — "&Scale!$E16)) | K36: =IF(OR(Scale!$AA16="",Scale!$AA16=0),"",IF(Scale!$AB16="",0,Scale!$AB16)+IF(Scale!$AC16="",0,Scale!$AC16)) | L36: =IF(OR(Scale!$AA16="",Scale!$AA16=0),"",Scale!$AB16) | M36: =IF(OR(Scale!$AA16="",Scale!$AA16=0),"",Scale!$AC16) | N36: =IF(OR(Scale!$AA16="",Scale!$AA16=0),"","پوز") | O36: =IF(OR(Scale!$AA16="",Scale!$AA16=0),"",IFERROR(VLOOKUP(Scale!$AA16,AcctTbl,3,0),"")) | P36: =IF(Scale!$AA16<>"X011","","BN02")
A37: =IF(OR(Scale!$AD16="",Scale!$AD16=0),"",Scale!$B16) | B37: =IF(OR(Scale!$AD16="",Scale!$AD16=0),"",Scale!$D16) | C37: =IF(OR(Scale!$AD16="",Scale!$AD16=0),"","باسکول") | D37: =IF(OR(Scale!$AD16="",Scale!$AD16=0),"",Scale!$AD16) | E37: =IF(OR(Scale!$AD16="",Scale!$AD16=0),"",IF(Scale!$AD16="","","مقابل پوز — "&Scale!$E16)) | K37: =IF(OR(Scale!$AD16="",Scale!$AD16=0),"",IF(Scale!$AE16="",0,Scale!$AE16)+IF(Scale!$AF16="",0,Scale!$AF16)) | L37: =IF(OR(Scale!$AD16="",Scale!$AD16=0),"",Scale!$AE16) | M37: =IF(OR(Scale!$AD16="",Scale!$AD16=0),"",Scale!$AF16) | N37: =IF(OR(Scale!$AD16="",Scale!$AD16=0),"","مقابل پوز") | O37: =IF(OR(Scale!$AD16="",Scale!$AD16=0),"",IFERROR(VLOOKUP(Scale!$AD16,AcctTbl,3,0),"")) | P37: =IF(Scale!$AD16<>"X011","","BN02")
A38: =IF(OR(Scale!$U17="",Scale!$U17=0),"",Scale!$B17) | B38: =IF(OR(Scale!$U17="",Scale!$U17=0),"",Scale!$D17) | C38: =IF(OR(Scale!$U17="",Scale!$U17=0),"","باسکول") | D38: =IF(OR(Scale!$U17="",Scale!$U17=0),"",Scale!$U17) | E38: =IF(OR(Scale!$U17="",Scale!$U17=0),"",Scale!$T17) | F38: =IF(OR(Scale!$U17="",Scale!$U17=0),"",Scale!$J17) | G38: =IF(OR(Scale!$U17="",Scale!$U17=0),"",Scale!$M17) | H38: =IF(OR(Scale!$U17="",Scale!$U17=0),"",Scale!$L17) | I38: =IF(OR(Scale!$U17="",Scale!$U17=0),"",Scale!$N17) | J38: =IF(OR(Scale!$U17="",Scale!$U17=0),"",Scale!$O17) | K38: =IF(OR(Scale!$U17="",Scale!$U17=0),"",IF(Scale!$V17="",0,Scale!$V17)+IF(Scale!$W17="",0,Scale!$W17)) | L38: =IF(OR(Scale!$U17="",Scale!$U17=0),"",Scale!$V17) | M38: =IF(OR(Scale!$U17="",Scale!$U17=0),"",Scale!$W17) | N38: =IF(OR(Scale!$U17="",Scale!$U17=0),"",Scale!$E17) | O38: =IF(OR(Scale!$U17="",Scale!$U17=0),"",IFERROR(VLOOKUP(Scale!$U17,AcctTbl,3,0),"")) | P38: =IF(Scale!$U17<>"X011","","BN02")
A39: =IF(OR(Scale!$X17="",Scale!$X17=0),"",Scale!$B17) | B39: =IF(OR(Scale!$X17="",Scale!$X17=0),"",Scale!$D17) | C39: =IF(OR(Scale!$X17="",Scale!$X17=0),"","باسکول") | D39: =IF(OR(Scale!$X17="",Scale!$X17=0),"",Scale!$X17) | E39: =IF(OR(Scale!$X17="",Scale!$X17=0),"",IF(Scale!$X17="","","مقابل: "&Scale!$E17)) | K39: =IF(OR(Scale!$X17="",Scale!$X17=0),"",IF(Scale!$Y17="",0,Scale!$Y17)+IF(Scale!$Z17="",0,Scale!$Z17)) | L39: =IF(OR(Scale!$X17="",Scale!$X17=0),"",Scale!$Y17) | M39: =IF(OR(Scale!$X17="",Scale!$X17=0),"",Scale!$Z17) | N39: =IF(OR(Scale!$X17="",Scale!$X17=0),"","مقابل") | O39: =IF(OR(Scale!$X17="",Scale!$X17=0),"",IFERROR(VLOOKUP(Scale!$X17,AcctTbl,3,0),"")) | P39: =IF(Scale!$X17<>"X011","","BN02")
A40: =IF(OR(Scale!$AA17="",Scale!$AA17=0),"",Scale!$B17) | B40: =IF(OR(Scale!$AA17="",Scale!$AA17=0),"",Scale!$D17) | C40: =IF(OR(Scale!$AA17="",Scale!$AA17=0),"","باسکول") | D40: =IF(OR(Scale!$AA17="",Scale!$AA17=0),"",Scale!$AA17) | E40: =IF(OR(Scale!$AA17="",Scale!$AA17=0),"",IF(Scale!$AA17="","","پوز باسکول — "&Scale!$E17)) | K40: =IF(OR(Scale!$AA17="",Scale!$AA17=0),"",IF(Scale!$AB17="",0,Scale!$AB17)+IF(Scale!$AC17="",0,Scale!$AC17)) | L40: =IF(OR(Scale!$AA17="",Scale!$AA17=0),"",Scale!$AB17) | M40: =IF(OR(Scale!$AA17="",Scale!$AA17=0),"",Scale!$AC17) | N40: =IF(OR(Scale!$AA17="",Scale!$AA17=0),"","پوز") | O40: =IF(OR(Scale!$AA17="",Scale!$AA17=0),"",IFERROR(VLOOKUP(Scale!$AA17,AcctTbl,3,0),"")) | P40: =IF(Scale!$AA17<>"X011","","BN02")
A41: =IF(OR(Scale!$AD17="",Scale!$AD17=0),"",Scale!$B17) | B41: =IF(OR(Scale!$AD17="",Scale!$AD17=0),"",Scale!$D17) | C41: =IF(OR(Scale!$AD17="",Scale!$AD17=0),"","باسکول") | D41: =IF(OR(Scale!$AD17="",Scale!$AD17=0),"",Scale!$AD17) | E41: =IF(OR(Scale!$AD17="",Scale!$AD17=0),"",IF(Scale!$AD17="","","مقابل پوز — "&Scale!$E17)) | K41: =IF(OR(Scale!$AD17="",Scale!$AD17=0),"",IF(Scale!$AE17="",0,Scale!$AE17)+IF(Scale!$AF17="",0,Scale!$AF17)) | L41: =IF(OR(Scale!$AD17="",Scale!$AD17=0),"",Scale!$AE17) | M41: =IF(OR(Scale!$AD17="",Scale!$AD17=0),"",Scale!$AF17) | N41: =IF(OR(Scale!$AD17="",Scale!$AD17=0),"","مقابل پوز") | O41: =IF(OR(Scale!$AD17="",Scale!$AD17=0),"",IFERROR(VLOOKUP(Scale!$AD17,AcctTbl,3,0),"")) | P41: =IF(Scale!$AD17<>"X011","","BN02")
A42: =IF(OR(Scale!$U18="",Scale!$U18=0),"",Scale!$B18) | B42: =IF(OR(Scale!$U18="",Scale!$U18=0),"",Scale!$D18) | C42: =IF(OR(Scale!$U18="",Scale!$U18=0),"","باسکول") | D42: =IF(OR(Scale!$U18="",Scale!$U18=0),"",Scale!$U18) | E42: =IF(OR(Scale!$U18="",Scale!$U18=0),"",Scale!$T18) | F42: =IF(OR(Scale!$U18="",Scale!$U18=0),"",Scale!$J18) | G42: =IF(OR(Scale!$U18="",Scale!$U18=0),"",Scale!$M18) | H42: =IF(OR(Scale!$U18="",Scale!$U18=0),"",Scale!$L18) | I42: =IF(OR(Scale!$U18="",Scale!$U18=0),"",Scale!$N18) | J42: =IF(OR(Scale!$U18="",Scale!$U18=0),"",Scale!$O18) | K42: =IF(OR(Scale!$U18="",Scale!$U18=0),"",IF(Scale!$V18="",0,Scale!$V18)+IF(Scale!$W18="",0,Scale!$W18)) | L42: =IF(OR(Scale!$U18="",Scale!$U18=0),"",Scale!$V18) | M42: =IF(OR(Scale!$U18="",Scale!$U18=0),"",Scale!$W18) | N42: =IF(OR(Scale!$U18="",Scale!$U18=0),"",Scale!$E18) | O42: =IF(OR(Scale!$U18="",Scale!$U18=0),"",IFERROR(VLOOKUP(Scale!$U18,AcctTbl,3,0),"")) | P42: =IF(Scale!$U18<>"X011","","BN02")
A43: =IF(OR(Scale!$X18="",Scale!$X18=0),"",Scale!$B18) | B43: =IF(OR(Scale!$X18="",Scale!$X18=0),"",Scale!$D18) | C43: =IF(OR(Scale!$X18="",Scale!$X18=0),"","باسکول") | D43: =IF(OR(Scale!$X18="",Scale!$X18=0),"",Scale!$X18) | E43: =IF(OR(Scale!$X18="",Scale!$X18=0),"",IF(Scale!$X18="","","مقابل: "&Scale!$E18)) | K43: =IF(OR(Scale!$X18="",Scale!$X18=0),"",IF(Scale!$Y18="",0,Scale!$Y18)+IF(Scale!$Z18="",0,Scale!$Z18)) | L43: =IF(OR(Scale!$X18="",Scale!$X18=0),"",Scale!$Y18) | M43: =IF(OR(Scale!$X18="",Scale!$X18=0),"",Scale!$Z18) | N43: =IF(OR(Scale!$X18="",Scale!$X18=0),"","مقابل") | O43: =IF(OR(Scale!$X18="",Scale!$X18=0),"",IFERROR(VLOOKUP(Scale!$X18,AcctTbl,3,0),"")) | P43: =IF(Scale!$X18<>"X011","","BN02")
A44: =IF(OR(Scale!$AA18="",Scale!$AA18=0),"",Scale!$B18) | B44: =IF(OR(Scale!$AA18="",Scale!$AA18=0),"",Scale!$D18) | C44: =IF(OR(Scale!$AA18="",Scale!$AA18=0),"","باسکول") | D44: =IF(OR(Scale!$AA18="",Scale!$AA18=0),"",Scale!$AA18) | E44: =IF(OR(Scale!$AA18="",Scale!$AA18=0),"",IF(Scale!$AA18="","","پوز باسکول — "&Scale!$E18)) | K44: =IF(OR(Scale!$AA18="",Scale!$AA18=0),"",IF(Scale!$AB18="",0,Scale!$AB18)+IF(Scale!$AC18="",0,Scale!$AC18)) | L44: =IF(OR(Scale!$AA18="",Scale!$AA18=0),"",Scale!$AB18) | M44: =IF(OR(Scale!$AA18="",Scale!$AA18=0),"",Scale!$AC18) | N44: =IF(OR(Scale!$AA18="",Scale!$AA18=0),"","پوز") | O44: =IF(OR(Scale!$AA18="",Scale!$AA18=0),"",IFERROR(VLOOKUP(Scale!$AA18,AcctTbl,3,0),"")) | P44: =IF(Scale!$AA18<>"X011","","BN02")
A45: =IF(OR(Scale!$AD18="",Scale!$AD18=0),"",Scale!$B18) | B45: =IF(OR(Scale!$AD18="",Scale!$AD18=0),"",Scale!$D18) | C45: =IF(OR(Scale!$AD18="",Scale!$AD18=0),"","باسکول") | D45: =IF(OR(Scale!$AD18="",Scale!$AD18=0),"",Scale!$AD18) | E45: =IF(OR(Scale!$AD18="",Scale!$AD18=0),"",IF(Scale!$AD18="","","مقابل پوز — "&Scale!$E18)) | K45: =IF(OR(Scale!$AD18="",Scale!$AD18=0),"",IF(Scale!$AE18="",0,Scale!$AE18)+IF(Scale!$AF18="",0,Scale!$AF18)) | L45: =IF(OR(Scale!$AD18="",Scale!$AD18=0),"",Scale!$AE18) | M45: =IF(OR(Scale!$AD18="",Scale!$AD18=0),"",Scale!$AF18) | N45: =IF(OR(Scale!$AD18="",Scale!$AD18=0),"","مقابل پوز") | O45: =IF(OR(Scale!$AD18="",Scale!$AD18=0),"",IFERROR(VLOOKUP(Scale!$AD18,AcctTbl,3,0),"")) | P45: =IF(Scale!$AD18<>"X011","","BN02")
A46: =IF(OR(Scale!$U19="",Scale!$U19=0),"",Scale!$B19) | B46: =IF(OR(Scale!$U19="",Scale!$U19=0),"",Scale!$D19) | C46: =IF(OR(Scale!$U19="",Scale!$U19=0),"","باسکول") | D46: =IF(OR(Scale!$U19="",Scale!$U19=0),"",Scale!$U19) | E46: =IF(OR(Scale!$U19="",Scale!$U19=0),"",Scale!$T19) | F46: =IF(OR(Scale!$U19="",Scale!$U19=0),"",Scale!$J19) | G46: =IF(OR(Scale!$U19="",Scale!$U19=0),"",Scale!$M19) | H46: =IF(OR(Scale!$U19="",Scale!$U19=0),"",Scale!$L19) | I46: =IF(OR(Scale!$U19="",Scale!$U19=0),"",Scale!$N19) | J46: =IF(OR(Scale!$U19="",Scale!$U19=0),"",Scale!$O19) | K46: =IF(OR(Scale!$U19="",Scale!$U19=0),"",IF(Scale!$V19="",0,Scale!$V19)+IF(Scale!$W19="",0,Scale!$W19)) | L46: =IF(OR(Scale!$U19="",Scale!$U19=0),"",Scale!$V19) | M46: =IF(OR(Scale!$U19="",Scale!$U19=0),"",Scale!$W19) | N46: =IF(OR(Scale!$U19="",Scale!$U19=0),"",Scale!$E19) | O46: =IF(OR(Scale!$U19="",Scale!$U19=0),"",IFERROR(VLOOKUP(Scale!$U19,AcctTbl,3,0),"")) | P46: =IF(Scale!$U19<>"X011","","BN02")
A47: =IF(OR(Scale!$X19="",Scale!$X19=0),"",Scale!$B19) | B47: =IF(OR(Scale!$X19="",Scale!$X19=0),"",Scale!$D19) | C47: =IF(OR(Scale!$X19="",Scale!$X19=0),"","باسکول") | D47: =IF(OR(Scale!$X19="",Scale!$X19=0),"",Scale!$X19) | E47: =IF(OR(Scale!$X19="",Scale!$X19=0),"",IF(Scale!$X19="","","مقابل: "&Scale!$E19)) | K47: =IF(OR(Scale!$X19="",Scale!$X19=0),"",IF(Scale!$Y19="",0,Scale!$Y19)+IF(Scale!$Z19="",0,Scale!$Z19)) | L47: =IF(OR(Scale!$X19="",Scale!$X19=0),"",Scale!$Y19) | M47: =IF(OR(Scale!$X19="",Scale!$X19=0),"",Scale!$Z19) | N47: =IF(OR(Scale!$X19="",Scale!$X19=0),"","مقابل") | O47: =IF(OR(Scale!$X19="",Scale!$X19=0),"",IFERROR(VLOOKUP(Scale!$X19,AcctTbl,3,0),"")) | P47: =IF(Scale!$X19<>"X011","","BN02")
A48: =IF(OR(Scale!$AA19="",Scale!$AA19=0),"",Scale!$B19) | B48: =IF(OR(Scale!$AA19="",Scale!$AA19=0),"",Scale!$D19) | C48: =IF(OR(Scale!$AA19="",Scale!$AA19=0),"","باسکول") | D48: =IF(OR(Scale!$AA19="",Scale!$AA19=0),"",Scale!$AA19) | E48: =IF(OR(Scale!$AA19="",Scale!$AA19=0),"",IF(Scale!$AA19="","","پوز باسکول — "&Scale!$E19)) | K48: =IF(OR(Scale!$AA19="",Scale!$AA19=0),"",IF(Scale!$AB19="",0,Scale!$AB19)+IF(Scale!$AC19="",0,Scale!$AC19)) | L48: =IF(OR(Scale!$AA19="",Scale!$AA19=0),"",Scale!$AB19) | M48: =IF(OR(Scale!$AA19="",Scale!$AA19=0),"",Scale!$AC19) | N48: =IF(OR(Scale!$AA19="",Scale!$AA19=0),"","پوز") | O48: =IF(OR(Scale!$AA19="",Scale!$AA19=0),"",IFERROR(VLOOKUP(Scale!$AA19,AcctTbl,3,0),"")) | P48: =IF(Scale!$AA19<>"X011","","BN02")
A49: =IF(OR(Scale!$AD19="",Scale!$AD19=0),"",Scale!$B19) | B49: =IF(OR(Scale!$AD19="",Scale!$AD19=0),"",Scale!$D19) | C49: =IF(OR(Scale!$AD19="",Scale!$AD19=0),"","باسکول") | D49: =IF(OR(Scale!$AD19="",Scale!$AD19=0),"",Scale!$AD19) | E49: =IF(OR(Scale!$AD19="",Scale!$AD19=0),"",IF(Scale!$AD19="","","مقابل پوز — "&Scale!$E19)) | K49: =IF(OR(Scale!$AD19="",Scale!$AD19=0),"",IF(Scale!$AE19="",0,Scale!$AE19)+IF(Scale!$AF19="",0,Scale!$AF19)) | L49: =IF(OR(Scale!$AD19="",Scale!$AD19=0),"",Scale!$AE19) | M49: =IF(OR(Scale!$AD19="",Scale!$AD19=0),"",Scale!$AF19) | N49: =IF(OR(Scale!$AD19="",Scale!$AD19=0),"","مقابل پوز") | O49: =IF(OR(Scale!$AD19="",Scale!$AD19=0),"",IFERROR(VLOOKUP(Scale!$AD19,AcctTbl,3,0),"")) | P49: =IF(Scale!$AD19<>"X011","","BN02")
A50: =IF(OR(Scale!$U20="",Scale!$U20=0),"",Scale!$B20) | B50: =IF(OR(Scale!$U20="",Scale!$U20=0),"",Scale!$D20) | C50: =IF(OR(Scale!$U20="",Scale!$U20=0),"","باسکول") | D50: =IF(OR(Scale!$U20="",Scale!$U20=0),"",Scale!$U20) | E50: =IF(OR(Scale!$U20="",Scale!$U20=0),"",Scale!$T20) | F50: =IF(OR(Scale!$U20="",Scale!$U20=0),"",Scale!$J20) | G50: =IF(OR(Scale!$U20="",Scale!$U20=0),"",Scale!$M20) | H50: =IF(OR(Scale!$U20="",Scale!$U20=0),"",Scale!$L20) | I50: =IF(OR(Scale!$U20="",Scale!$U20=0),"",Scale!$N20) | J50: =IF(OR(Scale!$U20="",Scale!$U20=0),"",Scale!$O20) | K50: =IF(OR(Scale!$U20="",Scale!$U20=0),"",IF(Scale!$V20="",0,Scale!$V20)+IF(Scale!$W20="",0,Scale!$W20)) | L50: =IF(OR(Scale!$U20="",Scale!$U20=0),"",Scale!$V20) | M50: =IF(OR(Scale!$U20="",Scale!$U20=0),"",Scale!$W20) | N50: =IF(OR(Scale!$U20="",Scale!$U20=0),"",Scale!$E20) | O50: =IF(OR(Scale!$U20="",Scale!$U20=0),"",IFERROR(VLOOKUP(Scale!$U20,AcctTbl,3,0),"")) | P50: =IF(Scale!$U20<>"X011","","BN02")
A51: =IF(OR(Scale!$X20="",Scale!$X20=0),"",Scale!$B20) | B51: =IF(OR(Scale!$X20="",Scale!$X20=0),"",Scale!$D20) | C51: =IF(OR(Scale!$X20="",Scale!$X20=0),"","باسکول") | D51: =IF(OR(Scale!$X20="",Scale!$X20=0),"",Scale!$X20) | E51: =IF(OR(Scale!$X20="",Scale!$X20=0),"",IF(Scale!$X20="","","مقابل: "&Scale!$E20)) | K51: =IF(OR(Scale!$X20="",Scale!$X20=0),"",IF(Scale!$Y20="",0,Scale!$Y20)+IF(Scale!$Z20="",0,Scale!$Z20)) | L51: =IF(OR(Scale!$X20="",Scale!$X20=0),"",Scale!$Y20) | M51: =IF(OR(Scale!$X20="",Scale!$X20=0),"",Scale!$Z20) | N51: =IF(OR(Scale!$X20="",Scale!$X20=0),"","مقابل") | O51: =IF(OR(Scale!$X20="",Scale!$X20=0),"",IFERROR(VLOOKUP(Scale!$X20,AcctTbl,3,0),"")) | P51: =IF(Scale!$X20<>"X011","","BN02")
A52: =IF(OR(Scale!$AA20="",Scale!$AA20=0),"",Scale!$B20) | B52: =IF(OR(Scale!$AA20="",Scale!$AA20=0),"",Scale!$D20) | C52: =IF(OR(Scale!$AA20="",Scale!$AA20=0),"","باسکول") | D52: =IF(OR(Scale!$AA20="",Scale!$AA20=0),"",Scale!$AA20) | E52: =IF(OR(Scale!$AA20="",Scale!$AA20=0),"",IF(Scale!$AA20="","","پوز باسکول — "&Scale!$E20)) | K52: =IF(OR(Scale!$AA20="",Scale!$AA20=0),"",IF(Scale!$AB20="",0,Scale!$AB20)+IF(Scale!$AC20="",0,Scale!$AC20)) | L52: =IF(OR(Scale!$AA20="",Scale!$AA20=0),"",Scale!$AB20) | M52: =IF(OR(Scale!$AA20="",Scale!$AA20=0),"",Scale!$AC20) | N52: =IF(OR(Scale!$AA20="",Scale!$AA20=0),"","پوز") | O52: =IF(OR(Scale!$AA20="",Scale!$AA20=0),"",IFERROR(VLOOKUP(Scale!$AA20,AcctTbl,3,0),"")) | P52: =IF(Scale!$AA20<>"X011","","BN02")
A53: =IF(OR(Scale!$AD20="",Scale!$AD20=0),"",Scale!$B20) | B53: =IF(OR(Scale!$AD20="",Scale!$AD20=0),"",Scale!$D20) | C53: =IF(OR(Scale!$AD20="",Scale!$AD20=0),"","باسکول") | D53: =IF(OR(Scale!$AD20="",Scale!$AD20=0),"",Scale!$AD20) | E53: =IF(OR(Scale!$AD20="",Scale!$AD20=0),"",IF(Scale!$AD20="","","مقابل پوز — "&Scale!$E20)) | K53: =IF(OR(Scale!$AD20="",Scale!$AD20=0),"",IF(Scale!$AE20="",0,Scale!$AE20)+IF(Scale!$AF20="",0,Scale!$AF20)) | L53: =IF(OR(Scale!$AD20="",Scale!$AD20=0),"",Scale!$AE20) | M53: =IF(OR(Scale!$AD20="",Scale!$AD20=0),"",Scale!$AF20) | N53: =IF(OR(Scale!$AD20="",Scale!$AD20=0),"","مقابل پوز") | O53: =IF(OR(Scale!$AD20="",Scale!$AD20=0),"",IFERROR(VLOOKUP(Scale!$AD20,AcctTbl,3,0),"")) | P53: =IF(Scale!$AD20<>"X011","","BN02")
A54: =IF(OR(Scale!$U21="",Scale!$U21=0),"",Scale!$B21) | B54: =IF(OR(Scale!$U21="",Scale!$U21=0),"",Scale!$D21) | C54: =IF(OR(Scale!$U21="",Scale!$U21=0),"","باسکول") | D54: =IF(OR(Scale!$U21="",Scale!$U21=0),"",Scale!$U21) | E54: =IF(OR(Scale!$U21="",Scale!$U21=0),"",Scale!$T21) | F54: =IF(OR(Scale!$U21="",Scale!$U21=0),"",Scale!$J21) | G54: =IF(OR(Scale!$U21="",Scale!$U21=0),"",Scale!$M21) | H54: =IF(OR(Scale!$U21="",Scale!$U21=0),"",Scale!$L21) | I54: =IF(OR(Scale!$U21="",Scale!$U21=0),"",Scale!$N21) | J54: =IF(OR(Scale!$U21="",Scale!$U21=0),"",Scale!$O21) | K54: =IF(OR(Scale!$U21="",Scale!$U21=0),"",IF(Scale!$V21="",0,Scale!$V21)+IF(Scale!$W21="",0,Scale!$W21)) | L54: =IF(OR(Scale!$U21="",Scale!$U21=0),"",Scale!$V21) | M54: =IF(OR(Scale!$U21="",Scale!$U21=0),"",Scale!$W21) | N54: =IF(OR(Scale!$U21="",Scale!$U21=0),"",Scale!$E21) | O54: =IF(OR(Scale!$U21="",Scale!$U21=0),"",IFERROR(VLOOKUP(Scale!$U21,AcctTbl,3,0),"")) | P54: =IF(Scale!$U21<>"X011","","BN02")
A55: =IF(OR(Scale!$X21="",Scale!$X21=0),"",Scale!$B21) | B55: =IF(OR(Scale!$X21="",Scale!$X21=0),"",Scale!$D21) | C55: =IF(OR(Scale!$X21="",Scale!$X21=0),"","باسکول") | D55: =IF(OR(Scale!$X21="",Scale!$X21=0),"",Scale!$X21) | E55: =IF(OR(Scale!$X21="",Scale!$X21=0),"",IF(Scale!$X21="","","مقابل: "&Scale!$E21)) | K55: =IF(OR(Scale!$X21="",Scale!$X21=0),"",IF(Scale!$Y21="",0,Scale!$Y21)+IF(Scale!$Z21="",0,Scale!$Z21)) | L55: =IF(OR(Scale!$X21="",Scale!$X21=0),"",Scale!$Y21) | M55: =IF(OR(Scale!$X21="",Scale!$X21=0),"",Scale!$Z21) | N55: =IF(OR(Scale!$X21="",Scale!$X21=0),"","مقابل") | O55: =IF(OR(Scale!$X21="",Scale!$X21=0),"",IFERROR(VLOOKUP(Scale!$X21,AcctTbl,3,0),"")) | P55: =IF(Scale!$X21<>"X011","","BN02")
A56: =IF(OR(Scale!$AA21="",Scale!$AA21=0),"",Scale!$B21) | B56: =IF(OR(Scale!$AA21="",Scale!$AA21=0),"",Scale!$D21) | C56: =IF(OR(Scale!$AA21="",Scale!$AA21=0),"","باسکول") | D56: =IF(OR(Scale!$AA21="",Scale!$AA21=0),"",Scale!$AA21) | E56: =IF(OR(Scale!$AA21="",Scale!$AA21=0),"",IF(Scale!$AA21="","","پوز باسکول — "&Scale!$E21)) | K56: =IF(OR(Scale!$AA21="",Scale!$AA21=0),"",IF(Scale!$AB21="",0,Scale!$AB21)+IF(Scale!$AC21="",0,Scale!$AC21)) | L56: =IF(OR(Scale!$AA21="",Scale!$AA21=0),"",Scale!$AB21) | M56: =IF(OR(Scale!$AA21="",Scale!$AA21=0),"",Scale!$AC21) | N56: =IF(OR(Scale!$AA21="",Scale!$AA21=0),"","پوز") | O56: =IF(OR(Scale!$AA21="",Scale!$AA21=0),"",IFERROR(VLOOKUP(Scale!$AA21,AcctTbl,3,0),"")) | P56: =IF(Scale!$AA21<>"X011","","BN02")
A57: =IF(OR(Scale!$AD21="",Scale!$AD21=0),"",Scale!$B21) | B57: =IF(OR(Scale!$AD21="",Scale!$AD21=0),"",Scale!$D21) | C57: =IF(OR(Scale!$AD21="",Scale!$AD21=0),"","باسکول") | D57: =IF(OR(Scale!$AD21="",Scale!$AD21=0),"",Scale!$AD21) | E57: =IF(OR(Scale!$AD21="",Scale!$AD21=0),"",IF(Scale!$AD21="","","مقابل پوز — "&Scale!$E21)) | K57: =IF(OR(Scale!$AD21="",Scale!$AD21=0),"",IF(Scale!$AE21="",0,Scale!$AE21)+IF(Scale!$AF21="",0,Scale!$AF21)) | L57: =IF(OR(Scale!$AD21="",Scale!$AD21=0),"",Scale!$AE21) | M57: =IF(OR(Scale!$AD21="",Scale!$AD21=0),"",Scale!$AF21) | N57: =IF(OR(Scale!$AD21="",Scale!$AD21=0),"","مقابل پوز") | O57: =IF(OR(Scale!$AD21="",Scale!$AD21=0),"",IFERROR(VLOOKUP(Scale!$AD21,AcctTbl,3,0),"")) | P57: =IF(Scale!$AD21<>"X011","","BN02")
A58: =IF(OR(Scale!$U22="",Scale!$U22=0),"",Scale!$B22) | B58: =IF(OR(Scale!$U22="",Scale!$U22=0),"",Scale!$D22) | C58: =IF(OR(Scale!$U22="",Scale!$U22=0),"","باسکول") | D58: =IF(OR(Scale!$U22="",Scale!$U22=0),"",Scale!$U22) | E58: =IF(OR(Scale!$U22="",Scale!$U22=0),"",Scale!$T22) | F58: =IF(OR(Scale!$U22="",Scale!$U22=0),"",Scale!$J22) | G58: =IF(OR(Scale!$U22="",Scale!$U22=0),"",Scale!$M22) | H58: =IF(OR(Scale!$U22="",Scale!$U22=0),"",Scale!$L22) | I58: =IF(OR(Scale!$U22="",Scale!$U22=0),"",Scale!$N22) | J58: =IF(OR(Scale!$U22="",Scale!$U22=0),"",Scale!$O22) | K58: =IF(OR(Scale!$U22="",Scale!$U22=0),"",IF(Scale!$V22="",0,Scale!$V22)+IF(Scale!$W22="",0,Scale!$W22)) | L58: =IF(OR(Scale!$U22="",Scale!$U22=0),"",Scale!$V22) | M58: =IF(OR(Scale!$U22="",Scale!$U22=0),"",Scale!$W22) | N58: =IF(OR(Scale!$U22="",Scale!$U22=0),"",Scale!$E22) | O58: =IF(OR(Scale!$U22="",Scale!$U22=0),"",IFERROR(VLOOKUP(Scale!$U22,AcctTbl,3,0),"")) | P58: =IF(Scale!$U22<>"X011","","BN02")
A59: =IF(OR(Scale!$X22="",Scale!$X22=0),"",Scale!$B22) | B59: =IF(OR(Scale!$X22="",Scale!$X22=0),"",Scale!$D22) | C59: =IF(OR(Scale!$X22="",Scale!$X22=0),"","باسکول") | D59: =IF(OR(Scale!$X22="",Scale!$X22=0),"",Scale!$X22) | E59: =IF(OR(Scale!$X22="",Scale!$X22=0),"",IF(Scale!$X22="","","مقابل: "&Scale!$E22)) | K59: =IF(OR(Scale!$X22="",Scale!$X22=0),"",IF(Scale!$Y22="",0,Scale!$Y22)+IF(Scale!$Z22="",0,Scale!$Z22)) | L59: =IF(OR(Scale!$X22="",Scale!$X22=0),"",Scale!$Y22) | M59: =IF(OR(Scale!$X22="",Scale!$X22=0),"",Scale!$Z22) | N59: =IF(OR(Scale!$X22="",Scale!$X22=0),"","مقابل") | O59: =IF(OR(Scale!$X22="",Scale!$X22=0),"",IFERROR(VLOOKUP(Scale!$X22,AcctTbl,3,0),"")) | P59: =IF(Scale!$X22<>"X011","","BN02")
A60: =IF(OR(Scale!$AA22="",Scale!$AA22=0),"",Scale!$B22) | B60: =IF(OR(Scale!$AA22="",Scale!$AA22=0),"",Scale!$D22) | C60: =IF(OR(Scale!$AA22="",Scale!$AA22=0),"","باسکول") | D60: =IF(OR(Scale!$AA22="",Scale!$AA22=0),"",Scale!$AA22) | E60: =IF(OR(Scale!$AA22="",Scale!$AA22=0),"",IF(Scale!$AA22="","","پوز باسکول — "&Scale!$E22)) | K60: =IF(OR(Scale!$AA22="",Scale!$AA22=0),"",IF(Scale!$AB22="",0,Scale!$AB22)+IF(Scale!$AC22="",0,Scale!$AC22)) | L60: =IF(OR(Scale!$AA22="",Scale!$AA22=0),"",Scale!$AB22) | M60: =IF(OR(Scale!$AA22="",Scale!$AA22=0),"",Scale!$AC22) | N60: =IF(OR(Scale!$AA22="",Scale!$AA22=0),"","پوز") | O60: =IF(OR(Scale!$AA22="",Scale!$AA22=0),"",IFERROR(VLOOKUP(Scale!$AA22,AcctTbl,3,0),"")) | P60: =IF(Scale!$AA22<>"X011","","BN02")
A61: =IF(OR(Scale!$AD22="",Scale!$AD22=0),"",Scale!$B22) | B61: =IF(OR(Scale!$AD22="",Scale!$AD22=0),"",Scale!$D22) | C61: =IF(OR(Scale!$AD22="",Scale!$AD22=0),"","باسکول") | D61: =IF(OR(Scale!$AD22="",Scale!$AD22=0),"",Scale!$AD22) | E61: =IF(OR(Scale!$AD22="",Scale!$AD22=0),"",IF(Scale!$AD22="","","مقابل پوز — "&Scale!$E22)) | K61: =IF(OR(Scale!$AD22="",Scale!$AD22=0),"",IF(Scale!$AE22="",0,Scale!$AE22)+IF(Scale!$AF22="",0,Scale!$AF22)) | L61: =IF(OR(Scale!$AD22="",Scale!$AD22=0),"",Scale!$AE22) | M61: =IF(OR(Scale!$AD22="",Scale!$AD22=0),"",Scale!$AF22) | N61: =IF(OR(Scale!$AD22="",Scale!$AD22=0),"","مقابل پوز") | O61: =IF(OR(Scale!$AD22="",Scale!$AD22=0),"",IFERROR(VLOOKUP(Scale!$AD22,AcctTbl,3,0),"")) | P61: =IF(Scale!$AD22<>"X011","","BN02")
